Workbook

Sheet MP Summary
A1: USPS MARKETING MAIL PARCEL
A2: MAIL PROCESSING UNIT COST SUMMARY
C4: [1] | D4: [2] | E4: [3]
A5: Parcels | B5: Entry | D5: Volume | E5: Adjusted
A6: Price Category | B6: Level | C6: Volume | D6: Percent | E6: Unit Cost | H6: FY 2025 | J6: FY 2014 | K6: FY 2015 | L6: FY 2016 | M6: FY 2017 | N6: FY 2018 | O6: FY 2019 | P6: FY 2020 | Q6: FY 2021 | R6: FY 2022 | S6: FY 2023 | T6: FY 2024 | U6: FY2025
A8: Machinable
A9: Machinable MNDC | B9: None | C9: ='Vol Data'!$I$20 -> 670396 | D9: =C9/$C$42 -> 0.057269253 | E9: ='MP Cost Adjustments'!$H$15 -> 1.3228001 | G9: None | H9: =C9+C10+C19+C20+C31+C32 -> 5795330 | J9: ='[1]MP Summary'!$I$9 -> 0.25566517 | K9: ='[2]MP Summary'!$I$9 -> 0.25305123 | L9: ='[3]MP Summary'!$I$9 -> 0.30656361 | M9: ='[4]MP Summary'!$I$9 -> 0.28799236 | N9: ='[5]MP Summary'!$I$9 -> 0.35479901 | O9: ='[6]MP Summary'!$I$9 -> 0.40556063 | P9: ='[7]MP Summary'!$I$9 -> 0.40129629 | Q9: ='[8]MP Summary'!$P$9 -> 0.39086773 | R9: ='[9]MP Summary'!$Q$9 -> 0.37313655 | S9: ='[10]MP Summary'!$R$9 -> 0.38815074 | T9: ='[11]MP Summary'!$T$9 -> 0.43662908 | U9: =H9/$H$13 -> 0.5208754
A10: Machinable NDC | B10: None | C10: ='Vol Data'!$I$21 -> 400984 | D10: =C10/$C$42 -> 0.034254462 | E10: ='MP Cost Adjustments'!$H$16 -> 0.96968742 | G10: DNDC | H10: =C11+C12+C21+C22+C25+C33+C34+C37 -> 2901013 | J10: ='[1]MP Summary'!$I$10 -> 0.26055708 | K10: ='[2]MP Summary'!$I$10 -> 0.23088463 | L10: ='[3]MP Summary'!$I$10 -> 0.19211897 | M10: ='[4]MP Summary'!$I$10 -> 0.22782286 | N10: ='[5]MP Summary'!$I$10 -> 0.23086444 | O10: ='[6]MP Summary'!$I$10 -> 0.20361308 | P10: ='[7]MP Summary'!$I$10 -> 0.18787059 | Q10: ='[8]MP Summary'!$P$10 -> 0.1743996 | R10: ='[9]MP Summary'!$Q$10 -> 0.19317385 | S10: ='[10]MP Summary'!$R$10 -> 0.24338289 | T10: ='[11]MP Summary'!$T$10 -> 0.27132454 | U10: =H10/$H$13 -> 0.26073861
A11: Machinable NDC | B11: DNDC | C11: ='Vol Data'!$I$22 -> 1729284 | D11: =C11/$C$42 -> 0.14772583 | E11: ='MP Cost Adjustments'!$H$17 -> 0.95314039 | G11: DSCF | H11: =C13+C26+C27+C38+C39 -> 2424346 | J11: ='[1]MP Summary'!$I$11 -> 0.29034166 | K11: ='[2]MP Summary'!$I$11 -> 0.30771953 | L11: ='[3]MP Summary'!$I$11 -> 0.37537139 | M11: ='[4]MP Summary'!$I$11 -> 0.32715847 | N11: ='[5]MP Summary'!$I$11 -> 0.30624084 | O11: ='[6]MP Summary'!$I$11 -> 0.25308584 | P11: ='[7]MP Summary'!$I$11 -> 0.26129558 | Q11: ='[8]MP Summary'!$P$11 -> 0.28927368 | R11: ='[9]MP Summary'!$Q$11 -> 0.25193691 | S11: ='[10]MP Summary'!$R$11 -> 0.18580454 | T11: ='[11]MP Summary'!$T$11 -> 0.16281449 | U11: =H11/$H$13 -> 0.21789651
A12: Machinable 5-Digit | B12: DNDC | C12: ='Vol Data'!$I$23 -> 6159 | D12: =C12/$C$42 -> 0.00052613878 | E12: ='MP Cost Adjustments'!$H$18 -> 0.4326447 | G12: DDU | H12: =C14+C28+C40 -> 5446 | J12: ='[1]MP Summary'!$I$12 -> 0.19343609 | K12: ='[2]MP Summary'!$I$12 -> 0.20834461 | L12: ='[3]MP Summary'!$I$12 -> 0.12594602 | M12: ='[4]MP Summary'!$I$12 -> 0.15702631 | N12: ='[5]MP Summary'!$I$12 -> 0.10809571 | O12: ='[6]MP Summary'!$I$12 -> 0.13774044 | P12: ='[7]MP Summary'!$I$12 -> 0.14953754 | Q12: ='[8]MP Summary'!$P$12 -> 0.14545899 | R12: ='[9]MP Summary'!$Q$12 -> 0.18175269 | S12: ='[10]MP Summary'!$R$12 -> 0.18266183 | T12: ='[11]MP Summary'!$T$12 -> 0.1292319 | U12: =H12/$H$13 -> 0.00048947815
A13: Machinable 5-Digit | B13: DSCF | C13: ='Vol Data'!$I$24 -> 32567 | D13: =C13/$C$42 -> 0.0027820688 | E13: ='MP Cost Adjustments'!$H$19 -> 0.41239554 | H13: =SUM(H9:H12) -> 11126135 | J13: =SUM(J9:J12) -> 1 | K13: =SUM(K9:K12) -> 1 | L13: =SUM(L9:L12) -> 1 | M13: =SUM(M9:M12) -> 1 | N13: =SUM(N9:N12) -> 1 | O13: =SUM(O9:O12) -> 1 | P13: =SUM(P9:P12) -> 1 | Q13: =SUM(Q9:Q12) -> 1 | ... T13: =SUM(T9:T12) -> 1 | U13: 1
A14: Machinable 5-Digit | B14: DDU | C14: ='Vol Data'!$I$25 -> 5446 | D14: =C14/$C$42 -> 0.00046523003 | E14: ='MP Cost Adjustments'!$H$20 -> 0.35921618
A15: Machinable 5-Digit Aggregate | E15: =SUMPRODUCT(C12:C14,E12:E14)/SUM(C12:C14) -> 0.4086624
G17: MNDC Presort | H17: =C9+C19+C31 -> 4144045 | J17: ='[1]MP Summary'!$I$15 -> 0.21284506 | K17: ='[2]MP Summary'!$I$15 -> 0.21299023 | L17: ='[3]MP Summary'!$I$15 -> 0.24918609 | M17: ='[4]MP Summary'!$I$15 -> 0.23236796 | N17: ='[5]MP Summary'!$I$15 -> 0.2540127 | O17: ='[6]MP Summary'!$I$15 -> 0.2649827 | P17: ='[7]MP Summary'!$I$15 -> 0.27654605 | Q17: ='[8]MP Summary'!$P$15 -> 0.29495501 | R17: ='[9]MP Summary'!$P$15 -> 0.29495501 | S17: ='[10]MP Summary'!$R$15 -> 0.26865797 | T17: ='[11]MP Summary'!$T$15 -> 0.29457256 | U17: =H17/$H$21 -> 0.37246043
A18: Nonstandard | G18: NDC Presort | H18: =C10+C11+C20+C21+C32+C33 -> 3986149 | J18: ='[1]MP Summary'!$I$16 -> 0.1925705 | K18: ='[2]MP Summary'!$I$16 -> 0.15191309 | L18: ='[3]MP Summary'!$I$16 -> 0.1708215 | M18: ='[4]MP Summary'!$I$16 -> 0.18081533 | N18: ='[5]MP Summary'!$I$16 -> 0.24325175 | O18: ='[6]MP Summary'!$I$16 -> 0.28661586 | P18: ='[7]MP Summary'!$I$16 -> 0.27354413 | Q18: ='[8]MP Summary'!$P$16 -> 0.23194789 | R18: ='[9]MP Summary'!$P$16 -> 0.23194789 | S18: ='[10]MP Summary'!$R$16 -> 0.32586789 | T18: ='[11]MP Summary'!$T$16 -> 0.37233789 | U18: =H18/$H$21 -> 0.35826898
A19: Nonstandard MNDC | B19: None | C19: ='Vol Data'!$I$9 -> 1347699 | D19: =C19/$C$42 -> 0.11512854 | E19: =('MP Cost Adjustments'!$D$23*'MP Cost Adjustments'!$H$23+'MP Cost Adjustments'!$D$33*'MP Cost Adjustments'!$H$33)/('MP Cost Adjustments'!$D$23+'MP Cost Adjustments'!$D$33) -> 1.4786327 | G19: SCF Presort | H19: =C22+C26+C34+C38 -> 2512374 | J19: ='[1]MP Summary'!$I$17 -> 0.17148004 | K19: ='[2]MP Summary'!$I$17 -> 0.21245376 | L19: ='[3]MP Summary'!$I$17 -> 0.26815547 | M19: ='[4]MP Summary'!$I$17 -> 0.19538321 | N19: ='[5]MP Summary'!$I$17 -> 0.16803137 | O19: ='[6]MP Summary'!$I$17 -> 0.10662493 | P19: ='[7]MP Summary'!$I$17 -> 0.10549834 | Q19: ='[8]MP Summary'!$P$17 -> 0.13995598 | R19: ='[9]MP Summary'!$P$17 -> 0.13995598 | S19: ='[10]MP Summary'!$R$17 -> 0.073261673 | T19: ='[11]MP Summary'!$T$17 -> 0.057009281 | U19: =H19/$H$21 -> 0.22580833
A20: Nonstandard NDC | B20: None | C20: ='Vol Data'!$I$10 -> 405562 | D20: =C20/$C$42 -> 0.034645542 | E20: =('MP Cost Adjustments'!$D$24*'MP Cost Adjustments'!$H$24+'MP Cost Adjustments'!$D$34*'MP Cost Adjustments'!$H$34)/('MP Cost Adjustments'!$D$24+'MP Cost Adjustments'!$D$34) -> 1.3870348 | G20: 5-Digit Presort | H20: =C12+C13+C14+C25+C27+C28+C37+C39+C40 -> 483567 | J20: ='[1]MP Summary'!$I$18 -> 0.4231044 | K20: ='[2]MP Summary'!$I$18 -> 0.42264291 | L20: ='[3]MP Summary'!$I$18 -> 0.31183694 | M20: ='[4]MP Summary'!$I$18 -> 0.3914335 | N20: ='[5]MP Summary'!$I$18 -> 0.33470417 | O20: ='[6]MP Summary'!$I$18 -> 0.34177652 | P20: ='[7]MP Summary'!$I$18 -> 0.34441148 | Q20: ='[8]MP Summary'!$P$18 -> 0.33314113 | R20: ='[9]MP Summary'!$P$18 -> 0.33314113 | S20: ='[10]MP Summary'!$R$18 -> 0.33221246 | T20: ='[11]MP Summary'!$T$18 -> 0.27608027 | U20: =H20/$H$21 -> 0.043462263
A21: Nonstandard NDC | B21: DNDC | C21: ='Vol Data'!$I$11 -> 468927 | D21: =C21/$C$42 -> 0.040058561 | E21: =('MP Cost Adjustments'!$D$25*'MP Cost Adjustments'!$H$25+'MP Cost Adjustments'!$D$35*'MP Cost Adjustments'!$H$35)/('MP Cost Adjustments'!$D$25+'MP Cost Adjustments'!$D$35) -> 1.3784601 | H21: =SUM(H17:H20) -> 11126135 | J21: =SUM(J17:J20) -> 1 | K21: =SUM(K17:K20) -> 1 | L21: =SUM(L17:L20) -> 1 | M21: =SUM(M17:M20) -> 1 | N21: =SUM(N17:N20) -> 1 | O21: =SUM(O17:O20) -> 1 | P21: =SUM(P17:P20) -> 1 | Q21: =SUM(Q17:Q20) -> 1 | ... T21: =SUM(T17:T20) -> 1 | U21: 1
A22: Nonstandard SCF | B22: None/DNDC | C22: ='Vol Data'!$I$13+'Vol Data'!I12 -> 388379 | D22: =C22/$C$42 -> 0.033177667 | E22: =('MP Cost Adjustments'!$D$26*'MP Cost Adjustments'!$H$26+'MP Cost Adjustments'!$D$36*'MP Cost Adjustments'!$H$36)/('MP Cost Adjustments'!$D$26+'MP Cost Adjustments'!$D$36) -> 1.1498791
A23: Nonstandard SCF | B23: DSCF | C23: ='Vol Data'!$I$15 -> 453672 | D23: =C23/$C$42 -> 0.038755387 | E23: =('MP Cost Adjustments'!$D$28*'MP Cost Adjustments'!$H$28+'MP Cost Adjustments'!$D$38*'MP Cost Adjustments'!$H$38)/('MP Cost Adjustments'!$D$28+'MP Cost Adjustments'!$D$38) -> 1.1461197
A24: Nonstandard SCF Aggregate | E24: =SUMPRODUCT(C22:C23,E22:E23)/SUM(C22:C23) -> 1.1478537
A25: Nonstandard 5-Digit | B25: DNDC | C25: ='Vol Data'!$I$14 -> 111340 | D25: =C25/$C$42 -> 0.0095113316 | E25: =('MP Cost Adjustments'!$D$27*'MP Cost Adjustments'!$H$27+'MP Cost Adjustments'!$D$37*'MP Cost Adjustments'!$H$37)/('MP Cost Adjustments'!$D$27+'MP Cost Adjustments'!$D$37) -> 0.41445109
A26: Nonstandard 5-Digit | B26: DSCF | C26: ='Vol Data'!$I$16 -> 111784 | D26: =C26/$C$42 -> 0.0095492608 | E26: =('MP Cost Adjustments'!$D$29*'MP Cost Adjustments'!$H$29+'MP Cost Adjustments'!$D$39*'MP Cost Adjustments'!$H$39)/('MP Cost Adjustments'!$D$29+'MP Cost Adjustments'!$D$39) -> 0.39145625 | G26: Machinable | H26: =SUM(C9:C14) -> 2844836 | J26: =SUM('[1]MP Summary'!$D$9:$D$14) -> 0.15032548 | K26: =SUM('[2]MP Summary'!$D$9:$D$14) -> 0.14022772 | L26: =SUM('[3]MP Summary'!$D$9:$D$14) -> 0.13582223 | M26: =SUM('[4]MP Summary'!$D$9:$D$14) -> 0.16126364 | N26: =SUM('[5]MP Summary'!$D$9:$D$14) -> 0.19976711 | O26: =SUM('[6]MP Summary'!$D$9:$D$14) -> 0.18849858 | P26: =SUM('[7]MP Summary'!$D$9:$D$14) -> 0.216614 | Q26: ='[8]MP Summary'!$P$22 -> 0.19831926 | R26: ='[9]MP Summary'!$P$22 -> 0.19831926 | S26: ='[10]MP Summary'!$R$22 -> 0.25642046 | T26: ='[11]MP Summary'!$T$22 -> 0.27539304 | U26: 0.24576646
A27: Nonstandard 5-Digit | B27: DDU | C27: ='Vol Data'!$I$17 -> 2877 | D27: =C27/$C$42 -> 0.00024577062 | E27: =('MP Cost Adjustments'!$D$30*'MP Cost Adjustments'!$H$30+'MP Cost Adjustments'!$D$40*'MP Cost Adjustments'!$H$40)/('MP Cost Adjustments'!$D$30+'MP Cost Adjustments'!$D$40) -> 0.35894376 | G27: Irregular | H27: =SUM(C19:C28) -> 3290240 | J27: =SUM('[1]MP Summary'!$D$17:$D$24) -> 0.10722376 | K27: =SUM('[2]MP Summary'!$D$17:$D$24) -> 0.10702189 | L27: =SUM('[3]MP Summary'!$D$17:$D$24) -> 0.15373909 | M27: =SUM('[4]MP Summary'!$D$17:$D$24) -> 0.14044821 | N27: =SUM('[5]MP Summary'!$D$17:$D$24) -> 0.16275013 | O27: =SUM('[6]MP Summary'!$D$17:$D$24) -> 0.13547176 | P27: =SUM('[7]MP Summary'!$D$17:$D$24) -> 0.15088468 | Q27: ='[8]MP Summary'!$P$23 -> 0.15412881 | R27: ='[9]MP Summary'!$P$23 -> 0.15412881 | S27: ='[10]MP Summary'!$R$23 -> 0.16235617 | T27: ='[11]MP Summary'!$T$23 -> 0.18991485 | U27: 0.27437273
A28: Nonstandard 5-Digit Aggregate | E28: =SUMPRODUCT(C25:C27,E25:E27)/SUM(C25:C27) -> 0.40237083 | G28: Marketing | H28: =SUM(C31:C40) -> 5570961 | J28: =SUM('[1]MP Summary'!$D$27:$D$34) -> 0.74245076 | K28: =SUM('[2]MP Summary'!$D$27:$D$34) -> 0.75275038 | L28: =SUM('[3]MP Summary'!$D$27:$D$34) -> 0.71043867 | M28: =SUM('[4]MP Summary'!$D$27:$D$34) -> 0.69828814 | N28: =SUM('[5]MP Summary'!$D$27:$D$34) -> 0.63748275 | O28: =SUM('[6]MP Summary'!$D$27:$D$34) -> 0.67602966 | P28: =SUM('[7]MP Summary'!$D$27:$D$34) -> 0.63250132 | Q28: ='[8]MP Summary'!$P$24 -> 0.64755193 | R28: ='[9]MP Summary'!$P$24 -> 0.64755193 | S28: ='[10]MP Summary'!$R$24 -> 0.58122336 | T28: ='[11]MP Summary'!$T$24 -> 0.5346921 | U28: 0.4798608
H29: =SUM(H26:H28) -> 11706037 | J29: =SUM(J26:J28) -> 1 | K29: =SUM(K26:K28) -> 1 | L29: =SUM(L26:L28) -> 1 | M29: =SUM(M26:M28) -> 1 | N29: =SUM(N26:N28) -> 1 | O29: =SUM(O26:O28) -> 1 | P29: =SUM(P26:P28) -> 1 | Q29: =SUM(Q26:Q28) -> 1 | ... T29: =SUM(T26:T28) -> 1 | U29: 1
A30: Marketing
A31: Marketing MNDC | B31: None | C31: ='Vol Data'!$I$30 -> 2125950 | D31: =C31/$C$42 -> 0.18161142 | E31: =('MP Cost Adjustments'!$D$43*'MP Cost Adjustments'!$H$43+'MP Cost Adjustments'!$D$53*'MP Cost Adjustments'!$H$53)/('MP Cost Adjustments'!$D$43+'MP Cost Adjustments'!$D$53) -> 1.3304765 | G31: USPS-FY25-26 | J31: ='[1]Cost Pool Data'!$F$77/100 -> 1.0565508 | K31: ='[2]Cost Pool Data'!$F$77/100 -> 0.89565652 | L31: ='[3]Cost Pool Data'!$F$77/100 -> 1.2418517 | M31: ='[4]Cost Pool Data'!$F$77/100 -> 1.1281294 | N31: ='[5]Cost Pool Data'!$F$63/100 -> 1.3768074 | O31: ='[6]Cost Pool Data'!$F$63/100 -> 1.5182103 | P31: ='[7]Cost Pool Data'!$F$63/100 -> 1.1494665 | Q31: ='[8]Cost Pool Data'!$F$63/100 -> 1.4488566 | R31: ='[9]Cost Pool Data'!$F$63/100 -> 1.4518395 | S31: 1.2992236 | T31: ='[11]MP Summary'!$T$27 -> 1.5434505 | U31: ='Cost Pool Data'!F63/100 -> 1.0373367
A32: Marketing NDC | B32: None | C32: ='Vol Data'!$I$31 -> 844739 | D32: =C32/$C$42 -> 0.07216268 | E32: =('MP Cost Adjustments'!$D$44*'MP Cost Adjustments'!$H$44+'MP Cost Adjustments'!$D$54*'MP Cost Adjustments'!$H$54)/('MP Cost Adjustments'!$D$44+'MP Cost Adjustments'!$D$54) -> 1.0858395 | G32: MP Unit Cost
A33: Marketing NDC | B33: DNDC | C33: ='Vol Data'!$I$32 -> 136653 | D33: =C33/$C$42 -> 0.01167372 | E33: =('MP Cost Adjustments'!$D$45*'MP Cost Adjustments'!$H$45+'MP Cost Adjustments'!$D$55*'MP Cost Adjustments'!$H$55)/('MP Cost Adjustments'!$D$45+'MP Cost Adjustments'!$D$55) -> 1.0822498
A34: Marketing SCF | B34: None/DNDC | C34: ='Vol Data'!$I$34+'Vol Data'!I33 -> 29535 | D34: =C34/$C$42 -> 0.0025230571 | E34: =('MP Cost Adjustments'!$D$46*'MP Cost Adjustments'!$H$46+'MP Cost Adjustments'!$D$56*'MP Cost Adjustments'!$H$56)/('MP Cost Adjustments'!$D$46+'MP Cost Adjustments'!$D$56) -> 1.0387448 | G34: Percent Difference | K34: =(K31-J31)/J31 -> -0.15228257 | L34: =(L31-K31)/K31 -> 0.38652677 | M34: =(M31-L31)/L31 -> -0.091574798 | N34: =(N31-M31)/M31 -> 0.22043393 | O34: =(O31-N31)/N31 -> 0.10270349 | P34: =(P31-O31)/O31 -> -0.24288059 | Q34: =(Q31-P31)/P31 -> 0.26046001 | R34: =(R31-Q31)/Q31 -> 0.0020588504 | ... U34: =(U31-T31)/T31 -> -0.32791061
A35: Marketing SCF | B35: DSCF | C35: ='Vol Data'!$I$36 -> 126230 | D35: =C35/$C$42 -> 0.010783325 | E35: =('MP Cost Adjustments'!$D$48*'MP Cost Adjustments'!$H$48+'MP Cost Adjustments'!$D$58*'MP Cost Adjustments'!$H$58)/('MP Cost Adjustments'!$D$48+'MP Cost Adjustments'!$D$58) -> 1.0372022
A36: Marketing SCF Aggregate | E36: =SUMPRODUCT(C34:C35,E34:E35)/SUM(C34:C35) -> 1.0374947
A37: Marketing 5-Digit | B37: DNDC | C37: ='Vol Data'!I35 -> 30736 | D37: =C37/$C$42 -> 0.0026256538 | E37: =('MP Cost Adjustments'!$D$47*'MP Cost Adjustments'!$H$47+'MP Cost Adjustments'!$D$57*'MP Cost Adjustments'!$H$57)/('MP Cost Adjustments'!$D$47+'MP Cost Adjustments'!$D$57) -> 0.40988981
A38: Marketing 5-Digit | B38: DSCF | C38: ='Vol Data'!$I$37 -> 1982676 | D38: =C38/$C$42 -> 0.16937209 | E38: =('MP Cost Adjustments'!$D$49*'MP Cost Adjustments'!$H$49+'MP Cost Adjustments'!$D$59*'MP Cost Adjustments'!$H$59)/('MP Cost Adjustments'!$D$49+'MP Cost Adjustments'!$D$59) -> 0.38770436 | G38: CRA Prop. | J38: ='[1]MP Cost Adjustments'!$D$7 -> 2.3407223 | K38: ='[2]MP Cost Adjustments'!$D$7 -> 2.0172629 | L38: ='[3]MP Cost Adjustments'!$D$7 -> 2.3522076 | M38: ='[4]MP Cost Adjustments'!$D$7 -> 2.129463 | N38: ='[5]MP Cost Adjustments'!$D$7 -> 2.5005134 | O38: ='[6]MP Cost Adjustments'!$D$7 -> 2.7532281 | P38: ='[7]MP Cost Adjustments'!$D$7 -> 1.7184008 | Q38: ='[8]MP Cost Adjustments'!$D$7 -> 2.2645775 | R38: ='[9]MP Cost Adjustments'!$D$7 -> 2.1552933 | S38: ='[10]MP Cost Adjustments'!$D$7 -> 1.6520831 | T38: ='[11]MP Summary'!$T$32 -> 1.6279592 | U38: ='MP Cost Adjustments'!D7 -> 1.2422848
A39: Marketing 5-Digit | B39: DDU | C39: ='Vol Data'!$I$38 -> 294442 | D39: =C39/$C$42 -> 0.025153004 | E39: =('MP Cost Adjustments'!$D$50*'MP Cost Adjustments'!$H$50+'MP Cost Adjustments'!$D$60*'MP Cost Adjustments'!$H$60)/('MP Cost Adjustments'!$D$50+'MP Cost Adjustments'!$D$60) -> 0.35810078 | G39: Adjustment Factor
A40: Marketing 5-Digit Aggregate | E40: =SUMPRODUCT(C37:C39,E37:E39)/SUM(C37:C39) -> 0.38422293
G41: Percent Difference | K41: =(K38-J38)/J38 -> -0.13818787 | L41: =(L38-K38)/K38 -> 0.1660392 | M41: =(M38-L38)/L38 -> -0.09469597 | N41: =(N38-M38)/M38 -> 0.17424598 | O41: =(O38-N38)/N38 -> 0.10106515 | P41: =(P38-O38)/O38 -> -0.37585963 | Q41: =(Q38-P38)/P38 -> 0.31784008 | R41: =(R38-Q38)/Q38 -> -0.048258096 | ... U41: =(U38-T38)/T38 -> -0.23690667
A42: Total / Aggregate | C42: =SUM(C9:C40) -> 11706037 | D42: =SUM(D9:D40) -> 1 | E42: =SUMPRODUCT(D9:D40,E9:E40) -> 1.0373367
E44: ="[4]" -> [4]
A45: Barcode Savings Estimate | E45: ='BC Savings'!F8 -> 0.050670399
A48: Sources:
A49: [1]: Page 4
A50: [2]: Price Category [1] / Total [ 1]
A51: [3]: Page 2
A52: [4]: Page 49

Sheet MP Cost Adjustments
A1: USPS MARKETING MAIL PARCEL MAIL PROCESSING COST ADJUSTMENTS
A5: Aggregate Weighted Model Cost | D5: =SUMPRODUCT(C15:C60,E15:E60) -> 0.78718151 | E5: [1]
A6: CRA Proportional Costs | D6: ='Cost Pool Data'!G63/100 -> 0.97790362 | E6: [2]
A7: CRA Proportional Adjustment Factor | D7: =D6/D5 -> 1.2422848 | E7: [3]
A8: CRA Fixed Costs | D8: ='Cost Pool Data'!H63/100 -> 0.059433111 | E8: [4]
C10: [5] | D10: [6] | E10: [7] | F10: [8] | G10: [9] | H10: [10]
A11: Parcels | B11: Entry | C11: Model | E11: Volume | F11: Proportional | G11: Fixed | H11: Adjusted
A12: Price Category | B12: Discount | C12: Cost | D12: Volume | E12: Percent | F12: Adjustment | G12: Adjustment | H12: Unit Cost
A14: Machinable
A15: Machinable MNDC | B15: None | C15: ='M-NONE-MNDC'!J89 -> 1.0169705 | D15: ='Vol Data'!$I$20 -> 670396 | E15: =D15/$D$62 -> 0.057269253 | F15: =$D$7 -> 1.2422848 | G15: =$D$8 -> 0.059433111 | H15: =C15*F15+G15 -> 1.3228001
A16: Machinable NDC | B16: None | C16: ='M-NONE-NDC'!J84 -> 0.73272595 | D16: ='Vol Data'!$I$21 -> 400984 | E16: =D16/$D$62 -> 0.034254462 | F16: =$D$7 -> 1.2422848 | G16: =$D$8 -> 0.059433111 | H16: =C16*F16+G16 -> 0.96968742
A17: Machinable NDC | B17: DNDC | C17: ='M-DNDC-NDC'!J56 -> 0.71940612 | D17: ='Vol Data'!$I$22 -> 1729284 | E17: =D17/$D$62 -> 0.14772583 | F17: =$D$7 -> 1.2422848 | G17: =$D$8 -> 0.059433111 | H17: =C17*F17+G17 -> 0.95314039
A18: Machinable 5-Digit | B18: DNDC | C18: ='M-DNDC-5D'!J39 -> 0.30042353 | D18: ='Vol Data'!$I$23 -> 6159 | E18: =D18/$D$62 -> 0.00052613878 | F18: =$D$7 -> 1.2422848 | G18: =$D$8 -> 0.059433111 | H18: =C18*F18+G18 -> 0.4326447
A19: Machinable 5-Digit | B19: DSCF | C19: ='M-DSCF-5D'!J24 -> 0.2841236 | D19: ='Vol Data'!$I$24 -> 32567 | E19: =D19/$D$62 -> 0.0027820688 | F19: =$D$7 -> 1.2422848 | G19: =$D$8 -> 0.059433111 | H19: =C19*F19+G19 -> 0.41239554
A20: Machinable 5-Digit | B20: DDU | C20: ='M-DDU-5D'!J15 -> 0.2413159 | D20: ='Vol Data'!$I$25 -> 5446 | E20: =D20/$D$62 -> 0.00046523003 | F20: =$D$7 -> 1.2422848 | G20: =$D$8 -> 0.059433111 | H20: =C20*F20+G20 -> 0.35921618
A22: Nonstandard Rolls
A23: Nonstandard MNDC | B23: None | C23: ='IR-NONE-MNDC'!J49 -> 1.8728046 | D23: ='Vol Data'!$D$47*'Vol Data'!$I9 -> 141056.91 | E23: =D23/$D$62 -> 0.012049928 | F23: =$D$7 -> 1.2422848 | G23: =$D$8 -> 0.059433111 | H23: =C23*F23+G23 -> 2.3859898
A24: Nonstandard NDC | B24: None | C24: ='IR-NONE-NDC'!J49 -> 1.7986898 | D24: ='Vol Data'!$D$47*'Vol Data'!$I$10 -> 42448.144 | E24: =D24/$D$62 -> 0.0036261754 | F24: =$D$7 -> 1.2422848 | G24: =$D$8 -> 0.059433111 | H24: =C24*F24+G24 -> 2.2939181
A25: Nonstandard NDC | B25: DNDC | C25: ='IR-DNDC-NDC'!J21 -> 1.7905114 | D25: ='Vol Data'!$D$47*'Vol Data'!$I$11 -> 49080.241 | E25: =D25/$D$62 -> 0.004192729 | F25: =$D$7 -> 1.2422848 | G25: =$D$8 -> 0.059433111 | H25: =C25*F25+G25 -> 2.2837583
A26: Nonstandard SCF | B26: None/DNDC | C26: ='IR-DNDC-SCF'!J25 -> 1.6057618 | D26: ='Vol Data'!$D$47*('Vol Data'!$I$13+'Vol Data'!I12) -> 40649.685 | E26: =D26/$D$62 -> 0.0034725403 | F26: =$D$7 -> 1.2422848 | G26: =$D$8 -> 0.059433111 | H26: =C26*F26+G26 -> 2.0542466
A27: Nonstandard 5-Digit | B27: DNDC | C27: ='IR-DNDC-5D'!J31 -> 0.28790722 | D27: ='Vol Data'!$D$47*'Vol Data'!$I$14 -> 11653.4 | E27: =D27/$D$62 -> 0.00099550346 | F27: =$D$7 -> 1.2422848 | G27: =$D$8 -> 0.059433111 | H27: =C27*F27+G27 -> 0.41709587
A28: Nonstandard SCF | B28: DSCF | C28: ='IR-DSCF-SCF'!J18 -> 1.6022401 | D28: ='Vol Data'!$D$47*'Vol Data'!$I$15 -> 47483.577 | E28: =D28/$D$62 -> 0.0040563324 | F28: =$D$7 -> 1.2422848 | G28: =$D$8 -> 0.059433111 | H28: =C28*F28+G28 -> 2.0498716
A29: Nonstandard 5-Digit | B29: DSCF | C29: ='IR-DSCF-5D'!J24 -> 0.26893969 | D29: ='Vol Data'!$D$47*'Vol Data'!$I$16 -> 11699.872 | E29: =D29/$D$62 -> 0.00099947331 | F29: =$D$7 -> 1.2422848 | G29: =$D$8 -> 0.059433111 | H29: =C29*F29+G29 -> 0.39353279
A30: Nonstandard 5-Digit | B30: DDU | C30: ='IR -DDU-5D'!J15 -> 0.24148946 | D30: ='Vol Data'!$D$47*'Vol Data'!$I$17 -> 301.12118 | E30: =D30/$D$62 -> 2.572358e-05 | F30: =$D$7 -> 1.2422848 | G30: =$D$8 -> 0.059433111 | H30: =C30*F30+G30 -> 0.35943179
A32: Nonstandard Other
A33: Nonstandard MNDC | B33: None | C33: ='IO-NONE-MNDC'!J51 -> 1.0570275 | D33: =(1-'Vol Data'!$D$47)*'Vol Data'!$I$9 -> 1206642.1 | E33: =D33/$D$62 -> 0.10307862 | F33: =$D$7 -> 1.2422848 | G33: =$D$8 -> 0.059433111 | H33: =C33*F33+G33 -> 1.3725623
A34: Nonstandard NDC | B34: None | C34: ='IO-NONE-NDC'!J51 -> 0.98333871 | D34: =(1-'Vol Data'!$D$47)*'Vol Data'!$I$10 -> 363113.86 | E34: =D34/$D$62 -> 0.031019367 | F34: =$D$7 -> 1.2422848 | G34: =$D$8 -> 0.059433111 | H34: =C34*F34+G34 -> 1.2810198
A35: Nonstandard NDC | B35: DNDC | C35: ='IO-DNDC-NDC'!J23 -> 0.97658553 | D35: =(1-'Vol Data'!$D$47)*'Vol Data'!$I$11 -> 419846.76 | E35: =D35/$D$62 -> 0.035865832 | F35: =$D$7 -> 1.2422848 | G35: =$D$8 -> 0.059433111 | H35: =C35*F35+G35 -> 1.2726305
A36: Nonstandard SCF | B36: None/DNDC | C36: ='IO-DNDC-SCF'!J27 -> 0.79267257 | D36: =(1-'Vol Data'!$D$47)*('Vol Data'!$I$13+'Vol Data'!I12) -> 347729.31 | E36: =D36/$D$62 -> 0.029705127 | F36: =$D$7 -> 1.2422848 | G36: =$D$8 -> 0.059433111 | H36: =C36*F36+G36 -> 1.0441582
A37: Nonstandard 5-Digit | B37: DNDC | C37: ='IO-DNDC-5D'!J31 -> 0.28552937 | D37: =(1-'Vol Data'!$D$47)*'Vol Data'!$I$14 -> 99686.6 | E37: =D37/$D$62 -> 0.0085158282 | F37: =$D$7 -> 1.2422848 | G37: =$D$8 -> 0.059433111 | H37: =C37*F37+G37 -> 0.41414191
A38: Nonstandard SCF | B38: DSCF | C38: ='IO-DSCF-SCF'!J20 -> 0.78970434 | D38: =(1-'Vol Data'!$D$47)*'Vol Data'!$I$15 -> 406188.42 | E38: =D38/$D$62 -> 0.034699055 | F38: =$D$7 -> 1.2422848 | G38: =$D$8 -> 0.059433111 | H38: =C38*F38+G38 -> 1.0404708
A39: Nonstandard 5-Digit | B39: DSCF | C39: ='IO-DSCF-5D'!J24 -> 0.26707273 | D39: =(1-'Vol Data'!$D$47)*'Vol Data'!$I$16 -> 100084.13 | E39: =D39/$D$62 -> 0.0085497875 | F39: =$D$7 -> 1.2422848 | G39: =$D$8 -> 0.059433111 | H39: =C39*F39+G39 -> 0.3912135
A40: Nonstandard 5-Digit | B40: DDU | C40: ='IO-DDU-5D'!J15 -> 0.24105068 | D40: =(1-'Vol Data'!$D$47)*'Vol Data'!$I$17 -> 2575.8788 | E40: =D40/$D$62 -> 0.00022004704 | F40: =$D$7 -> 1.2422848 | G40: =$D$8 -> 0.059433111 | H40: =C40*F40+G40 -> 0.35888671
A42: Marketing Other
A43: Marketing MNDC | B43: None | C43: ='MO-NONE-MNDC'!J51 -> 1.0484017 | D43: =(1-'Vol Data'!$C$46)*'Vol Data'!$I$30 -> 929617.4 | E43: =D43/$D$62 -> 0.079413503 | F43: =$D$7 -> 1.2422848 | G43: =$D$8 -> 0.059433111 | H43: =C43*F43+G43 -> 1.3618466
A44: Marketing NDC | B44: None | C44: ='MO-NONE-NDC'!J51 -> 0.97539283 | D44: =(1-'Vol Data'!$C$46)*'Vol Data'!$I$31 -> 369380.31 | E44: =D44/$D$62 -> 0.031554685 | F44: =$D$7 -> 1.2422848 | G44: =$D$8 -> 0.059433111 | H44: =C44*F44+G44 -> 1.2711488
A45: Marketing NDC | B45: DNDC | C45: ='MO-DNDC-NDC'!J23 -> 0.97185654 | D45: =(1-'Vol Data'!$C$46)*'Vol Data'!$I$32 -> 59754.466 | E45: =D45/$D$62 -> 0.0051045854 | F45: =$D$7 -> 1.2422848 | G45: =$D$8 -> 0.059433111 | H45: =C45*F45+G45 -> 1.2667557
A46: Marketing SCF | B46: None/DNDC | C46: ='MO-DNDC-SCF'!J27 -> 0.78831495 | D46: =(1-'Vol Data'!$C$46)*('Vol Data'!$I$34+'Vol Data'!$I$33) -> 12914.815 | E46: =D46/$D$62 -> 0.001103261 | F46: =$D$7 -> 1.2422848 | G46: =$D$8 -> 0.059433111 | H46: =C46*F46+G46 -> 1.0387448
A47: Marketing 5-Digit | B47: DNDC | C47: ='MO-DNDC-5D'!J31 -> 0.28210657 | D47: =(1-'Vol Data'!$C$46)*'Vol Data'!$I$35 -> 13439.978 | E47: =D47/$D$62 -> 0.0011481236 | F47: =$D$7 -> 1.2422848 | G47: =$D$8 -> 0.059433111 | H47: =C47*F47+G47 -> 0.40988981
A48: Marketing SCF | B48: DSCF | C48: ='MO-DSCF-SCF'!J20 -> 0.78707323 | D48: =(1-'Vol Data'!$C$46)*'Vol Data'!$I$36 -> 55196.785 | E48: =D48/$D$62 -> 0.0047152409 | F48: =$D$7 -> 1.2422848 | G48: =$D$8 -> 0.059433111 | H48: =C48*F48+G48 -> 1.0372022
A49: Marketing 5-Digit | B49: DSCF | C49: ='MO-DSCF-5D'!J24 -> 0.26424798 | D49: =(1-'Vol Data'!$C$46)*'Vol Data'!$I$37 -> 866967.76 | E49: =D49/$D$62 -> 0.074061594 | F49: =$D$7 -> 1.2422848 | G49: =$D$8 -> 0.059433111 | H49: =C49*F49+G49 -> 0.38770436
A50: Marketing 5-Digit | B50: DDU | C50: ='MO-DDU-5D'!J15 -> 0.24041803 | D50: =(1-'Vol Data'!$C$46)*'Vol Data'!$I$38 -> 128751.1 | E50: =D50/$D$62 -> 0.010998693 | F50: =$D$7 -> 1.2422848 | G50: =$D$8 -> 0.059433111 | H50: =C50*F50+G50 -> 0.35810078
A52: Marketing > 6 Oz
A53: Marketing MNDC | B53: None | C53: ='M>6-NONE-MNDC'!J89 -> 1.0035277 | D53: ='Vol Data'!$C$46*'Vol Data'!$I$30 -> 1196332.6 | E53: =D53/$D$62 -> 0.10219792 | F53: =$D$7 -> 1.2422848 | G53: =$D$8 -> 0.059433111 | H53: =C53*F53+G53 -> 1.3061003
A54: Marketing NDC | B54: None | C54: ='M>6-NONE-NDC'!J84 -> 0.7103128 | D54: ='Vol Data'!$C$46*'Vol Data'!$I$31 -> 475358.69 | E54: =D54/$D$62 -> 0.040607995 | F54: =$D$7 -> 1.2422848 | G54: =$D$8 -> 0.059433111 | H54: =C54*F54+G54 -> 0.94184389
A55: Marketing NDC | B55: DNDC | C55: ='M>6-DNDC-NDC'!J56 -> 0.7079256 | D55: ='Vol Data'!$C$46*'Vol Data'!$I$32 -> 76898.534 | E55: =D55/$D$62 -> 0.0065691347 | F55: =$D$7 -> 1.2422848 | G55: =$D$8 -> 0.059433111 | H55: =C55*F55+G55 -> 0.93887832
A56: Marketing SCF | B56: None/DNDC | C56: ='M>6-DNDC-SCF'!J27 -> 0.78831495 | D56: ='Vol Data'!$C$46*('Vol Data'!$I$34+'Vol Data'!$I$33) -> 16620.185 | E56: =D56/$D$62 -> 0.0014197961 | F56: =$D$7 -> 1.2422848 | G56: =$D$8 -> 0.059433111 | H56: =C56*F56+G56 -> 1.0387448
A57: Marketing 5-Digit | B57: DNDC | C57: ='M>6-DNDC-5D'!J31 -> 0.28210657 | D57: ='Vol Data'!$C$46*'Vol Data'!$I$35 -> 17296.022 | E57: =D57/$D$62 -> 0.0014775301 | F57: =$D$7 -> 1.2422848 | G57: =$D$8 -> 0.059433111 | H57: =C57*F57+G57 -> 0.40988981
A58: Marketing SCF | B58: DSCF | C58: ='M>6-DSCF-SCF'!J20 -> 0.78707323 | D58: ='Vol Data'!$C$46*'Vol Data'!$I$36 -> 71033.215 | E58: =D58/$D$62 -> 0.0060680839 | F58: =$D$7 -> 1.2422848 | G58: =$D$8 -> 0.059433111 | H58: =C58*F58+G58 -> 1.0372022
A59: Marketing 5-Digit | B59: DSCF | C59: ='M>6-DSCF-5D'!J24 -> 0.26424798 | D59: ='Vol Data'!$C$46*'Vol Data'!$I$37 -> 1115708.2 | E59: =D59/$D$62 -> 0.0953105 | F59: =$D$7 -> 1.2422848 | G59: =$D$8 -> 0.059433111 | H59: =C59*F59+G59 -> 0.38770436
A60: Marketing 5-Digit | B60: DDU | C60: ='M>6-DDU-5D'!J15 -> 0.24041803 | D60: ='Vol Data'!$C$46*'Vol Data'!$I$38 -> 165690.9 | E60: =D60/$D$62 -> 0.014154312 | F60: =$D$7 -> 1.2422848 | G60: =$D$8 -> 0.059433111 | H60: =C60*F60+G60 -> 0.35810078
A62: Total / Aggregate | D62: =SUM(D15:D60) -> 11706037 | E62: =SUM(E15:E60) -> 1 | H62: =SUMPRODUCT(H15:H60,E15:E60) -> 1.0373367
A65: Sources:
A66: [1]: Sumproduct [5] * [7]
A67: [2]: Page 3
A68: [3]: [2] / [1]
A69: [4]: Page 3
A70: [5]: Pages 11-48
A71: [6]: Page 4
A72: [7]: Price Category [6] / Total [6]
A73: [8]: [3]
A74: [9]: [4]
A75: [10]: [5] * [8] + [9]

Sheet Cost Pool Data
A1: USPS MARKETING MAIL PARCEL MAIL PROCESSING COST POOL DATA
F4: [1] | G4: [2] | H4: [3] | I4: [4] | J4: [5] | K4: [6]
A5: Cost | I5: Volume
A6: Pool | C6: Cost Pool | D6: Proportional | E6: Fixed | F6: Total | G6: Proportional | H6: Fixed | I6: Variability | J6: Overhead | K6: Piggyback
A7: No. | B7: Source | C7: Abbreviation | D7: Costs | E7: Costs | F7: (Cents) | G7: (Cents) | H7: (Cents) | I7: Factors | J7: Factors | K7: Factors
A9: 1 | B9: MODS 11 & 15 | C9: D/BCS | E9: X | F9: ='[12]PARCEL Unit Costs W Final Adj.'!$F$6 -> 9.5842082 | G9: =F9*$G$69 -> 9.0350911 | H9: =F9*$H$69 -> 0.54911708 | I9: ='[13]8 MP Cost Pool Variabilities'!$E$9 -> 0.98913372 | J9: ='[14]VII-3a. ovhead factors-MODS1&2'!$G$9 -> 1.3893525 | K9: ='[15]MP Piggybacks'!$J$7 -> 1.7543598
A10: =A9+1 -> 2 | B10: MODS 12 & 17 | C10: AFSM100 | E10: X | F10: ='[12]PARCEL Unit Costs W Final Adj.'!$F$7 -> 0.29633707 | G10: =F10*$G$69 -> 0.27935876 | H10: =F10*$H$69 -> 0.016978319 | I10: ='[13]8 MP Cost Pool Variabilities'!$E$12 -> 0.97340818 | J10: ='[14]VII-3a. ovhead factors-MODS1&2'!$G$12 -> 1.4309838 | K10: ='[15]MP Piggybacks'!$J$8 -> 1.6305774 | L10: APBS
A11: =A10+1 -> 3 | B11: MODS 12 & 17 | C11: FSS | E11: X | F11: ='[12]PARCEL Unit Costs W Final Adj.'!$F$8 -> 0 | G11: =F11*$G$69 -> 0 | H11: =F11*$H$69 -> 0 | I11: ='[13]8 MP Cost Pool Variabilities'!$E$13 -> 0 | J11: ='[14]VII-3a. ovhead factors-MODS1&2'!$G$15 -> 0 | K11: ='[15]MP Piggybacks'!$J$9 -> 0 | L11: ='[15]MP Piggybacks'!$J$78 -> 1.6056413
A12: =A11+1 -> 4 | B12: MODS 13 | C12: APBS OTH | D12: X | F12: ='[12]PARCEL Unit Costs W Final Adj.'!$F$9 -> 3.5336098 | G12: =F12 -> 3.5336098 | I12: ='[13]8 MP Cost Pool Variabilities'!$E$16 -> 0.96403554 | J12: ='[14]VII-3a. ovhead factors-MODS1&2'!$G$18 -> 1.4847804 | K12: ='[15]MP Piggybacks'!$J$10 -> 1.6595873
A13: =A12+1 -> 5 | B13: MODS 13 | C13: APBSPRIO | D13: X | F13: ='[12]PARCEL Unit Costs W Final Adj.'!$F$10 -> 13.343898 | G13: =F13 -> 13.343898 | I13: ='[13]8 MP Cost Pool Variabilities'!$E$17 -> 0.96805898 | J13: ='[14]VII-3a. ovhead factors-MODS1&2'!$G$21 -> 1.5054165 | K13: ='[15]MP Piggybacks'!$J$11 -> 1.6636637
A14: =A13+1 -> 6 | B14: MODS 14 | C14: MANF | E14: X | F14: ='[12]PARCEL Unit Costs W Final Adj.'!$F$13 -> 0.07320992 | G14: =F14*$G$69 -> 0.069015435 | H14: =F14*$H$69 -> 0.004194485 | I14: ='[13]8 MP Cost Pool Variabilities'!$E$20 -> 0.9675812 | J14: ='[14]VII-3a. ovhead factors-MODS1&2'!$G$24 -> 1.4612893 | K14: ='[15]MP Piggybacks'!$J$14 -> 1.3622907 | L14: ='[15]MP Piggybacks'!$J$84 -> 1.8052502
A15: =A14+1 -> 7 | B15: MODS 14 | C15: MANL | E15: X | F15: ='[12]PARCEL Unit Costs W Final Adj.'!$F$14 -> 0.00047377307 | G15: =F15*$G$69 -> 0.00044662874 | H15: =F15*$H$69 -> 2.7144327e-05 | I15: ='[13]8 MP Cost Pool Variabilities'!$E$21 -> 0.97238125 | J15: ='[14]VII-3a. ovhead factors-MODS1&2'!$G$27 -> 1.3647592 | K15: ='[15]MP Piggybacks'!$J$15 -> 1.2988119 | L15: APPS (WITH REC COSTS AS INDIRECT)
A16: =A15+1 -> 8 | B16: MODS 14 | C16: MANP | D16: X | F16: ='[12]PARCEL Unit Costs W Final Adj.'!$F$15 -> 0 | G16: =F16 -> 0 | I16: ='[13]8 MP Cost Pool Variabilities'!$E$22 -> 0.97225878 | J16: ='[14]VII-3a. ovhead factors-MODS1&2'!$G$30 -> 1.4652042 | K16: ='[15]MP Piggybacks'!$J$16 -> 1.3208756
A17: =A16+1 -> 9 | B17: MODS 14 | C17: PRIORITY | E17: X | F17: ='[12]PARCEL Unit Costs W Final Adj.'!$F$16 -> 3.5705299 | G17: =F17*$G$69 -> 3.3659602 | H17: =F17*$H$69 -> 0.20456974 | I17: ='[13]8 MP Cost Pool Variabilities'!$E$23 -> 0.9614871 | J17: ='[14]VII-3a. ovhead factors-MODS1&2'!$G$33 -> 1.583582 | K17: ='[15]MP Piggybacks'!$J$17 -> 1.3673172
A18: =A17+1 -> 10 | B18: MODS 15 | C18: LD15 | E18: X | F18: ='[12]PARCEL Unit Costs W Final Adj.'!$F$17 -> 0 | G18: =F18*$G$69 -> 0 | H18: =F18*$H$69 -> 0 | I18: ='[13]8 MP Cost Pool Variabilities'!$E$25 -> 0.87303 | J18: NA | K18: ='[15]MP Piggybacks'!$J$18 -> 1.3915843
A19: =A18+1 -> 11 | B19: MODS 16 | C19: LCUS-SSM | D19: X | F19: ='[12]PARCEL Unit Costs W Final Adj.'!$F$11 -> 0.0019283303 | G19: =F19*$G$69 -> 0.0018178487 | H19: =F19*$H$69 -> 0.00011048165 | I19: ='[13]8 MP Cost Pool Variabilities'!$E$28 -> 0.95929236 | J19: ='[14]VII-3a. ovhead factors-MODS1&2'!$G$36 -> 1.4332178 | K19: ='[15]MP Piggybacks'!$J$12 -> 1.5773008
A20: =A19+1 -> 12 | B20: MODS 16 | C20: 1TRAYSRT | E20: X | F20: ='[12]PARCEL Unit Costs W Final Adj.'!$F$12 -> 0.30732048 | G20: =F20*$G$69 -> 0.28971288 | H20: =F20*$H$69 -> 0.017607602 | I20: ='[13]8 MP Cost Pool Variabilities'!$E$29 -> 0.94974595 | J20: ='[14]VII-3a. ovhead factors-MODS1&2'!$G$39 -> 1.577485 | K20: ='[15]MP Piggybacks'!$J$13 -> 1.5358045
A21: =A20+1 -> 13 | B21: MODS 17 | C21: 1CANCEL | E21: X | F21: ='[12]PARCEL Unit Costs W Final Adj.'!$F$18 -> 0.16556736 | H21: =F21 -> 0.16556736 | I21: ='[13]8 MP Cost Pool Variabilities'!$E$32 -> 0.97853723 | J21: ='[14]VII-3a. ovhead factors-MODS1&2'!$G$42 -> 1.4757547 | K21: ='[15]MP Piggybacks'!$J$19 -> 2.1937318
A22: =A21+1 -> 14 | B22: MODS 17 | C22: 1DSPATCH | E22: X | F22: ='[12]PARCEL Unit Costs W Final Adj.'!$F$19 -> 0.21112398 | H22: =F22 -> 0.21112398 | I22: ='[13]8 MP Cost Pool Variabilities'!$E$33 -> 0.96402406 | J22: ='[14]VII-3a. ovhead factors-MODS1&2'!$G$45 -> 1.6294675 | K22: ='[15]MP Piggybacks'!$J$20 -> 1.996303
A23: =A22+1 -> 15 | B23: MODS 17 | C23: 1MTRPREP | E23: X | F23: ='[12]PARCEL Unit Costs W Final Adj.'!$F$20 -> 0 | G23: =F23*$G$69 -> 0 | H23: =F23*$H$69 -> 0 | I23: ='[13]8 MP Cost Pool Variabilities'!$E$34 -> 0.95316198 | J23: ='[14]VII-3a. ovhead factors-MODS1&2'!$G$48 -> 1.35665 | K23: ='[15]MP Piggybacks'!$J$21 -> 1.4592078
A24: =A23+1 -> 16 | B24: MODS 17 | C24: 1OPBULK | E24: X | F24: ='[12]PARCEL Unit Costs W Final Adj.'!$F$21 -> 0.018926324 | G24: =F24*$G$69 -> 0.01784196 | H24: =F24*$H$69 -> 0.0010843637 | I24: ='[13]8 MP Cost Pool Variabilities'!$E$35 -> 0.98981851 | J24: ='[14]VII-3a. ovhead factors-MODS1&2'!$G$51 -> 1.5382885 | K24: ='[15]MP Piggybacks'!$J$22 -> 1.5480484
A25: =A24+1 -> 17 | B25: MODS 17 | C25: 1OPPREF | E25: X | F25: ='[12]PARCEL Unit Costs W Final Adj.'!$F$22 -> 0.18282581 | G25: =F25*$G$69 -> 0.172351 | H25: =F25*$H$69 -> 0.010474811 | I25: ='[13]8 MP Cost Pool Variabilities'!$E$36 -> 0.96735625 | J25: ='[14]VII-3a. ovhead factors-MODS1&2'!$G$54 -> 1.5365022 | K25: ='[15]MP Piggybacks'!$J$23 -> 1.3297825
A26: =A25+1 -> 18 | B26: MODS 17 | C26: 1OPTRANS | E26: X | F26: ='[12]PARCEL Unit Costs W Final Adj.'!$F$23 -> 0.11753503 | G26: =F26*$G$69 -> 0.11080099 | H26: =F26*$H$69 -> 0.0067340456 | I26: ='[13]8 MP Cost Pool Variabilities'!$E$37 -> 0.92643886 | J26: ='[14]VII-3a. ovhead factors-MODS1&2'!$G$57 -> 1.6313963 | K26: ='[15]MP Piggybacks'!$J$24 -> 1.3430299
A27: =A26+1 -> 19 | B27: MODS 17 | C27: 1PLATFRM | D27: X | F27: ='[12]PARCEL Unit Costs W Final Adj.'!$F$24 -> 15.888003 | G27: =F27*$G$69 -> 14.977716 | H27: =F27*$H$69 -> 0.91028632 | I27: ='[13]8 MP Cost Pool Variabilities'!$E$38 -> 0.91687625 | J27: ='[14]VII-3a. ovhead factors-MODS1&2'!$G$60 -> 1.4478255 | K27: ='[15]MP Piggybacks'!$J$25 -> 1.3606062
A28: =A27+1 -> 20 | B28: MODS 17 | C28: 1POUCHNG | D28: X | F28: ='[12]PARCEL Unit Costs W Final Adj.'!$F$25 -> 0.011427104 | G28: =F28*$G$69 -> 0.0107724 | H28: =F28*$H$69 -> 0.00065470385 | I28: ='[13]8 MP Cost Pool Variabilities'!$E$39 -> 0.94237641 | J28: ='[14]VII-3a. ovhead factors-MODS1&2'!$G$63 -> 1.3718328 | K28: ='[15]MP Piggybacks'!$J$26 -> 1.5985379
A29: =A28+1 -> 21 | B29: MODS 17 | C29: 1PRESORT | E29: X | F29: ='[12]PARCEL Unit Costs W Final Adj.'!$F$26 -> 0.011481221 | G29: =F29*$G$69 -> 0.010823417 | H29: =F29*$H$69 -> 0.00065780444 | I29: ='[13]8 MP Cost Pool Variabilities'!$E$40 -> 0.95326085 | J29: ='[14]VII-3a. ovhead factors-MODS1&2'!$G$66 -> 1.3920854 | K29: ='[15]MP Piggybacks'!$J$27 -> 1.3835778
A30: =A29+1 -> 22 | B30: MODS 17 | C30: 1SACKS_H | D30: X | F30: ='[12]PARCEL Unit Costs W Final Adj.'!$F$27 -> 0.050567053 | G30: =F30*$G$69 -> 0.047669867 | H30: =F30*$H$69 -> 0.0028971859 | I30: ='[13]8 MP Cost Pool Variabilities'!$E$41 -> 0.9460562 | J30: ='[14]VII-3a. ovhead factors-MODS1&2'!$G$69 -> 1.6529864 | K30: ='[15]MP Piggybacks'!$J$28 -> 1.2805163
A31: =A30+1 -> 23 | B31: MODS 17 | C31: 1SCAN | E31: X | F31: ='[12]PARCEL Unit Costs W Final Adj.'!$F$28 -> 0.24846401 | G31: =F31*$G$69 -> 0.23422853 | H31: =F31*$H$69 -> 0.014235483 | I31: ='[13]8 MP Cost Pool Variabilities'!$E$42 -> 0.98882842 | J31: ='[14]VII-3a. ovhead factors-MODS1&2'!$G$72 -> 1.5133584 | K31: ='[15]MP Piggybacks'!$J$29 -> 1.7604648
A32: =A31+1 -> 24 | B32: MODS 18 | C32: BUSREPLY | E32: X | F32: ='[12]PARCEL Unit Costs W Final Adj.'!$F$29 -> 0 | H32: =F32 -> 0 | I32: ='[13]8 MP Cost Pool Variabilities'!$E$45 -> 0.98872015 | J32: ='[14]VII-3a. ovhead factors-MODS1&2'!$G$75 -> 1.1470045 | K32: ='[15]MP Piggybacks'!$J$30 -> 1.2907912
A33: =A32+1 -> 25 | B33: MODS 18 | C33: EXPRESS | E33: X | F33: ='[12]PARCEL Unit Costs W Final Adj.'!$F$30 -> 0.00093944502 | G33: =F33*$G$69 -> 0.00088562051 | H33: =F33*$H$69 -> 5.3824509e-05 | I33: ='[13]8 MP Cost Pool Variabilities'!$E$46 -> 0.89440665 | J33: ='[14]VII-3a. ovhead factors-MODS1&2'!$G$78 -> 1.5379311 | K33: ='[15]MP Piggybacks'!$J$31 -> 1.3454732
A34: =A33+1 -> 26 | B34: MODS 18 | C34: REGISTRY | E34: X | F34: ='[12]PARCEL Unit Costs W Final Adj.'!$F$31 -> 0.0040357607 | H34: =F34 -> 0.0040357607 | I34: ='[13]8 MP Cost Pool Variabilities'!$E$47 -> 0.45629614 | J34: ='[14]VII-3a. ovhead factors-MODS1&2'!$G$81 -> 1.6743714 | K34: ='[15]MP Piggybacks'!$J$32 -> 1.4574115
A35: =A34+1 -> 27 | B35: MODS 18 | C35: REWRAP | E35: X | F35: ='[12]PARCEL Unit Costs W Final Adj.'!$F$32 -> 0.0017455899 | G35: =F35*$G$69 -> 0.0016455781 | H35: =F35*$H$69 -> 0.00010001173 | I35: ='[13]8 MP Cost Pool Variabilities'!$E$48 -> 0.96803836 | J35: ='[14]VII-3a. ovhead factors-MODS1&2'!$G$84 -> 1.4335549 | K35: ='[15]MP Piggybacks'!$J$33 -> 1.3190104
A36: =A35+1 -> 28 | B36: MODS 18 | C36: 1EEQMT | E36: X | F36: ='[12]PARCEL Unit Costs W Final Adj.'!$F$33 -> 0.37797183 | G36: =F36*$G$69 -> 0.35631633 | H36: =F36*$H$69 -> 0.021655496 | I36: ='[13]8 MP Cost Pool Variabilities'!$E$49 -> 0.98854348 | J36: ='[14]VII-3a. ovhead factors-MODS1&2'!$G$87 -> 2.8909569 | K36: ='[15]MP Piggybacks'!$J$34 -> 1.7174724
A37: =A36+1 -> 29 | B37: MODS 18 | C37: 1MISC | E37: X | F37: ='[12]PARCEL Unit Costs W Final Adj.'!$F$34 -> 0.1231653 | G37: =F37*$G$69 -> 0.11610867 | H37: =F37*$H$69 -> 0.0070566257 | I37: ='[13]8 MP Cost Pool Variabilities'!$E$50 -> 0.94447461 | J37: ='[14]VII-3a. ovhead factors-MODS1&2'!$G$90 -> 1.5458015 | K37: ='[15]MP Piggybacks'!$J$35 -> 1.2712452
A38: =A37+1 -> 30 | B38: MODS 18 | C38: 1SUPPORT | E38: X | F38: ='[12]PARCEL Unit Costs W Final Adj.'!$F$35 -> 0.13783212 | G38: =F38*$G$69 -> 0.12993517 | H38: =F38*$H$69 -> 0.0078969455 | I38: ='[13]8 MP Cost Pool Variabilities'!$E$51 -> 0.80783515 | J38: ='[14]VII-3a. ovhead factors-MODS1&2'!$G$93 -> 1.5748499 | K38: ='[15]MP Piggybacks'!$J$36 -> 1.2900243
A39: =A38+1 -> 31 | B39: All LDCs | C39: INTL ISC | E39: X | F39: ='[12]PARCEL Unit Costs W Final Adj.'!$F$36 -> 0 | H39: =F39 -> 0 | I39: ='[13]8 MP Cost Pool Variabilities'!$E$53 -> 0.91490899 | J39: ='[14]VII-3a. ovhead factors-MODS1&2'!$G$96 -> 1.4057199 | K39: ='[15]MP Piggybacks'!$J$37 -> 1.5816647
A40: =A39+1 -> 32 | B40: NDCS 12 & 17 | C40: FSS | E40: X | F40: ='[12]PARCEL Unit Costs W Final Adj.'!$F$37 -> 0 | G40: =F40*$G$69 -> 0 | H40: =F40*$H$69 -> 0 | I40: ='[13]8 MP Cost Pool Variabilities'!$E$63 -> 0 | J40: ='[14]VII-3c. Ovhead Factors NDCs'!$H$8 -> 0 | K40: ='[15]MP Piggybacks'!$J$38 -> 0
A41: =A40+1 -> 33 | B41: NDCS 14 | C41: MANP | D41: X | F41: ='[12]PARCEL Unit Costs W Final Adj.'!$F$38 -> 0.006059402 | G41: =F41 -> 0.006059402 | I41: ='[13]8 MP Cost Pool Variabilities'!$E$64 -> 0.91586806 | J41: ='[14]VII-3c. Ovhead Factors NDCs'!$H$11 -> 1.5946397 | K41: ='[15]MP Piggybacks'!$J$39 -> 1.4774317
A42: =A41+1 -> 34 | B42: NDCS All LDCs | C42: OTHR | D42: X | F42: ='[12]PARCEL Unit Costs W Final Adj.'!$F$39 -> 0.099326253 | G42: =F42 -> 0.099326253 | I42: ='[13]8 MP Cost Pool Variabilities'!$E$65 -> 0.91140966 | J42: ='[14]VII-3c. Ovhead Factors NDCs'!$H$14 -> 1.5517735 | K42: ='[15]MP Piggybacks'!$J$40 -> 1.5176144 | L42: PPSM
A43: =A42+1 -> 35 | B43: NDCS 17 | C43: PLA | D43: X | F43: ='[12]PARCEL Unit Costs W Final Adj.'!$F$40 -> 1.4548415 | G43: =F43 -> 1.4548415 | I43: ='[13]8 MP Cost Pool Variabilities'!$E$66 -> 0.88894222 | J43: ='[14]VII-3c. Ovhead Factors NDCs'!$H$17 -> 1.4041376 | K43: ='[15]MP Piggybacks'!$J$41 -> 1.3860239 | L43: ='[15]MP Piggybacks'!$J$63 -> 1.9204979
A44: =A43+1 -> 36 | B44: NDCS 13 | C44: PSM | D44: X | F44: ='[12]PARCEL Unit Costs W Final Adj.'!$F$41 -> 0.28368976 | G44: =F44 -> 0.28368976 | I44: ='[13]8 MP Cost Pool Variabilities'!$E$67 -> 0.9584975 | J44: ='[14]VII-3c. Ovhead Factors NDCs'!$H$20 -> 1.4843514 | K44: ='[15]MP Piggybacks'!$J$42 -> 2.0353663
A45: =A44+1 -> 37 | B45: NDCS 13 | C45: APBS | D45: X | F45: ='[12]PARCEL Unit Costs W Final Adj.'!$F$42 -> 5.161404 | G45: =F45 -> 5.161404 | I45: ='[13]8 MP Cost Pool Variabilities'!$E$68 -> 0.96007445 | J45: ='[14]VII-3c. Ovhead Factors NDCs'!$H$23 -> 1.5180379 | K45: ='[15]MP Piggybacks'!$J$43 -> 1.4922245 | L45: ='[15]MP Piggybacks'!$J$64 -> 2.0700178
A46: =A45+1 -> 38 | B46: NDCS 16 | C46: LCUS-SSM | D46: X | F46: ='[12]PARCEL Unit Costs W Final Adj.'!$F$43 -> 0 | G46: =F46 -> 0 | I46: ='[13]8 MP Cost Pool Variabilities'!$E$69 -> 0.928342 | J46: ='[14]VII-3c. Ovhead Factors NDCs'!$H$26 -> 1.4950151 | K46: ='[15]MP Piggybacks'!$J$44 -> 1.6196175 | L46: SPSM
A47: =A46+1 -> 39 | B47: NDCS 16 | C47: TRAYSORT | D47: X | F47: ='[12]PARCEL Unit Costs W Final Adj.'!$F$44 -> 0.0040449452 | G47: =F47 -> 0.0040449452 | I47: ='[13]8 MP Cost Pool Variabilities'!$E$70 -> 0.86648112 | J47: ='[14]VII-3c. Ovhead Factors NDCs'!$H$29 -> 1.4706735 | K47: ='[15]MP Piggybacks'!$J$45 -> 1.8711129
A48: =A47+1 -> 40 | B48: NONMODS IOCS | C48: ALLIED | D48: X | F48: ='[12]PARCEL Unit Costs W Final Adj.'!$F$45 -> 10.671249 | G48: =F48 -> 10.671249 | I48: ='[13]8 MP Cost Pool Variabilities'!$E$77 -> 0.92642031 | J48: ='[14]VII-3b. Ovhead Factrs-NonMODS'!$G$10 -> 1.6399656 | K48: ='[15]MP Piggybacks'!$J$46 -> 1.6214861
A49: =A48+1 -> 41 | B49: NONMODS IOCS | C49: AUTO/MEC | E49: X | F49: ='[12]PARCEL Unit Costs W Final Adj.'!$F$46 -> 0.99268486 | H49: =F49 -> 0.99268486 | I49: ='[13]8 MP Cost Pool Variabilities'!$E$78 -> 0.95643783 | J49: ='[14]VII-3b. Ovhead Factrs-NonMODS'!$G$11 -> 1.377564 | K49: ='[15]MP Piggybacks'!$J$47 -> 1.4978878
A50: =A49+1 -> 42 | B50: NONMODS IOCS | C50: BULKACCP | E50: X | F50: ='[12]PARCEL Unit Costs W Final Adj.'!$F$47 -> 2.3200139 | H50: =F50 -> 2.3200139 | I50: ='[13]8 MP Cost Pool Variabilities'!$E$79 -> 0.19555653 | J50: ='[14]VII-3b. Ovhead Factrs-NonMODS'!$G$12 -> 1.1836975 | K50: ='[15]MP Piggybacks'!$J$48 -> 2.7152513
A51: =A50+1 -> 43 | B51: NONMODS IOCS | C51: BUSREPLY | E51: X | F51: ='[12]PARCEL Unit Costs W Final Adj.'!$F$48 -> 0.0099018909 | G51: =F51*$G$69 -> 0.0093345725 | H51: =F51*$H$69 -> 0.00056731837 | I51: ='[13]8 MP Cost Pool Variabilities'!$E$80 -> 0.99745216 | J51: ='[14]VII-3b. Ovhead Factrs-NonMODS'!$G$13 -> 1.1805242 | K51: ='[15]MP Piggybacks'!$J$49 -> 1.594004
A52: =A51+1 -> 44 | B52: NONMODS IOCS | C52: CFS | E52: X | F52: ='[12]PARCEL Unit Costs W Final Adj.'!$F$49 -> 0.20532665 | H52: =F52 -> 0.20532665 | I52: ='[13]8 MP Cost Pool Variabilities'!$E$81 -> 1 | J52: ='[14]VII-3b. Ovhead Factrs-NonMODS'!$G$14 -> 1.1927529 | K52: ='[15]MP Piggybacks'!$J$50 -> 1.7750951
A53: =A52+1 -> 45 | B53: NONMODS IOCS | C53: D.PO BOX | E53: X | F53: ='[12]PARCEL Unit Costs W Final Adj.'!$F$50 -> 0.0036972507 | H53: =F53 -> 0.0036972507 | I53: ='[13]8 MP Cost Pool Variabilities'!$E$82 -> 0.9820365 | J53: ='[14]VII-3b. Ovhead Factrs-NonMODS'!$G$15 -> 1.1979797 | K53: ='[15]MP Piggybacks'!$J$51 -> 1.7431862
A54: =A53+1 -> 46 | B54: NONMODS IOCS | C54: EXPRESS | E54: X | F54: ='[12]PARCEL Unit Costs W Final Adj.'!$F$51 -> 0 | G54: =F54*$G$69 -> 0 | H54: =F54*$H$69 -> 0 | I54: ='[13]8 MP Cost Pool Variabilities'!$E$83 -> 0.71239829 | J54: ='[14]VII-3b. Ovhead Factrs-NonMODS'!$G$16 -> 1.2270183 | K54: ='[15]MP Piggybacks'!$J$52 -> 1.3683698
A55: =A54+1 -> 47 | B55: NONMODS IOCS | C55: MANF | E55: X | F55: ='[12]PARCEL Unit Costs W Final Adj.'!$F$52 -> 0 | G55: =F55*$G$69 -> 0 | H55: =F55*$H$69 -> 0 | I55: ='[13]8 MP Cost Pool Variabilities'!$E$84 -> 0.97377163 | J55: ='[14]VII-3b. Ovhead Factrs-NonMODS'!$G$17 -> 1.2109269 | K55: ='[15]MP Piggybacks'!$J$53 -> 1.5675507
A56: =A55+1 -> 48 | B56: NONMODS IOCS | C56: MANL | E56: X | F56: ='[12]PARCEL Unit Costs W Final Adj.'!$F$53 -> 0.03854487 | G56: =F56*$G$69 -> 0.036336482 | H56: =F56*$H$69 -> 0.0022083876 | I56: ='[13]8 MP Cost Pool Variabilities'!$E$85 -> 0.97149798 | J56: ='[14]VII-3b. Ovhead Factrs-NonMODS'!$G$18 -> 1.1979086 | K56: ='[15]MP Piggybacks'!$J$54 -> 1.4234618
A57: =A56+1 -> 49 | B57: NONMODS IOCS | C57: MANP | D57: X | F57: ='[12]PARCEL Unit Costs W Final Adj.'!$F$54 -> 29.793569 | G57: =F57 -> 29.793569 | I57: ='[13]8 MP Cost Pool Variabilities'!$E$86 -> 0.96152246 | J57: ='[14]VII-3b. Ovhead Factrs-NonMODS'!$G$19 -> 1.2883112 | K57: ='[15]MP Piggybacks'!$J$55 -> 1.4957787
A58: =A57+1 -> 50 | B58: NONMODS IOCS | C58: MISC | E58: X | F58: ='[12]PARCEL Unit Costs W Final Adj.'!$F$55 -> 4.4176014 | G58: =F58*$G$69 -> 4.1644996 | H58: =F58*$H$69 -> 0.2531018 | I58: ='[13]8 MP Cost Pool Variabilities'!$E$87 -> 0.96306144 | J58: ='[14]VII-3b. Ovhead Factrs-NonMODS'!$G$20 -> 1.2037147 | K58: ='[15]MP Piggybacks'!$J$56 -> 1.594004
A59: =A58+1 -> 51 | B59: NONMODS IOCS | C59: OTH ACCT | E59: X | F59: ='[12]PARCEL Unit Costs W Final Adj.'!$F$56 -> 0.0085913234 | H59: =F59 -> 0.0085913234 | I59: ='[13]8 MP Cost Pool Variabilities'!$E$88 -> 0.24950933 | J59: ='[14]VII-3b. Ovhead Factrs-NonMODS'!$G$21 -> 1.1783263 | K59: ='[15]MP Piggybacks'!$J$57 -> 1.594004
A60: =A59+1 -> 52 | B60: NONMODS IOCS | C60: REGISTRY | E60: X | F60: ='[12]PARCEL Unit Costs W Final Adj.'!$F$57 -> 0 | H60: =F60 -> 0 | I60: ='[13]8 MP Cost Pool Variabilities'!$E$89 -> 0.48256776 | J60: ='[14]VII-3b. Ovhead Factrs-NonMODS'!$G$22 -> 1.2329904 | K60: ='[15]MP Piggybacks'!$J$58 -> 3.5156084
F63: =SUM(F9:F60) -> 103.73367 | G63: =SUM(G9:G60) -> 97.790362 | H63: =SUM(H9:H60) -> 5.9433111
G65: =G63/$F$63 -> 0.94270606 | H65: =H63/$F$63 -> 0.057293943
A66: Sources:
A67: [1]: USPS-FY25-26
A68: [2]: USPS-FY25-26 | E68: Total Assigned | F68: =SUM(F12:F13,F16,F21:F22,F32,F34,F39,F41:F50,F52:F53,F57,F59:F60) -> 68.262733 | G68: =SUM(G12:G13,G16,G21:G22,G32,G34,G39,G41:G50,G52:G53,G57,G59:G60) -> 64.351692 | H68: =SUM(H12:H13,H16,H21:H22,H32,H34,H39,H41:H50,H52:H53,H57,H59:H60) -> 3.9110411
A69: [3]: USPS-FY25-26 | E69: (piggyback basis) | G69: =G68/F68 -> 0.94270606 | H69: =H68/F68 -> 0.057293943
A70: [4]: USPS-FY25-7, Part 6
A71: [5]: USPS-FY25-7, Part 7
A72: [6]: USPS-FY25-25

Sheet Vol Data
A1: USPS MARKETING MAIL PARCEL VOLUME DATA
C3: [1] | D3: [2] | E3: [3] | F3: [4] | G3: [5] | H3: [6] | I3: [7]
C5: Commercial | D5: Commercial | E5: Commercial | F5: Non Profit | G5: Non Profit | H5: Non Profit | I5: Grand
B6: Entry | C6: Piece-Rated | D6: Pound-Rated | E6: Total | F6: Piece-Rated | G6: Pound-Rated | H6: Total | I6: Total
A7: Price Category | B7: Discount | C7: Volume | D7: Volume | E7: Volume | F7: Volume | G7: Volume | H7: Volume | I7: Volume
A9: Nonstandard MNDC | B9: None | C9: 0 | D9: 0 | E9: =C9+D9 -> 0 | F9: =[16]Parcels!$E$113 -> 244203 | G9: =[16]Parcels!$E$130 -> 1103496 | H9: =F9+G9 -> 1347699 | I9: =E9+H9 -> 1347699
A10: Nonstandard NDC | B10: None | C10: 0 | D10: 0 | E10: =C10+D10 -> 0 | F10: =[16]Parcels!$E$115 -> 4087 | G10: =[16]Parcels!$E$132 -> 401475 | H10: =F10+G10 -> 405562 | I10: =E10+H10 -> 405562
A11: Nonstandard NDC | B11: DNDC | C11: 0 | D11: 0 | E11: =C11+D11 -> 0 | F11: =[16]Parcels!$E$116 -> 18753 | G11: =[16]Parcels!$E$133 -> 450174 | H11: =F11+G11 -> 468927 | I11: =E11+H11 -> 468927
A12: Nonstandard SCF | B12: None | C12: 0 | D12: 0 | E12: =C12+D12 -> 0 | F12: =[16]Parcels!$E$118 -> 9 | G12: =[16]Parcels!$E$135 -> 114267 | H12: =F12+G12 -> 114276 | I12: =E12+H12 -> 114276
A13: Nonstandard SCF | B13: DNDC | C13: 0 | D13: 0 | E13: =C13+D13 -> 0 | F13: =[16]Parcels!$E$119 -> 28 | G13: =[16]Parcels!$E$136 -> 274075 | H13: =F13+G13 -> 274103 | I13: =E13+H13 -> 274103
A14: Nonstandard 5-Digit | B14: DNDC | C14: 0 | D14: 0 | E14: =C14+D14 -> 0 | F14: =[16]Parcels!$E$122 -> 711 | G14: =[16]Parcels!$E$139 -> 110629 | H14: =F14+G14 -> 111340 | I14: =E14+H14 -> 111340
A15: Nonstandard SCF | B15: DSCF | C15: 0 | D15: 0 | E15: =C15+D15 -> 0 | F15: =[16]Parcels!$E$120 -> 4687 | G15: =[16]Parcels!$E$137 -> 448985 | H15: =F15+G15 -> 453672 | I15: =E15+H15 -> 453672
A16: Nonstandard 5-Digit | B16: DSCF | C16: 0 | D16: 0 | E16: =C16+D16 -> 0 | F16: =[16]Parcels!$E$123 -> 738 | G16: =[16]Parcels!$E$140 -> 111046 | H16: =F16+G16 -> 111784 | I16: =E16+H16 -> 111784
A17: Nonstandard 5-Digit | B17: DDU | C17: 0 | D17: 0 | E17: =C17+D17 -> 0 | F17: =[16]Parcels!$E$124 -> 1650 | G17: =[16]Parcels!$E$141 -> 1227 | H17: =F17+G17 -> 2877 | I17: =E17+H17 -> 2877
C18: =SUM(C9:C17) -> 0 | D18: =SUM(D9:D17) -> 0 | E18: =SUM(E9:E17) -> 0 | F18: =SUM(F9:F17) -> 274866 | G18: =SUM(G9:G17) -> 3015374 | H18: =SUM(H9:H17) -> 3290240 | I18: =SUM(I9:I17) -> 3290240
A20: Machinable MNDC | B20: None | C20: 0 | D20: 0 | E20: =C20+D20 -> 0 | F20: 0 | G20: =[16]Parcels!$E$100 -> 670396 | H20: =F20+G20 -> 670396 | I20: =E20+H20 -> 670396
A21: Machinable NDC | B21: None | C21: 0 | D21: 0 | E21: =C21+D21 -> 0 | F21: 0 | G21: =[16]Parcels!$E$102 -> 400984 | H21: =F21+G21 -> 400984 | I21: =E21+H21 -> 400984
A22: Machinable NDC | B22: DNDC | C22: 0 | D22: 0 | E22: =C22+D22 -> 0 | F22: 0 | G22: =[16]Parcels!$E$103 -> 1729284 | H22: =F22+G22 -> 1729284 | I22: =E22+H22 -> 1729284
A23: Machinable 5-Digit | B23: DNDC | C23: 0 | D23: 0 | E23: =C23+D23 -> 0 | F23: 0 | G23: =[16]Parcels!$E$105 -> 6159 | H23: =F23+G23 -> 6159 | I23: =E23+H23 -> 6159
A24: Machinable 5-Digit | B24: DSCF | C24: 0 | D24: 0 | E24: =C24+D24 -> 0 | F24: 0 | G24: =[16]Parcels!$E$106 -> 32567 | H24: =F24+G24 -> 32567 | I24: =E24+H24 -> 32567
A25: Machinable 5-Digit | B25: DDU | C25: 0 | D25: 0 | E25: =C25+D25 -> 0 | F25: 0 | G25: =[16]Parcels!$E$107 -> 5446 | H25: =F25+G25 -> 5446 | I25: =E25+H25 -> 5446
C26: =SUM(C20:C25) -> 0 | D26: =SUM(D20:D25) -> 0 | E26: =SUM(E20:E25) -> 0 | F26: =SUM(F20:F25) -> 0 | G26: =SUM(G20:G25) -> 2844836 | H26: =SUM(H20:H25) -> 2844836 | I26: =SUM(I20:I25) -> 2844836
A28: Total Parcels | C28: =C26+C18 -> 0 | D28: =D26+D18 -> 0 | E28: =E26+E18 -> 0 | F28: =F26+F18 -> 274866 | G28: =G26+G18 -> 5860210 | H28: =H26+H18 -> 6135076 | I28: =I26+I18 -> 6135076
A30: Marketing MNDC | B30: None | C30: =[16]Parcels!$E$7 -> 451593 | D30: =[16]Parcels!$E$41 -> 1119890 | E30: =C30+D30 -> 1571483 | F30: =[16]Parcels!$E$24 -> 118623 | G30: =[16]Parcels!$E$58 -> 435844 | H30: =F30+G30 -> 554467 | I30: =E30+H30 -> 2125950
A31: Marketing NDC | B31: None | C31: =[16]Parcels!$E$9 -> 92446 | D31: =[16]Parcels!$E$43 -> 642181 | E31: =C31+D31 -> 734627 | F31: =[16]Parcels!$E$26 -> 7295 | G31: =[16]Parcels!$E$60 -> 102817 | H31: =F31+G31 -> 110112 | I31: =E31+H31 -> 844739
A32: Marketing NDC | B32: DNDC | C32: =[16]Parcels!$E$10 -> 72762 | D32: =[16]Parcels!$E$44 -> 46921 | E32: =C32+D32 -> 119683 | F32: =[16]Parcels!$E$27 -> 2145 | G32: =[16]Parcels!$E$61 -> 14825 | H32: =F32+G32 -> 16970 | I32: =E32+H32 -> 136653
A33: Marketing SCF | B33: None | C33: =[16]Parcels!$E$12 -> 0 | D33: =[16]Parcels!$E$46 -> 8726 | E33: =C33+D33 -> 8726 | F33: =[16]Parcels!$E$29 -> 218 | G33: =[16]Parcels!$E$63 -> 7454 | H33: =F33+G33 -> 7672 | I33: =E33+H33 -> 16398
A34: Marketing SCF | B34: DNDC | C34: =[16]Parcels!$E$13 -> 7219 | D34: =[16]Parcels!$E$47 -> 5738 | E34: =C34+D34 -> 12957 | F34: =[16]Parcels!$E$30 -> 0 | G34: =[16]Parcels!$E$64 -> 180 | H34: =F34+G34 -> 180 | I34: =E34+H34 -> 13137
A35: Marketing 5-Digit | B35: DNDC | C35: =[16]Parcels!$E$16 -> 5413 | D35: =[16]Parcels!$E$50 -> 17426 | E35: =C35+D35 -> 22839 | F35: =[16]Parcels!$E$33 -> 5179 | G35: =[16]Parcels!$E$67 -> 2718 | H35: =F35+G35 -> 7897 | I35: =E35+H35 -> 30736
A36: Marketing SCF | B36: DSCF | C36: =[16]Parcels!$E$14 -> 43751 | D36: =[16]Parcels!$E$48 -> 63030 | E36: =C36+D36 -> 106781 | F36: =[16]Parcels!$E$31 -> 7190 | G36: =[16]Parcels!$E$65 -> 12259 | H36: =F36+G36 -> 19449 | I36: =E36+H36 -> 126230
A37: Marketing 5-Digit | B37: DSCF | C37: =[16]Parcels!$E$17 -> 1363639 | D37: =[16]Parcels!$E$51 -> 603421 | E37: =C37+D37 -> 1967060 | F37: =[16]Parcels!$E$34 -> 5859 | G37: =[16]Parcels!$E$68 -> 9757 | H37: =F37+G37 -> 15616 | I37: =E37+H37 -> 1982676
A38: Marketing 5-Digit | B38: DDU | C38: =[16]Parcels!$E$18 -> 193234 | D38: =[16]Parcels!$E$52 -> 92232 | E38: =C38+D38 -> 285466 | F38: =[16]Parcels!$E$35 -> 1116 | G38: =[16]Parcels!$E$69 -> 7860 | H38: =F38+G38 -> 8976 | I38: =E38+H38 -> 294442
A39: Total Mktg Parcels | C39: =SUM(C30:C38) -> 2230057 | D39: =SUM(D30:D38) -> 2599565 | E39: =SUM(E30:E38) -> 4829622 | F39: =SUM(F30:F38) -> 147625 | G39: =SUM(G30:G38) -> 593714 | H39: =SUM(H30:H38) -> 741339 | I39: =SUM(I30:I38) -> 5570961
A42: Grand Total | C42: =C28+C39 -> 2230057 | D42: =D28+D39 -> 2599565 | E42: =E28+E39 -> 4829622 | F42: =F28+F39 -> 422491 | G42: =G28+G39 -> 6453924 | H42: =H28+H39 -> 6876415 | I42: =I28+I39 -> 11706037
C44: [8] | D44: [9] | E44: [10]
B46: Mktg > 6 Oz Percentage | C46: =[17]MarketingMail2025!$J$77 -> 0.56272847
B47: Irregular Rolls Percentage | D47: ='[18]Miscellaneous Data'!$B$3 -> 0.10466499
B48: Marketing Mail Parcel Pounds (000s) | E48: ='[19]Adjusted RPW Rpt'!$I$32 -> 4941.206
A51: Sources:
A52: [1]: USPS-FY25-4 (The Irregular MNDC volume includes Standard Mail paid at First-Class Mail rates)
A53: [2]: USPS-FY25-4 (The Irregular MNDC volume includes Standard Mail paid at Priority Mail rates)
A54: [3]: USPS-FY25-4
A55: [4]: USPS-FY25-4
A56: [5]: USPS-FY25-4
A57: [6]: USPS-FY25-4
A58: [7]: USPS-FY25-4
A59: [8]: Special Weight Reports
A60: [9]: 2009 Standard Mail Parcel / NFM Field Study
A61: [10]: RPW

Sheet Productivity Data
A1: USPS MARKETING MAIL PARCEL PRODUCTIVITY ESTIMATES
C4: [1] | D4: [2] | E4: [3] | F4: [4] | G4: [5] | H4: [6] | I4: [7]
H6: Volume
A7: Operation | B7: Facility | C7: MODS | D7: eFlash | E7: Field Study | F7: Overhead | G7: Adjusted | H7: Variability | I7: Marginal
A8: Description | B8: Type | C8: Productivity | D8: Productivity | E8: Productivity | F8: Factor | G8: Productivity | H8: Factor | I8: Productivity
A10: APPS incoming primary sort | B10: P&DC/F | C10: ='[20]FY25 Table'!$I$62 -> 236.38446 | D10: ="---" -> --- | E10: ="---" -> --- | F10: ="---" -> --- | G10: ="---" -> --- | H10: ='Cost Pool Data'!$I$12 -> 0.96403554 | I10: =C10/H10 -> 245.20306
A11: APBS / LIPS incoming primary sort | B11: P&DC/F | C11: =('[20]FY25 Table'!$F$59+'[20]FY25 Table'!$F$60)/('[20]FY25 Table'!$H$59+'[20]FY25 Table'!$H$60) -> 183.94301 | D11: ="---" -> --- | E11: ="---" -> --- | F11: ="---" -> --- | G11: ="---" -> --- | H11: ='Cost Pool Data'!$I$12 -> 0.96403554 | I11: =C11/H11 -> 190.80521
A12: Outgoing Tray Sort | B12: P&DC/F | C12: ='[20]FY25 Table'!$I$11 -> 85.837148 | D12: ="---" -> --- | E12: ="---" -> --- | F12: ="---" -> --- | G12: ="---" -> --- | H12: ='Cost Pool Data'!$I$20 -> 0.94974595 | I12: =C12/H12 -> 90.379062
A13: Incoming Tray Sort | B13: P&DC/F | C13: ='[20]FY25 Table'!$I$12 -> 60.943313 | D13: ="---" -> --- | E13: ="---" -> --- | F13: ="---" -> --- | G13: ="---" -> --- | H13: ='Cost Pool Data'!$I$20 -> 0.94974595 | I13: =C13/H13 -> 64.168016
A14: Sack Manual Sort | B14: P&DC/F | C14: ='[20]FY25 Table'!$I$57 -> 46.663259 | D14: ="---" -> --- | E14: ="---" -> --- | F14: ="---" -> --- | G14: ="---" -> --- | H14: ='Cost Pool Data'!$I$30 -> 0.9460562 | I14: =C14/H14 -> 49.323982
A15: NMO Manual Sort | B15: P&DC/F | C15: ='[20]FY25 Table'!$I$57 -> 46.663259 | D15: ="---" -> --- | E15: ="---" -> --- | F15: ="---" -> --- | G15: ="---" -> --- | H15: ='Cost Pool Data'!$I$16 -> 0.97225878 | I15: =C15/H15 -> 47.99469
A16: IPP Manual Sort | B16: P&DC/F | C16: ='[20]FY25 Table'!$I$57 -> 46.663259 | D16: ="---" -> --- | E16: ="---" -> --- | F16: ="---" -> --- | G16: ="---" -> --- | H16: ='Cost Pool Data'!$I$16 -> 0.97225878 | I16: =C16/H16 -> 47.99469
A17: Primary Parcel Sorting Machine (PPSM) | B17: NDC | C17: ='[21]Table FY25'!$I$8 -> 392.67992 | D17: ="---" -> --- | E17: ="---" -> --- | F17: ="---" -> --- | G17: ="---" -> --- | H17: ='Cost Pool Data'!$I$44 -> 0.9584975 | I17: =C17/H17 -> 409.68278
A18: Secondary Parcel Sorting Machine (SPSM) | B18: NDC | C18: ='[21]Table FY25'!$I$9 -> 317.61234 | D18: ="---" -> --- | E18: ="---" -> --- | F18: ="---" -> --- | G18: ="---" -> --- | H18: ='Cost Pool Data'!$I$44 -> 0.9584975 | I18: =C18/H18 -> 331.3648
A19: Sack Sorting Machine (SSM) | B19: NDC | C19: ='[21]Table FY25'!$I$10 -> 2848.2562 | D19: ="---" -> --- | E19: ="---" -> --- | F19: ="---" -> --- | G19: ="---" -> --- | H19: ='Cost Pool Data'!$I$46 -> 0.928342 | I19: =C19/H19 -> 3068.1109
A20: NMO Manual Sort | B20: NDC | C20: ='[21]Table FY25'!$I$11 -> 48.365822 | D20: ="---" -> --- | E20: ="---" -> --- | F20: ="---" -> --- | G20: ="---" -> --- | H20: ='Cost Pool Data'!$I$41 -> 0.91586806 | I20: =C20/H20 -> 52.808722
A21: IPP manual sort | B21: NDC | C21: ='[21]Table FY25'!$I$12 -> 368.91057 | D21: ="---" -> --- | E21: ="---" -> --- | F21: ="---" -> --- | G21: ="---" -> --- | H21: ='Cost Pool Data'!$I$41 -> 0.91586806 | I21: =C21/H21 -> 402.79881
A22: Incoming Secondary Parcel Sort | B22: DU | C22: ="---" -> --- | D22: ='[22]FY25 F4 Manual Productivity'!$D$6 -> 295.82991 | E22: ="---" -> --- | F22: ="---" -> --- | G22: ="---" -> --- | H22: ='Cost Pool Data'!$I$57 -> 0.96152246 | I22: =D22/H22 -> 307.66823
A23: Load Rolling Stock | B23: DU | C23: ="---" -> --- | D23: ="---" -> --- | E23: ='[23]Productivity Summary'!$E$7 -> 104.16918 | F23: ='Cost Pool Data'!$J$48 -> 1.6399656 | G23: =E23/F23 -> 63.519123 | H23: ='Cost Pool Data'!$I$48 -> 0.92642031 | I23: =G23/H23 -> 68.564044
A24: Load Pallet / Pallet Box | B24: DU | C24: ="---" -> --- | D24: ="---" -> --- | E24: ='[23]Productivity Summary'!$E$8 -> 65.538639 | F24: ='Cost Pool Data'!$J$48 -> 1.6399656 | G24: =E24/F24 -> 39.963423 | H24: ='Cost Pool Data'!$I$48 -> 0.92642031 | I24: =G24/H24 -> 43.137464
A25: Unload Rolling Stock | B25: DU | C25: ="---" -> --- | D25: ="---" -> --- | E25: ='[23]Productivity Summary'!$E$9 -> 91.663152 | F25: ='Cost Pool Data'!$J$48 -> 1.6399656 | G25: =E25/F25 -> 55.893338 | H25: ='Cost Pool Data'!$I$48 -> 0.92642031 | I25: =G25/H25 -> 60.332591
A26: Unload Pallet / Pallet Box | B26: DU | C26: ="---" -> --- | D26: ="---" -> --- | E26: ='[23]Productivity Summary'!$E$10 -> 73.807993 | F26: ='Cost Pool Data'!$J$48 -> 1.6399656 | G26: =E26/F26 -> 45.005818 | H26: ='Cost Pool Data'!$I$48 -> 0.92642031 | I26: =G26/H26 -> 48.580344
A27: Unload Rolling Stock | B27: P&DC/F | C27: ="---" -> --- | D27: ="---" -> --- | E27: ='[23]Productivity Summary'!$E$12 -> 108.68527 | F27: ='Cost Pool Data'!$J$27 -> 1.4478255 | G27: =E27/F27 -> 75.067934 | H27: ='Cost Pool Data'!$I$27 -> 0.91687625 | I27: =G27/H27 -> 81.873572
A28: Unload Pallet / Pallet Box | B28: P&DC/F | C28: ="---" -> --- | D28: ="---" -> --- | E28: ='[23]Productivity Summary'!$E$13 -> 77.202049 | F28: ='Cost Pool Data'!$J$27 -> 1.4478255 | G28: =E28/F28 -> 53.322759 | H28: ='Cost Pool Data'!$I$27 -> 0.91687625 | I28: =G28/H28 -> 58.156985
A29: Crossdock Rolling Stock | B29: P&DC/F | C29: ="---" -> --- | D29: ="---" -> --- | E29: ='[23]Productivity Summary'!$E$14 -> 67.388557 | F29: ='Cost Pool Data'!$J$27 -> 1.4478255 | G29: =E29/F29 -> 46.544668 | H29: ='Cost Pool Data'!$I$27 -> 0.91687625 | I29: =G29/H29 -> 50.764395
A30: Crossdock Pallet / Pallet box | B30: P&DC/F | C30: ="---" -> --- | D30: ="---" -> --- | E30: ='[23]Productivity Summary'!$E$15 -> 52.96533 | F30: ='Cost Pool Data'!$J$27 -> 1.4478255 | G30: =E30/F30 -> 36.582676 | H30: ='Cost Pool Data'!$I$27 -> 0.91687625 | I30: =G30/H30 -> 39.899251
A31: Load Rolling Stock | B31: P&DC/F | C31: ="---" -> --- | D31: ="---" -> --- | E31: ='[23]Productivity Summary'!$E$16 -> 120.89542 | F31: ='Cost Pool Data'!$J$27 -> 1.4478255 | G31: =E31/F31 -> 83.501376 | H31: ='Cost Pool Data'!$I$27 -> 0.91687625 | I31: =G31/H31 -> 91.071588
A32: Load Pallet / Pallet Box | B32: P&DC/F | C32: ="---" -> --- | D32: ="---" -> --- | E32: ='[23]Productivity Summary'!$E$17 -> 81.943084 | F32: ='Cost Pool Data'!$J$27 -> 1.4478255 | G32: =E32/F32 -> 56.597349 | H32: ='Cost Pool Data'!$I$27 -> 0.91687625 | I32: =G32/H32 -> 61.728449
A33: Unload Rolling Stock | B33: ASF | C33: ="---" -> --- | D33: ="---" -> --- | E33: ='[23]Productivity Summary'!$E$18 -> 99.080107 | F33: ='Cost Pool Data'!$J$27 -> 1.4478255 | G33: =E33/F33 -> 68.433736 | H33: ='Cost Pool Data'!$I$27 -> 0.91687625 | I33: =G33/H33 -> 74.63792
A34: Unload Pallet / Pallet Box | B34: ASF | C34: ="---" -> --- | D34: ="---" -> --- | E34: ='[23]Productivity Summary'!$E$19 -> 78.22115 | F34: ='Cost Pool Data'!$J$27 -> 1.4478255 | G34: =E34/F34 -> 54.026643 | H34: ='Cost Pool Data'!$I$27 -> 0.91687625 | I34: =G34/H34 -> 58.924683
A35: Load Rolling Stock | B35: ASF | C35: ="---" -> --- | D35: ="---" -> --- | E35: ='[23]Productivity Summary'!$E$20 -> 108.93754 | F35: ='Cost Pool Data'!$J$27 -> 1.4478255 | G35: =E35/F35 -> 75.242174 | H35: ='Cost Pool Data'!$I$27 -> 0.91687625 | I35: =G35/H35 -> 82.063609
A36: Load Pallet / Pallet Box | B36: ASF | C36: ="---" -> --- | D36: ="---" -> --- | E36: ='[23]Productivity Summary'!$E$21 -> 76.602997 | F36: ='Cost Pool Data'!$J$27 -> 1.4478255 | G36: =E36/F36 -> 52.908999 | H36: ='Cost Pool Data'!$I$27 -> 0.91687625 | I36: =G36/H36 -> 57.705714
A37: Unload Rolling Stock | B37: NDC | C37: ="---" -> --- | D37: ="---" -> --- | E37: ='[23]Productivity Summary'!$E$22 -> 69.89497 | F37: ='Cost Pool Data'!$J$43 -> 1.4041376 | G37: =E37/F37 -> 49.777864 | H37: ='Cost Pool Data'!$I$43 -> 0.88894222 | I37: =G37/H37 -> 55.996737
A38: Unload Pallet / Pallet Box | B38: NDC | C38: ="---" -> --- | D38: ="---" -> --- | E38: ='[23]Productivity Summary'!$E$23 -> 58.010029 | F38: ='Cost Pool Data'!$J$43 -> 1.4041376 | G38: =E38/F38 -> 41.313636 | H38: ='Cost Pool Data'!$I$43 -> 0.88894222 | I38: =G38/H38 -> 46.475052
A39: Unload Postal Pak | B39: NDC | C39: ="---" -> --- | D39: ="---" -> --- | E39: ='[23]Productivity Summary'!$E$24 -> 66.337249 | F39: ='Cost Pool Data'!$J$43 -> 1.4041376 | G39: =E39/F39 -> 47.244123 | H39: ='Cost Pool Data'!$I$43 -> 0.88894222 | I39: =G39/H39 -> 53.14645
A40: Induct Rolling Stock | B40: NDC | C40: ="---" -> --- | D40: ="---" -> --- | E40: ='[23]Productivity Summary'!$E$25 -> 32.62217 | F40: ='Cost Pool Data'!$J$42 -> 1.5517735 | G40: =E40/F40 -> 21.022507 | H40: ='Cost Pool Data'!$I$42 -> 0.91140966 | I40: =G40/H40 -> 23.065925
A41: Induct Pallet / Pallet Box | B41: NDC | C41: ="---" -> --- | D41: ="---" -> --- | E41: ='[23]Productivity Summary'!$E$26 -> 23.313312 | F41: ='Cost Pool Data'!$J$42 -> 1.5517735 | G41: =E41/F41 -> 15.023656 | H41: ='Cost Pool Data'!$I$42 -> 0.91140966 | I41: =G41/H41 -> 16.483977
A42: Induct Postal Pak | B42: NDC | C42: ="---" -> --- | D42: ="---" -> --- | E42: ='[23]Productivity Summary'!$E$27 -> 23.543443 | F42: ='Cost Pool Data'!$J$42 -> 1.5517735 | G42: =E42/F42 -> 15.171958 | H42: ='Cost Pool Data'!$I$42 -> 0.91140966 | I42: =G42/H42 -> 16.646694
A43: Sack Shake Out | B43: NDC | C43: ="---" -> --- | D43: ="---" -> --- | E43: ='[23]Productivity Summary'!$E$28 -> 207.56223 | F43: ='Cost Pool Data'!$J$42 -> 1.5517735 | G43: =E43/F43 -> 133.75807 | H43: ='Cost Pool Data'!$I$42 -> 0.91140966 | I43: =G43/H43 -> 146.75955
A44: Load Rolling Stock | B44: NDC | C44: ="---" -> --- | D44: ="---" -> --- | E44: ='[23]Productivity Summary'!$E$29 -> 88.133733 | F44: ='Cost Pool Data'!$J$43 -> 1.4041376 | G44: =E44/F44 -> 62.767163 | H44: ='Cost Pool Data'!$I$43 -> 0.88894222 | I44: =G44/H44 -> 70.608822
A45: Load Pallet / Pallet Box | B45: NDC | C45: ="---" -> --- | D45: ="---" -> --- | E45: ='[23]Productivity Summary'!$E$30 -> 69.377616 | F45: ='Cost Pool Data'!$J$43 -> 1.4041376 | G45: =E45/F45 -> 49.409414 | H45: ='Cost Pool Data'!$I$43 -> 0.88894222 | I45: =G45/H45 -> 55.582256
A46: Load Postal Pak | B46: NDC | C46: ="---" -> --- | D46: ="---" -> --- | E46: ='[23]Productivity Summary'!$E$31 -> 25.976476 | F46: ='Cost Pool Data'!$J$43 -> 1.4041376 | G46: =E46/F46 -> 18.49995 | H46: ='Cost Pool Data'!$I$43 -> 0.88894222 | I46: =G46/H46 -> 20.811195
A47: Manually Apply Barcode Label | B47: NDC | C47: ="---" -> --- | D47: ="---" -> --- | E47: ='[23]Productivity Summary'!$E$32 -> 313.09994 | F47: ='Cost Pool Data'!$J$42 -> 1.5517735 | G47: =E47/F47 -> 201.76909 | H47: ='Cost Pool Data'!$I$42 -> 0.91140966 | I47: =G47/H47 -> 221.38134
A50: Sources:
A51: [1]: USPS-FY25-23
A52: [2]: Docket No. RM2025-4 Order No. 8713 (February 21, 2025)
A53: [3]: 2014 Parcel Field Study
A54: [4]: Page 3
A55: [5]: [3] / [4]
A56: [6]: Page 3
A57: [7]: [1] / [6] (MODS Productivity), [2] / [6] (eFlash Productivity), or [5] / [6] (Field Study Productivity)

Sheet Wage Data
A1: USPS MARKETING MAIL PARCEL WAGE DATA
B3: [1] | C3: [2]
A5: Description | B5: Value | C5: Value
A7: Other Mail Processing Wage Rate | B7: ='[24]Disaggregated wage rates'!$C$8 -> 50.107175
A9: Premium Pay Factor | B9: ='[24]Premium Pay Fctrs'!$D$22 -> 0.98098316
A11: Adjusted Mail Processing Wage Rate | C11: =B7*B9 -> 49.154295
A14: Sources:
A15: [1]: USPS-FY25-7, Part 8 (wage rate) and Part 5 (premium Pay factor)
A16: [2]: Other Mail Processing Wage Rate * Premium Pay Factor

Sheet Mailer Arrival Profile
A1: USPS MARKETING MAIL PARCEL MAILER CONTAINER ARRIVAL PROFILE
C4: [1] | D4: [2] | E4: [3] | F4: [4] | G4: [5] | I4: [6]
A5: Standard Parcels | B5: Entry | C5: Pallet Box | D5: Pallet (Pieces) | E5: Pallet (Sacks) | F5: Sack | G5: Total | I5: Pieces Per
A6: Price Category | B6: Discount | C6: Percent | D6: Percent | E6: Percent | F6: Percent | G6: Percent | I6: Sack
A8: Machinable MNDC | B8: None | C8: ='[18]Arrival Profile Summary'!$C$36 -> 0.026058632 | D8: ='[18]Arrival Profile Summary'!$D$36 -> 0.97394137 | E8: ='[18]Arrival Profile Summary'!$E$36 -> 0 | F8: ='[18]Arrival Profile Summary'!$F$36 -> 0 | G8: =SUM(C8:F8) -> 1 | I8: ="---" -> ---
A9: Machinable NDC | B9: None | C9: ='[18]Arrival Profile Summary'!$C$37 -> 1 | D9: ='[18]Arrival Profile Summary'!$D$37 -> 0 | E9: ='[18]Arrival Profile Summary'!$E$37 -> 0 | F9: ='[18]Arrival Profile Summary'!$F$37 -> 0 | G9: =SUM(C9:F9) -> 1 | I9: ="---" -> ---
A10: Machinable NDC | B10: DNDC | C10: ='[18]Arrival Profile Summary'!$C$38 -> 0.49310796 | D10: ='[18]Arrival Profile Summary'!$D$38 -> 0.46621265 | E10: ='[18]Arrival Profile Summary'!$E$38 -> 0.012311105 | F10: ='[18]Arrival Profile Summary'!$F$38 -> 0.028368278 | G10: =SUM(C10:F10) -> 1 | I10: ='[18]Sack Pieces Summary'!$C$10 -> 17.04918
A11: Machinable 5-Digit | B11: DNDC | C11: ='[18]Arrival Profile Summary'!$C$39 -> 0 | D11: ='[18]Arrival Profile Summary'!$D$39 -> 0.045113611 | E11: ='[18]Arrival Profile Summary'!$E$39 -> 0.95488639 | F11: ='[18]Arrival Profile Summary'!$F$39 -> 0 | G11: =SUM(C11:F11) -> 1 | I11: ='[18]Sack Pieces Summary'!$C$11 -> 33.104839
A12: Machinable 5-Digit | B12: DSCF | C12: ='[18]Arrival Profile Summary'!$C$40 -> 0.094705277 | D12: ='[18]Arrival Profile Summary'!$D$40 -> 0.03893837 | E12: ='[18]Arrival Profile Summary'!$E$40 -> 0.83717495 | F12: ='[18]Arrival Profile Summary'!$F$40 -> 0.029181399 | G12: =SUM(C12:F12) -> 1 | I12: ='[18]Sack Pieces Summary'!$C$12 -> 33.104839
A13: Machinable 5-Digit | B13: DDU | C13: ='[18]Arrival Profile Summary'!$C$41 -> 0 | D13: ='[18]Arrival Profile Summary'!$D$41 -> 0.5384801 | E13: ='[18]Arrival Profile Summary'!$E$41 -> 0 | F13: ='[18]Arrival Profile Summary'!$F$41 -> 0.4615199 | G13: =SUM(C13:F13) -> 1 | I13: ='[18]Sack Pieces Summary'!$C$13 -> 22.77381
A15: Nonstandard MNDC | B15: None | C15: ='[18]Arrival Profile Summary'!$C$43 -> 0.39277926 | D15: ='[18]Arrival Profile Summary'!$D$43 -> 0.55270172 | E15: ='[18]Arrival Profile Summary'!$E$43 -> 0 | F15: ='[18]Arrival Profile Summary'!$F$43 -> 0.054519021 | G15: =SUM(C15:F15) -> 1 | I15: ='[18]Sack Pieces Summary'!$C$15 -> 45
A16: Nonstandard NDC | B16: None | C16: ='[18]Arrival Profile Summary'!$C$44 -> 0.16173007 | D16: ='[18]Arrival Profile Summary'!$D$44 -> 0.68745985 | E16: ='[18]Arrival Profile Summary'!$E$44 -> 0.096709728 | F16: ='[18]Arrival Profile Summary'!$F$44 -> 0.05410035 | G16: =SUM(C16:F16) -> 1 | I16: ='[18]Sack Pieces Summary'!$C$16 -> 50.533333
A17: Nonstandard NDC | B17: DNDC | C17: ='[18]Arrival Profile Summary'!$C$45 -> 0.16173007 | D17: ='[18]Arrival Profile Summary'!$D$45 -> 0.68745985 | E17: ='[18]Arrival Profile Summary'!$E$45 -> 0.096709728 | F17: ='[18]Arrival Profile Summary'!$F$45 -> 0.05410035 | G17: =SUM(C17:F17) -> 1 | I17: ='[18]Sack Pieces Summary'!$C$17 -> 50.533333
A18: Nonstandard SCF | B18: DNDC | C18: ='[18]Arrival Profile Summary'!$C$46 -> 0 | D18: ='[18]Arrival Profile Summary'!$D$46 -> 0 | E18: ='[18]Arrival Profile Summary'!$E$46 -> 1 | F18: ='[18]Arrival Profile Summary'!$F$46 -> 0 | G18: =SUM(C18:F18) -> 1 | I18: ='[18]Sack Pieces Summary'!$C$18 -> 78.272727
A19: Nonstandard 5-Digit | B19: DNDC | C19: ='[18]Arrival Profile Summary'!$C$47 -> 0 | D19: ='[18]Arrival Profile Summary'!$D$47 -> 0 | E19: ='[18]Arrival Profile Summary'!$E$47 -> 0.77812317 | F19: ='[18]Arrival Profile Summary'!$F$47 -> 0.22187683 | G19: =SUM(C19:F19) -> 1 | I19: ='[18]Sack Pieces Summary'!$C$19 -> 36.926829
A20: Nonstandard SCF | B20: DSCF | C20: ='[18]Arrival Profile Summary'!$C$48 -> 0.039651767 | D20: ='[18]Arrival Profile Summary'!$D$48 -> 0.047479699 | E20: ='[18]Arrival Profile Summary'!$E$48 -> 0 | F20: ='[18]Arrival Profile Summary'!$F$48 -> 0.91286853 | G20: =SUM(C20:F20) -> 1 | I20: ='[18]Sack Pieces Summary'!$C$20 -> 89.82684
A21: Nonstandard 5-Digit | B21: DSCF | C21: ='[18]Arrival Profile Summary'!$C$49 -> 0 | D21: ='[18]Arrival Profile Summary'!$D$49 -> 0 | E21: ='[18]Arrival Profile Summary'!$E$49 -> 0.77812317 | F21: ='[18]Arrival Profile Summary'!$F$49 -> 0.22187683 | G21: =SUM(C21:F21) -> 1 | I21: ='[18]Sack Pieces Summary'!$C$21 -> 66.275974
A22: Nonstandard 5-Digit | B22: DDU | C22: ='[18]Arrival Profile Summary'!$C$50 -> 0 | D22: ='[18]Arrival Profile Summary'!$D$50 -> 0 | E22: ='[18]Arrival Profile Summary'!$E$50 -> 0 | F22: ='[18]Arrival Profile Summary'!$F$50 -> 1 | G22: =SUM(C22:F22) -> 1 | I22: ='[18]Sack Pieces Summary'!$C$22 -> 36.926829
A24: Marketing MNDC | B24: None | C24: ='[18]Arrival Profile Summary'!$C$52 -> 0.024763879 | D24: ='[18]Arrival Profile Summary'!$D$52 -> 0.81674729 | E24: ='[18]Arrival Profile Summary'!$E$52 -> 0.11011288 | F24: ='[18]Arrival Profile Summary'!$F$52 -> 0.04837595 | G24: =SUM(C24:F24) -> 1 | I24: ='[18]Sack Pieces Summary'!$C$24 -> 45
A25: Marketing NDC | B25: None | C25: ='[18]Arrival Profile Summary'!$C$53 -> 0.10645613 | D25: ='[18]Arrival Profile Summary'!$D$53 -> 0.86712085 | E25: ='[18]Arrival Profile Summary'!$E$53 -> 0 | F25: ='[18]Arrival Profile Summary'!$F$53 -> 0.026423023 | G25: =SUM(C25:F25) -> 1 | I25: ='[18]Sack Pieces Summary'!$C$25 -> 50.533333
A26: Marketing NDC | B26: DNDC | C26: ='[18]Arrival Profile Summary'!$C$54 -> 0.011095126 | D26: ='[18]Arrival Profile Summary'!$D$54 -> 0.86038451 | E26: ='[18]Arrival Profile Summary'!$E$54 -> 0.0014822565 | F26: ='[18]Arrival Profile Summary'!$F$54 -> 0.1270381 | G26: =SUM(C26:F26) -> 1 | I26: ='[18]Sack Pieces Summary'!$C$26 -> 50.533333
A27: Marketing SCF | B27: DNDC | C27: ='[18]Arrival Profile Summary'!$C$55 -> 0 | D27: ='[18]Arrival Profile Summary'!$D$55 -> 1 | E27: ='[18]Arrival Profile Summary'!$E$55 -> 0 | F27: ='[18]Arrival Profile Summary'!$F$55 -> 0 | G27: =SUM(C27:F27) -> 1 | I27: ="---" -> ---
A28: Marketing 5-Digit | B28: DNDC | C28: ='[18]Arrival Profile Summary'!$C$56 -> 0 | D28: ='[18]Arrival Profile Summary'!$D$56 -> 0 | E28: ='[18]Arrival Profile Summary'!$E$56 -> 1 | F28: ='[18]Arrival Profile Summary'!$F$56 -> 0 | G28: =SUM(C28:F28) -> 1 | I28: ='[18]Sack Pieces Summary'!$C$28 -> 36.926829
A29: Marketing SCF | B29: DSCF | C29: ='[18]Arrival Profile Summary'!$C$57 -> 0 | D29: ='[18]Arrival Profile Summary'!$D$57 -> 0 | E29: ='[18]Arrival Profile Summary'!$E$57 -> 0 | F29: ='[18]Arrival Profile Summary'!$F$57 -> 1 | G29: =SUM(C29:F29) -> 1 | I29: ='[18]Sack Pieces Summary'!$C$29 -> 89.82684
A30: Marketing 5-Digit | B30: DSCF | C30: ='[18]Arrival Profile Summary'!$C$58 -> 0 | D30: ='[18]Arrival Profile Summary'!$D$58 -> 0 | E30: ='[18]Arrival Profile Summary'!$E$58 -> 0 | F30: ='[18]Arrival Profile Summary'!$F$58 -> 1 | G30: =SUM(C30:F30) -> 1 | I30: ='[18]Sack Pieces Summary'!$C$30 -> 66.275974
A31: Marketing 5-Digit | B31: DDU | C31: ='[18]Arrival Profile Summary'!$C$59 -> 0 | D31: ='[18]Arrival Profile Summary'!$D$59 -> 0 | E31: ='[18]Arrival Profile Summary'!$E$59 -> 0 | F31: ='[18]Arrival Profile Summary'!$F$59 -> 1 | G31: =SUM(C31:F31) -> 1 | I31: ='[18]Sack Pieces Summary'!$C$31 -> 36.926829
G33: Average Pieces Per Sack | I33: =(I10*'MP Summary'!D11+I11*'MP Summary'!D12+I12*'MP Summary'!D13+I13*'MP Summary'!D14+I15*'MP Summary'!D19+I16^'MP Summary'!D20+I17*'MP Summary'!D21+I18*'MP Summary'!D22+I19*'MP Summary'!D25+I20*'MP Summary'!D26+I21*'MP Summary'!D27+I22*'MP Summary'!D28+I24*'MP Summary'!D31+I25*'MP Summary'!D32+I26*'MP Summary'!D33+I28*'MP Summary'!D37+I29*'MP Summary'!D38+I30*'MP Summary'!D39+I31*'MP Summary'!D40)/((SUM('MP Summary'!D9:D40)-'MP Summary'!D9-'MP Summary'!D10-'MP Summary'!D34)) -> 48.787028
B35: [7] | C35: [8]
B36: Average | C36: Average
A37: Mailer Arrival | B37: Height | C37: Percent
A38: Container Type | B38: (Inches) | C38: Full
A40: Pallet Box | B40: ='[18]Container Statistics'!$B$8 -> 45.309278 | C40: ='[18]Container Statistics'!$C$8 -> 0.82439863
A41: Pallet | B41: ='[18]Container Statistics'!$B$9 -> 38.478261 | C41: ='[18]Container Statistics'!$C$9 -> 1
A42: APC With Sacks | B42: --- | C42: ='[18]Container Statistics'!$C$10 -> 0.9
C44: [9] | D44: [10]
C45: Non-Marketing | D45: Marketing
A46: Nondropship Entry Point | C46: Percent | D46: Percent
A47: DU | C47: 0.43072278 | D47: 0.19092012
A48: P&DC/F | C48: 0.2157048 | D48: 0.35983935
A49: NDC | C49: 0.35357241 | D49: 0.44924053
C50: =SUM(C47:C49) -> 1 | D50: =SUM(D47:D49) -> 1
A53: Sources:
A54: [1]: 2009 Standard Mail Parcel / NFM Field Study
A55: [2]: 2009 Standard Mail Parcel / NFM Field Study
A56: [3]: 2009 Standard Mail Parcel / NFM Field Study
A57: [4]: 2009 Standard Mail Parcel / NFM Field Study
A58: [5]: 2009 Standard Mail Parcel / NFM Field Study
A59: [6]: 2009 Standard Mail Parcel / NFM Field Study
A60: Average Pieces Per Sack calculated using volume percentages from page 1
A61: [7]: 2009 Standard Mail Parcel / NFM Field Study
A62: [8]: 2009 Standard Mail Parcel / NFM Field Study
A63: [9]: 2010 PostalOne! Mailing Statement Data
A64: [10]: 2010 PostalOne! Mailing Statement Data

Sheet Postal Arrival-Dispatch Profile
A1: USPS MARKETING MAIL PARCEL POSTAL CONTAINER ARRIVAL / DISPATCH PROFILE
B3: [1] | C3: [2]
C4: Average
A5: Postal Arrival | B5: Percent | C5: Percent
A6: Container Type | B6: Cu Ft | C6: Full
A8: APC | B8: ='[23]Profile Summary'!$F$10 -> 0.48199537 | C8: ='[23]Profile Summary'!$H$10 -> 0.63807339
A9: OTR | B9: ='[23]Profile Summary'!$F$11 -> 0.32269216 | C9: ='[23]Profile Summary'!$H$11 -> 0.73206522
A10: Wiretainer | B10: ='[23]Profile Summary'!$F$12 -> 0.19531246 | C10: ='[23]Profile Summary'!$H$12 -> 0.79536082
B11: =SUM(B8:B10) -> 1
C13: Average
A14: Postal Dispatch | B14: Percent | C14: Percent
A15: Container Type | B15: Cu Ft | C15: Full
A18: Postal Pak | B18: 1 | C18: ='[18]Container Statistics'!$C$26 -> 0.98309859 | D18: (Other NDCs)
A21: Pallet Box | B21: ='[23]Profile Summary'!$F$19 -> 0.11896972 | C21: ='[23]Profile Summary'!$H$19 -> 0.80756303 | D21: (P&DCs / P&DFs / DUs)
A22: APC | B22: ='[23]Profile Summary'!$F$20 -> 0.080349918 | C22: ='[23]Profile Summary'!$H$20 -> 0.6865
A23: OTR | B23: ='[23]Profile Summary'!$F$21 -> 0.60164686 | C23: ='[23]Profile Summary'!$H$21 -> 0.81419492
A24: Wiretainer | B24: ='[23]Profile Summary'!$F$22 -> 0.19903351 | C24: ='[23]Profile Summary'!$H$22 -> 0.72893382
B25: =SUM(B21:B24) -> 1
A28: Sources:
A29: [1]: 2014 Parcel Field Study
A30: [2]: 2009 Standard Mail Parcel Field Study or 2014 Parcel Field Study

Sheet Other Inputs
A1: USPS MARKETING MAIL PARCEL OTHER INPUTS
A4: EQUIPMENT REJECT RATES:
A6: Equipment | B6: Percent | C6: Source
A7: PPSM | B7: =1-[25]Parcels!$C$4 -> 0.13138089 | C7: 2025 WebEOR
A8: SPSM | B8: =1-[25]Parcels!$C$5 -> 0.12028717 | C8: 2025 WebEOR
A9: SSM | B9: =1-[25]Parcels!$C$6 -> 0.042386534 | C9: 2025 WebEOR
A10: APPS | B10: =1-[25]Flats!$H$11 -> 0.11837115 | C10: 2025 WebEOR
A11: APBS / LIPS | B11: =1-[25]Flats!$H$11 -> 0.11837115 | C11: 2025 WebEOR
A14: ASF MACHINABLE 5-DIGIT PROCESSING COVERAGE:
A16: Equipment | B16: Percent | C16: Source
A17: APPS | B17: ='[26]Coverage Factors'!$D$9 -> 0.036727712 | C17: 2025 ODIS
A18: APBS / LIPS | B18: ='[26]Coverage Factors'!$D$10 -> 0.02383555 | C18: 2025 ODIS
A19: Manual | B19: ='[26]Coverage Factors'!$D$11 -> 0.034773485 | C19: 2025 ODIS
B20: =SUM(B17:B19) -> 0.095336748
A23: ASF Dock Transfer Required | B23: ='[26]Coverage Factors'!$D$18 -> 0.052796652 | C23: 2025 ODIS
A24: At Second Plant
A27: SCF 5-DIGIT IPP / NFM COVERAGE:
A29: Equipment | B29: Percent | C29: Source
A30: APPS | B30: ='[26]Coverage Factors'!$D$26 -> 0.3789013 | C30: 2025 ODIS
A31: APBS / LIPS | B31: ='[26]Coverage Factors'!$D$27 -> 0.50718024 | C31: 2025 ODIS
A32: Manual | B32: ='[26]Coverage Factors'!$D$28 -> 0.11391845 | C32: 2025 ODIS
B33: =SUM(B30:B32) -> 1
A36: PPSM Transfer Volume Percent | B36: 0.40960621 | C36: FY09 WebEOR
A38: PPSM Finalization (5-Digit) Percent | B38: 0.039119558 | C38: FY09 WebEOR
A40: Space Utilization Percent | B40: ='[18]Container Statistics'!$C$39 -> 0.64404799 | C40: 2009 Standard Mail Parcel / NFM Field Study
A41: (Loose Pieces / Sacked Pieces on Pallets
A42: and in Rolling Stock)
A44: Space Utilization Percent | B44: 1 | C44: 2009 Standard Mail Parcel / NFM Field Study
A45: [Pieces on Pallets)
A48: IPP Operation Outgoing Percent | B48: ='[18]Miscellaneous Data'!$B$5 -> 0.39751958 | C48: 2009 Standard Mail Parcel / NFM Field Study

Sheet Conversion Factors
A1: USPS MARKETING MAIL PARCEL CONVERSION FACTORS
B3: [1]
B4: Cu. Ft.
A5: Mail Type | B5: Per Piece
A6: Machinable | B6: ='[23]Cubic Feet Summary'!$C$8 -> 0.050051979
A7: Irregular Rolls | B7: ='[23]Cubic Feet Summary'!$C$9 -> 0.044396436
A8: Irregular Other | B8: ='[23]Cubic Feet Summary'!$C$10 -> 0.036659933
A9: Marketing | B9: ='[23]Cubic Feet Summary'!$C$11 -> 0.02550504
A12: MAILER CONTAINERS:
B14: [2] | C14: [3] | D14: [4] | E14: [5] | F14: [6] | G14: [7] | H14: [8] | I14: [9] | J14: [10] | K14: [11] | L14: [12] | M14: [13] | N14: [14]
H16: Utilized | I16: Mach | J16: IPP Roll | K16: IPP Other | L16: Mktg | M16: Avg | N16: Avg
B17: Interior | C17: Interior | D17: Interior | E17: Interior | F17: Average | G17: Space | H17: Interior | I17: Pieces | J17: Pieces | K17: Pieces | L17: Pieces | M17: Pieces | N17: Sacks
B18: Length | C18: Width | D18: Height | E18: Volume | F18: Percent | G18: Utilization | H18: Volume | I18: Per | J18: Per | K18: Per | L18: Per | M18: Per | N18: Per
A19: Container Type | B19: (Inches) | C19: (Inches) | D19: (Inches) | E19: (Cu Ft) | F19: Full | G19: Percent | H19: (Cu Ft) | I19: Container | J19: Container | K19: Container | L19: Container | M19: Container | N19: Container
A20: Pallet Box | B20: 48 | C20: 40 | D20: ='Mailer Arrival Profile'!$B$40 -> 45.309278 | E20: =(B20/12)*(C20/12)*(D20/12) -> 50.343643 | F20: ='Mailer Arrival Profile'!$C$40 -> 0.82439863 | G20: ='Other Inputs'!$B$40 -> 0.64404799 | H20: =E20*F20*G20 -> 26.730072 | I20: =H20/$B$6 -> 534.04625 | J20: =H20/$B$7 -> 602.07697 | K20: =H20/$B$8 -> 729.13585 | L20: =H20/$B$9 -> 1048.031 | M20: =I20*SUM('MP Cost Adjustments'!$E$15:$E$20)+J20*SUM('MP Cost Adjustments'!$E$23:$E$30)+K20*SUM('MP Cost Adjustments'!$E$33:$E$40)+L20*SUM('MP Cost Adjustments'!$E$43:$E$60) -> 829.75049
A21: Pallet (Pieces) | B21: 48 | C21: 40 | D21: ='Mailer Arrival Profile'!$B$41 -> 38.478261 | E21: =(B21/12)*(C21/12)*(D21/12) -> 42.753623 | F21: ='Mailer Arrival Profile'!$C$41 -> 1 | G21: ='Other Inputs'!$B$44 -> 1 | H21: =E21*F21*G21 -> 42.753623 | I21: =H21/$B$6 -> 854.18447 | J21: =H21/$B$7 -> 962.99674 | K21: =H21/$B$8 -> 1166.2221 | L21: =H21/$B$9 -> 1676.2814 | M21: =I21*SUM('MP Cost Adjustments'!$E$15:$E$20)+J21*SUM('MP Cost Adjustments'!$E$23:$E$30)+K21*SUM('MP Cost Adjustments'!$E$33:$E$40)+L21*SUM('MP Cost Adjustments'!$E$43:$E$60) -> 1327.151
A22: Pallet (Sacks) | B22: 48 | C22: 40 | D22: ='Mailer Arrival Profile'!$B$41 -> 38.478261 | E22: =(B22/12)*(C22/12)*(D22/12) -> 42.753623 | F22: ='Mailer Arrival Profile'!$C$41 -> 1 | G22: ='Other Inputs'!$B$40 -> 0.64404799 | H22: =E22*F22*G22 -> 27.535385 | I22: =H22/$B$6 -> 550.13579 | J22: =H22/$B$7 -> 620.21611 | K22: =H22/$B$8 -> 751.10298 | L22: =H22/$B$9 -> 1079.6057 | M22: =I22*SUM('MP Cost Adjustments'!$E$15:$E$20)+J22*SUM('MP Cost Adjustments'!$E$23:$E$30)+K22*SUM('MP Cost Adjustments'!$E$33:$E$40)+L22*SUM('MP Cost Adjustments'!$E$43:$E$60) -> 854.7489 | N22: =M22/'Mailer Arrival Profile'!$I$33 -> 17.520003
A23: APC (Sacks) | B23: 40 | C23: 28 | D23: 62 | E23: =(B23/12)*(C23/12)*(D23/12) -> 40.185185 | F23: ='Mailer Arrival Profile'!$C$42 -> 0.9 | G23: ='Other Inputs'!$B$40 -> 0.64404799 | H23: =E23*F23*G23 -> 23.293069 | I23: =H23/$B$6 -> 465.37758 | J23: =H23/$B$7 -> 524.66078 | K23: =H23/$B$8 -> 635.3822 | L23: =H23/$B$9 -> 913.27319 | M23: =I23*SUM('MP Cost Adjustments'!$E$15:$E$20)+J23*SUM('MP Cost Adjustments'!$E$23:$E$30)+K23*SUM('MP Cost Adjustments'!$E$33:$E$40)+L23*SUM('MP Cost Adjustments'!$E$43:$E$60) -> 723.05962 | N23: =M23/'Mailer Arrival Profile'!$I$33 -> 14.820735
A26: POSTAL CONTAINERS (ARRIVAL):
H28: Utilized | I28: Mach | J28: IPP Roll | K28: IPP Other | L28: Mktg
B29: Interior | C29: Interior | D29: Interior | E29: Interior | F29: Average | G29: Space | H29: Interior | I29: Pieces | J29: Pieces | K29: Pieces | L29: Pieces
B30: Length | C30: Width | D30: Height | E30: Volume | F30: Percent | G30: Utilization | H30: Volume | I30: Per | J30: Per | K30: Per | L30: Per
A31: Container Type | B31: (Inches) | C31: (Inches) | D31: (Inches) | E31: (Cu Ft) | F31: Full | G31: Percent | H31: (Cu Ft) | I31: Container | J31: Container | K31: Container | L31: Container
A32: APC | B32: 40 | C32: 28 | D32: 62 | E32: =(B32/12)*(C32/12)*(D32/12) -> 40.185185 | F32: ='Postal Arrival-Dispatch Profile'!$C$8 -> 0.63807339 | G32: ='Other Inputs'!$B$40 -> 0.64404799 | H32: =E32*F32*G32 -> 16.514097 | I32: =H32/$B$6 -> 329.93895 | J32: =H32/$B$7 -> 371.96898 | K32: =H32/$B$8 -> 450.46719 | L32: =H32/$B$9 -> 647.48369
A33: OTR | B33: 51 | C33: 40 | D33: 54 | E33: =(B33/12)*(C33/12)*(D33/12) -> 63.75 | F33: ='Postal Arrival-Dispatch Profile'!$C$9 -> 0.73206522 | G33: ='Other Inputs'!$B$40 -> 0.64404799 | H33: =E33*F33*G33 -> 30.057177 | I33: =H33/$B$6 -> 600.51925 | J33: =H33/$B$7 -> 677.01779 | K33: =H33/$B$8 -> 819.89176 | L33: =H33/$B$9 -> 1178.4799
A34: Wiretainer | B34: 47 | C34: 39 | D34: 34.5 | E34: =(B34/12)*(C34/12)*(D34/12) -> 36.596354 | F34: ='Postal Arrival-Dispatch Profile'!$C$10 -> 0.79536082 | G34: ='Other Inputs'!$B$40 -> 0.64404799 | H34: =E34*F34*G34 -> 18.746502 | I34: =H34/$B$6 -> 374.54068 | J34: =H34/$B$7 -> 422.25241 | K34: =H34/$B$8 -> 511.36215 | L34: =H34/$B$9 -> 735.01168
A37: POSTAL CONTAINERS (DISPATCH):
H39: Utilized | I39: Mach | J39: IPP Roll | K39: IPP Other | L39: Mktg
B40: Interior | C40: Interior | D40: Interior | E40: Interior | F40: Average | G40: Space | H40: Interior | I40: Pieces | J40: Pieces | K40: Pieces | L40: Pieces
B41: Length | C41: Width | D41: Height | E41: Volume | F41: Percent | G41: Utilization | H41: Volume | I41: Per | J41: Per | K41: Per | L41: Per
A42: Container Type | B42: (Inches) | C42: (Inches) | D42: (Inches) | E42: (Cu Ft) | F42: Full | G42: Percent | H42: (Cu Ft) | I42: Container | J42: Container | K42: Container | L42: Container
A43: Pallet Box | B43: 48 | C43: 40 | D43: ='Mailer Arrival Profile'!B40 -> 45.309278 | E43: =(B43/12)*(C43/12)*(D43/12) -> 50.343643 | F43: ='Postal Arrival-Dispatch Profile'!$C$21 -> 0.80756303 | G43: ='Other Inputs'!$B$40 -> 0.64404799 | H43: =E43*F43*G43 -> 26.184199 | I43: =H43/$B$6 -> 523.14013 | J43: =H43/$B$7 -> 589.78155 | K43: =H43/$B$8 -> 714.24568 | L43: =H43/$B$9 -> 1026.6284
A44: APC | B44: 40 | C44: 28 | D44: 62 | E44: =(B44/12)*(C44/12)*(D44/12) -> 40.185185 | F44: ='Postal Arrival-Dispatch Profile'!$C$22 -> 0.6865 | G44: ='Other Inputs'!$B$40 -> 0.64404799 | H44: =E44*F44*G44 -> 17.767435 | I44: =H44/$B$6 -> 354.97968 | J44: =H44/$B$7 -> 400.19958 | K44: =H44/$B$8 -> 484.65542 | L44: =H44/$B$9 -> 696.62449
A45: OTR | B45: 51 | C45: 40 | D45: 54 | E45: =(B45/12)*(C45/12)*(D45/12) -> 63.75 | F45: ='Postal Arrival-Dispatch Profile'!$C$23 -> 0.81419492 | G45: ='Other Inputs'!$B$40 -> 0.64404799 | H45: =E45*F45*G45 -> 33.429263 | I45: =H45/$B$6 -> 667.89093 | J45: =H45/$B$7 -> 752.97177 | K45: =H45/$B$8 -> 911.87463 | L45: =H45/$B$9 -> 1310.6925
A46: Wiretainer | B46: 47 | C46: 39 | D46: 34.5 | E46: =(B46/12)*(C46/12)*(D46/12) -> 36.596354 | F46: ='Postal Arrival-Dispatch Profile'!$C$24 -> 0.72893382 | G46: ='Other Inputs'!$B$40 -> 0.64404799 | H46: =E46*F46*G46 -> 17.18083 | I46: =H46/$B$6 -> 343.25976 | J46: =H46/$B$7 -> 386.9867 | K46: =H46/$B$8 -> 468.65417 | L46: =H46/$B$9 -> 673.62493
A47: Postal Pak | B47: 48 | C47: 40 | D47: 69 | E47: =(B47/12)*(C47/12)*(D47/12) -> 76.666667 | F47: ='Postal Arrival-Dispatch Profile'!$C$18 -> 0.98309859 | G47: ='Other Inputs'!$B$40 -> 0.64404799 | H47: =E47*F47*G47 -> 48.542471 | I47: =H47/$B$6 -> 969.84119 | J47: =H47/$B$7 -> 1093.3867 | K47: =H47/$B$8 -> 1324.1287 | L47: =H47/$B$9 -> 1903.2502 | M47: =I47*SUM('MP Cost Adjustments'!$E$15:$E$20)+J47*SUM('MP Cost Adjustments'!$E$23:$E$30)+K47*SUM('MP Cost Adjustments'!$E$33:$E$40)+L47*SUM('MP Cost Adjustments'!$E$43:$E$60) -> 1506.8474 | N47: =M47/'Mailer Arrival Profile'!$I$33 -> 30.886231
A48: Hamper | B48: 48 | C48: 28 | D48: 28 | E48: =(B48/12)*(C48/12)*(D48/12) -> 21.777778 | F48: =F46 -> 0.72893382 | G48: ='Other Inputs'!$B$40 -> 0.64404799 | H48: =E48*F48*G48 -> 10.223978 | I48: =H48/$B$6 -> 204.2672 | J48: =H48/$B$7 -> 230.28825 | K48: =H48/$B$8 -> 278.88697 | L48: =H48/$B$9 -> 400.86108
A49: No. 1 Sack | B49: 34 | C49: =(61*7)/(2*22) -> 9.7045455 | D49: ="---" -> --- | E49: =(22/7)*(C49/12)^2*(B49/12) -> 5.8238505 | F49: 1 | G49: ='Other Inputs'!$B$40 -> 0.64404799 | H49: =E49*F49*G49 -> 3.7508392 | I49: =H49/$B$6 -> 74.938878 | J49: =H49/$B$7 -> 84.485141 | K49: =H49/$B$8 -> 102.3144 | L49: =H49/$B$9 -> 147.06267
A52: Sources:
A53: [1]: 2014 Parcel Field Study
A54: [2]: Container Dimensions
A55: [3]: Container Dimensions
A56: [4]: Container Dimensions
A57: [5]: ( [2] / 12 ) * ( [3] / 12 ) * ( [4] / 12 )
A58: [6]: 2009 Standard Mail Parcel / NFM Field Study (Page 7 or 8)
A59: [7]: 2009 Standard Mail Parcel / NFM Field Study (Page 9)
A60: [8]: [5] * [6] * [7]
A61: [9]: [8] / [1] (Machinable)
A62: [10]: [8] / [1] (IPP Roll)
A63: [11]: [8] / [1] (IPP Other)
... A66: [14]: [13] / Average Pieces Per Sack (Page 7)

Sheet M-NONE-MNDC
A1: USPS MARKETING MAIL MACHINABLE NON-DROPSHIP MNDC PRESORT PARCELS
C4: [1] | D4: [2] | E4: [3] | F4: [4] | G4: [5] | H4: [6] | I4: [7]
F5: Adjusted | H5: Cost | I5: Cost
D6: Conversion | E6: Units | F6: Wage | G6: Piggyback | H6: Per | I6: Per
A7: Facility | B7: Operation | C7: Handlings | D7: Factor | E7: Per Hour | F7: Rate | G7: Factor | H7: Operation | I7: Facility
A9: Origin | B9: Unload Mailer Pallet Box | C9: ='Mailer Arrival Profile'!$C$47*'Mailer Arrival Profile'!$C$8 -> 0.011224046 | D9: ='Conversion Factors'!$I$20 -> 534.04625 | E9: ='Productivity Data'!$I$26 -> 48.580344 | F9: ='Wage Data'!$C$11 -> 49.154295 | G9: ='Cost Pool Data'!$K$48 -> 1.6214861 | H9: =(F9*G9)/(D9*E9) -> 0.0030720992 | I9: =C9*H9 -> 3.4481384e-05
A10: DU | B10: Unload Mailer Pallet (Pieces) | C10: ='Mailer Arrival Profile'!$C$47*'Mailer Arrival Profile'!$D$8 -> 0.41949874 | D10: ='Conversion Factors'!$I$21 -> 854.18447 | E10: ='Productivity Data'!$I$26 -> 48.580344 | F10: ='Wage Data'!$C$11 -> 49.154295 | G10: ='Cost Pool Data'!$K$48 -> 1.6214861 | H10: =(F10*G10)/(D10*E10) -> 0.0019207128 | I10: =C10*H10 -> 0.00080573659
B11: Unload Mailer Pallet (Sacks) | C11: ='Mailer Arrival Profile'!$C$47*'Mailer Arrival Profile'!$E$8 -> 0 | D11: ='Conversion Factors'!$I$22 -> 550.13579 | E11: ='Productivity Data'!$I$26 -> 48.580344 | F11: ='Wage Data'!$C$11 -> 49.154295 | G11: ='Cost Pool Data'!$K$48 -> 1.6214861 | H11: =(F11*G11)/(D11*E11) -> 0.0029822511 | I11: =C11*H11 -> 0
B12: Unload Mailer APC (Sacks) | C12: ='Mailer Arrival Profile'!$C$47*'Mailer Arrival Profile'!$F$8 -> 0 | D12: ='Conversion Factors'!$I$23 -> 465.37758 | E12: ='Productivity Data'!$I$25 -> 60.332591 | F12: ='Wage Data'!$C$11 -> 49.154295 | G12: ='Cost Pool Data'!$K$48 -> 1.6214861 | H12: =(F12*G12)/(D12*E12) -> 0.0028386853 | I12: =C12*H12 -> 0
B13: Load Mailer Pallet Box | C13: =C9 -> 0.011224046 | D13: ='Conversion Factors'!$I$20 -> 534.04625 | E13: ='Productivity Data'!$I$24 -> 43.137464 | F13: ='Wage Data'!$C$11 -> 49.154295 | G13: ='Cost Pool Data'!$K$48 -> 1.6214861 | H13: =(F13*G13)/(D13*E13) -> 0.0034597221 | I13: =C13*H13 -> 3.8832081e-05
B14: Load Mailer Pallet (Pieces) | C14: =C10 -> 0.41949874 | D14: ='Conversion Factors'!$I$21 -> 854.18447 | E14: ='Productivity Data'!$I$24 -> 43.137464 | F14: ='Wage Data'!$C$11 -> 49.154295 | G14: ='Cost Pool Data'!$K$48 -> 1.6214861 | H14: =(F14*G14)/(D14*E14) -> 0.0021630592 | I14: =C14*H14 -> 0.0009074006
B15: Load Mailer Pallet (Sacks) | C15: =C11 -> 0 | D15: ='Conversion Factors'!$I$22 -> 550.13579 | E15: ='Productivity Data'!$I$24 -> 43.137464 | F15: ='Wage Data'!$C$11 -> 49.154295 | G15: ='Cost Pool Data'!$K$48 -> 1.6214861 | H15: =(F15*G15)/(D15*E15) -> 0.0033585373 | I15: =C15*H15 -> 0
B16: Load Mailer APC (Sacks) | C16: =C12 -> 0 | D16: ='Conversion Factors'!$I$23 -> 465.37758 | E16: ='Productivity Data'!$I$23 -> 68.564044 | F16: ='Wage Data'!$C$11 -> 49.154295 | G16: ='Cost Pool Data'!$K$48 -> 1.6214861 | H16: =(F16*G16)/(D16*E16) -> 0.0024978871 | I16: =C16*H16 -> 0 | J16: =SUM(I9:I16) -> 0.0017864507
A17: Origin | B17: Unload Mailer Pallet Box | C17: ='Mailer Arrival Profile'!$C$48*'Mailer Arrival Profile'!$C$8+C13 -> 0.016845019 | D17: ='Conversion Factors'!$I$20 -> 534.04625 | E17: ='Productivity Data'!$I$28 -> 58.156985 | F17: ='Wage Data'!$C$11 -> 49.154295 | G17: ='Cost Pool Data'!$K$27 -> 1.3606062 | H17: =(F17*G17)/(D17*E17) -> 0.0021533427 | I17: =C17*H17 -> 3.6273098e-05
A18: P&DC / P&DF | B18: Unload Mailer Pallet (Pieces) | C18: ='Mailer Arrival Profile'!$C$48*'Mailer Arrival Profile'!$D$8+C14 -> 0.62958257 | D18: ='Conversion Factors'!$I$21 -> 854.18447 | E18: ='Productivity Data'!$I$28 -> 58.156985 | F18: ='Wage Data'!$C$11 -> 49.154295 | G18: ='Cost Pool Data'!$K$27 -> 1.3606062 | H18: =(F18*G18)/(D18*E18) -> 0.0013462954 | I18: =C18*H18 -> 0.0008476041
B19: Unload Mailer Pallet (Sacks) | C19: ='Mailer Arrival Profile'!$C$48*'Mailer Arrival Profile'!$E$8+C15 -> 0 | D19: ='Conversion Factors'!$I$22 -> 550.13579 | E19: ='Productivity Data'!$I$28 -> 58.156985 | F19: ='Wage Data'!$C$11 -> 49.154295 | G19: ='Cost Pool Data'!$K$27 -> 1.3606062 | H19: =(F19*G19)/(D19*E19) -> 0.002090365 | I19: =C19*H19 -> 0
B20: Unload Mailer APC (Sacks) | C20: ='Mailer Arrival Profile'!$C$48*'Mailer Arrival Profile'!$F$8+C16 -> 0 | D20: ='Conversion Factors'!$I$23 -> 465.37758 | E20: ='Productivity Data'!$I$27 -> 81.873572 | F20: ='Wage Data'!$C$11 -> 49.154295 | G20: ='Cost Pool Data'!$K$27 -> 1.3606062 | H20: =(F20*G20)/(D20*E20) -> 0.0017552732 | I20: =C20*H20 -> 0
B21: Crossdock Mailer Pallet Box | C21: =C17 -> 0.016845019 | D21: ='Conversion Factors'!$I$20 -> 534.04625 | E21: ='Productivity Data'!$I$30 -> 39.899251 | F21: ='Wage Data'!$C$11 -> 49.154295 | G21: ='Cost Pool Data'!$K$27 -> 1.3606062 | H21: =(F21*G21)/(D21*E21) -> 0.0031387036 | I21: =C21*H21 -> 5.287152e-05
B22: Crossdock Mailer Pallet (Pieces) | C22: =C18 -> 0.62958257 | D22: ='Conversion Factors'!$I$21 -> 854.18447 | E22: ='Productivity Data'!$I$30 -> 39.899251 | F22: ='Wage Data'!$C$11 -> 49.154295 | G22: ='Cost Pool Data'!$K$27 -> 1.3606062 | H22: =(F22*G22)/(D22*E22) -> 0.0019623546 | I22: =C22*H22 -> 0.0012354643
B23: Crossdock Mailer Pallet (Sacks) | C23: =C19 -> 0 | D23: ='Conversion Factors'!$I$22 -> 550.13579 | E23: ='Productivity Data'!$I$30 -> 39.899251 | F23: ='Wage Data'!$C$11 -> 49.154295 | G23: ='Cost Pool Data'!$K$27 -> 1.3606062 | H23: =(F23*G23)/(D23*E23) -> 0.0030469075 | I23: =C23*H23 -> 0
B24: Crossdock Mailer APC (Sacks) | C24: =C20 -> 0 | D24: ='Conversion Factors'!$I$23 -> 465.37758 | E24: ='Productivity Data'!$I$29 -> 50.764395 | F24: ='Wage Data'!$C$11 -> 49.154295 | G24: ='Cost Pool Data'!$K$27 -> 1.3606062 | H24: =(F24*G24)/(D24*E24) -> 0.0028309307 | I24: =C24*H24 -> 0
B25: Load Mailer Pallet Box | C25: =C21 -> 0.016845019 | D25: ='Conversion Factors'!$I$20 -> 534.04625 | E25: ='Productivity Data'!$I$32 -> 61.728449 | F25: ='Wage Data'!$C$11 -> 49.154295 | G25: ='Cost Pool Data'!$K$27 -> 1.3606062 | H25: =(F25*G25)/(D25*E25) -> 0.0020287554 | I25: =C25*H25 -> 3.4174422e-05
B26: Load Mailer Pallet (Pieces) | C26: =C22 -> 0.62958257 | D26: ='Conversion Factors'!$I$21 -> 854.18447 | E26: ='Productivity Data'!$I$32 -> 61.728449 | F26: ='Wage Data'!$C$11 -> 49.154295 | G26: ='Cost Pool Data'!$K$27 -> 1.3606062 | H26: =(F26*G26)/(D26*E26) -> 0.0012684019 | I26: =C26*H26 -> 0.00079856371
B27: Load Mailer Pallet (Sacks) | C27: =C23 -> 0 | D27: ='Conversion Factors'!$I$22 -> 550.13579 | E27: ='Productivity Data'!$I$32 -> 61.728449 | F27: ='Wage Data'!$C$11 -> 49.154295 | G27: ='Cost Pool Data'!$K$27 -> 1.3606062 | H27: =(F27*G27)/(D27*E27) -> 0.0019694214 | I27: =C27*H27 -> 0
B28: Load Mailer APC (Sacks) | C28: =C24 -> 0 | D28: ='Conversion Factors'!$I$23 -> 465.37758 | E28: ='Productivity Data'!$I$31 -> 91.071588 | F28: ='Wage Data'!$C$11 -> 49.154295 | G28: ='Cost Pool Data'!$K$27 -> 1.3606062 | H28: =(F28*G28)/(D28*E28) -> 0.0015779947 | I28: =C28*H28 -> 0 | J28: =SUM(I17:I28) -> 0.0030049511
A29: Origin | B29: Unload Mailer Pallet Box | C29: ='Mailer Arrival Profile'!$C$49*'Mailer Arrival Profile'!$C$8+C25 -> 0.026058632 | D29: ='Conversion Factors'!$I$20 -> 534.04625 | E29: ='Productivity Data'!$I$38 -> 46.475052 | F29: ='Wage Data'!$C$11 -> 49.154295 | G29: ='Cost Pool Data'!$K$43 -> 1.3860239 | H29: =(F29*G29)/(D29*E29) -> 0.0027449437 | I29: =C29*H29 -> 7.1529476e-05
A30: NDC | B30: Unload Mailer Pallet (Pieces) | C30: ='Mailer Arrival Profile'!$C$49*'Mailer Arrival Profile'!$D$8+C26 -> 0.97394137 | D30: ='Conversion Factors'!$I$21 -> 854.18447 | E30: ='Productivity Data'!$I$38 -> 46.475052 | F30: ='Wage Data'!$C$11 -> 49.154295 | G30: ='Cost Pool Data'!$K$43 -> 1.3860239 | H30: =(F30*G30)/(D30*E30) -> 0.0017161713 | I30: =C30*H30 -> 0.0016714502
B31: Unload Mailer Pallet (Sacks) | C31: ='Mailer Arrival Profile'!$C$49*'Mailer Arrival Profile'!$E$8+C27 -> 0 | D31: ='Conversion Factors'!$I$22 -> 550.13579 | E31: ='Productivity Data'!$I$38 -> 46.475052 | F31: ='Wage Data'!$C$11 -> 49.154295 | G31: ='Cost Pool Data'!$K$43 -> 1.3860239 | H31: =(F31*G31)/(D31*E31) -> 0.0026646637 | I31: =C31*H31 -> 0
B32: Unload Mailer APC (Sacks) | C32: ='Mailer Arrival Profile'!$C$49*'Mailer Arrival Profile'!$F$8+C28 -> 0 | D32: ='Conversion Factors'!$I$23 -> 465.37758 | E32: ='Productivity Data'!$I$37 -> 55.996737 | F32: ='Wage Data'!$C$11 -> 49.154295 | G32: ='Cost Pool Data'!$K$43 -> 1.3860239 | H32: =(F32*G32)/(D32*E32) -> 0.0026143517 | I32: =C32*H32 -> 0
B33: Induct Mailer Pallet Box | C33: =C29 -> 0.026058632 | D33: ='Conversion Factors'!$I$20 -> 534.04625 | E33: ='Productivity Data'!$I$41 -> 16.483977 | F33: ='Wage Data'!$C$11 -> 49.154295 | G33: ='Cost Pool Data'!$K$42 -> 1.5176144 | H33: =(F33*G33)/(D33*E33) -> 0.0084738746 | I33: =C33*H33 -> 0.00022081758
B34: Induct Mailer Pallet (Pieces) | C34: =C30 -> 0.97394137 | D34: ='Conversion Factors'!$I$21 -> 854.18447 | E34: ='Productivity Data'!$I$41 -> 16.483977 | F34: ='Wage Data'!$C$11 -> 49.154295 | G34: ='Cost Pool Data'!$K$42 -> 1.5176144 | H34: =(F34*G34)/(D34*E34) -> 0.0052979668 | I34: =C34*H34 -> 0.005159909
B35: Induct Mailer Pallet (Sacks) | C35: =C31 -> 0 | D35: ='Conversion Factors'!$I$22 -> 550.13579 | E35: ='Productivity Data'!$I$41 -> 16.483977 | F35: ='Wage Data'!$C$11 -> 49.154295 | G35: ='Cost Pool Data'!$K$42 -> 1.5176144 | H35: =(F35*G35)/(D35*E35) -> 0.0082260435 | I35: =C35*H35 -> 0
B36: Induct Mailer APC (Sacks) | C36: =C32 -> 0 | D36: ='Conversion Factors'!$I$23 -> 465.37758 | E36: ='Productivity Data'!$I$40 -> 23.065925 | F36: ='Wage Data'!$C$11 -> 49.154295 | G36: ='Cost Pool Data'!$K$42 -> 1.5176144 | H36: =(F36*G36)/(D36*E36) -> 0.006949388 | I36: =C36*H36 -> 0
B37: Sack Sorting Machine | C37: =(C35+C36)*(1+'Other Inputs'!$B$9) -> 0 | D37: ='Conversion Factors'!$I$49 -> 74.938878 | E37: ='Productivity Data'!$I$19 -> 3068.1109 | F37: ='Wage Data'!$C$11 -> 49.154295 | G37: ='Cost Pool Data'!$K$46 -> 1.6196175 | H37: =(F37*G37)/(D37*E37) -> 0.0003462547 | I37: =C37*H37 -> 0
B38: Sack Shake Out | C38: =(C35+C36) -> 0 | D38: ='Conversion Factors'!$I$49 -> 74.938878 | E38: ='Productivity Data'!$I$43 -> 146.75955 | F38: ='Wage Data'!$C$11 -> 49.154295 | G38: ='Cost Pool Data'!$K$42 -> 1.5176144 | H38: =(F38*G38)/(D38*E38) -> 0.0067828052 | I38: =C38*H38 -> 0
B39: Primary Parcel Sorting Machine | C39: =(C33+C34+C38)*(1+'Other Inputs'!$B$7) -> 1.1313809 | D39: 1 | E39: ='Productivity Data'!$I$17 -> 409.68278 | F39: ='Wage Data'!$C$11 -> 49.154295 | G39: ='Cost Pool Data'!$L$43 -> 1.9204979 | H39: =(F39*G39)/(D39*E39) -> 0.23042394 | I39: =C39*H39 -> 0.26069724
B40: Manually Apply Barcode Label | C40: =(C33+C34+C38)*'Other Inputs'!$B$7 -> 0.13138089 | D40: 1 | E40: ='Productivity Data'!$I$47 -> 221.38134 | F40: ='Wage Data'!$C$11 -> 49.154295 | G40: ='Cost Pool Data'!$K$42 -> 1.5176144 | H40: =(F40*G40)/(D40*E40) -> 0.33696274 | I40: =C40*H40 -> 0.044270465
B41: Induct Wiretainer | C41: =C40 -> 0.13138089 | D41: ='Conversion Factors'!$I$34 -> 374.54068 | E41: ='Productivity Data'!$I$40 -> 23.065925 | F41: ='Wage Data'!$C$11 -> 49.154295 | G41: ='Cost Pool Data'!$K$42 -> 1.5176144 | H41: =(F41*G41)/(D41*E41) -> 0.0086348147 | I41: =C41*H41 -> 0.0011344496
B42: Secondary Parcel Sorting Machine | C42: =((C33+C34+C38)*'Other Inputs'!$B$36)*(1+'Other Inputs'!$B$8) -> 0.45887658 | D42: 1 | E42: ='Productivity Data'!$I$18 -> 331.3648 | F42: ='Wage Data'!$C$11 -> 49.154295 | G42: ='Cost Pool Data'!$L$45 -> 2.0700178 | H42: =(F42*G42)/(D42*E42) -> 0.30706419 | I42: =C42*H42 -> 0.14090457
B43: Manually Apply Barcode Label | C43: =((C33+C34+C38)*'Other Inputs'!$B$36)*('Other Inputs'!$B$8) -> 0.049270373 | D43: 1 | E43: ='Productivity Data'!$I$47 -> 221.38134 | F43: ='Wage Data'!$C$11 -> 49.154295 | G43: ='Cost Pool Data'!$K$42 -> 1.5176144 | H43: =(F43*G43)/(D43*E43) -> 0.33696274 | I43: =C43*H43 -> 0.01660228
B44: Induct Wiretainer | C44: =C43 -> 0.049270373 | D44: ='Conversion Factors'!$I$34 -> 374.54068 | E44: ='Productivity Data'!$I$40 -> 23.065925 | F44: ='Wage Data'!$C$11 -> 49.154295 | G44: ='Cost Pool Data'!$K$42 -> 1.5176144 | H44: =(F44*G44)/(D44*E44) -> 0.0086348147 | I44: =C44*H44 -> 0.00042544055
B45: Load Postal Pallet Box | C45: =(1-C49)*'Postal Arrival-Dispatch Profile'!$B$21 -> 0.053384777 | D45: ='Conversion Factors'!$I$43 -> 523.14013 | E45: ='Productivity Data'!$I$45 -> 55.582256 | F45: ='Wage Data'!$C$11 -> 49.154295 | G45: ='Cost Pool Data'!$K$43 -> 1.3860239 | H45: =(F45*G45)/(D45*E45) -> 0.0023430307 | I45: =C45*H45 -> 0.00012508217
B46: Load Postal APC | C46: =(1-C49)*'Postal Arrival-Dispatch Profile'!$B$22 -> 0.036055078 | D46: ='Conversion Factors'!$I$44 -> 354.97968 | E46: ='Productivity Data'!$I$44 -> 70.608822 | F46: ='Wage Data'!$C$11 -> 49.154295 | G46: ='Cost Pool Data'!$K$43 -> 1.3860239 | H46: =(F46*G46)/(D46*E46) -> 0.0027181269 | I46: =C46*H46 -> 9.800228e-05
B47: Load Postal OTR | C47: =(1-C49)*'Postal Arrival-Dispatch Profile'!$B$23 -> 0.26997445 | D47: ='Conversion Factors'!$I$45 -> 667.89093 | E47: ='Productivity Data'!$I$44 -> 70.608822 | F47: ='Wage Data'!$C$11 -> 49.154295 | G47: ='Cost Pool Data'!$K$43 -> 1.3860239 | H47: =(F47*G47)/(D47*E47) -> 0.0014446667 | I47: =C47*H47 -> 0.0003900231
B48: Load Postal Wiretainer | C48: =(1-C49)*'Postal Arrival-Dispatch Profile'!$B$24 -> 0.089311461 | D48: ='Conversion Factors'!$I$46 -> 343.25976 | E48: ='Productivity Data'!$I$44 -> 70.608822 | F48: ='Wage Data'!$C$11 -> 49.154295 | G48: ='Cost Pool Data'!$K$43 -> 1.3860239 | H48: =(F48*G48)/(D48*E48) -> 0.0028109319 | I48: =C48*H48 -> 0.00025104844
B49: Load Postal Pak | C49: =(C33+C34+C38)*(1-'Other Inputs'!$B$36-'Other Inputs'!$B$38) -> 0.55127424 | D49: ='Conversion Factors'!$I$47 -> 969.84119 | E49: ='Productivity Data'!$I$46 -> 20.811195 | F49: ='Wage Data'!$C$11 -> 49.154295 | G49: ='Cost Pool Data'!$K$43 -> 1.3860239 | H49: =(F49*G49)/(D49*E49) -> 0.0033754722 | I49: =C49*H49 -> 0.0018608109 | J49: =SUM(I29:I49) -> 0.47388312
A50: Destination | B50: Unload Postal Pak | C50: =C49 -> 0.55127424 | D50: ='Conversion Factors'!$I$47 -> 969.84119 | E50: ='Productivity Data'!$I$39 -> 53.14645 | F50: ='Wage Data'!$C$11 -> 49.154295 | G50: ='Cost Pool Data'!$K$43 -> 1.3860239 | H50: =(F50*G50)/(D50*E50) -> 0.0013217743 | I50: =C50*H50 -> 0.00072866012
A51: NDC | B51: Induct Postal Pak | C51: =C50 -> 0.55127424 | D51: ='Conversion Factors'!$I$47 -> 969.84119 | E51: ='Productivity Data'!$I$42 -> 16.646694 | F51: ='Wage Data'!$C$11 -> 49.154295 | G51: ='Cost Pool Data'!$K$42 -> 1.5176144 | H51: =(F51*G51)/(D51*E51) -> 0.0046205563 | I51: =C51*H51 -> 0.0025471936
B52: Secondary Parcel Sorting Machine | C52: =C51*(1+'Other Inputs'!$B$8) -> 0.61758546 | D52: 1 | E52: ='Productivity Data'!$I$18 -> 331.3648 | F52: ='Wage Data'!$C$11 -> 49.154295 | G52: ='Cost Pool Data'!$L$45 -> 2.0700178 | H52: =(F52*G52)/(D52*E52) -> 0.30706419 | I52: =C52*H52 -> 0.18963838
B53: Manually Apply Barcode Label | C53: =C51*('Other Inputs'!$B$8) -> 0.066311221 | D53: 1 | E53: ='Productivity Data'!$I$47 -> 221.38134 | F53: ='Wage Data'!$C$11 -> 49.154295 | G53: ='Cost Pool Data'!$K$42 -> 1.5176144 | H53: =(F53*G53)/(D53*E53) -> 0.33696274 | I53: =C53*H53 -> 0.022344411
B54: Induct Wiretainer | C54: =C53 -> 0.066311221 | D54: ='Conversion Factors'!$I$34 -> 374.54068 | E54: ='Productivity Data'!$I$40 -> 23.065925 | F54: ='Wage Data'!$C$11 -> 49.154295 | G54: ='Cost Pool Data'!$K$42 -> 1.5176144 | H54: =(F54*G54)/(D54*E54) -> 0.0086348147 | I54: =C54*H54 -> 0.00057258511
B55: Load Postal Pallet Box | C55: =C51*'Postal Arrival-Dispatch Profile'!$B$21 -> 0.06558494 | D55: ='Conversion Factors'!$I$43 -> 523.14013 | E55: ='Productivity Data'!$I$45 -> 55.582256 | F55: ='Wage Data'!$C$11 -> 49.154295 | G55: ='Cost Pool Data'!$K$43 -> 1.3860239 | H55: =(F55*G55)/(D55*E55) -> 0.0023430307 | I55: =C55*H55 -> 0.00015366753
B56: Load Postal APC | C56: =C51*'Postal Arrival-Dispatch Profile'!$B$22 -> 0.04429484 | D56: ='Conversion Factors'!$I$44 -> 354.97968 | E56: ='Productivity Data'!$I$44 -> 70.608822 | F56: ='Wage Data'!$C$11 -> 49.154295 | G56: ='Cost Pool Data'!$K$43 -> 1.3860239 | H56: =(F56*G56)/(D56*E56) -> 0.0027181269 | I56: =C56*H56 -> 0.000120399
B57: Load Postal OTR | C57: =C51*'Postal Arrival-Dispatch Profile'!$B$23 -> 0.33167241 | D57: ='Conversion Factors'!$I$45 -> 667.89093 | E57: ='Productivity Data'!$I$44 -> 70.608822 | F57: ='Wage Data'!$C$11 -> 49.154295 | G57: ='Cost Pool Data'!$K$43 -> 1.3860239 | H57: =(F57*G57)/(D57*E57) -> 0.0014446667 | I57: =C57*H57 -> 0.0004791561
B58: Load Postal Wiretainer | C58: =C51*'Postal Arrival-Dispatch Profile'!$B$24 -> 0.10972204 | D58: ='Conversion Factors'!$I$46 -> 343.25976 | E58: ='Productivity Data'!$I$44 -> 70.608822 | F58: ='Wage Data'!$C$11 -> 49.154295 | G58: ='Cost Pool Data'!$K$43 -> 1.3860239 | H58: =(F58*G58)/(D58*E58) -> 0.0028109319 | I58: =C58*H58 -> 0.00030842119 | J58: =SUM(I50:I58) -> 0.21689287
A59: Destination | B59: Unload Postal Pallet Box | C59: =(C45+C55)*'Other Inputs'!$B$20 -> 0.011342186 | D59: ='Conversion Factors'!$I$43 -> 523.14013 | E59: ='Productivity Data'!$I$34 -> 58.924683 | F59: ='Wage Data'!$C$11 -> 49.154295 | G59: ='Cost Pool Data'!$K$27 -> 1.3606062 | H59: =(F59*G59)/(D59*E59) -> 0.0021695947 | I59: =C59*H59 -> 2.4607947e-05
A60: ASF | B60: Unload Postal APC | C60: =(C46+C56)*'Other Inputs'!$B$20 -> 0.0076602999 | D60: ='Conversion Factors'!$I$44 -> 354.97968 | E60: ='Productivity Data'!$I$33 -> 74.63792 | F60: ='Wage Data'!$C$11 -> 49.154295 | G60: ='Cost Pool Data'!$K$27 -> 1.3606062 | H60: =(F60*G60)/(D60*E60) -> 0.0025242415 | I60: =C60*H60 -> 1.9336447e-05
B61: Unload Postal OTR | C61: =(C47+C57)*'Other Inputs'!$B$20 -> 0.057359055 | D61: ='Conversion Factors'!$I$45 -> 667.89093 | E61: ='Productivity Data'!$I$33 -> 74.63792 | F61: ='Wage Data'!$C$11 -> 49.154295 | G61: ='Cost Pool Data'!$K$27 -> 1.3606062 | H61: =(F61*G61)/(D61*E61) -> 0.0013416179 | I61: =C61*H61 -> 7.6953934e-05
B62: Unload Postal Wiretainer | C62: =(C48+C58)*'Other Inputs'!$B$20 -> 0.018975207 | D62: ='Conversion Factors'!$I$46 -> 343.25976 | E62: ='Productivity Data'!$I$33 -> 74.63792 | F62: ='Wage Data'!$C$11 -> 49.154295 | G62: ='Cost Pool Data'!$K$27 -> 1.3606062 | H62: =(F62*G62)/(D62*E62) -> 0.0026104266 | I62: =C62*H62 -> 4.9533386e-05
B63: APPS Incoming Sort | C63: ='Other Inputs'!$B$17*(1+'Other Inputs'!$B$10) -> 0.041075214 | D63: 1 | E63: ='Productivity Data'!$I$10 -> 245.20306 | F63: ='Wage Data'!$C$11 -> 49.154295 | G63: ='Cost Pool Data'!$L$14 -> 1.8052502 | H63: =(F63*G63)/(D63*E63) -> 0.36188702 | I63: =C63*H63 -> 0.014864587
B64: APBS / LIPS Incoming Sort | C64: ='Other Inputs'!$B$18*(1+'Other Inputs'!$B$11) -> 0.026656992 | D64: 1 | E64: ='Productivity Data'!$I$11 -> 190.80521 | F64: ='Wage Data'!$C$11 -> 49.154295 | G64: ='Cost Pool Data'!$L$11 -> 1.6056413 | H64: =(F64*G64)/(D64*E64) -> 0.41363736 | I64: =C64*H64 -> 0.011026328
B65: Manual Incoming Sort | C65: ='Other Inputs'!$B$19 -> 0.034773485 | D65: 1 | E65: ='Productivity Data'!$I$15 -> 47.99469 | F65: ='Wage Data'!$C$11 -> 49.154295 | G65: ='Cost Pool Data'!$K$16 -> 1.3208756 | H65: =(F65*G65)/(D65*E65) -> 1.3527894 | I65: =C65*H65 -> 0.047041203
B66: Load Postal Hamper | C66: =SUM(C59:C62) -> 0.095336748 | D66: ='Conversion Factors'!$I$48 -> 204.2672 | E66: ='Productivity Data'!$I$35 -> 82.063609 | F66: ='Wage Data'!$C$11 -> 49.154295 | G66: ='Cost Pool Data'!$K$27 -> 1.3606062 | H66: =(F66*G66)/(D66*E66) -> 0.0039897406 | I66: =C66*H66 -> 0.0003803689 | J66: =SUM(I59:I66) -> 0.073482918
A67: Destination | B67: Unload Postal Pallet Box | C67: =(C45+C55)*(1-'Other Inputs'!$B$20) -> 0.10762753 | D67: ='Conversion Factors'!$I$43 -> 523.14013 | E67: ='Productivity Data'!$I$28 -> 58.156985 | F67: ='Wage Data'!$C$11 -> 49.154295 | G67: ='Cost Pool Data'!$K$27 -> 1.3606062 | H67: =(F67*G67)/(D67*E67) -> 0.0021982344 | I67: =C67*H67 -> 0.00023659054
A68: P&DC / P&DF | B68: Unload Postal APC | C68: =(C46+C56)*(1-'Other Inputs'!$B$20) -> 0.072689618 | D68: ='Conversion Factors'!$I$44 -> 354.97968 | E68: ='Productivity Data'!$I$27 -> 81.873572 | F68: ='Wage Data'!$C$11 -> 49.154295 | G68: ='Cost Pool Data'!$K$27 -> 1.3606062 | H68: =(F68*G68)/(D68*E68) -> 0.0023011593 | I68: =C68*H68 -> 0.00016727039
B69: Unload Postal OTR | C69: =(C47+C57)*(1-'Other Inputs'!$B$20) -> 0.5442878 | D69: ='Conversion Factors'!$I$45 -> 667.89093 | E69: ='Productivity Data'!$I$27 -> 81.873572 | F69: ='Wage Data'!$C$11 -> 49.154295 | G69: ='Cost Pool Data'!$K$27 -> 1.3606062 | H69: =(F69*G69)/(D69*E69) -> 0.0012230512 | I69: =C69*H69 -> 0.00066569183
B70: Unload Postal Wiretainer | C70: =(C48+C58)*(1-'Other Inputs'!$B$20) -> 0.1800583 | D70: ='Conversion Factors'!$I$46 -> 343.25976 | E70: ='Productivity Data'!$I$27 -> 81.873572 | F70: ='Wage Data'!$C$11 -> 49.154295 | G70: ='Cost Pool Data'!$K$27 -> 1.3606062 | H70: =(F70*G70)/(D70*E70) -> 0.0023797278 | I70: =C70*H70 -> 0.00042848973
B71: Unload Postal Hamper | C71: ='Other Inputs'!$B$23 -> 0.052796652 | D71: ='Conversion Factors'!$I$48 -> 204.2672 | E71: ='Productivity Data'!$I$31 -> 91.071588 | F71: ='Wage Data'!$C$11 -> 49.154295 | G71: ='Cost Pool Data'!$K$27 -> 1.3606062 | H71: =(F71*G71)/(D71*E71) -> 0.0035951115 | I71: =C71*H71 -> 0.00018980985
B72: Crossdock Postal Pallet Box | C72: =C67 -> 0.10762753 | D72: ='Conversion Factors'!$I$43 -> 523.14013 | E72: ='Productivity Data'!$I$30 -> 39.899251 | F72: ='Wage Data'!$C$11 -> 49.154295 | G72: ='Cost Pool Data'!$K$27 -> 1.3606062 | H72: =(F72*G72)/(D72*E72) -> 0.0032041374 | I72: =C72*H72 -> 0.0003448534
B73: Crossdock Postal APC | C73: =C68 -> 0.072689618 | D73: ='Conversion Factors'!$I$44 -> 354.97968 | E73: ='Productivity Data'!$I$29 -> 50.764395 | F73: ='Wage Data'!$C$11 -> 49.154295 | G73: ='Cost Pool Data'!$K$27 -> 1.3606062 | H73: =(F73*G73)/(D73*E73) -> 0.003711344 | I73: =C73*H73 -> 0.00026977618
B74: Crossdock Postal OTR | C74: =C69 -> 0.5442878 | D74: ='Conversion Factors'!$I$45 -> 667.89093 | E74: ='Productivity Data'!$I$29 -> 50.764395 | F74: ='Wage Data'!$C$11 -> 49.154295 | G74: ='Cost Pool Data'!$K$27 -> 1.3606062 | H74: =(F74*G74)/(D74*E74) -> 0.0019725551 | I74: =C74*H74 -> 0.0010736377
B75: Crossdock Postal Wiretainer | C75: =C70 -> 0.1800583 | D75: ='Conversion Factors'!$I$46 -> 343.25976 | E75: ='Productivity Data'!$I$29 -> 50.764395 | F75: ='Wage Data'!$C$11 -> 49.154295 | G75: ='Cost Pool Data'!$K$27 -> 1.3606062 | H75: =(F75*G75)/(D75*E75) -> 0.0038380604 | I75: =C75*H75 -> 0.00069107462
B76: Crossdock Postal Hamper | C76: =C71 -> 0.052796652 | D76: ='Conversion Factors'!$I$48 -> 204.2672 | E76: ='Productivity Data'!$I$29 -> 50.764395 | F76: ='Wage Data'!$C$11 -> 49.154295 | G76: ='Cost Pool Data'!$K$27 -> 1.3606062 | H76: =(F76*G76)/(D76*E76) -> 0.0064496487 | I76: =C76*H76 -> 0.00034051986
B77: Load Postal Pallet Box | C77: =C72 -> 0.10762753 | D77: ='Conversion Factors'!$I$43 -> 523.14013 | E77: ='Productivity Data'!$I$32 -> 61.728449 | F77: ='Wage Data'!$C$11 -> 49.154295 | G77: ='Cost Pool Data'!$K$27 -> 1.3606062 | H77: =(F77*G77)/(D77*E77) -> 0.0020710497 | I77: =C77*H77 -> 0.00022290196
B78: Load Postal APC | C78: =C73 -> 0.072689618 | D78: ='Conversion Factors'!$I$44 -> 354.97968 | E78: ='Productivity Data'!$I$31 -> 91.071588 | F78: ='Wage Data'!$C$11 -> 49.154295 | G78: ='Cost Pool Data'!$K$27 -> 1.3606062 | H78: =(F78*G78)/(D78*E78) -> 0.0020687476 | I78: =C78*H78 -> 0.00015037648
B79: Load Postal OTR | C79: =C74 -> 0.5442878 | D79: ='Conversion Factors'!$I$45 -> 667.89093 | E79: ='Productivity Data'!$I$31 -> 91.071588 | F79: ='Wage Data'!$C$11 -> 49.154295 | G79: ='Cost Pool Data'!$K$27 -> 1.3606062 | H79: =(F79*G79)/(D79*E79) -> 0.0010995259 | I79: =C79*H79 -> 0.00059845853
B80: Load Postal Wiretainer | C80: =C75 -> 0.1800583 | D80: ='Conversion Factors'!$I$46 -> 343.25976 | E80: ='Productivity Data'!$I$31 -> 91.071588 | F80: ='Wage Data'!$C$11 -> 49.154295 | G80: ='Cost Pool Data'!$K$27 -> 1.3606062 | H80: =(F80*G80)/(D80*E80) -> 0.0021393809 | I80: =C80*H80 -> 0.00038521328
B81: Load Postal Hamper | C81: =C76 -> 0.052796652 | D81: ='Conversion Factors'!$I$48 -> 204.2672 | E81: ='Productivity Data'!$I$31 -> 91.071588 | F81: ='Wage Data'!$C$11 -> 49.154295 | G81: ='Cost Pool Data'!$K$27 -> 1.3606062 | H81: =(F81*G81)/(D81*E81) -> 0.0035951115 | I81: =C81*H81 -> 0.00018980985 | J81: =SUM(I67:I81) -> 0.0059544742
A82: Destination | B82: Unload Postal Pallet Box | C82: =C77 -> 0.10762753 | D82: ='Conversion Factors'!$I$43 -> 523.14013 | E82: ='Productivity Data'!$I$26 -> 48.580344 | F82: ='Wage Data'!$C$11 -> 49.154295 | G82: ='Cost Pool Data'!$K$48 -> 1.6214861 | H82: =(F82*G82)/(D82*E82) -> 0.0031361445 | I82: =C82*H82 -> 0.00033753549
A83: DU | B83: Unload Postal APC | C83: =C78 -> 0.072689618 | D83: ='Conversion Factors'!$I$44 -> 354.97968 | E83: ='Productivity Data'!$I$25 -> 60.332591 | F83: ='Wage Data'!$C$11 -> 49.154295 | G83: ='Cost Pool Data'!$K$48 -> 1.6214861 | H83: =(F83*G83)/(D83*E83) -> 0.0037215103 | I83: =C83*H83 -> 0.00027051516
B84: Unload Postal OTR | C84: =C79 -> 0.5442878 | D84: ='Conversion Factors'!$I$45 -> 667.89093 | E84: ='Productivity Data'!$I$25 -> 60.332591 | F84: ='Wage Data'!$C$11 -> 49.154295 | G84: ='Cost Pool Data'!$K$48 -> 1.6214861 | H84: =(F84*G84)/(D84*E84) -> 0.0019779584 | I84: =C84*H84 -> 0.0010765787
B85: Unload Postal Wiretainer | C85: =C80 -> 0.1800583 | D85: ='Conversion Factors'!$I$46 -> 343.25976 | E85: ='Productivity Data'!$I$25 -> 60.332591 | F85: ='Wage Data'!$C$11 -> 49.154295 | G85: ='Cost Pool Data'!$K$48 -> 1.6214861 | H85: =(F85*G85)/(D85*E85) -> 0.0038485737 | I85: =C85*H85 -> 0.00069296764
B86: Unload Postal Hamper | C86: =C66 -> 0.095336748 | D86: ='Conversion Factors'!$I$48 -> 204.2672 | E86: ='Productivity Data'!$I$25 -> 60.332591 | F86: ='Wage Data'!$C$11 -> 49.154295 | G86: ='Cost Pool Data'!$K$48 -> 1.6214861 | H86: =(F86*G86)/(D86*E86) -> 0.0064673159 | I86: =C86*H86 -> 0.00061657286
B87: Incoming Secondary Parcel Sort | C87: =SUM(C82:C86) -> 1 | D87: 1 | E87: ='Productivity Data'!$I$22 -> 307.66823 | F87: ='Wage Data'!$C$11 -> 49.154295 | G87: ='Cost Pool Data'!$K$57 -> 1.4957787 | H87: =(F87*G87)/(D87*E87) -> 0.23897152 | I87: =C87*H87 -> 0.23897152 | J87: =SUM(I82:I87) -> 0.24196569
A89: Sources: | I89: Grand Total | J89: =J16+J28+J49+J58+J66+J81+J87 -> 1.0169705
A90: [1]: Page 7, 8, 9
A91: [2]: Page 7, 10
A92: [3]: Page 5
A93: [4]: Page 6
A94: [5]: Page 3
A95: [6]: ( [4] * [5] ) / ( [2] * [3] )
A96: [7]: [1] * [6]

Sheet M-NONE-NDC
A1: USPS MARKETING MAIL MACHINABLE NON-DROPSHIP NDC PRESORT PARCELS
C4: [1] | D4: [2] | E4: [3] | F4: [4] | G4: [5] | H4: [6] | I4: [7]
F5: Adjusted | H5: Cost | I5: Cost
D6: Conversion | E6: Units | F6: Wage | G6: Piggyback | H6: Per | I6: Per
A7: Facility | B7: Operation | C7: Handlings | D7: Factor | E7: Per Hour | F7: Rate | G7: Factor | H7: Operation | I7: Facility
A9: Origin | B9: Unload Mailer Pallet Box | C9: ='Mailer Arrival Profile'!$C$47*'Mailer Arrival Profile'!$C$9 -> 0.43072278 | D9: ='Conversion Factors'!$I$20 -> 534.04625 | E9: ='Productivity Data'!$I$26 -> 48.580344 | F9: ='Wage Data'!$C$11 -> 49.154295 | G9: ='Cost Pool Data'!$K$48 -> 1.6214861 | H9: =(F9*G9)/(D9*E9) -> 0.0030720992 | I9: =C9*H9 -> 0.0013232231
A10: DU | B10: Unload Mailer Pallet (Pieces) | C10: ='Mailer Arrival Profile'!$C$47*'Mailer Arrival Profile'!$D$9 -> 0 | D10: ='Conversion Factors'!$I$21 -> 854.18447 | E10: ='Productivity Data'!$I$26 -> 48.580344 | F10: ='Wage Data'!$C$11 -> 49.154295 | G10: ='Cost Pool Data'!$K$48 -> 1.6214861 | H10: =(F10*G10)/(D10*E10) -> 0.0019207128 | I10: =C10*H10 -> 0
B11: Unload Mailer Pallet (Sacks) | C11: ='Mailer Arrival Profile'!$C$47*'Mailer Arrival Profile'!$E$9 -> 0 | D11: ='Conversion Factors'!$I$22 -> 550.13579 | E11: ='Productivity Data'!$I$26 -> 48.580344 | F11: ='Wage Data'!$C$11 -> 49.154295 | G11: ='Cost Pool Data'!$K$48 -> 1.6214861 | H11: =(F11*G11)/(D11*E11) -> 0.0029822511 | I11: =C11*H11 -> 0
B12: Unload Mailer APC (Sacks) | C12: ='Mailer Arrival Profile'!$C$47*'Mailer Arrival Profile'!$F$9 -> 0 | D12: ='Conversion Factors'!$I$23 -> 465.37758 | E12: ='Productivity Data'!$I$25 -> 60.332591 | F12: ='Wage Data'!$C$11 -> 49.154295 | G12: ='Cost Pool Data'!$K$48 -> 1.6214861 | H12: =(F12*G12)/(D12*E12) -> 0.0028386853 | I12: =C12*H12 -> 0
B13: Load Mailer Pallet Box | C13: =C9 -> 0.43072278 | D13: ='Conversion Factors'!$I$20 -> 534.04625 | E13: ='Productivity Data'!$I$24 -> 43.137464 | F13: ='Wage Data'!$C$11 -> 49.154295 | G13: ='Cost Pool Data'!$K$48 -> 1.6214861 | H13: =(F13*G13)/(D13*E13) -> 0.0034597221 | I13: =C13*H13 -> 0.0014901811
B14: Load Mailer Pallet (Pieces) | C14: =C10 -> 0 | D14: ='Conversion Factors'!$I$21 -> 854.18447 | E14: ='Productivity Data'!$I$24 -> 43.137464 | F14: ='Wage Data'!$C$11 -> 49.154295 | G14: ='Cost Pool Data'!$K$48 -> 1.6214861 | H14: =(F14*G14)/(D14*E14) -> 0.0021630592 | I14: =C14*H14 -> 0
B15: Load Mailer Pallet (Sacks) | C15: =C11 -> 0 | D15: ='Conversion Factors'!$I$22 -> 550.13579 | E15: ='Productivity Data'!$I$24 -> 43.137464 | F15: ='Wage Data'!$C$11 -> 49.154295 | G15: ='Cost Pool Data'!$K$48 -> 1.6214861 | H15: =(F15*G15)/(D15*E15) -> 0.0033585373 | I15: =C15*H15 -> 0
B16: Load Mailer APC (Sacks) | C16: =C12 -> 0 | D16: ='Conversion Factors'!$I$23 -> 465.37758 | E16: ='Productivity Data'!$I$23 -> 68.564044 | F16: ='Wage Data'!$C$11 -> 49.154295 | G16: ='Cost Pool Data'!$K$48 -> 1.6214861 | H16: =(F16*G16)/(D16*E16) -> 0.0024978871 | I16: =C16*H16 -> 0 | J16: =SUM(I9:I16) -> 0.0028134042
A17: Origin | B17: Unload Mailer Pallet Box | C17: ='Mailer Arrival Profile'!$C$48*'Mailer Arrival Profile'!$C$9+C13 -> 0.64642759 | D17: ='Conversion Factors'!$I$20 -> 534.04625 | E17: ='Productivity Data'!$I$28 -> 58.156985 | F17: ='Wage Data'!$C$11 -> 49.154295 | G17: ='Cost Pool Data'!$K$27 -> 1.3606062 | H17: =(F17*G17)/(D17*E17) -> 0.0021533427 | I17: =C17*H17 -> 0.0013919801
A18: P&DC / P&DF | B18: Unload Mailer Pallet (Pieces) | C18: ='Mailer Arrival Profile'!$C$48*'Mailer Arrival Profile'!$D$9+C14 -> 0 | D18: ='Conversion Factors'!$I$21 -> 854.18447 | E18: ='Productivity Data'!$I$28 -> 58.156985 | F18: ='Wage Data'!$C$11 -> 49.154295 | G18: ='Cost Pool Data'!$K$27 -> 1.3606062 | H18: =(F18*G18)/(D18*E18) -> 0.0013462954 | I18: =C18*H18 -> 0
B19: Unload Mailer Pallet (Sacks) | C19: ='Mailer Arrival Profile'!$C$48*'Mailer Arrival Profile'!$E$9+C15 -> 0 | D19: ='Conversion Factors'!$I$22 -> 550.13579 | E19: ='Productivity Data'!$I$28 -> 58.156985 | F19: ='Wage Data'!$C$11 -> 49.154295 | G19: ='Cost Pool Data'!$K$27 -> 1.3606062 | H19: =(F19*G19)/(D19*E19) -> 0.002090365 | I19: =C19*H19 -> 0
B20: Unload Mailer APC (Sacks) | C20: ='Mailer Arrival Profile'!$C$48*'Mailer Arrival Profile'!$F$9+C16 -> 0 | D20: ='Conversion Factors'!$I$23 -> 465.37758 | E20: ='Productivity Data'!$I$27 -> 81.873572 | F20: ='Wage Data'!$C$11 -> 49.154295 | G20: ='Cost Pool Data'!$K$27 -> 1.3606062 | H20: =(F20*G20)/(D20*E20) -> 0.0017552732 | I20: =C20*H20 -> 0
B21: Crossdock Mailer Pallet Box | C21: =C17 -> 0.64642759 | D21: ='Conversion Factors'!$I$20 -> 534.04625 | E21: ='Productivity Data'!$I$30 -> 39.899251 | F21: ='Wage Data'!$C$11 -> 49.154295 | G21: ='Cost Pool Data'!$K$27 -> 1.3606062 | H21: =(F21*G21)/(D21*E21) -> 0.0031387036 | I21: =C21*H21 -> 0.0020289446
B22: Crossdock Mailer Pallet (Pieces) | C22: =C18 -> 0 | D22: ='Conversion Factors'!$I$21 -> 854.18447 | E22: ='Productivity Data'!$I$30 -> 39.899251 | F22: ='Wage Data'!$C$11 -> 49.154295 | G22: ='Cost Pool Data'!$K$27 -> 1.3606062 | H22: =(F22*G22)/(D22*E22) -> 0.0019623546 | I22: =C22*H22 -> 0
B23: Crossdock Mailer Pallet (Sacks) | C23: =C19 -> 0 | D23: ='Conversion Factors'!$I$22 -> 550.13579 | E23: ='Productivity Data'!$I$30 -> 39.899251 | F23: ='Wage Data'!$C$11 -> 49.154295 | G23: ='Cost Pool Data'!$K$27 -> 1.3606062 | H23: =(F23*G23)/(D23*E23) -> 0.0030469075 | I23: =C23*H23 -> 0
B24: Crossdock Mailer APC (Sacks) | C24: =C20 -> 0 | D24: ='Conversion Factors'!$I$23 -> 465.37758 | E24: ='Productivity Data'!$I$29 -> 50.764395 | F24: ='Wage Data'!$C$11 -> 49.154295 | G24: ='Cost Pool Data'!$K$27 -> 1.3606062 | H24: =(F24*G24)/(D24*E24) -> 0.0028309307 | I24: =C24*H24 -> 0
B25: Load Mailer Pallet Box | C25: =C21 -> 0.64642759 | D25: ='Conversion Factors'!$I$20 -> 534.04625 | E25: ='Productivity Data'!$I$32 -> 61.728449 | F25: ='Wage Data'!$C$11 -> 49.154295 | G25: ='Cost Pool Data'!$K$27 -> 1.3606062 | H25: =(F25*G25)/(D25*E25) -> 0.0020287554 | I25: =C25*H25 -> 0.0013114434
B26: Load Mailer Pallet (Pieces) | C26: =C22 -> 0 | D26: ='Conversion Factors'!$I$21 -> 854.18447 | E26: ='Productivity Data'!$I$32 -> 61.728449 | F26: ='Wage Data'!$C$11 -> 49.154295 | G26: ='Cost Pool Data'!$K$27 -> 1.3606062 | H26: =(F26*G26)/(D26*E26) -> 0.0012684019 | I26: =C26*H26 -> 0
B27: Load Mailer Pallet (Sacks) | C27: =C23 -> 0 | D27: ='Conversion Factors'!$I$22 -> 550.13579 | E27: ='Productivity Data'!$I$32 -> 61.728449 | F27: ='Wage Data'!$C$11 -> 49.154295 | G27: ='Cost Pool Data'!$K$27 -> 1.3606062 | H27: =(F27*G27)/(D27*E27) -> 0.0019694214 | I27: =C27*H27 -> 0
B28: Load Mailer APC (Sacks) | C28: =C24 -> 0 | D28: ='Conversion Factors'!$I$23 -> 465.37758 | E28: ='Productivity Data'!$I$31 -> 91.071588 | F28: ='Wage Data'!$C$11 -> 49.154295 | G28: ='Cost Pool Data'!$K$27 -> 1.3606062 | H28: =(F28*G28)/(D28*E28) -> 0.0015779947 | I28: =C28*H28 -> 0 | J28: =SUM(I17:I28) -> 0.0047323681
A29: Origin | B29: Unload Mailer Pallet Box | C29: ='Mailer Arrival Profile'!$C$49*'Mailer Arrival Profile'!$C$9+C25 -> 1 | D29: ='Conversion Factors'!$I$20 -> 534.04625 | E29: ='Productivity Data'!$I$38 -> 46.475052 | F29: ='Wage Data'!$C$11 -> 49.154295 | G29: ='Cost Pool Data'!$K$43 -> 1.3860239 | H29: =(F29*G29)/(D29*E29) -> 0.0027449437 | I29: =C29*H29 -> 0.0027449437
A30: NDC | B30: Unload Mailer Pallet (Pieces) | C30: ='Mailer Arrival Profile'!$C$49*'Mailer Arrival Profile'!$D$9+C26 -> 0 | D30: ='Conversion Factors'!$I$21 -> 854.18447 | E30: ='Productivity Data'!$I$38 -> 46.475052 | F30: ='Wage Data'!$C$11 -> 49.154295 | G30: ='Cost Pool Data'!$K$43 -> 1.3860239 | H30: =(F30*G30)/(D30*E30) -> 0.0017161713 | I30: =C30*H30 -> 0
B31: Unload Mailer Pallet (Sacks) | C31: ='Mailer Arrival Profile'!$C$49*'Mailer Arrival Profile'!$E$9+C27 -> 0 | D31: ='Conversion Factors'!$I$22 -> 550.13579 | E31: ='Productivity Data'!$I$38 -> 46.475052 | F31: ='Wage Data'!$C$11 -> 49.154295 | G31: ='Cost Pool Data'!$K$43 -> 1.3860239 | H31: =(F31*G31)/(D31*E31) -> 0.0026646637 | I31: =C31*H31 -> 0
B32: Unload Mailer APC (Sacks) | C32: ='Mailer Arrival Profile'!$C$49*'Mailer Arrival Profile'!$F$9+C28 -> 0 | D32: ='Conversion Factors'!$I$23 -> 465.37758 | E32: ='Productivity Data'!$I$37 -> 55.996737 | F32: ='Wage Data'!$C$11 -> 49.154295 | G32: ='Cost Pool Data'!$K$43 -> 1.3860239 | H32: =(F32*G32)/(D32*E32) -> 0.0026143517 | I32: =C32*H32 -> 0
B33: Load Mailer Pallet Box | C33: =C29 -> 1 | D33: ='Conversion Factors'!$I$20 -> 534.04625 | E33: ='Productivity Data'!$I$45 -> 55.582256 | F33: ='Wage Data'!$C$11 -> 49.154295 | G33: ='Cost Pool Data'!$K$43 -> 1.3860239 | H33: =(F33*G33)/(D33*E33) -> 0.0022951821 | I33: =C33*H33 -> 0.0022951821
B34: Load Mailer Pallet (Pieces) | C34: =C30 -> 0 | D34: ='Conversion Factors'!$I$21 -> 854.18447 | E34: ='Productivity Data'!$I$44 -> 70.608822 | F34: ='Wage Data'!$C$11 -> 49.154295 | G34: ='Cost Pool Data'!$K$43 -> 1.3860239 | H34: =(F34*G34)/(D34*E34) -> 0.0011295919 | I34: =C34*H34 -> 0
B35: Load Mailer Pallet (Sacks) | C35: =C31 -> 0 | D35: ='Conversion Factors'!$I$22 -> 550.13579 | E35: ='Productivity Data'!$I$44 -> 70.608822 | F35: ='Wage Data'!$C$11 -> 49.154295 | G35: ='Cost Pool Data'!$K$43 -> 1.3860239 | H35: =(F35*G35)/(D35*E35) -> 0.0017538939 | I35: =C35*H35 -> 0
B36: Load Mailer APC (Sacks) | C36: =C32 -> 0 | D36: ='Conversion Factors'!$I$23 -> 465.37758 | E36: ='Productivity Data'!$I$44 -> 70.608822 | F36: ='Wage Data'!$C$11 -> 49.154295 | G36: ='Cost Pool Data'!$K$43 -> 1.3860239 | H36: =(F36*G36)/(D36*E36) -> 0.0020733268 | I36: =C36*H36 -> 0 | J36: =SUM(I29:I36) -> 0.0050401258
A37: Destination | B37: Unload Mailer Pallet Box | C37: =C33 -> 1 | D37: ='Conversion Factors'!$I$20 -> 534.04625 | E37: ='Productivity Data'!$I$38 -> 46.475052 | F37: ='Wage Data'!$C$11 -> 49.154295 | G37: ='Cost Pool Data'!$K$43 -> 1.3860239 | H37: =(F37*G37)/(D37*E37) -> 0.0027449437 | I37: =C37*H37 -> 0.0027449437
A38: NDC | B38: Unload Mailer Pallet (Pieces) | C38: =C34 -> 0 | D38: ='Conversion Factors'!$I$21 -> 854.18447 | E38: ='Productivity Data'!$I$38 -> 46.475052 | F38: ='Wage Data'!$C$11 -> 49.154295 | G38: ='Cost Pool Data'!$K$43 -> 1.3860239 | H38: =(F38*G38)/(D38*E38) -> 0.0017161713 | I38: =C38*H38 -> 0
B39: Unload Mailer Pallet (Sacks) | C39: =C35 -> 0 | D39: ='Conversion Factors'!$I$22 -> 550.13579 | E39: ='Productivity Data'!$I$38 -> 46.475052 | F39: ='Wage Data'!$C$11 -> 49.154295 | G39: ='Cost Pool Data'!$K$43 -> 1.3860239 | H39: =(F39*G39)/(D39*E39) -> 0.0026646637 | I39: =C39*H39 -> 0
B40: Unload Mailer APC (Sacks) | C40: =C36 -> 0 | D40: ='Conversion Factors'!$I$23 -> 465.37758 | E40: ='Productivity Data'!$I$37 -> 55.996737 | F40: ='Wage Data'!$C$11 -> 49.154295 | G40: ='Cost Pool Data'!$K$43 -> 1.3860239 | H40: =(F40*G40)/(D40*E40) -> 0.0026143517 | I40: =C40*H40 -> 0
B41: Induct Mailer Pallet Box | C41: =C37 -> 1 | D41: ='Conversion Factors'!$I$20 -> 534.04625 | E41: ='Productivity Data'!$I$41 -> 16.483977 | F41: ='Wage Data'!$C$11 -> 49.154295 | G41: ='Cost Pool Data'!$K$42 -> 1.5176144 | H41: =(F41*G41)/(D41*E41) -> 0.0084738746 | I41: =C41*H41 -> 0.0084738746
B42: Induct Mailer Pallet (Pieces) | C42: =C38 -> 0 | D42: ='Conversion Factors'!$I$21 -> 854.18447 | E42: ='Productivity Data'!$I$41 -> 16.483977 | F42: ='Wage Data'!$C$11 -> 49.154295 | G42: ='Cost Pool Data'!$K$42 -> 1.5176144 | H42: =(F42*G42)/(D42*E42) -> 0.0052979668 | I42: =C42*H42 -> 0
B43: Induct Mailer Pallet (Sacks) | C43: =C39 -> 0 | D43: ='Conversion Factors'!$I$22 -> 550.13579 | E43: ='Productivity Data'!$I$41 -> 16.483977 | F43: ='Wage Data'!$C$11 -> 49.154295 | G43: ='Cost Pool Data'!$K$42 -> 1.5176144 | H43: =(F43*G43)/(D43*E43) -> 0.0082260435 | I43: =C43*H43 -> 0
B44: Induct Mailer APC (Sacks) | C44: =C40 -> 0 | D44: ='Conversion Factors'!$I$23 -> 465.37758 | E44: ='Productivity Data'!$I$40 -> 23.065925 | F44: ='Wage Data'!$C$11 -> 49.154295 | G44: ='Cost Pool Data'!$K$42 -> 1.5176144 | H44: =(F44*G44)/(D44*E44) -> 0.006949388 | I44: =C44*H44 -> 0
B45: Sack Sorting Machine | C45: =(C43+C44)*(1+'Other Inputs'!$B$9) -> 0 | D45: ='Conversion Factors'!$I$49 -> 74.938878 | E45: ='Productivity Data'!$I$19 -> 3068.1109 | F45: ='Wage Data'!$C$11 -> 49.154295 | G45: ='Cost Pool Data'!$K$46 -> 1.6196175 | H45: =(F45*G45)/(D45*E45) -> 0.0003462547 | I45: =C45*H45 -> 0
B46: Sack Shake Out | C46: =C43+C44 -> 0 | D46: ='Conversion Factors'!$I$49 -> 74.938878 | E46: ='Productivity Data'!$I$43 -> 146.75955 | F46: ='Wage Data'!$C$11 -> 49.154295 | G46: ='Cost Pool Data'!$K$42 -> 1.5176144 | H46: =(F46*G46)/(D46*E46) -> 0.0067828052 | I46: =C46*H46 -> 0
B47: Secondary Parcel Sorting Machine | C47: =(C41+C42+C46)*(1+'Other Inputs'!$B$8) -> 1.1202872 | D47: 1 | E47: ='Productivity Data'!$I$18 -> 331.3648 | F47: ='Wage Data'!$C$11 -> 49.154295 | G47: ='Cost Pool Data'!$L$45 -> 2.0700178 | H47: =(F47*G47)/(D47*E47) -> 0.30706419 | I47: =C47*H47 -> 0.34400008
B48: Manually Apply Barcode Label | C48: =(C41+C42+C46)*('Other Inputs'!$B$8) -> 0.12028717 | D48: 1 | E48: ='Productivity Data'!$I$47 -> 221.38134 | F48: ='Wage Data'!$C$11 -> 49.154295 | G48: ='Cost Pool Data'!$K$42 -> 1.5176144 | H48: =(F48*G48)/(D48*E48) -> 0.33696274 | I48: =C48*H48 -> 0.040532296
B49: Induct Wiretainer | C49: =C48 -> 0.12028717 | D49: ='Conversion Factors'!$I$34 -> 374.54068 | E49: ='Productivity Data'!$I$40 -> 23.065925 | F49: ='Wage Data'!$C$11 -> 49.154295 | G49: ='Cost Pool Data'!$K$42 -> 1.5176144 | H49: =(F49*G49)/(D49*E49) -> 0.0086348147 | I49: =C49*H49 -> 0.0010386575
B50: Load Postal Pallet Box | C50: =(C41+C42+C46)*'Postal Arrival-Dispatch Profile'!$B$21 -> 0.11896972 | D50: ='Conversion Factors'!$I$43 -> 523.14013 | E50: ='Productivity Data'!$I$45 -> 55.582256 | F50: ='Wage Data'!$C$11 -> 49.154295 | G50: ='Cost Pool Data'!$K$43 -> 1.3860239 | H50: =(F50*G50)/(D50*E50) -> 0.0023430307 | I50: =C50*H50 -> 0.0002787497
B51: Load Postal APC | C51: =(C41+C42+C46)*'Postal Arrival-Dispatch Profile'!$B$22 -> 0.080349918 | D51: ='Conversion Factors'!$I$44 -> 354.97968 | E51: ='Productivity Data'!$I$44 -> 70.608822 | F51: ='Wage Data'!$C$11 -> 49.154295 | G51: ='Cost Pool Data'!$K$43 -> 1.3860239 | H51: =(F51*G51)/(D51*E51) -> 0.0027181269 | I51: =C51*H51 -> 0.00021840128
B52: Load Postal OTR | C52: =(C41+C42+C46)*'Postal Arrival-Dispatch Profile'!$B$23 -> 0.60164686 | D52: ='Conversion Factors'!$I$45 -> 667.89093 | E52: ='Productivity Data'!$I$44 -> 70.608822 | F52: ='Wage Data'!$C$11 -> 49.154295 | G52: ='Cost Pool Data'!$K$43 -> 1.3860239 | H52: =(F52*G52)/(D52*E52) -> 0.0014446667 | I52: =C52*H52 -> 0.00086917921
B53: Load Postal Wiretainer | C53: =(C41+C42+C46)*'Postal Arrival-Dispatch Profile'!$B$24 -> 0.19903351 | D53: ='Conversion Factors'!$I$46 -> 343.25976 | E53: ='Productivity Data'!$I$44 -> 70.608822 | F53: ='Wage Data'!$C$11 -> 49.154295 | G53: ='Cost Pool Data'!$K$43 -> 1.3860239 | H53: =(F53*G53)/(D53*E53) -> 0.0028109319 | I53: =C53*H53 -> 0.00055946963 | J53: =SUM(I37:I53) -> 0.39871565
A54: Destination | B54: Unload Postal Pallet Box | C54: =C50*'Other Inputs'!$B$20 -> 0.011342186 | D54: ='Conversion Factors'!$I$43 -> 523.14013 | E54: ='Productivity Data'!$I$34 -> 58.924683 | F54: ='Wage Data'!$C$11 -> 49.154295 | G54: ='Cost Pool Data'!$K$27 -> 1.3606062 | H54: =(F54*G54)/(D54*E54) -> 0.0021695947 | I54: =C54*H54 -> 2.4607947e-05
A55: ASF | B55: Unload Postal APC | C55: =C51*'Other Inputs'!$B$20 -> 0.0076602999 | D55: ='Conversion Factors'!$I$44 -> 354.97968 | E55: ='Productivity Data'!$I$33 -> 74.63792 | F55: ='Wage Data'!$C$11 -> 49.154295 | G55: ='Cost Pool Data'!$K$27 -> 1.3606062 | H55: =(F55*G55)/(D55*E55) -> 0.0025242415 | I55: =C55*H55 -> 1.9336447e-05
B56: Unload Postal OTR | C56: =C52*'Other Inputs'!$B$20 -> 0.057359055 | D56: ='Conversion Factors'!$I$45 -> 667.89093 | E56: ='Productivity Data'!$I$33 -> 74.63792 | F56: ='Wage Data'!$C$11 -> 49.154295 | G56: ='Cost Pool Data'!$K$27 -> 1.3606062 | H56: =(F56*G56)/(D56*E56) -> 0.0013416179 | I56: =C56*H56 -> 7.6953934e-05
B57: Unload Postal Wiretainer | C57: =C53*'Other Inputs'!$B$20 -> 0.018975207 | D57: ='Conversion Factors'!$I$46 -> 343.25976 | E57: ='Productivity Data'!$I$33 -> 74.63792 | F57: ='Wage Data'!$C$11 -> 49.154295 | G57: ='Cost Pool Data'!$K$27 -> 1.3606062 | H57: =(F57*G57)/(D57*E57) -> 0.0026104266 | I57: =C57*H57 -> 4.9533386e-05
B58: APPS Incoming Sort | C58: ='Other Inputs'!$B$17*(1+'Other Inputs'!$B$10) -> 0.041075214 | D58: 1 | E58: ='Productivity Data'!$I$10 -> 245.20306 | F58: ='Wage Data'!$C$11 -> 49.154295 | G58: ='Cost Pool Data'!$L$14 -> 1.8052502 | H58: =(F58*G58)/(D58*E58) -> 0.36188702 | I58: =C58*H58 -> 0.014864587
B59: APBS / LIPS Incoming Sort | C59: ='Other Inputs'!$B$18*(1+'Other Inputs'!$B$11) -> 0.026656992 | D59: 1 | E59: ='Productivity Data'!$I$11 -> 190.80521 | F59: ='Wage Data'!$C$11 -> 49.154295 | G59: ='Cost Pool Data'!$L$11 -> 1.6056413 | H59: =(F59*G59)/(D59*E59) -> 0.41363736 | I59: =C59*H59 -> 0.011026328
B60: Manual Incoming Sort | C60: ='Other Inputs'!$B$19 -> 0.034773485 | D60: 1 | E60: ='Productivity Data'!$I$15 -> 47.99469 | F60: ='Wage Data'!$C$11 -> 49.154295 | G60: ='Cost Pool Data'!$K$16 -> 1.3208756 | H60: =(F60*G60)/(D60*E60) -> 1.3527894 | I60: =C60*H60 -> 0.047041203
B61: Load Postal Hamper | C61: =SUM(C54:C57) -> 0.095336748 | D61: ='Conversion Factors'!$I$48 -> 204.2672 | E61: ='Productivity Data'!$I$35 -> 82.063609 | F61: ='Wage Data'!$C$11 -> 49.154295 | G61: ='Cost Pool Data'!$K$27 -> 1.3606062 | H61: =(F61*G61)/(D61*E61) -> 0.0039897406 | I61: =C61*H61 -> 0.0003803689 | J61: =SUM(I54:I61) -> 0.073482918
A62: Destination | B62: Unload Postal Pallet Box | C62: =C50*(1-'Other Inputs'!$B$20) -> 0.10762753 | D62: ='Conversion Factors'!$I$43 -> 523.14013 | E62: ='Productivity Data'!$I$28 -> 58.156985 | F62: ='Wage Data'!$C$11 -> 49.154295 | G62: ='Cost Pool Data'!$K$27 -> 1.3606062 | H62: =(F62*G62)/(D62*E62) -> 0.0021982344 | I62: =C62*H62 -> 0.00023659054
A63: P&DC / P&DF | B63: Unload Postal APC | C63: =C51*(1-'Other Inputs'!$B$20) -> 0.072689618 | D63: ='Conversion Factors'!$I$44 -> 354.97968 | E63: ='Productivity Data'!$I$27 -> 81.873572 | F63: ='Wage Data'!$C$11 -> 49.154295 | G63: ='Cost Pool Data'!$K$27 -> 1.3606062 | H63: =(F63*G63)/(D63*E63) -> 0.0023011593 | I63: =C63*H63 -> 0.00016727039
B64: Unload Postal OTR | C64: =C52*(1-'Other Inputs'!$B$20) -> 0.5442878 | D64: ='Conversion Factors'!$I$45 -> 667.89093 | E64: ='Productivity Data'!$I$27 -> 81.873572 | F64: ='Wage Data'!$C$11 -> 49.154295 | G64: ='Cost Pool Data'!$K$27 -> 1.3606062 | H64: =(F64*G64)/(D64*E64) -> 0.0012230512 | I64: =C64*H64 -> 0.00066569183
B65: Unload Postal Wiretainer | C65: =C53*(1-'Other Inputs'!$B$20) -> 0.1800583 | D65: ='Conversion Factors'!$I$46 -> 343.25976 | E65: ='Productivity Data'!$I$27 -> 81.873572 | F65: ='Wage Data'!$C$11 -> 49.154295 | G65: ='Cost Pool Data'!$K$27 -> 1.3606062 | H65: =(F65*G65)/(D65*E65) -> 0.0023797278 | I65: =C65*H65 -> 0.00042848973
B66: Unload Postal Hamper | C66: ='Other Inputs'!$B$23 -> 0.052796652 | D66: ='Conversion Factors'!$I$48 -> 204.2672 | E66: ='Productivity Data'!$I$27 -> 81.873572 | F66: ='Wage Data'!$C$11 -> 49.154295 | G66: ='Cost Pool Data'!$K$27 -> 1.3606062 | H66: =(F66*G66)/(D66*E66) -> 0.0039990012 | I66: =C66*H66 -> 0.00021113388
B67: Crossdock Postal Pallet Box | C67: =C62 -> 0.10762753 | D67: ='Conversion Factors'!$I$43 -> 523.14013 | E67: ='Productivity Data'!$I$30 -> 39.899251 | F67: ='Wage Data'!$C$11 -> 49.154295 | G67: ='Cost Pool Data'!$K$27 -> 1.3606062 | H67: =(F67*G67)/(D67*E67) -> 0.0032041374 | I67: =C67*H67 -> 0.0003448534
B68: Crossdock Postal APC | C68: =C63 -> 0.072689618 | D68: ='Conversion Factors'!$I$44 -> 354.97968 | E68: ='Productivity Data'!$I$29 -> 50.764395 | F68: ='Wage Data'!$C$11 -> 49.154295 | G68: ='Cost Pool Data'!$K$27 -> 1.3606062 | H68: =(F68*G68)/(D68*E68) -> 0.003711344 | I68: =C68*H68 -> 0.00026977618
B69: Crossdock Postal OTR | C69: =C64 -> 0.5442878 | D69: ='Conversion Factors'!$I$45 -> 667.89093 | E69: ='Productivity Data'!$I$29 -> 50.764395 | F69: ='Wage Data'!$C$11 -> 49.154295 | G69: ='Cost Pool Data'!$K$27 -> 1.3606062 | H69: =(F69*G69)/(D69*E69) -> 0.0019725551 | I69: =C69*H69 -> 0.0010736377
B70: Crossdock Postal Wiretainer | C70: =C65 -> 0.1800583 | D70: ='Conversion Factors'!$I$46 -> 343.25976 | E70: ='Productivity Data'!$I$29 -> 50.764395 | F70: ='Wage Data'!$C$11 -> 49.154295 | G70: ='Cost Pool Data'!$K$27 -> 1.3606062 | H70: =(F70*G70)/(D70*E70) -> 0.0038380604 | I70: =C70*H70 -> 0.00069107462
B71: Crossdock Postal Hamper | C71: =C66 -> 0.052796652 | D71: ='Conversion Factors'!$I$48 -> 204.2672 | E71: ='Productivity Data'!$I$29 -> 50.764395 | F71: ='Wage Data'!$C$11 -> 49.154295 | G71: ='Cost Pool Data'!$K$27 -> 1.3606062 | H71: =(F71*G71)/(D71*E71) -> 0.0064496487 | I71: =C71*H71 -> 0.00034051986
B72: Load Postal Pallet Box | C72: =C67 -> 0.10762753 | D72: ='Conversion Factors'!$I$43 -> 523.14013 | E72: ='Productivity Data'!$I$32 -> 61.728449 | F72: ='Wage Data'!$C$11 -> 49.154295 | G72: ='Cost Pool Data'!$K$27 -> 1.3606062 | H72: =(F72*G72)/(D72*E72) -> 0.0020710497 | I72: =C72*H72 -> 0.00022290196
B73: Load Postal APC | C73: =C68 -> 0.072689618 | D73: ='Conversion Factors'!$I$44 -> 354.97968 | E73: ='Productivity Data'!$I$31 -> 91.071588 | F73: ='Wage Data'!$C$11 -> 49.154295 | G73: ='Cost Pool Data'!$K$27 -> 1.3606062 | H73: =(F73*G73)/(D73*E73) -> 0.0020687476 | I73: =C73*H73 -> 0.00015037648
B74: Load Postal OTR | C74: =C69 -> 0.5442878 | D74: ='Conversion Factors'!$I$45 -> 667.89093 | E74: ='Productivity Data'!$I$31 -> 91.071588 | F74: ='Wage Data'!$C$11 -> 49.154295 | G74: ='Cost Pool Data'!$K$27 -> 1.3606062 | H74: =(F74*G74)/(D74*E74) -> 0.0010995259 | I74: =C74*H74 -> 0.00059845853
B75: Load Postal Wiretainer | C75: =C70 -> 0.1800583 | D75: ='Conversion Factors'!$I$46 -> 343.25976 | E75: ='Productivity Data'!$I$31 -> 91.071588 | F75: ='Wage Data'!$C$11 -> 49.154295 | G75: ='Cost Pool Data'!$K$27 -> 1.3606062 | H75: =(F75*G75)/(D75*E75) -> 0.0021393809 | I75: =C75*H75 -> 0.00038521328
B76: Load Postal Hamper | C76: =C71 -> 0.052796652 | D76: ='Conversion Factors'!$I$48 -> 204.2672 | E76: ='Productivity Data'!$I$31 -> 91.071588 | F76: ='Wage Data'!$C$11 -> 49.154295 | G76: ='Cost Pool Data'!$K$27 -> 1.3606062 | H76: =(F76*G76)/(D76*E76) -> 0.0035951115 | I76: =C76*H76 -> 0.00018980985 | J76: =SUM(I62:I76) -> 0.0059757982
A77: Destination | B77: Unload Postal Pallet Box | C77: =C72 -> 0.10762753 | D77: ='Conversion Factors'!$I$43 -> 523.14013 | E77: ='Productivity Data'!$I$26 -> 48.580344 | F77: ='Wage Data'!$C$11 -> 49.154295 | G77: ='Cost Pool Data'!$K$48 -> 1.6214861 | H77: =(F77*G77)/(D77*E77) -> 0.0031361445 | I77: =C77*H77 -> 0.00033753549
A78: DU | B78: Unload Postal APC | C78: =C73 -> 0.072689618 | D78: ='Conversion Factors'!$I$44 -> 354.97968 | E78: ='Productivity Data'!$I$25 -> 60.332591 | F78: ='Wage Data'!$C$11 -> 49.154295 | G78: ='Cost Pool Data'!$K$48 -> 1.6214861 | H78: =(F78*G78)/(D78*E78) -> 0.0037215103 | I78: =C78*H78 -> 0.00027051516
B79: Unload Postal OTR | C79: =C74 -> 0.5442878 | D79: ='Conversion Factors'!$I$45 -> 667.89093 | E79: ='Productivity Data'!$I$25 -> 60.332591 | F79: ='Wage Data'!$C$11 -> 49.154295 | G79: ='Cost Pool Data'!$K$48 -> 1.6214861 | H79: =(F79*G79)/(D79*E79) -> 0.0019779584 | I79: =C79*H79 -> 0.0010765787
B80: Unload Postal Wiretainer | C80: =C75 -> 0.1800583 | D80: ='Conversion Factors'!$I$46 -> 343.25976 | E80: ='Productivity Data'!$I$25 -> 60.332591 | F80: ='Wage Data'!$C$11 -> 49.154295 | G80: ='Cost Pool Data'!$K$48 -> 1.6214861 | H80: =(F80*G80)/(D80*E80) -> 0.0038485737 | I80: =C80*H80 -> 0.00069296764
B81: Unload Postal Hamper | C81: =C61 -> 0.095336748 | D81: ='Conversion Factors'!$I$48 -> 204.2672 | E81: ='Productivity Data'!$I$25 -> 60.332591 | F81: ='Wage Data'!$C$11 -> 49.154295 | G81: ='Cost Pool Data'!$K$48 -> 1.6214861 | H81: =(F81*G81)/(D81*E81) -> 0.0064673159 | I81: =C81*H81 -> 0.00061657286
B82: Incoming Secondary Parcel Sort | C82: =SUM(C77:C81) -> 1 | D82: 1 | E82: ='Productivity Data'!$I$22 -> 307.66823 | F82: ='Wage Data'!$C$11 -> 49.154295 | G82: ='Cost Pool Data'!$K$57 -> 1.4957787 | H82: =(F82*G82)/(D82*E82) -> 0.23897152 | I82: =C82*H82 -> 0.23897152 | J82: =SUM(I77:I82) -> 0.24196569
A84: Sources: | I84: Grand Total | J84: =J16+J28+J36+J53+J61+J76+J82 -> 0.73272595
A85: [1]: Page 7, 8, 9
A86: [2]: Page 7, 10
A87: [3]: Page 5
A88: [4]: Page 6
A89: [5]: Page 3
A90: [6]: ( [4] * [5] ) / ( [2] * [3] )
A91: [7]: [1] * [6]

Sheet M-DNDC-NDC
A1: USPS MARKETING MAIL MACHINABLE DNDC NDC PRESORT PARCELS
C4: [1] | D4: [2] | E4: [3] | F4: [4] | G4: [5] | H4: [6] | I4: [7]
F5: Adjusted | H5: Cost | I5: Cost
D6: Conversion | E6: Units | F6: Wage | G6: Piggyback | H6: Per | I6: Per
A7: Facility | B7: Operation | C7: Handlings | D7: Factor | E7: Per Hour | F7: Rate | G7: Factor | H7: Operation | I7: Facility
A9: Destination | B9: Unload Mailer Pallet Box | C9: ='Mailer Arrival Profile'!$C$10 -> 0.49310796 | D9: ='Conversion Factors'!$I$20 -> 534.04625 | E9: ='Productivity Data'!$I$38 -> 46.475052 | F9: ='Wage Data'!$C$11 -> 49.154295 | G9: ='Cost Pool Data'!$K$43 -> 1.3860239 | H9: =(F9*G9)/(D9*E9) -> 0.0027449437 | I9: =C9*H9 -> 0.0013535536
A10: NDC | B10: Unload Mailer Pallet (Pieces) | C10: ='Mailer Arrival Profile'!$D$10 -> 0.46621265 | D10: ='Conversion Factors'!$I$21 -> 854.18447 | E10: ='Productivity Data'!$I$38 -> 46.475052 | F10: ='Wage Data'!$C$11 -> 49.154295 | G10: ='Cost Pool Data'!$K$43 -> 1.3860239 | H10: =(F10*G10)/(D10*E10) -> 0.0017161713 | I10: =C10*H10 -> 0.00080010077
B11: Unload Mailer Pallet (Sacks) | C11: ='Mailer Arrival Profile'!$E$10 -> 0.012311105 | D11: ='Conversion Factors'!$I$22 -> 550.13579 | E11: ='Productivity Data'!$I$38 -> 46.475052 | F11: ='Wage Data'!$C$11 -> 49.154295 | G11: ='Cost Pool Data'!$K$43 -> 1.3860239 | H11: =(F11*G11)/(D11*E11) -> 0.0026646637 | I11: =C11*H11 -> 3.2804956e-05
B12: Unload Mailer APC (Sacks) | C12: ='Mailer Arrival Profile'!$F$10 -> 0.028368278 | D12: ='Conversion Factors'!$I$23 -> 465.37758 | E12: ='Productivity Data'!$I$37 -> 55.996737 | F12: ='Wage Data'!$C$11 -> 49.154295 | G12: ='Cost Pool Data'!$K$43 -> 1.3860239 | H12: =(F12*G12)/(D12*E12) -> 0.0026143517 | I12: =C12*H12 -> 7.4164657e-05
B13: Induct Mailer Pallet Box | C13: =C9 -> 0.49310796 | D13: ='Conversion Factors'!$I$20 -> 534.04625 | E13: ='Productivity Data'!$I$41 -> 16.483977 | F13: ='Wage Data'!$C$11 -> 49.154295 | G13: ='Cost Pool Data'!$K$42 -> 1.5176144 | H13: =(F13*G13)/(D13*E13) -> 0.0084738746 | I13: =C13*H13 -> 0.004178535
B14: Induct Mailer Pallet (Pieces) | C14: =C10 -> 0.46621265 | D14: ='Conversion Factors'!$I$21 -> 854.18447 | E14: ='Productivity Data'!$I$41 -> 16.483977 | F14: ='Wage Data'!$C$11 -> 49.154295 | G14: ='Cost Pool Data'!$K$42 -> 1.5176144 | H14: =(F14*G14)/(D14*E14) -> 0.0052979668 | I14: =C14*H14 -> 0.0024699791
B15: Induct Mailer Pallet (Sacks) | C15: =C11 -> 0.012311105 | D15: ='Conversion Factors'!$I$22 -> 550.13579 | E15: ='Productivity Data'!$I$41 -> 16.483977 | F15: ='Wage Data'!$C$11 -> 49.154295 | G15: ='Cost Pool Data'!$K$42 -> 1.5176144 | H15: =(F15*G15)/(D15*E15) -> 0.0082260435 | I15: =C15*H15 -> 0.00010127169
B16: Induct Mailer APC (Sacks) | C16: =C12 -> 0.028368278 | D16: ='Conversion Factors'!$I$23 -> 465.37758 | E16: ='Productivity Data'!$I$40 -> 23.065925 | F16: ='Wage Data'!$C$11 -> 49.154295 | G16: ='Cost Pool Data'!$K$42 -> 1.5176144 | H16: =(F16*G16)/(D16*E16) -> 0.006949388 | I16: =C16*H16 -> 0.00019714217
B17: Sack Sorting Machine | C17: =(C15+C16)*(1+'Other Inputs'!$B$9) -> 0.042403642 | D17: ='Mailer Arrival Profile'!$I$10 -> 17.04918 | E17: ='Productivity Data'!$I$19 -> 3068.1109 | F17: ='Wage Data'!$C$11 -> 49.154295 | G17: ='Cost Pool Data'!$K$46 -> 1.6196175 | H17: =(F17*G17)/(D17*E17) -> 0.0015219464 | I17: =C17*H17 -> 6.453607e-05
B18: Sack Shake Out | C18: =(C15+C16) -> 0.040679384 | D18: ='Mailer Arrival Profile'!$I$10 -> 17.04918 | E18: ='Productivity Data'!$I$43 -> 146.75955 | F18: ='Wage Data'!$C$11 -> 49.154295 | G18: ='Cost Pool Data'!$K$42 -> 1.5176144 | H18: =(F18*G18)/(D18*E18) -> 0.029813505 | I18: =C18*H18 -> 0.001212795
B19: Secondary Parcel Sorting Machine | C19: =(C13+C14+C18)*(1+'Other Inputs'!$B$8) -> 1.1202872 | D19: 1 | E19: ='Productivity Data'!$I$18 -> 331.3648 | F19: ='Wage Data'!$C$11 -> 49.154295 | G19: ='Cost Pool Data'!$L$45 -> 2.0700178 | H19: =(F19*G19)/(D19*E19) -> 0.30706419 | I19: =C19*H19 -> 0.34400008
B20: Manually Apply Barcode Label | C20: =(C13+C14+C18)*('Other Inputs'!$B$8) -> 0.12028717 | D20: 1 | E20: ='Productivity Data'!$I$47 -> 221.38134 | F20: ='Wage Data'!$C$11 -> 49.154295 | G20: ='Cost Pool Data'!$K$42 -> 1.5176144 | H20: =(F20*G20)/(D20*E20) -> 0.33696274 | I20: =C20*H20 -> 0.040532296
B21: Induct Wiretainer | C21: =C20 -> 0.12028717 | D21: ='Conversion Factors'!$I$34 -> 374.54068 | E21: ='Productivity Data'!$I$40 -> 23.065925 | F21: ='Wage Data'!$C$11 -> 49.154295 | G21: ='Cost Pool Data'!$K$42 -> 1.5176144 | H21: =(F21*G21)/(D21*E21) -> 0.0086348147 | I21: =C21*H21 -> 0.0010386575
B22: Load Postal Pallet Box | C22: =(C13+C14+C18)*'Postal Arrival-Dispatch Profile'!$B$21 -> 0.11896972 | D22: ='Conversion Factors'!$I$43 -> 523.14013 | E22: ='Productivity Data'!$I$45 -> 55.582256 | F22: ='Wage Data'!$C$11 -> 49.154295 | G22: ='Cost Pool Data'!$K$43 -> 1.3860239 | H22: =(F22*G22)/(D22*E22) -> 0.0023430307 | I22: =C22*H22 -> 0.0002787497
B23: Load Postal APC | C23: =(C13+C14+C18)*'Postal Arrival-Dispatch Profile'!$B$22 -> 0.080349918 | D23: ='Conversion Factors'!$I$44 -> 354.97968 | E23: ='Productivity Data'!$I$44 -> 70.608822 | F23: ='Wage Data'!$C$11 -> 49.154295 | G23: ='Cost Pool Data'!$K$43 -> 1.3860239 | H23: =(F23*G23)/(D23*E23) -> 0.0027181269 | I23: =C23*H23 -> 0.00021840128
B24: Load Postal OTR | C24: =(C13+C14+C18)*'Postal Arrival-Dispatch Profile'!$B$23 -> 0.60164686 | D24: ='Conversion Factors'!$I$45 -> 667.89093 | E24: ='Productivity Data'!$I$44 -> 70.608822 | F24: ='Wage Data'!$C$11 -> 49.154295 | G24: ='Cost Pool Data'!$K$43 -> 1.3860239 | H24: =(F24*G24)/(D24*E24) -> 0.0014446667 | I24: =C24*H24 -> 0.00086917921
B25: Load Postal Wiretainer | C25: =(C13+C14+C18)*'Postal Arrival-Dispatch Profile'!$B$24 -> 0.19903351 | D25: ='Conversion Factors'!$I$46 -> 343.25976 | E25: ='Productivity Data'!$I$44 -> 70.608822 | F25: ='Wage Data'!$C$11 -> 49.154295 | G25: ='Cost Pool Data'!$K$43 -> 1.3860239 | H25: =(F25*G25)/(D25*E25) -> 0.0028109319 | I25: =C25*H25 -> 0.00055946963 | J25: =SUM(I9:I25) -> 0.39798171
A26: Destination | B26: Unload Postal Pallet Box | C26: =C22*'Other Inputs'!$B$20 -> 0.011342186 | D26: ='Conversion Factors'!$I$43 -> 523.14013 | E26: ='Productivity Data'!$I$34 -> 58.924683 | F26: ='Wage Data'!$C$11 -> 49.154295 | G26: ='Cost Pool Data'!$K$27 -> 1.3606062 | H26: =(F26*G26)/(D26*E26) -> 0.0021695947 | I26: =C26*H26 -> 2.4607947e-05
A27: ASF | B27: Unload Postal APC | C27: =C23*'Other Inputs'!$B$20 -> 0.0076602999 | D27: ='Conversion Factors'!$I$44 -> 354.97968 | E27: ='Productivity Data'!$I$33 -> 74.63792 | F27: ='Wage Data'!$C$11 -> 49.154295 | G27: ='Cost Pool Data'!$K$27 -> 1.3606062 | H27: =(F27*G27)/(D27*E27) -> 0.0025242415 | I27: =C27*H27 -> 1.9336447e-05
B28: Unload Postal OTR | C28: =C24*'Other Inputs'!$B$20 -> 0.057359055 | D28: ='Conversion Factors'!$I$45 -> 667.89093 | E28: ='Productivity Data'!$I$33 -> 74.63792 | F28: ='Wage Data'!$C$11 -> 49.154295 | G28: ='Cost Pool Data'!$K$27 -> 1.3606062 | H28: =(F28*G28)/(D28*E28) -> 0.0013416179 | I28: =C28*H28 -> 7.6953934e-05
B29: Unload Postal Wiretainer | C29: =C25*'Other Inputs'!$B$20 -> 0.018975207 | D29: ='Conversion Factors'!$I$46 -> 343.25976 | E29: ='Productivity Data'!$I$33 -> 74.63792 | F29: ='Wage Data'!$C$11 -> 49.154295 | G29: ='Cost Pool Data'!$K$27 -> 1.3606062 | H29: =(F29*G29)/(D29*E29) -> 0.0026104266 | I29: =C29*H29 -> 4.9533386e-05
B30: APPS Incoming Sort | C30: ='Other Inputs'!$B$17*(1+'Other Inputs'!$B$10) -> 0.041075214 | D30: 1 | E30: ='Productivity Data'!$I$10 -> 245.20306 | F30: ='Wage Data'!$C$11 -> 49.154295 | G30: ='Cost Pool Data'!$L$14 -> 1.8052502 | H30: =(F30*G30)/(D30*E30) -> 0.36188702 | I30: =C30*H30 -> 0.014864587
B31: APBS / LIPS Incoming Sort | C31: ='Other Inputs'!$B$18*(1+'Other Inputs'!$B$11) -> 0.026656992 | D31: 1 | E31: ='Productivity Data'!$I$11 -> 190.80521 | F31: ='Wage Data'!$C$11 -> 49.154295 | G31: ='Cost Pool Data'!$L$11 -> 1.6056413 | H31: =(F31*G31)/(D31*E31) -> 0.41363736 | I31: =C31*H31 -> 0.011026328
B32: Manual Incoming Sort | C32: ='Other Inputs'!$B$19 -> 0.034773485 | D32: 1 | E32: ='Productivity Data'!$I$15 -> 47.99469 | F32: ='Wage Data'!$C$11 -> 49.154295 | G32: ='Cost Pool Data'!$K$16 -> 1.3208756 | H32: =(F32*G32)/(D32*E32) -> 1.3527894 | I32: =C32*H32 -> 0.047041203
B33: Load Postal Hamper | C33: =SUM(C26:C29) -> 0.095336748 | D33: ='Conversion Factors'!$I$48 -> 204.2672 | E33: ='Productivity Data'!$I$35 -> 82.063609 | F33: ='Wage Data'!$C$11 -> 49.154295 | G33: ='Cost Pool Data'!$K$27 -> 1.3606062 | H33: =(F33*G33)/(D33*E33) -> 0.0039897406 | I33: =C33*H33 -> 0.0003803689 | J33: =SUM(I26:I33) -> 0.073482918
A34: Destination | B34: Unload Postal Pallet Box | C34: =C22*(1-'Other Inputs'!$B$20) -> 0.10762753 | D34: ='Conversion Factors'!$I$43 -> 523.14013 | E34: ='Productivity Data'!$I$28 -> 58.156985 | F34: ='Wage Data'!$C$11 -> 49.154295 | G34: ='Cost Pool Data'!$K$27 -> 1.3606062 | H34: =(F34*G34)/(D34*E34) -> 0.0021982344 | I34: =C34*H34 -> 0.00023659054
A35: P&DC / P&DF | B35: Unload Postal APC | C35: =C23*(1-'Other Inputs'!$B$20) -> 0.072689618 | D35: ='Conversion Factors'!$I$44 -> 354.97968 | E35: ='Productivity Data'!$I$27 -> 81.873572 | F35: ='Wage Data'!$C$11 -> 49.154295 | G35: ='Cost Pool Data'!$K$27 -> 1.3606062 | H35: =(F35*G35)/(D35*E35) -> 0.0023011593 | I35: =C35*H35 -> 0.00016727039
B36: Unload Postal OTR | C36: =C24*(1-'Other Inputs'!$B$20) -> 0.5442878 | D36: ='Conversion Factors'!$I$45 -> 667.89093 | E36: ='Productivity Data'!$I$27 -> 81.873572 | F36: ='Wage Data'!$C$11 -> 49.154295 | G36: ='Cost Pool Data'!$K$27 -> 1.3606062 | H36: =(F36*G36)/(D36*E36) -> 0.0012230512 | I36: =C36*H36 -> 0.00066569183
B37: Unload Postal Wiretainer | C37: =C25*(1-'Other Inputs'!$B$20) -> 0.1800583 | D37: ='Conversion Factors'!$I$46 -> 343.25976 | E37: ='Productivity Data'!$I$27 -> 81.873572 | F37: ='Wage Data'!$C$11 -> 49.154295 | G37: ='Cost Pool Data'!$K$27 -> 1.3606062 | H37: =(F37*G37)/(D37*E37) -> 0.0023797278 | I37: =C37*H37 -> 0.00042848973
B38: Unload Postal Hamper | C38: ='Other Inputs'!$B$23 -> 0.052796652 | D38: ='Conversion Factors'!$I$48 -> 204.2672 | E38: ='Productivity Data'!$I$27 -> 81.873572 | F38: ='Wage Data'!$C$11 -> 49.154295 | G38: ='Cost Pool Data'!$K$27 -> 1.3606062 | H38: =(F38*G38)/(D38*E38) -> 0.0039990012 | I38: =C38*H38 -> 0.00021113388
B39: Crossdock Postal Pallet Box | C39: =C34 -> 0.10762753 | D39: ='Conversion Factors'!$I$43 -> 523.14013 | E39: ='Productivity Data'!$I$30 -> 39.899251 | F39: ='Wage Data'!$C$11 -> 49.154295 | G39: ='Cost Pool Data'!$K$27 -> 1.3606062 | H39: =(F39*G39)/(D39*E39) -> 0.0032041374 | I39: =C39*H39 -> 0.0003448534
B40: Crossdock Postal APC | C40: =C35 -> 0.072689618 | D40: ='Conversion Factors'!$I$44 -> 354.97968 | E40: ='Productivity Data'!$I$29 -> 50.764395 | F40: ='Wage Data'!$C$11 -> 49.154295 | G40: ='Cost Pool Data'!$K$27 -> 1.3606062 | H40: =(F40*G40)/(D40*E40) -> 0.003711344 | I40: =C40*H40 -> 0.00026977618
B41: Crossdock Postal OTR | C41: =C36 -> 0.5442878 | D41: ='Conversion Factors'!$I$45 -> 667.89093 | E41: ='Productivity Data'!$I$29 -> 50.764395 | F41: ='Wage Data'!$C$11 -> 49.154295 | G41: ='Cost Pool Data'!$K$27 -> 1.3606062 | H41: =(F41*G41)/(D41*E41) -> 0.0019725551 | I41: =C41*H41 -> 0.0010736377
B42: Crossdock Postal Wiretainer | C42: =C37 -> 0.1800583 | D42: ='Conversion Factors'!$I$46 -> 343.25976 | E42: ='Productivity Data'!$I$29 -> 50.764395 | F42: ='Wage Data'!$C$11 -> 49.154295 | G42: ='Cost Pool Data'!$K$27 -> 1.3606062 | H42: =(F42*G42)/(D42*E42) -> 0.0038380604 | I42: =C42*H42 -> 0.00069107462
B43: Crossdock Postal Hamper | C43: =C38 -> 0.052796652 | D43: ='Conversion Factors'!$I$48 -> 204.2672 | E43: ='Productivity Data'!$I$29 -> 50.764395 | F43: ='Wage Data'!$C$11 -> 49.154295 | G43: ='Cost Pool Data'!$K$27 -> 1.3606062 | H43: =(F43*G43)/(D43*E43) -> 0.0064496487 | I43: =C43*H43 -> 0.00034051986
B44: Load Postal Pallet Box | C44: =C34 -> 0.10762753 | D44: ='Conversion Factors'!$I$43 -> 523.14013 | E44: ='Productivity Data'!$I$32 -> 61.728449 | F44: ='Wage Data'!$C$11 -> 49.154295 | G44: ='Cost Pool Data'!$K$27 -> 1.3606062 | H44: =(F44*G44)/(D44*E44) -> 0.0020710497 | I44: =C44*H44 -> 0.00022290196
B45: Load Postal APC | C45: =C35 -> 0.072689618 | D45: ='Conversion Factors'!$I$44 -> 354.97968 | E45: ='Productivity Data'!$I$31 -> 91.071588 | F45: ='Wage Data'!$C$11 -> 49.154295 | G45: ='Cost Pool Data'!$K$27 -> 1.3606062 | H45: =(F45*G45)/(D45*E45) -> 0.0020687476 | I45: =C45*H45 -> 0.00015037648
B46: Load Postal OTR | C46: =C36 -> 0.5442878 | D46: ='Conversion Factors'!$I$45 -> 667.89093 | E46: ='Productivity Data'!$I$31 -> 91.071588 | F46: ='Wage Data'!$C$11 -> 49.154295 | G46: ='Cost Pool Data'!$K$27 -> 1.3606062 | H46: =(F46*G46)/(D46*E46) -> 0.0010995259 | I46: =C46*H46 -> 0.00059845853
B47: Load Postal Wiretainer | C47: =C42 -> 0.1800583 | D47: ='Conversion Factors'!$I$46 -> 343.25976 | E47: ='Productivity Data'!$I$31 -> 91.071588 | F47: ='Wage Data'!$C$11 -> 49.154295 | G47: ='Cost Pool Data'!$K$27 -> 1.3606062 | H47: =(F47*G47)/(D47*E47) -> 0.0021393809 | I47: =C47*H47 -> 0.00038521328
B48: Load Postal Hamper | C48: =C43 -> 0.052796652 | D48: ='Conversion Factors'!$I$48 -> 204.2672 | E48: ='Productivity Data'!$I$31 -> 91.071588 | F48: ='Wage Data'!$C$11 -> 49.154295 | G48: ='Cost Pool Data'!$K$27 -> 1.3606062 | H48: =(F48*G48)/(D48*E48) -> 0.0035951115 | I48: =C48*H48 -> 0.00018980985 | J48: =SUM(I34:I48) -> 0.0059757982
A49: Destination | B49: Unload Postal Pallet Box | C49: =C44 -> 0.10762753 | D49: ='Conversion Factors'!$I$43 -> 523.14013 | E49: ='Productivity Data'!$I$26 -> 48.580344 | F49: ='Wage Data'!$C$11 -> 49.154295 | G49: ='Cost Pool Data'!$K$48 -> 1.6214861 | H49: =(F49*G49)/(D49*E49) -> 0.0031361445 | I49: =C49*H49 -> 0.00033753549
A50: DU | B50: Unload Postal APC | C50: =C45 -> 0.072689618 | D50: ='Conversion Factors'!$I$44 -> 354.97968 | E50: ='Productivity Data'!$I$25 -> 60.332591 | F50: ='Wage Data'!$C$11 -> 49.154295 | G50: ='Cost Pool Data'!$K$48 -> 1.6214861 | H50: =(F50*G50)/(D50*E50) -> 0.0037215103 | I50: =C50*H50 -> 0.00027051516
B51: Unload Postal OTR | C51: =C46 -> 0.5442878 | D51: ='Conversion Factors'!$I$45 -> 667.89093 | E51: ='Productivity Data'!$I$25 -> 60.332591 | F51: ='Wage Data'!$C$11 -> 49.154295 | G51: ='Cost Pool Data'!$K$48 -> 1.6214861 | H51: =(F51*G51)/(D51*E51) -> 0.0019779584 | I51: =C51*H51 -> 0.0010765787
B52: Unload Postal Wiretainer | C52: =C47 -> 0.1800583 | D52: ='Conversion Factors'!$I$46 -> 343.25976 | E52: ='Productivity Data'!$I$25 -> 60.332591 | F52: ='Wage Data'!$C$11 -> 49.154295 | G52: ='Cost Pool Data'!$K$48 -> 1.6214861 | H52: =(F52*G52)/(D52*E52) -> 0.0038485737 | I52: =C52*H52 -> 0.00069296764
B53: Unload Postal Hamper | C53: =C33 -> 0.095336748 | D53: ='Conversion Factors'!$I$48 -> 204.2672 | E53: ='Productivity Data'!$I$25 -> 60.332591 | F53: ='Wage Data'!$C$11 -> 49.154295 | G53: ='Cost Pool Data'!$K$48 -> 1.6214861 | H53: =(F53*G53)/(D53*E53) -> 0.0064673159 | I53: =C53*H53 -> 0.00061657286
B54: Incoming Secondary Parcel Sort | C54: =SUM(C49:C53) -> 1 | D54: 1 | E54: ='Productivity Data'!$I$22 -> 307.66823 | F54: ='Wage Data'!$C$11 -> 49.154295 | G54: ='Cost Pool Data'!$K$57 -> 1.4957787 | H54: =(F54*G54)/(D54*E54) -> 0.23897152 | I54: =C54*H54 -> 0.23897152 | J54: =SUM(I49:I54) -> 0.24196569
A56: Sources: | I56: Grand Total | J56: =J25+J33+J48+J54 -> 0.71940612
A57: [1]: Page 7, 8, 9
A58: [2]: Page 7, 10
A59: [3]: Page 5
A60: [4]: Page 6
A61: [5]: Page 3
A62: [6]: ( [4] * [5] ) / ( [2] * [3] )
A63: [7]: [1] * [6]

Sheet M-DNDC-5D
A1: USPS MARKETING MAIL MACHINABLE DNDC 5-DIGIT PRESORT PARCELS
C4: [1] | D4: [2] | E4: [3] | F4: [4] | G4: [5] | H4: [6] | I4: [7]
F5: Adjusted | H5: Cost | I5: Cost
D6: Conversion | E6: Units | F6: Wage | G6: Piggyback | H6: Per | I6: Per
A7: Facility | B7: Operation | C7: Handlings | D7: Factor | E7: Per Hour | F7: Rate | G7: Factor | H7: Operation | I7: Facility
A9: Destination | B9: Unload Mailer Pallet Box | C9: ='Mailer Arrival Profile'!$C$11 -> 0 | D9: ='Conversion Factors'!$I$20 -> 534.04625 | E9: ='Productivity Data'!$I$38 -> 46.475052 | F9: ='Wage Data'!$C$11 -> 49.154295 | G9: ='Cost Pool Data'!$K$43 -> 1.3860239 | H9: =(F9*G9)/(D9*E9) -> 0.0027449437 | I9: =C9*H9 -> 0
A10: NDC | B10: Unload Mailer Pallet (Pieces) | C10: ='Mailer Arrival Profile'!$D$11 -> 0.045113611 | D10: ='Conversion Factors'!$I$21 -> 854.18447 | E10: ='Productivity Data'!$I$38 -> 46.475052 | F10: ='Wage Data'!$C$11 -> 49.154295 | G10: ='Cost Pool Data'!$K$43 -> 1.3860239 | H10: =(F10*G10)/(D10*E10) -> 0.0017161713 | I10: =C10*H10 -> 7.7422684e-05
B11: Unload Mailer Pallet (Sacks) | C11: ='Mailer Arrival Profile'!$E$11 -> 0.95488639 | D11: ='Conversion Factors'!$I$22 -> 550.13579 | E11: ='Productivity Data'!$I$38 -> 46.475052 | F11: ='Wage Data'!$C$11 -> 49.154295 | G11: ='Cost Pool Data'!$K$43 -> 1.3860239 | H11: =(F11*G11)/(D11*E11) -> 0.0026646637 | I11: =C11*H11 -> 0.0025444511
B12: Unload Mailer APC (Sacks) | C12: ='Mailer Arrival Profile'!$F$11 -> 0 | D12: ='Conversion Factors'!$I$23 -> 465.37758 | E12: ='Productivity Data'!$I$37 -> 55.996737 | F12: ='Wage Data'!$C$11 -> 49.154295 | G12: ='Cost Pool Data'!$K$43 -> 1.3860239 | H12: =(F12*G12)/(D12*E12) -> 0.0026143517 | I12: =C12*H12 -> 0
B13: Induct Mailer Pallet (Sacks) | C13: =C11 -> 0.95488639 | D13: ='Conversion Factors'!$I$22 -> 550.13579 | E13: ='Productivity Data'!$I$41 -> 16.483977 | F13: ='Wage Data'!$C$11 -> 49.154295 | G13: ='Cost Pool Data'!$K$42 -> 1.5176144 | H13: =(F13*G13)/(D13*E13) -> 0.0082260435 | I13: =C13*H13 -> 0.007854937
B14: Induct Mailer APC (Sacks) | C14: =C12 -> 0 | D14: ='Conversion Factors'!$I$23 -> 465.37758 | E14: ='Productivity Data'!$I$40 -> 23.065925 | F14: ='Wage Data'!$C$11 -> 49.154295 | G14: ='Cost Pool Data'!$K$42 -> 1.5176144 | H14: =(F14*G14)/(D14*E14) -> 0.006949388 | I14: =C14*H14 -> 0
B15: Sack Sorting Machine | C15: =(C13+C14)*(1+'Other Inputs'!$B$9) -> 0.99536071 | D15: ='Mailer Arrival Profile'!$I$11 -> 33.104839 | E15: ='Productivity Data'!$I$19 -> 3068.1109 | F15: ='Wage Data'!$C$11 -> 49.154295 | G15: ='Cost Pool Data'!$K$46 -> 1.6196175 | H15: =(F15*G15)/(D15*E15) -> 0.00078381106 | I15: =C15*H15 -> 0.00078017473
B16: Load Mailer Pallet Box | C16: =C9 -> 0 | D16: ='Conversion Factors'!$I$20 -> 534.04625 | E16: ='Productivity Data'!$I$45 -> 55.582256 | F16: ='Wage Data'!$C$11 -> 49.154295 | G16: ='Cost Pool Data'!$K$43 -> 1.3860239 | H16: =(F16*G16)/(D16*E16) -> 0.0022951821 | I16: =C16*H16 -> 0
B17: Load Mailer Pallet (Pieces) | C17: =C10 -> 0.045113611 | D17: ='Conversion Factors'!$I$21 -> 854.18447 | E17: ='Productivity Data'!$I$45 -> 55.582256 | F17: ='Wage Data'!$C$11 -> 49.154295 | G17: ='Cost Pool Data'!$K$43 -> 1.3860239 | H17: =(F17*G17)/(D17*E17) -> 0.001434975 | I17: =C17*H17 -> 6.4736906e-05
B18: Load Postal Pallet Box | C18: =(C13+C14)*'Postal Arrival-Dispatch Profile'!$B$21 -> 0.11360256 | D18: ='Conversion Factors'!$I$43 -> 523.14013 | E18: ='Productivity Data'!$I$45 -> 55.582256 | F18: ='Wage Data'!$C$11 -> 49.154295 | G18: ='Cost Pool Data'!$K$43 -> 1.3860239 | H18: =(F18*G18)/(D18*E18) -> 0.0023430307 | I18: =C18*H18 -> 0.0002661743
B19: Load Postal APC | C19: =(C13+C14)*'Postal Arrival-Dispatch Profile'!$B$22 -> 0.076725043 | D19: ='Conversion Factors'!$I$44 -> 354.97968 | E19: ='Productivity Data'!$I$44 -> 70.608822 | F19: ='Wage Data'!$C$11 -> 49.154295 | G19: ='Cost Pool Data'!$K$43 -> 1.3860239 | H19: =(F19*G19)/(D19*E19) -> 0.0027181269 | I19: =C19*H19 -> 0.00020854841
B20: Load Postal OTR | C20: =(C13+C14)*'Postal Arrival-Dispatch Profile'!$B$23 -> 0.5745044 | D20: ='Conversion Factors'!$I$45 -> 667.89093 | E20: ='Productivity Data'!$I$44 -> 70.608822 | F20: ='Wage Data'!$C$11 -> 49.154295 | G20: ='Cost Pool Data'!$K$43 -> 1.3860239 | H20: =(F20*G20)/(D20*E20) -> 0.0014446667 | I20: =C20*H20 -> 0.00082996739
B21: Load Postal Wiretainer | C21: =(C13+C14)*'Postal Arrival-Dispatch Profile'!$B$24 -> 0.19005439 | D21: ='Conversion Factors'!$I$46 -> 343.25976 | E21: ='Productivity Data'!$I$44 -> 70.608822 | F21: ='Wage Data'!$C$11 -> 49.154295 | G21: ='Cost Pool Data'!$K$43 -> 1.3860239 | H21: =(F21*G21)/(D21*E21) -> 0.0028109319 | I21: =C21*H21 -> 0.00053422993 | J21: =SUM(I9:I21) -> 0.013160642
A22: Destination | B22: Unload Mailer Pallet Box | C22: =C16 -> 0 | D22: ='Conversion Factors'!$I$20 -> 534.04625 | E22: ='Productivity Data'!$I$28 -> 58.156985 | F22: ='Wage Data'!$C$11 -> 49.154295 | G22: ='Cost Pool Data'!$K$27 -> 1.3606062 | H22: =(F22*G22)/(D22*E22) -> 0.0021533427 | I22: =C22*H22 -> 0
A23: P&DC / P&DF | B23: Unload Mailer Pallet (Pieces) | C23: =C17 -> 0.045113611 | D23: ='Conversion Factors'!$I$21 -> 854.18447 | E23: ='Productivity Data'!$I$28 -> 58.156985 | F23: ='Wage Data'!$C$11 -> 49.154295 | G23: ='Cost Pool Data'!$K$27 -> 1.3606062 | H23: =(F23*G23)/(D23*E23) -> 0.0013462954 | I23: =C23*H23 -> 6.0736247e-05
B24: Unload Postal Pallet Box | C24: =C18 -> 0.11360256 | D24: ='Conversion Factors'!$I$43 -> 523.14013 | E24: ='Productivity Data'!$I$28 -> 58.156985 | F24: ='Wage Data'!$C$11 -> 49.154295 | G24: ='Cost Pool Data'!$K$27 -> 1.3606062 | H24: =(F24*G24)/(D24*E24) -> 0.0021982344 | I24: =C24*H24 -> 0.00024972506
B25: Unload Postal APC | C25: =C19 -> 0.076725043 | D25: ='Conversion Factors'!$I$44 -> 354.97968 | E25: ='Productivity Data'!$I$27 -> 81.873572 | F25: ='Wage Data'!$C$11 -> 49.154295 | G25: ='Cost Pool Data'!$K$27 -> 1.3606062 | H25: =(F25*G25)/(D25*E25) -> 0.0023011593 | I25: =C25*H25 -> 0.00017655655
B26: Unload Postal OTR | C26: =C20 -> 0.5745044 | D26: ='Conversion Factors'!$I$45 -> 667.89093 | E26: ='Productivity Data'!$I$27 -> 81.873572 | F26: ='Wage Data'!$C$11 -> 49.154295 | G26: ='Cost Pool Data'!$K$27 -> 1.3606062 | H26: =(F26*G26)/(D26*E26) -> 0.0012230512 | I26: =C26*H26 -> 0.00070264827
B27: Unload Postal Wiretainer | C27: =C21 -> 0.19005439 | D27: ='Conversion Factors'!$I$46 -> 343.25976 | E27: ='Productivity Data'!$I$27 -> 81.873572 | F27: ='Wage Data'!$C$11 -> 49.154295 | G27: ='Cost Pool Data'!$K$27 -> 1.3606062 | H27: =(F27*G27)/(D27*E27) -> 0.0023797278 | I27: =C27*H27 -> 0.0004522777
B28: Crossdock Mailer Pallet Box | C28: =C22 -> 0 | D28: ='Conversion Factors'!$I$20 -> 534.04625 | E28: ='Productivity Data'!$I$30 -> 39.899251 | F28: ='Wage Data'!$C$11 -> 49.154295 | G28: ='Cost Pool Data'!$K$27 -> 1.3606062 | H28: =(F28*G28)/(D28*E28) -> 0.0031387036 | I28: =C28*H28 -> 0
B29: Crossdock Mailer Pallet (Pieces) | C29: =C23 -> 0.045113611 | D29: ='Conversion Factors'!$I$21 -> 854.18447 | E29: ='Productivity Data'!$I$30 -> 39.899251 | F29: ='Wage Data'!$C$11 -> 49.154295 | G29: ='Cost Pool Data'!$K$27 -> 1.3606062 | H29: =(F29*G29)/(D29*E29) -> 0.0019623546 | I29: =C29*H29 -> 8.8528904e-05
B30: Sack Incoming Sort | C30: =SUM(C24:C27) -> 0.95488639 | D30: ='Mailer Arrival Profile'!$I$11 -> 33.104839 | E30: ='Productivity Data'!$I$14 -> 49.323982 | F30: ='Wage Data'!$C$11 -> 49.154295 | G30: ='Cost Pool Data'!$K$30 -> 1.2805163 | H30: =(F30*G30)/(D30*E30) -> 0.038547567 | I30: =C30*H30 -> 0.036808547
B31: Load Mailer Pallet Box | C31: =C28 -> 0 | D31: ='Conversion Factors'!$I$20 -> 534.04625 | E31: ='Productivity Data'!$I$32 -> 61.728449 | F31: ='Wage Data'!$C$11 -> 49.154295 | G31: ='Cost Pool Data'!$K$27 -> 1.3606062 | H31: =(F31*G31)/(D31*E31) -> 0.0020287554 | I31: =C31*H31 -> 0
B32: Load Mailer Pallet (Pieces) | C32: =C29 -> 0.045113611 | D32: ='Conversion Factors'!$I$21 -> 854.18447 | E32: ='Productivity Data'!$I$32 -> 61.728449 | F32: ='Wage Data'!$C$11 -> 49.154295 | G32: ='Cost Pool Data'!$K$27 -> 1.3606062 | H32: =(F32*G32)/(D32*E32) -> 0.0012684019 | I32: =C32*H32 -> 5.722219e-05
B33: Load Postal Hamper | C33: =C30 -> 0.95488639 | D33: ='Conversion Factors'!$I$48 -> 204.2672 | E33: ='Productivity Data'!$I$31 -> 91.071588 | F33: ='Wage Data'!$C$11 -> 49.154295 | G33: ='Cost Pool Data'!$K$27 -> 1.3606062 | H33: =(F33*G33)/(D33*E33) -> 0.0035951115 | I33: =C33*H33 -> 0.0034329231 | J33: =SUM(I22:I33) -> 0.042029165
A34: Destination | B34: Unload Mailer Pallet Box | C34: =C31 -> 0 | D34: ='Conversion Factors'!$I$20 -> 534.04625 | E34: ='Productivity Data'!$I$26 -> 48.580344 | F34: ='Wage Data'!$C$11 -> 49.154295 | G34: ='Cost Pool Data'!$K$48 -> 1.6214861 | H34: =(F34*G34)/(D34*E34) -> 0.0030720992 | I34: =C34*H34 -> 0
A35: DU | B35: Unload Mailer Pallet (Pieces) | C35: =C32 -> 0.045113611 | D35: ='Conversion Factors'!$I$21 -> 854.18447 | E35: ='Productivity Data'!$I$26 -> 48.580344 | F35: ='Wage Data'!$C$11 -> 49.154295 | G35: ='Cost Pool Data'!$K$48 -> 1.6214861 | H35: =(F35*G35)/(D35*E35) -> 0.0019207128 | I35: =C35*H35 -> 8.6650291e-05
B36: Unload Postal Hamper | C36: =C33 -> 0.95488639 | D36: ='Conversion Factors'!$I$48 -> 204.2672 | E36: ='Productivity Data'!$I$25 -> 60.332591 | F36: ='Wage Data'!$C$11 -> 49.154295 | G36: ='Cost Pool Data'!$K$48 -> 1.6214861 | H36: =(F36*G36)/(D36*E36) -> 0.0064673159 | I36: =C36*H36 -> 0.0061755519
B37: Incoming Secondary Parcel Sort | C37: =SUM(C34:C36) -> 1 | D37: 1 | E37: ='Productivity Data'!$I$22 -> 307.66823 | F37: ='Wage Data'!$C$11 -> 49.154295 | G37: ='Cost Pool Data'!$K$57 -> 1.4957787 | H37: =(F37*G37)/(D37*E37) -> 0.23897152 | I37: =C37*H37 -> 0.23897152 | J37: =SUM(I34:I37) -> 0.24523372
A39: Sources: | I39: Grand Total | J39: =J21+J33+J37 -> 0.30042353
A40: [1]: Page 7, 8, 9
A41: [2]: Page 7, 10
A42: [3]: Page 5
A43: [4]: Page 6
A44: [5]: Page 3
A45: [6]: ( [4] * [5] ) / ( [2] * [3] )
A46: [7]: [1] * [6]

Sheet M-DSCF-5D
A1: USPS MARKETING MAIL MACHINABLE DSCF 5-DIGIT PRESORT PARCELS
C4: [1] | D4: [2] | E4: [3] | F4: [4] | G4: [5] | H4: [6] | I4: [7]
F5: Adjusted | H5: Cost | I5: Cost
D6: Conversion | E6: Units | F6: Wage | G6: Piggyback | H6: Per | I6: Per
A7: Facility | B7: Operation | C7: Handlings | D7: Factor | E7: Per Hour | F7: Rate | G7: Factor | H7: Operation | I7: Facility
A9: Destination | B9: Unload Mailer Pallet Box | C9: ='Mailer Arrival Profile'!$C$12 -> 0.094705277 | D9: ='Conversion Factors'!$I$20 -> 534.04625 | E9: ='Productivity Data'!$I$28 -> 58.156985 | F9: ='Wage Data'!$C$11 -> 49.154295 | G9: ='Cost Pool Data'!$K$27 -> 1.3606062 | H9: =(F9*G9)/(D9*E9) -> 0.0021533427 | I9: =C9*H9 -> 0.00020393292
A10: P&DC / P&DF | B10: Unload Mailer Pallet (Pieces) | C10: ='Mailer Arrival Profile'!$D$12 -> 0.03893837 | D10: ='Conversion Factors'!$I$21 -> 854.18447 | E10: ='Productivity Data'!$I$28 -> 58.156985 | F10: ='Wage Data'!$C$11 -> 49.154295 | G10: ='Cost Pool Data'!$K$27 -> 1.3606062 | H10: =(F10*G10)/(D10*E10) -> 0.0013462954 | I10: =C10*H10 -> 5.2422548e-05
B11: Unload Mailer Pallet (Sacks) | C11: ='Mailer Arrival Profile'!$E$12 -> 0.83717495 | D11: ='Conversion Factors'!$I$22 -> 550.13579 | E11: ='Productivity Data'!$I$28 -> 58.156985 | F11: ='Wage Data'!$C$11 -> 49.154295 | G11: ='Cost Pool Data'!$K$27 -> 1.3606062 | H11: =(F11*G11)/(D11*E11) -> 0.002090365 | I11: =C11*H11 -> 0.0017500012
B12: Unload Mailer APC (Sacks) | C12: ='Mailer Arrival Profile'!$F$12 -> 0.029181399 | D12: ='Conversion Factors'!$I$23 -> 465.37758 | E12: ='Productivity Data'!$I$27 -> 81.873572 | F12: ='Wage Data'!$C$11 -> 49.154295 | G12: ='Cost Pool Data'!$K$27 -> 1.3606062 | H12: =(F12*G12)/(D12*E12) -> 0.0017552732 | I12: =C12*H12 -> 5.1221327e-05
B13: Crossdock Mailer Pallet Box | C13: =C9 -> 0.094705277 | D13: ='Conversion Factors'!$I$20 -> 534.04625 | E13: ='Productivity Data'!$I$30 -> 39.899251 | F13: ='Wage Data'!$C$11 -> 49.154295 | G13: ='Cost Pool Data'!$K$27 -> 1.3606062 | H13: =(F13*G13)/(D13*E13) -> 0.0031387036 | I13: =C13*H13 -> 0.00029725179
B14: Crossdock Mailer Pallet (Pieces) | C14: =C10 -> 0.03893837 | D14: ='Conversion Factors'!$I$21 -> 854.18447 | E14: ='Productivity Data'!$I$30 -> 39.899251 | F14: ='Wage Data'!$C$11 -> 49.154295 | G14: ='Cost Pool Data'!$K$27 -> 1.3606062 | H14: =(F14*G14)/(D14*E14) -> 0.0019623546 | I14: =C14*H14 -> 7.6410891e-05
B15: Sack Incoming Sort | C15: =C11+C12 -> 0.86635635 | D15: ='Mailer Arrival Profile'!$I$12 -> 33.104839 | E15: ='Productivity Data'!$I$14 -> 49.323982 | F15: ='Wage Data'!$C$11 -> 49.154295 | G15: ='Cost Pool Data'!$K$30 -> 1.2805163 | H15: =(F15*G15)/(D15*E15) -> 0.038547567 | I15: =C15*H15 -> 0.03339593
B16: Load Mailer Pallet Box | C16: =C13 -> 0.094705277 | D16: ='Conversion Factors'!$I$20 -> 534.04625 | E16: ='Productivity Data'!$I$32 -> 61.728449 | F16: ='Wage Data'!$C$11 -> 49.154295 | G16: ='Cost Pool Data'!$K$27 -> 1.3606062 | H16: =(F16*G16)/(D16*E16) -> 0.0020287554 | I16: =C16*H16 -> 0.00019213384
B17: Load Mailer Pallet (Pieces) | C17: =C14 -> 0.03893837 | D17: ='Conversion Factors'!$I$21 -> 854.18447 | E17: ='Productivity Data'!$I$32 -> 61.728449 | F17: ='Wage Data'!$C$11 -> 49.154295 | G17: ='Cost Pool Data'!$K$27 -> 1.3606062 | H17: =(F17*G17)/(D17*E17) -> 0.0012684019 | I17: =C17*H17 -> 4.9389502e-05
B18: Load Postal Hamper | C18: =C15 -> 0.86635635 | D18: ='Conversion Factors'!$I$48 -> 204.2672 | E18: ='Productivity Data'!$I$31 -> 91.071588 | F18: ='Wage Data'!$C$11 -> 49.154295 | G18: ='Cost Pool Data'!$K$27 -> 1.3606062 | H18: =(F18*G18)/(D18*E18) -> 0.0035951115 | I18: =C18*H18 -> 0.0031146477 | J18: =SUM(I9:I18) -> 0.039183341
A19: Destination | B19: Unload Mailer Pallet Box | C19: =C16 -> 0.094705277 | D19: ='Conversion Factors'!$I$20 -> 534.04625 | E19: ='Productivity Data'!$I$26 -> 48.580344 | F19: ='Wage Data'!$C$11 -> 49.154295 | G19: ='Cost Pool Data'!$K$48 -> 1.6214861 | H19: =(F19*G19)/(D19*E19) -> 0.0030720992 | I19: =C19*H19 -> 0.000290944
A20: DU | B20: Unload Mailer Pallet (Pieces) | C20: =C17 -> 0.03893837 | D20: ='Conversion Factors'!$I$21 -> 854.18447 | E20: ='Productivity Data'!$I$26 -> 48.580344 | F20: ='Wage Data'!$C$11 -> 49.154295 | G20: ='Cost Pool Data'!$K$48 -> 1.6214861 | H20: =(F20*G20)/(D20*E20) -> 0.0019207128 | I20: =C20*H20 -> 7.4789426e-05
B21: Unload Postal Hamper | C21: =C18 -> 0.86635635 | D21: ='Conversion Factors'!$I$48 -> 204.2672 | E21: ='Productivity Data'!$I$25 -> 60.332591 | F21: ='Wage Data'!$C$11 -> 49.154295 | G21: ='Cost Pool Data'!$K$48 -> 1.6214861 | H21: =(F21*G21)/(D21*E21) -> 0.0064673159 | I21: =C21*H21 -> 0.0056030002
B22: Incoming Secondary Parcel Sort | C22: =SUM(C19:C21) -> 1 | D22: 1 | E22: ='Productivity Data'!$I$22 -> 307.66823 | F22: ='Wage Data'!$C$11 -> 49.154295 | G22: ='Cost Pool Data'!$K$57 -> 1.4957787 | H22: =(F22*G22)/(D22*E22) -> 0.23897152 | I22: =C22*H22 -> 0.23897152 | J22: =SUM(I19:I22) -> 0.24494026
A24: Sources: | I24: Grand Total | J24: =J18+J22 -> 0.2841236
A25: [1]: Page 7, 8, 9
A26: [2]: Page 7, 10
A27: [3]: Page 5
A28: [4]: Page 6
A29: [5]: Page 3
A30: [6]: ( [4] * [5] ) / ( [2] * [3] )
A31: [7]: [1] * [6]

Sheet M-DDU-5D
A1: USPS MARKETING MAIL MACHINABLE DDU 5-DIGIT PRESORT PARCELS
C4: [1] | D4: [2] | E4: [3] | F4: [4] | G4: [5] | H4: [6] | I4: [7]
F5: Adjusted | H5: Cost | I5: Cost
D6: Conversion | E6: Units | F6: Wage | G6: Piggyback | H6: Per | I6: Per
A7: Facility | B7: Operation | C7: Handlings | D7: Factor | E7: Per Hour | F7: Rate | G7: Factor | H7: Operation | I7: Facility
A9: Destination | B9: Unload Mailer Pallet Box | C9: ='Mailer Arrival Profile'!$C$13 -> 0 | D9: ='Conversion Factors'!$I$20 -> 534.04625 | E9: ='Productivity Data'!$I$26 -> 48.580344 | F9: ='Wage Data'!$C$11 -> 49.154295 | G9: ='Cost Pool Data'!$K$48 -> 1.6214861 | H9: =(F9*G9)/(D9*E9) -> 0.0030720992 | I9: =C9*H9 -> 0
A10: DU | B10: Unload Mailer Pallet (Pieces) | C10: ='Mailer Arrival Profile'!$D$13 -> 0.5384801 | D10: ='Conversion Factors'!$I$21 -> 854.18447 | E10: ='Productivity Data'!$I$26 -> 48.580344 | F10: ='Wage Data'!$C$11 -> 49.154295 | G10: ='Cost Pool Data'!$K$48 -> 1.6214861 | H10: =(F10*G10)/(D10*E10) -> 0.0019207128 | I10: =C10*H10 -> 0.0010342656
B11: Unload Mailer Pallet (Sacks) | C11: ='Mailer Arrival Profile'!$E$13 -> 0 | D11: ='Conversion Factors'!$I$22 -> 550.13579 | E11: ='Productivity Data'!$I$26 -> 48.580344 | F11: ='Wage Data'!$C$11 -> 49.154295 | G11: ='Cost Pool Data'!$K$48 -> 1.6214861 | H11: =(F11*G11)/(D11*E11) -> 0.0029822511 | I11: =C11*H11 -> 0
B12: Unload Mailer APC (Sacks) | C12: ='Mailer Arrival Profile'!$F$13 -> 0.4615199 | D12: ='Conversion Factors'!$I$23 -> 465.37758 | E12: ='Productivity Data'!$I$25 -> 60.332591 | F12: ='Wage Data'!$C$11 -> 49.154295 | G12: ='Cost Pool Data'!$K$48 -> 1.6214861 | H12: =(F12*G12)/(D12*E12) -> 0.0028386853 | I12: =C12*H12 -> 0.0013101098
B13: Incoming Secondary Parcel Sort | C13: =SUM(C9:C12) -> 1 | D13: 1 | E13: ='Productivity Data'!$I$22 -> 307.66823 | F13: ='Wage Data'!$C$11 -> 49.154295 | G13: ='Cost Pool Data'!$K$57 -> 1.4957787 | H13: =(F13*G13)/(D13*E13) -> 0.23897152 | I13: =C13*H13 -> 0.23897152 | J13: =SUM(I9:I13) -> 0.2413159
A15: Sources: | I15: Grand Total | J15: =J13 -> 0.2413159
A16: [1]: Page 7, 8, 9
A17: [2]: Page 7, 10
A18: [3]: Page 5
A19: [4]: Page 6
A20: [5]: Page 3
A21: [6]: ( [4] * [5] ) / ( [2] * [3] )
A22: [7]: [1] * [6]

Sheet IR-NONE-MNDC
A1: USPS MARKETING MAIL IRREGULAR ROLLS NON-DROPSHIP MNDC PRESORT PARCELS
C4: [1] | D4: [2] | E4: [3] | F4: [4] | G4: [5] | H4: [6] | I4: [7]
F5: Adjusted | H5: Cost | I5: Cost
D6: Conversion | E6: Units | F6: Wage | G6: Piggyback | H6: Per | I6: Per
A7: Facility | B7: Operation | C7: Handlings | D7: Factor | E7: Per Hour | F7: Rate | G7: Factor | H7: Operation | I7: Facility
A9: Origin | B9: Unload Mailer Pallet Box | C9: ='Mailer Arrival Profile'!$C$47*'Mailer Arrival Profile'!$C$15 -> 0.16917898 | D9: ='Conversion Factors'!$J$20 -> 602.07697 | E9: ='Productivity Data'!$I$26 -> 48.580344 | F9: ='Wage Data'!$C$11 -> 49.154295 | G9: ='Cost Pool Data'!$K$48 -> 1.6214861 | H9: =(F9*G9)/(D9*E9) -> 0.0027249723 | I9: =C9*H9 -> 0.00046100802
A10: DU | B10: Unload Mailer Pallet (Pieces) | C10: ='Mailer Arrival Profile'!$C$47*'Mailer Arrival Profile'!$D$15 -> 0.23806122 | D10: ='Conversion Factors'!$J$21 -> 962.99674 | E10: ='Productivity Data'!$I$26 -> 48.580344 | F10: ='Wage Data'!$C$11 -> 49.154295 | G10: ='Cost Pool Data'!$K$48 -> 1.6214861 | H10: =(F10*G10)/(D10*E10) -> 0.0017036849 | I10: =C10*H10 -> 0.00040558132
B11: Unload Mailer Pallet (Sacks) | C11: ='Mailer Arrival Profile'!$C$47*'Mailer Arrival Profile'!$E$15 -> 0 | D11: ='Conversion Factors'!$J$22 -> 620.21611 | E11: ='Productivity Data'!$I$26 -> 48.580344 | F11: ='Wage Data'!$C$11 -> 49.154295 | G11: ='Cost Pool Data'!$K$48 -> 1.6214861 | H11: =(F11*G11)/(D11*E11) -> 0.0026452764 | I11: =C11*H11 -> 0
B12: Unload Mailer APC (Sacks) | C12: ='Mailer Arrival Profile'!$C$47*'Mailer Arrival Profile'!$F$15 -> 0.023482584 | D12: ='Conversion Factors'!$J$23 -> 524.66078 | E12: ='Productivity Data'!$I$25 -> 60.332591 | F12: ='Wage Data'!$C$11 -> 49.154295 | G12: ='Cost Pool Data'!$K$48 -> 1.6214861 | H12: =(F12*G12)/(D12*E12) -> 0.0025179326 | I12: =C12*H12 -> 5.9127566e-05
B13: Load Mailer Pallet Box | C13: =C9 -> 0.16917898 | D13: ='Conversion Factors'!$J$20 -> 602.07697 | E13: ='Productivity Data'!$I$24 -> 43.137464 | F13: ='Wage Data'!$C$11 -> 49.154295 | G13: ='Cost Pool Data'!$K$48 -> 1.6214861 | H13: =(F13*G13)/(D13*E13) -> 0.0030687963 | I13: =C13*H13 -> 0.00051917582
B14: Load Mailer Pallet (Pieces) | C14: =C10 -> 0.23806122 | D14: ='Conversion Factors'!$J$21 -> 962.99674 | E14: ='Productivity Data'!$I$24 -> 43.137464 | F14: ='Wage Data'!$C$11 -> 49.154295 | G14: ='Cost Pool Data'!$K$48 -> 1.6214861 | H14: =(F14*G14)/(D14*E14) -> 0.0019186478 | I14: =C14*H14 -> 0.00045675564
B15: Load Mailer Pallet (Sacks) | C15: =C11 -> 0 | D15: ='Conversion Factors'!$J$22 -> 620.21611 | E15: ='Productivity Data'!$I$24 -> 43.137464 | F15: ='Wage Data'!$C$11 -> 49.154295 | G15: ='Cost Pool Data'!$K$48 -> 1.6214861 | H15: =(F15*G15)/(D15*E15) -> 0.0029790448 | I15: =C15*H15 -> 0
B16: Load Mailer APC (Sacks) | C16: =C12 -> 0.023482584 | D16: ='Conversion Factors'!$J$23 -> 524.66078 | E16: ='Productivity Data'!$I$23 -> 68.564044 | F16: ='Wage Data'!$C$11 -> 49.154295 | G16: ='Cost Pool Data'!$K$48 -> 1.6214861 | H16: =(F16*G16)/(D16*E16) -> 0.0022156424 | I16: =C16*H16 -> 5.2029009e-05 | J16: =SUM(I9:I16) -> 0.0019536774
A17: Origin | B17: Unload Mailer Pallet Box | C17: ='Mailer Arrival Profile'!$C$48*'Mailer Arrival Profile'!$C$15+C13 -> 0.25390335 | D17: ='Conversion Factors'!$J$20 -> 602.07697 | E17: ='Productivity Data'!$I$28 -> 58.156985 | F17: ='Wage Data'!$C$11 -> 49.154295 | G17: ='Cost Pool Data'!$K$27 -> 1.3606062 | H17: =(F17*G17)/(D17*E17) -> 0.0019100292 | I17: =C17*H17 -> 0.00048496282
A18: P&DC / P&DF | B18: Unload Mailer Pallet (Pieces) | C18: ='Mailer Arrival Profile'!$C$48*'Mailer Arrival Profile'!$D$15+C14 -> 0.35728164 | D18: ='Conversion Factors'!$J$21 -> 962.99674 | E18: ='Productivity Data'!$I$28 -> 58.156985 | F18: ='Wage Data'!$C$11 -> 49.154295 | G18: ='Cost Pool Data'!$K$27 -> 1.3606062 | H18: =(F18*G18)/(D18*E18) -> 0.0011941729 | I18: =C18*H18 -> 0.00042665605
B19: Unload Mailer Pallet (Sacks) | C19: ='Mailer Arrival Profile'!$C$48*'Mailer Arrival Profile'!$E$15+C15 -> 0 | D19: ='Conversion Factors'!$J$22 -> 620.21611 | E19: ='Productivity Data'!$I$28 -> 58.156985 | F19: ='Wage Data'!$C$11 -> 49.154295 | G19: ='Cost Pool Data'!$K$27 -> 1.3606062 | H19: =(F19*G19)/(D19*E19) -> 0.0018541676 | I19: =C19*H19 -> 0
B20: Unload Mailer APC (Sacks) | C20: ='Mailer Arrival Profile'!$C$48*'Mailer Arrival Profile'!$F$15+C16 -> 0.035242599 | D20: ='Conversion Factors'!$J$23 -> 524.66078 | E20: ='Productivity Data'!$I$27 -> 81.873572 | F20: ='Wage Data'!$C$11 -> 49.154295 | G20: ='Cost Pool Data'!$K$27 -> 1.3606062 | H20: =(F20*G20)/(D20*E20) -> 0.0015569389 | I20: =C20*H20 -> 5.4870574e-05
B21: Crossdock Mailer Pallet Box | C21: =C17 -> 0.25390335 | D21: ='Conversion Factors'!$J$20 -> 602.07697 | E21: ='Productivity Data'!$I$30 -> 39.899251 | F21: ='Wage Data'!$C$11 -> 49.154295 | G21: ='Cost Pool Data'!$K$27 -> 1.3606062 | H21: =(F21*G21)/(D21*E21) -> 0.0027840508 | I21: =C21*H21 -> 0.00070687982
B22: Crossdock Mailer Pallet (Pieces) | C22: =C18 -> 0.35728164 | D22: ='Conversion Factors'!$J$21 -> 962.99674 | E22: ='Productivity Data'!$I$30 -> 39.899251 | F22: ='Wage Data'!$C$11 -> 49.154295 | G22: ='Cost Pool Data'!$K$27 -> 1.3606062 | H22: =(F22*G22)/(D22*E22) -> 0.0017406215 | I22: =C22*H22 -> 0.00062189211
B23: Crossdock Mailer Pallet (Sacks) | C23: =C19 -> 0 | D23: ='Conversion Factors'!$J$22 -> 620.21611 | E23: ='Productivity Data'!$I$30 -> 39.899251 | F23: ='Wage Data'!$C$11 -> 49.154295 | G23: ='Cost Pool Data'!$K$27 -> 1.3606062 | H23: =(F23*G23)/(D23*E23) -> 0.0027026271 | I23: =C23*H23 -> 0
B24: Crossdock Mailer APC (Sacks) | C24: =C20 -> 0.035242599 | D24: ='Conversion Factors'!$J$23 -> 524.66078 | E24: ='Productivity Data'!$I$29 -> 50.764395 | F24: ='Wage Data'!$C$11 -> 49.154295 | G24: ='Cost Pool Data'!$K$27 -> 1.3606062 | H24: =(F24*G24)/(D24*E24) -> 0.0025110543 | I24: =C24*H24 -> 8.8496079e-05
B25: Load Mailer Pallet Box | C25: =C21 -> 0.25390335 | D25: ='Conversion Factors'!$J$20 -> 602.07697 | E25: ='Productivity Data'!$I$32 -> 61.728449 | F25: ='Wage Data'!$C$11 -> 49.154295 | G25: ='Cost Pool Data'!$K$27 -> 1.3606062 | H25: =(F25*G25)/(D25*E25) -> 0.0017995194 | I25: =C25*H25 -> 0.000456904
B26: Load Mailer Pallet (Pieces) | C26: =C22 -> 0.35728164 | D26: ='Conversion Factors'!$J$21 -> 962.99674 | E26: ='Productivity Data'!$I$32 -> 61.728449 | F26: ='Wage Data'!$C$11 -> 49.154295 | G26: ='Cost Pool Data'!$K$27 -> 1.3606062 | H26: =(F26*G26)/(D26*E26) -> 0.0011250808 | I26: =C26*H26 -> 0.00040197073
B27: Load Mailer Pallet (Sacks) | C27: =C23 -> 0 | D27: ='Conversion Factors'!$J$22 -> 620.21611 | E27: ='Productivity Data'!$I$32 -> 61.728449 | F27: ='Wage Data'!$C$11 -> 49.154295 | G27: ='Cost Pool Data'!$K$27 -> 1.3606062 | H27: =(F27*G27)/(D27*E27) -> 0.0017468898 | I27: =C27*H27 -> 0
B28: Load Mailer APC (Sacks) | C28: =C24 -> 0.035242599 | D28: ='Conversion Factors'!$J$23 -> 524.66078 | E28: ='Productivity Data'!$I$31 -> 91.071588 | F28: ='Wage Data'!$C$11 -> 49.154295 | G28: ='Cost Pool Data'!$K$27 -> 1.3606062 | H28: =(F28*G28)/(D28*E28) -> 0.0013996917 | I28: =C28*H28 -> 4.9328775e-05 | J28: =SUM(I17:I28) -> 0.003291961
A29: Origin | B29: Unload Mailer Pallet Box | C29: ='Mailer Arrival Profile'!$C$49*'Mailer Arrival Profile'!$C$15+C25 -> 0.39277926 | D29: ='Conversion Factors'!$J$20 -> 602.07697 | E29: ='Productivity Data'!$I$38 -> 46.475052 | F29: ='Wage Data'!$C$11 -> 49.154295 | G29: ='Cost Pool Data'!$K$43 -> 1.3860239 | H29: =(F29*G29)/(D29*E29) -> 0.0024347832 | I29: =C29*H29 -> 0.00095633232
A30: NDC | B30: Unload Mailer Pallet (Pieces) | C30: ='Mailer Arrival Profile'!$C$49*'Mailer Arrival Profile'!$D$15+C26 -> 0.55270172 | D30: ='Conversion Factors'!$J$21 -> 962.99674 | E30: ='Productivity Data'!$I$38 -> 46.475052 | F30: ='Wage Data'!$C$11 -> 49.154295 | G30: ='Cost Pool Data'!$K$43 -> 1.3860239 | H30: =(F30*G30)/(D30*E30) -> 0.0015222553 | I30: =C30*H30 -> 0.00084135311
B31: Unload Mailer Pallet (Sacks) | C31: ='Mailer Arrival Profile'!$C$49*'Mailer Arrival Profile'!$E$15+C27 -> 0 | D31: ='Conversion Factors'!$J$22 -> 620.21611 | E31: ='Productivity Data'!$I$38 -> 46.475052 | F31: ='Wage Data'!$C$11 -> 49.154295 | G31: ='Cost Pool Data'!$K$43 -> 1.3860239 | H31: =(F31*G31)/(D31*E31) -> 0.0023635743 | I31: =C31*H31 -> 0
B32: Unload Mailer APC (Sacks) | C32: ='Mailer Arrival Profile'!$C$49*'Mailer Arrival Profile'!$F$15+C28 -> 0.054519021 | D32: ='Conversion Factors'!$J$23 -> 524.66078 | E32: ='Productivity Data'!$I$37 -> 55.996737 | F32: ='Wage Data'!$C$11 -> 49.154295 | G32: ='Cost Pool Data'!$K$43 -> 1.3860239 | H32: =(F32*G32)/(D32*E32) -> 0.0023189472 | I32: =C32*H32 -> 0.00012642673
B33: IPP Manual Sort | C33: =SUM(C29:C32) -> 1 | D33: 1 | E33: ='Productivity Data'!$I$21 -> 402.79881 | F33: ='Wage Data'!$C$11 -> 49.154295 | G33: ='Cost Pool Data'!$K$41 -> 1.4774317 | H33: =(F33*G33)/(D33*E33) -> 0.18029376 | I33: =C33*H33 -> 0.18029376
B34: Induct OTR (Non-Local IPP Sacks) | C34: =C33*'Other Inputs'!$B$48 -> 0.39751958 | D34: ='Conversion Factors'!$J$45 -> 752.97177 | E34: ='Productivity Data'!$I$40 -> 23.065925 | F34: ='Wage Data'!$C$11 -> 49.154295 | G34: ='Cost Pool Data'!$K$42 -> 1.5176144 | H34: =(F34*G34)/(D34*E34) -> 0.0042951004 | I34: =C34*H34 -> 0.0017073865
B35: Sack Sorting Machine | C35: =C34*(1+'Other Inputs'!$B$9) -> 0.41436906 | D35: ='Conversion Factors'!$J$49 -> 84.485141 | E35: ='Productivity Data'!$I$19 -> 3068.1109 | F35: ='Wage Data'!$C$11 -> 49.154295 | G35: ='Cost Pool Data'!$K$46 -> 1.6196175 | H35: =(F35*G35)/(D35*E35) -> 0.0003071302 | I35: =C35*H35 -> 0.00012726525
B36: Load Postal Hamper | C36: =C33*(1-'Other Inputs'!$B$48) -> 0.60248042 | D36: ='Conversion Factors'!$J$48 -> 230.28825 | E36: ='Productivity Data'!$I$44 -> 70.608822 | F36: ='Wage Data'!$C$11 -> 49.154295 | G36: ='Cost Pool Data'!$K$43 -> 1.3860239 | H36: =(F36*G36)/(D36*E36) -> 0.0041898786 | I36: =C36*H36 -> 0.0025243198
B37: Load Postal Pak | C37: =C34 -> 0.39751958 | D37: ='Conversion Factors'!$J$47 -> 1093.3867 | E37: ='Productivity Data'!$I$46 -> 20.811195 | F37: ='Wage Data'!$C$11 -> 49.154295 | G37: ='Cost Pool Data'!$K$43 -> 1.3860239 | H37: =(F37*G37)/(D37*E37) -> 0.0029940661 | I37: =C37*H37 -> 0.0011901999 | J37: =SUM(I29:I37) -> 0.18776704
A38: Destination | B38: Unload Postal Pak | C38: =C37 -> 0.39751958 | D38: ='Conversion Factors'!$J$47 -> 1093.3867 | E38: ='Productivity Data'!$I$39 -> 53.14645 | F38: ='Wage Data'!$C$11 -> 49.154295 | G38: ='Cost Pool Data'!$K$43 -> 1.3860239 | H38: =(F38*G38)/(D38*E38) -> 0.0011724225 | I38: =C38*H38 -> 0.00046606092
A39: NDC | B39: Induct Postal Pak | C39: =C38 -> 0.39751958 | D39: ='Conversion Factors'!$J$47 -> 1093.3867 | E39: ='Productivity Data'!$I$42 -> 16.646694 | F39: ='Wage Data'!$C$11 -> 49.154295 | G39: ='Cost Pool Data'!$K$42 -> 1.5176144 | H39: =(F39*G39)/(D39*E39) -> 0.0040984639 | I39: =C39*H39 -> 0.0016292197
B40: Sack Sorting Machine | C40: =C39*(1+'Other Inputs'!$B$9) -> 0.41436906 | D40: ='Conversion Factors'!$J$49 -> 84.485141 | E40: ='Productivity Data'!$I$19 -> 3068.1109 | F40: ='Wage Data'!$C$11 -> 49.154295 | G40: ='Cost Pool Data'!$K$46 -> 1.6196175 | H40: =(F40*G40)/(D40*E40) -> 0.0003071302 | I40: =C40*H40 -> 0.00012726525
B41: IPP Manual Sort | C41: =C39 -> 0.39751958 | D41: 1 | E41: ='Productivity Data'!$I$21 -> 402.79881 | F41: ='Wage Data'!$C$11 -> 49.154295 | G41: ='Cost Pool Data'!$K$41 -> 1.4774317 | H41: =(F41*G41)/(D41*E41) -> 0.18029376 | I41: =C41*H41 -> 0.071670299
B42: Load Postal Hamper | C42: =C41 -> 0.39751958 | D42: ='Conversion Factors'!$J$48 -> 230.28825 | E42: ='Productivity Data'!$I$44 -> 70.608822 | F42: ='Wage Data'!$C$11 -> 49.154295 | G42: ='Cost Pool Data'!$K$43 -> 1.3860239 | H42: =(F42*G42)/(D42*E42) -> 0.0041898786 | I42: =C42*H42 -> 0.0016655588 | J42: =SUM(I38:I42) -> 0.075558403
A43: Destination | B43: Unload Postal Hamper | C43: =C36+C42 -> 1 | D43: ='Conversion Factors'!$J$48 -> 230.28825 | E43: ='Productivity Data'!$I$27 -> 81.873572 | F43: ='Wage Data'!$C$11 -> 49.154295 | G43: ='Cost Pool Data'!$K$27 -> 1.3606062 | H43: =(F43*G43)/(D43*E43) -> 0.0035471405 | I43: =C43*H43 -> 0.0035471405
A44: P&DC / P&DF | B44: IPP Incoming Sort | C44: =C43 -> 1 | D44: 1 | E44: ='Productivity Data'!$I$16 -> 47.99469 | F44: ='Wage Data'!$C$11 -> 49.154295 | G44: ='Cost Pool Data'!$K$16 -> 1.3208756 | H44: =(F44*G44)/(D44*E44) -> 1.3527894 | I44: =C44*H44 -> 1.3527894
B45: Load Postal Hamper | C45: =C44 -> 1 | D45: ='Conversion Factors'!$J$48 -> 230.28825 | E45: ='Productivity Data'!$I$31 -> 91.071588 | F45: ='Wage Data'!$C$11 -> 49.154295 | G45: ='Cost Pool Data'!$K$27 -> 1.3606062 | H45: =(F45*G45)/(D45*E45) -> 0.0031888877 | I45: =C45*H45 -> 0.0031888877 | J45: =SUM(I43:I45) -> 1.3595254
A46: Destination | B46: Unload Postal Hamper | C46: =C45 -> 1 | D46: ='Conversion Factors'!$J$48 -> 230.28825 | E46: ='Productivity Data'!$I$25 -> 60.332591 | F46: ='Wage Data'!$C$11 -> 49.154295 | G46: ='Cost Pool Data'!$K$48 -> 1.6214861 | H46: =(F46*G46)/(D46*E46) -> 0.0057365519 | I46: =C46*H46 -> 0.0057365519
A47: DU | B47: Incoming Secondary Parcel Sort | C47: =C46 -> 1 | D47: 1 | E47: ='Productivity Data'!$I$22 -> 307.66823 | F47: ='Wage Data'!$C$11 -> 49.154295 | G47: ='Cost Pool Data'!$K$57 -> 1.4957787 | H47: =(F47*G47)/(D47*E47) -> 0.23897152 | I47: =C47*H47 -> 0.23897152 | J47: =SUM(I46:I47) -> 0.24470807
A49: Sources: | I49: Grand Total | J49: =J16+J28+J37+J42+J45+J47 -> 1.8728046
A50: [1]: Page 7, 8, 9
A51: [2]: Page 7, 10
A52: [3]: Page 5
A53: [4]: Page 6
A54: [5]: Page 3
A55: [6]: ( [4] * [5] ) / ( [2] * [3] )
A56: [7]: [1] * [6]

Sheet IR-NONE-NDC
A1: USPS MARKETING MAIL IRREGULAR ROLLS NON-DROPSHIP NDC PRESORT PARCELS
C4: [1] | D4: [2] | E4: [3] | F4: [4] | G4: [5] | H4: [6] | I4: [7]
F5: Adjusted | H5: Cost | I5: Cost
D6: Conversion | E6: Units | F6: Wage | G6: Piggyback | H6: Per | I6: Per
A7: Facility | B7: Operation | C7: Handlings | D7: Factor | E7: Per Hour | F7: Rate | G7: Factor | H7: Operation | I7: Facility
A9: Origin | B9: Unload Mailer Pallet Box | C9: ='Mailer Arrival Profile'!$C$47*'Mailer Arrival Profile'!$C$16 -> 0.069660825 | D9: ='Conversion Factors'!$J$20 -> 602.07697 | E9: ='Productivity Data'!$I$26 -> 48.580344 | F9: ='Wage Data'!$C$11 -> 49.154295 | G9: ='Cost Pool Data'!$K$48 -> 1.6214861 | H9: =(F9*G9)/(D9*E9) -> 0.0027249723 | I9: =C9*H9 -> 0.00018982382
A10: DU | B10: Unload Mailer Pallet (Pieces) | C10: ='Mailer Arrival Profile'!$C$47*'Mailer Arrival Profile'!$D$16 -> 0.29610462 | D10: ='Conversion Factors'!$J$21 -> 962.99674 | E10: ='Productivity Data'!$I$26 -> 48.580344 | F10: ='Wage Data'!$C$11 -> 49.154295 | G10: ='Cost Pool Data'!$K$48 -> 1.6214861 | H10: =(F10*G10)/(D10*E10) -> 0.0017036849 | I10: =C10*H10 -> 0.00050446898
B11: Unload Mailer Pallet (Sacks) | C11: ='Mailer Arrival Profile'!$C$47*'Mailer Arrival Profile'!$E$16 -> 0.041655083 | D11: ='Conversion Factors'!$J$22 -> 620.21611 | E11: ='Productivity Data'!$I$26 -> 48.580344 | F11: ='Wage Data'!$C$11 -> 49.154295 | G11: ='Cost Pool Data'!$K$48 -> 1.6214861 | H11: =(F11*G11)/(D11*E11) -> 0.0026452764 | I11: =C11*H11 -> 0.00011018921
B12: Unload Mailer APC (Sacks) | C12: ='Mailer Arrival Profile'!$C$47*'Mailer Arrival Profile'!$F$16 -> 0.023302253 | D12: ='Conversion Factors'!$J$23 -> 524.66078 | E12: ='Productivity Data'!$I$25 -> 60.332591 | F12: ='Wage Data'!$C$11 -> 49.154295 | G12: ='Cost Pool Data'!$K$48 -> 1.6214861 | H12: =(F12*G12)/(D12*E12) -> 0.0025179326 | I12: =C12*H12 -> 5.8673504e-05
B13: Load Mailer Pallet Box | C13: =C9 -> 0.069660825 | D13: ='Conversion Factors'!$J$20 -> 602.07697 | E13: ='Productivity Data'!$I$24 -> 43.137464 | F13: ='Wage Data'!$C$11 -> 49.154295 | G13: ='Cost Pool Data'!$K$48 -> 1.6214861 | H13: =(F13*G13)/(D13*E13) -> 0.0030687963 | I13: =C13*H13 -> 0.00021377489
B14: Load Mailer Pallet (Pieces) | C14: =C10 -> 0.29610462 | D14: ='Conversion Factors'!$J$21 -> 962.99674 | E14: ='Productivity Data'!$I$24 -> 43.137464 | F14: ='Wage Data'!$C$11 -> 49.154295 | G14: ='Cost Pool Data'!$K$48 -> 1.6214861 | H14: =(F14*G14)/(D14*E14) -> 0.0019186478 | I14: =C14*H14 -> 0.00056812048
B15: Load Mailer Pallet (Sacks) | C15: =C11 -> 0.041655083 | D15: ='Conversion Factors'!$J$22 -> 620.21611 | E15: ='Productivity Data'!$I$24 -> 43.137464 | F15: ='Wage Data'!$C$11 -> 49.154295 | G15: ='Cost Pool Data'!$K$48 -> 1.6214861 | H15: =(F15*G15)/(D15*E15) -> 0.0029790448 | I15: =C15*H15 -> 0.00012409236
B16: Load Mailer APC (Sacks) | C16: =C12 -> 0.023302253 | D16: ='Conversion Factors'!$J$23 -> 524.66078 | E16: ='Productivity Data'!$I$23 -> 68.564044 | F16: ='Wage Data'!$C$11 -> 49.154295 | G16: ='Cost Pool Data'!$K$48 -> 1.6214861 | H16: =(F16*G16)/(D16*E16) -> 0.0022156424 | I16: =C16*H16 -> 5.1629459e-05 | J16: =SUM(I9:I16) -> 0.0018207727
A17: Origin | B17: Unload Mailer Pallet Box | C17: ='Mailer Arrival Profile'!$C$48*'Mailer Arrival Profile'!$C$16+C13 -> 0.10454678 | D17: ='Conversion Factors'!$J$20 -> 602.07697 | E17: ='Productivity Data'!$I$28 -> 58.156985 | F17: ='Wage Data'!$C$11 -> 49.154295 | G17: ='Cost Pool Data'!$K$27 -> 1.3606062 | H17: =(F17*G17)/(D17*E17) -> 0.0019100292 | I17: =C17*H17 -> 0.0001996874
A18: P&DC / P&DF | B18: Unload Mailer Pallet (Pieces) | C18: ='Mailer Arrival Profile'!$C$48*'Mailer Arrival Profile'!$D$16+C14 -> 0.44439301 | D18: ='Conversion Factors'!$J$21 -> 962.99674 | E18: ='Productivity Data'!$I$28 -> 58.156985 | F18: ='Wage Data'!$C$11 -> 49.154295 | G18: ='Cost Pool Data'!$K$27 -> 1.3606062 | H18: =(F18*G18)/(D18*E18) -> 0.0011941729 | I18: =C18*H18 -> 0.00053068209
B19: Unload Mailer Pallet (Sacks) | C19: ='Mailer Arrival Profile'!$C$48*'Mailer Arrival Profile'!$E$16+C15 -> 0.062515836 | D19: ='Conversion Factors'!$J$22 -> 620.21611 | E19: ='Productivity Data'!$I$28 -> 58.156985 | F19: ='Wage Data'!$C$11 -> 49.154295 | G19: ='Cost Pool Data'!$K$27 -> 1.3606062 | H19: =(F19*G19)/(D19*E19) -> 0.0018541676 | I19: =C19*H19 -> 0.00011591484
B20: Unload Mailer APC (Sacks) | C20: ='Mailer Arrival Profile'!$C$48*'Mailer Arrival Profile'!$F$16+C16 -> 0.034971958 | D20: ='Conversion Factors'!$J$23 -> 524.66078 | E20: ='Productivity Data'!$I$27 -> 81.873572 | F20: ='Wage Data'!$C$11 -> 49.154295 | G20: ='Cost Pool Data'!$K$27 -> 1.3606062 | H20: =(F20*G20)/(D20*E20) -> 0.0015569389 | I20: =C20*H20 -> 5.4449203e-05
B21: Crossdock Mailer Pallet Box | C21: =C17 -> 0.10454678 | D21: ='Conversion Factors'!$J$20 -> 602.07697 | E21: ='Productivity Data'!$I$30 -> 39.899251 | F21: ='Wage Data'!$C$11 -> 49.154295 | G21: ='Cost Pool Data'!$K$27 -> 1.3606062 | H21: =(F21*G21)/(D21*E21) -> 0.0027840508 | I21: =C21*H21 -> 0.00029106354
B22: Crossdock Mailer Pallet (Pieces) | C22: =C18 -> 0.44439301 | D22: ='Conversion Factors'!$J$21 -> 962.99674 | E22: ='Productivity Data'!$I$30 -> 39.899251 | F22: ='Wage Data'!$C$11 -> 49.154295 | G22: ='Cost Pool Data'!$K$27 -> 1.3606062 | H22: =(F22*G22)/(D22*E22) -> 0.0017406215 | I22: =C22*H22 -> 0.00077352005
B23: Crossdock Mailer Pallet (Sacks) | C23: =C19 -> 0.062515836 | D23: ='Conversion Factors'!$J$22 -> 620.21611 | E23: ='Productivity Data'!$I$30 -> 39.899251 | F23: ='Wage Data'!$C$11 -> 49.154295 | G23: ='Cost Pool Data'!$K$27 -> 1.3606062 | H23: =(F23*G23)/(D23*E23) -> 0.0027026271 | I23: =C23*H23 -> 0.00016895699
B24: Crossdock Mailer APC (Sacks) | C24: =C20 -> 0.034971958 | D24: ='Conversion Factors'!$J$23 -> 524.66078 | E24: ='Productivity Data'!$I$29 -> 50.764395 | F24: ='Wage Data'!$C$11 -> 49.154295 | G24: ='Cost Pool Data'!$K$27 -> 1.3606062 | H24: =(F24*G24)/(D24*E24) -> 0.0025110543 | I24: =C24*H24 -> 8.7816485e-05
B25: Load Mailer Pallet Box | C25: =C21 -> 0.10454678 | D25: ='Conversion Factors'!$J$20 -> 602.07697 | E25: ='Productivity Data'!$I$32 -> 61.728449 | F25: ='Wage Data'!$C$11 -> 49.154295 | G25: ='Cost Pool Data'!$K$27 -> 1.3606062 | H25: =(F25*G25)/(D25*E25) -> 0.0017995194 | I25: =C25*H25 -> 0.00018813396
B26: Load Mailer Pallet (Pieces) | C26: =C22 -> 0.44439301 | D26: ='Conversion Factors'!$J$21 -> 962.99674 | E26: ='Productivity Data'!$I$32 -> 61.728449 | F26: ='Wage Data'!$C$11 -> 49.154295 | G26: ='Cost Pool Data'!$K$27 -> 1.3606062 | H26: =(F26*G26)/(D26*E26) -> 0.0011250808 | I26: =C26*H26 -> 0.00049997807
B27: Load Mailer Pallet (Sacks) | C27: =C23 -> 0.062515836 | D27: ='Conversion Factors'!$J$22 -> 620.21611 | E27: ='Productivity Data'!$I$32 -> 61.728449 | F27: ='Wage Data'!$C$11 -> 49.154295 | G27: ='Cost Pool Data'!$K$27 -> 1.3606062 | H27: =(F27*G27)/(D27*E27) -> 0.0017468898 | I27: =C27*H27 -> 0.00010920828
B28: Load Mailer APC (Sacks) | C28: =C24 -> 0.034971958 | D28: ='Conversion Factors'!$J$23 -> 524.66078 | E28: ='Productivity Data'!$I$31 -> 91.071588 | F28: ='Wage Data'!$C$11 -> 49.154295 | G28: ='Cost Pool Data'!$K$27 -> 1.3606062 | H28: =(F28*G28)/(D28*E28) -> 0.0013996917 | I28: =C28*H28 -> 4.8949962e-05 | J28: =SUM(I17:I28) -> 0.0030683609
A29: Origin | B29: Unload Mailer Pallet Box | C29: ='Mailer Arrival Profile'!$C$49*'Mailer Arrival Profile'!$C$16+C25 -> 0.16173007 | D29: ='Conversion Factors'!$J$20 -> 602.07697 | E29: ='Productivity Data'!$I$38 -> 46.475052 | F29: ='Wage Data'!$C$11 -> 49.154295 | G29: ='Cost Pool Data'!$K$43 -> 1.3860239 | H29: =(F29*G29)/(D29*E29) -> 0.0024347832 | I29: =C29*H29 -> 0.00039377765
A30: NDC | B30: Unload Mailer Pallet (Pieces) | C30: ='Mailer Arrival Profile'!$C$49*'Mailer Arrival Profile'!$D$16+C26 -> 0.68745985 | D30: ='Conversion Factors'!$J$21 -> 962.99674 | E30: ='Productivity Data'!$I$38 -> 46.475052 | F30: ='Wage Data'!$C$11 -> 49.154295 | G30: ='Cost Pool Data'!$K$43 -> 1.3860239 | H30: =(F30*G30)/(D30*E30) -> 0.0015222553 | I30: =C30*H30 -> 0.0010464894
B31: Unload Mailer Pallet (Sacks) | C31: ='Mailer Arrival Profile'!$C$49*'Mailer Arrival Profile'!$E$16+C27 -> 0.096709728 | D31: ='Conversion Factors'!$J$22 -> 620.21611 | E31: ='Productivity Data'!$I$38 -> 46.475052 | F31: ='Wage Data'!$C$11 -> 49.154295 | G31: ='Cost Pool Data'!$K$43 -> 1.3860239 | H31: =(F31*G31)/(D31*E31) -> 0.0023635743 | I31: =C31*H31 -> 0.00022858063
B32: Unload Mailer APC (Sacks) | C32: ='Mailer Arrival Profile'!$C$49*'Mailer Arrival Profile'!$F$16+C28 -> 0.05410035 | D32: ='Conversion Factors'!$J$23 -> 524.66078 | E32: ='Productivity Data'!$I$37 -> 55.996737 | F32: ='Wage Data'!$C$11 -> 49.154295 | G32: ='Cost Pool Data'!$K$43 -> 1.3860239 | H32: =(F32*G32)/(D32*E32) -> 0.0023189472 | I32: =C32*H32 -> 0.00012545586
B33: Load Mailer Pallet Box | C33: =C29 -> 0.16173007 | D33: ='Conversion Factors'!$J$20 -> 602.07697 | E33: ='Productivity Data'!$I$45 -> 55.582256 | F33: ='Wage Data'!$C$11 -> 49.154295 | G33: ='Cost Pool Data'!$K$43 -> 1.3860239 | H33: =(F33*G33)/(D33*E33) -> 0.0020358417 | I33: =C33*H33 -> 0.00032925682
B34: Load Mailer Pallet (Pieces) | C34: =C30 -> 0.68745985 | D34: ='Conversion Factors'!$J$21 -> 962.99674 | E34: ='Productivity Data'!$I$45 -> 55.582256 | F34: ='Wage Data'!$C$11 -> 49.154295 | G34: ='Cost Pool Data'!$K$43 -> 1.3860239 | H34: =(F34*G34)/(D34*E34) -> 0.0012728323 | I34: =C34*H34 -> 0.00087502113
B35: Load Mailer Pallet (Sacks) | C35: =C31 -> 0.096709728 | D35: ='Conversion Factors'!$J$22 -> 620.21611 | E35: ='Productivity Data'!$I$45 -> 55.582256 | F35: ='Wage Data'!$C$11 -> 49.154295 | G35: ='Cost Pool Data'!$K$43 -> 1.3860239 | H35: =(F35*G35)/(D35*E35) -> 0.0019763005 | I35: =C35*H35 -> 0.00019112748
B36: Load Mailer APC (Sacks) | C36: =C32 -> 0.05410035 | D36: ='Conversion Factors'!$J$23 -> 524.66078 | E36: ='Productivity Data'!$I$44 -> 70.608822 | F36: ='Wage Data'!$C$11 -> 49.154295 | G36: ='Cost Pool Data'!$K$43 -> 1.3860239 | H36: =(F36*G36)/(D36*E36) -> 0.0018390546 | I36: =C36*H36 -> 9.9493496e-05 | J36: =SUM(I29:I36) -> 0.0032892024
A37: Destination | B37: Unload Mailer Pallet Box | C37: =C33 -> 0.16173007 | D37: ='Conversion Factors'!$J$20 -> 602.07697 | E37: ='Productivity Data'!$I$38 -> 46.475052 | F37: ='Wage Data'!$C$11 -> 49.154295 | G37: ='Cost Pool Data'!$K$43 -> 1.3860239 | H37: =(F37*G37)/(D37*E37) -> 0.0024347832 | I37: =C37*H37 -> 0.00039377765
A38: NDC | B38: Unload Mailer Pallet (Pieces) | C38: =C34 -> 0.68745985 | D38: ='Conversion Factors'!$J$21 -> 962.99674 | E38: ='Productivity Data'!$I$38 -> 46.475052 | F38: ='Wage Data'!$C$11 -> 49.154295 | G38: ='Cost Pool Data'!$K$43 -> 1.3860239 | H38: =(F38*G38)/(D38*E38) -> 0.0015222553 | I38: =C38*H38 -> 0.0010464894
B39: Unload Mailer Pallet (Sacks) | C39: =C35 -> 0.096709728 | D39: ='Conversion Factors'!$J$22 -> 620.21611 | E39: ='Productivity Data'!$I$38 -> 46.475052 | F39: ='Wage Data'!$C$11 -> 49.154295 | G39: ='Cost Pool Data'!$K$43 -> 1.3860239 | H39: =(F39*G39)/(D39*E39) -> 0.0023635743 | I39: =C39*H39 -> 0.00022858063
B40: Unload Mailer APC (Sacks) | C40: =C36 -> 0.05410035 | D40: ='Conversion Factors'!$J$23 -> 524.66078 | E40: ='Productivity Data'!$I$37 -> 55.996737 | F40: ='Wage Data'!$C$11 -> 49.154295 | G40: ='Cost Pool Data'!$K$43 -> 1.3860239 | H40: =(F40*G40)/(D40*E40) -> 0.0023189472 | I40: =C40*H40 -> 0.00012545586
B41: IPP Manual Sort | C41: =SUM(C37:C40) -> 1 | D41: 1 | E41: ='Productivity Data'!$I$21 -> 402.79881 | F41: ='Wage Data'!$C$11 -> 49.154295 | G41: ='Cost Pool Data'!$K$41 -> 1.4774317 | H41: =(F41*G41)/(D41*E41) -> 0.18029376 | I41: =C41*H41 -> 0.18029376
B42: Load Postal Hamper | C42: =C41 -> 1 | D42: ='Conversion Factors'!$J$48 -> 230.28825 | E42: ='Productivity Data'!$I$44 -> 70.608822 | F42: ='Wage Data'!$C$11 -> 49.154295 | G42: ='Cost Pool Data'!$K$43 -> 1.3860239 | H42: =(F42*G42)/(D42*E42) -> 0.0041898786 | I42: =C42*H42 -> 0.0041898786 | J42: =SUM(I37:I42) -> 0.18627794
A43: Destination | B43: Unload Postal Hamper | C43: =C42 -> 1 | D43: ='Conversion Factors'!$J$48 -> 230.28825 | E43: ='Productivity Data'!$I$27 -> 81.873572 | F43: ='Wage Data'!$C$11 -> 49.154295 | G43: ='Cost Pool Data'!$K$27 -> 1.3606062 | H43: =(F43*G43)/(D43*E43) -> 0.0035471405 | I43: =C43*H43 -> 0.0035471405
A44: P&DC / P&DF | B44: IPP Incoming Sort | C44: =C43 -> 1 | D44: 1 | E44: ='Productivity Data'!$I$16 -> 47.99469 | F44: ='Wage Data'!$C$11 -> 49.154295 | G44: ='Cost Pool Data'!$K$16 -> 1.3208756 | H44: =(F44*G44)/(D44*E44) -> 1.3527894 | I44: =C44*H44 -> 1.3527894
B45: Load Postal Hamper | C45: =C44 -> 1 | D45: ='Conversion Factors'!$J$48 -> 230.28825 | E45: ='Productivity Data'!$I$31 -> 91.071588 | F45: ='Wage Data'!$C$11 -> 49.154295 | G45: ='Cost Pool Data'!$K$27 -> 1.3606062 | H45: =(F45*G45)/(D45*E45) -> 0.0031888877 | I45: =C45*H45 -> 0.0031888877 | J45: =SUM(I43:I45) -> 1.3595254
A46: Destination | B46: Unload Postal Hamper | C46: =C45 -> 1 | D46: ='Conversion Factors'!$J$48 -> 230.28825 | E46: ='Productivity Data'!$I$25 -> 60.332591 | F46: ='Wage Data'!$C$11 -> 49.154295 | G46: ='Cost Pool Data'!$K$48 -> 1.6214861 | H46: =(F46*G46)/(D46*E46) -> 0.0057365519 | I46: =C46*H46 -> 0.0057365519
A47: DU | B47: Incoming Secondary Parcel Sort | C47: =C46 -> 1 | D47: 1 | E47: ='Productivity Data'!$I$22 -> 307.66823 | F47: ='Wage Data'!$C$11 -> 49.154295 | G47: ='Cost Pool Data'!$K$57 -> 1.4957787 | H47: =(F47*G47)/(D47*E47) -> 0.23897152 | I47: =C47*H47 -> 0.23897152 | J47: =SUM(I46:I47) -> 0.24470807
A49: Sources: | I49: Grand Total | J49: =J16+J28+J36+J42+J45+J47 -> 1.7986898
A50: [1]: Page 7, 8, 9
A51: [2]: Page 7, 10
A52: [3]: Page 5
A53: [4]: Page 6
A54: [5]: Page 3
A55: [6]: ( [4] * [5] ) / ( [2] * [3] )
A56: [7]: [1] * [6]

Sheet IR-DNDC-NDC
A1: USPS MARKETING MAIL IRREGULAR ROLLS DNDC NDC PRESORT PARCELS
C4: [1] | D4: [2] | E4: [3] | F4: [4] | G4: [5] | H4: [6] | I4: [7]
F5: Adjusted | H5: Cost | I5: Cost
D6: Conversion | E6: Units | F6: Wage | G6: Piggyback | H6: Per | I6: Per
A7: Facility | B7: Operation | C7: Handlings | D7: Factor | E7: Per Hour | F7: Rate | G7: Factor | H7: Operation | I7: Facility
A9: Destination | B9: Unload Mailer Pallet Box | C9: ='Mailer Arrival Profile'!$C$17 -> 0.16173007 | D9: ='Conversion Factors'!$J$20 -> 602.07697 | E9: ='Productivity Data'!$I$38 -> 46.475052 | F9: ='Wage Data'!$C$11 -> 49.154295 | G9: ='Cost Pool Data'!$K$43 -> 1.3860239 | H9: =(F9*G9)/(D9*E9) -> 0.0024347832 | I9: =C9*H9 -> 0.00039377765
A10: NDC | B10: Unload Mailer Pallet (Pieces) | C10: ='Mailer Arrival Profile'!$D$17 -> 0.68745985 | D10: ='Conversion Factors'!$J$21 -> 962.99674 | E10: ='Productivity Data'!$I$38 -> 46.475052 | F10: ='Wage Data'!$C$11 -> 49.154295 | G10: ='Cost Pool Data'!$K$43 -> 1.3860239 | H10: =(F10*G10)/(D10*E10) -> 0.0015222553 | I10: =C10*H10 -> 0.0010464894
B11: Unload Mailer Pallet (Sacks) | C11: ='Mailer Arrival Profile'!$E$17 -> 0.096709728 | D11: ='Conversion Factors'!$J$22 -> 620.21611 | E11: ='Productivity Data'!$I$38 -> 46.475052 | F11: ='Wage Data'!$C$11 -> 49.154295 | G11: ='Cost Pool Data'!$K$43 -> 1.3860239 | H11: =(F11*G11)/(D11*E11) -> 0.0023635743 | I11: =C11*H11 -> 0.00022858063
B12: Unload Mailer APC (Sacks) | C12: ='Mailer Arrival Profile'!$F$17 -> 0.05410035 | D12: ='Conversion Factors'!$J$23 -> 524.66078 | E12: ='Productivity Data'!$I$37 -> 55.996737 | F12: ='Wage Data'!$C$11 -> 49.154295 | G12: ='Cost Pool Data'!$K$43 -> 1.3860239 | H12: =(F12*G12)/(D12*E12) -> 0.0023189472 | I12: =C12*H12 -> 0.00012545586
B13: IPP Manual Sort | C13: =SUM(C9:C12) -> 1 | D13: 1 | E13: ='Productivity Data'!$I$21 -> 402.79881 | F13: ='Wage Data'!$C$11 -> 49.154295 | G13: ='Cost Pool Data'!$K$41 -> 1.4774317 | H13: =(F13*G13)/(D13*E13) -> 0.18029376 | I13: =C13*H13 -> 0.18029376
B14: Load Postal Hamper | C14: =C13 -> 1 | D14: ='Conversion Factors'!$J$48 -> 230.28825 | E14: ='Productivity Data'!$I$44 -> 70.608822 | F14: ='Wage Data'!$C$11 -> 49.154295 | G14: ='Cost Pool Data'!$K$43 -> 1.3860239 | H14: =(F14*G14)/(D14*E14) -> 0.0041898786 | I14: =C14*H14 -> 0.0041898786 | J14: =SUM(I9:I14) -> 0.18627794
