Workbook
Name a_coa_exp: 'Parameters demand'!$Y$11:$Y$84
Name a_coa_ind: 'Parameters demand'!$V$11:$V$84
Name a_coa_oth: 'Parameters demand'!$X$11:$X$84
Name a_ele_com: 'Parameters demand'!$R$11:$R$84
Name a_ele_ind: 'Parameters demand'!$S$11:$S$84
Name a_ele_oth: 'Parameters demand'!$U$11:$U$84
Name a_ele_res: 'Parameters demand'!$Q$11:$Q$84
Name a_ele_tra: 'Parameters demand'!$T$11:$T$84
Name a_gas_com: 'Parameters demand'!$L$11:$L$84
Name a_gas_exp: 'Parameters demand'!$P$11:$P$84
Name a_gas_ind: 'Parameters demand'!$M$11:$M$84
Name a_gas_res: 'Parameters demand'!$K$11:$K$84
Name a_gas_tra: 'Parameters demand'!$N$11:$N$84
Name a_oil_com: 'Parameters demand'!$D$11:$D$84
Name a_oil_ind: 'Parameters demand'!$E$11:$E$84
Name a_oil_res: 'Parameters demand'!$C$11:$C$84
Name a_oil_row_crude: 'Parameters demand'!$H$11:$H$84
Name a_oil_row_non_us: 'Parameters demand'!$J$11:$J$84
Name a_oil_row_ref: 'Parameters demand'!$I$11:$I$84
Name a_oil_tra: 'Parameters demand'!$F$11:$F$84
Name aeo_dem_coa_2010: 'Coal demand projection'!$C$10:$G$10
Name aeo_dem_coa_ele: 'Coal demand projection'!$D$10:$D$84
Name aeo_dem_coa_exp: 'Coal demand projection'!$F$10:$F$84
Name aeo_dem_coa_ind: 'Coal demand projection'!$C$10:$C$84
Name aeo_dem_coa_oth: 'Coal demand projection'!$E$10:$E$84
Name aeo_dem_coa_tot: 'Coal demand projection'!$G$10:$G$84
Name aeo_dem_ele_2010: 'Electricity demand projection'!$C$10:$H$10
Name aeo_dem_ele_com: 'Electricity demand projection'!$D$10:$D$84
Name aeo_dem_ele_ind: 'Electricity demand projection'!$E$10:$E$84
Name aeo_dem_ele_oth: 'Electricity demand projection'!$G$10:$G$84
Name aeo_dem_ele_res: 'Electricity demand projection'!$C$10:$C$84
Name aeo_dem_ele_tot: 'Electricity demand projection'!$H$10:$H$84
Name aeo_dem_ele_tra: 'Electricity demand projection'!$F$10:$F$84
Name aeo_dem_gas_2010: 'Gas demand projection'!$C$10:$I$10
Name aeo_dem_gas_com: 'Gas demand projection'!$D$10:$D$84
Name aeo_dem_gas_ele: 'Gas demand projection'!$G$10:$G$84
Name aeo_dem_gas_exp: 'Gas demand projection'!$H$10:$H$84
Name aeo_dem_gas_ind: 'Gas demand projection'!$E$10:$E$84
Name aeo_dem_gas_res: 'Gas demand projection'!$C$10:$C$84
Name aeo_dem_gas_tot: 'Gas demand projection'!$I$10:$I$84
Name aeo_dem_gas_tra: 'Gas demand projection'!$F$10:$F$84
Name aeo_dem_oil_2010: 'Oil demand projection'!$C$10:$K$10
Name aeo_dem_oil_com: 'Oil demand projection'!$D$10:$D$84
Name aeo_dem_oil_ele: 'Oil demand projection'!$G$10:$G$84
Name aeo_dem_oil_ind: 'Oil demand projection'!$E$10:$E$84
Name aeo_dem_oil_res: 'Oil demand projection'!$C$10:$C$84
Name aeo_dem_oil_row: 'Oil demand projection'!$M$10:$M$84
Name aeo_dem_oil_row_2010: 'Oil demand projection'!$H$10:$J$10
Name aeo_dem_oil_row_crude: 'Oil demand projection'!$H$10:$H$84
Name aeo_dem_oil_row_non_us: 'Oil demand projection'!$J$10:$J$84
Name aeo_dem_oil_row_ref: 'Oil demand projection'!$I$10:$I$84
Name aeo_dem_oil_tot: 'Oil demand projection'!$K$10:$K$84
Name aeo_dem_oil_tra: 'Oil demand projection'!$F$10:$F$84
Name aeo_price_2010: Prices!$C$10:$F$10
Name aeo_price_coa: Prices!$E$10:$E$84
Name aeo_price_ele: Prices!$F$10:$F$84
Name aeo_price_gas: Prices!$D$10:$D$84
Name aeo_price_oil: Prices!$C$10:$C$84
Name aeo_prices: Prices!$C$10:$F$84
Name aeo_sup_coa_2010: 'Coal supply projection'!$C$10:$E$10

Sheet Table of Contents
B2: MARKETSIM TABLE OF CONTENTS
B3: Click an underlined heading below to view the associated tab
C5: MODEL RUN INTERFACE
C7: Detailed Results
C9: E&D SCENARIO INPUT: OIL | F9: AEO BASELINE PROJECTIONS
C10: E&D SCENARIO INPUT: GAS | F10: Supply | G10: Demand
C11: BOE Percentage by Planning Area | F11: Oil | G11: Oil
F12: Gas | G12: Gas
C13: SIMULATION QUANTITIES | F13: Electricity | G13: Electricity
C14: Supply | D14: Demand | F14: Coal | G14: Coal
C15: Oil | D15: Oil
C16: Gas | D16: Gas | F16: PARAMETER CALCULATIONS
C17: Electricity | D17: Electricity | F17: Supply | G17: Demand
C18: Coal | D18: Coal
F19: ELASTICITY & ADJUSTMENT
C20: AEO Baseline Prices & MarketSim Simulated Prices | F20: Supply | G20: Demand
F21: Oil | G21: Oil
F22: Gas | G22: Gas
C23: Change in Consumer Surplus | F23: Electricity | G23: Electricity
F24: Coal | G24: Coal
F25: Adjustment Rates
C27: CALCULATIONS FOR ESTIMATION OF OCS EXPORTS | F27: DATA SUPPORTING CALCULATION OF OCS EXPORTS
C28: Calculaton of OCS Crude Oil Exports | F28: API Gravity of U.S. Crude Production and Imports
C29: Calculation of OCS-Derived Refined Product Exports | F29: API Gravity of OCS Crude

Sheet Update Directions
B1: Return to Table of Contents
B3: DIRECTIONS FOR UPDATING
B5: Updates to MarketSim may involve: (1) updates to baseline supply and demand projections, (2) updates to elasticity values or adjustment rates, or (3) updates to the inflation forecast. Baseline Supply and Demand Projections In Item 1 below, the existing baseline data may be cleared from MarketSim. It is recommended that users do this rather than copy over the existing data. In Item 2 the user enters the first year and last year to be reflected in the AEO baseline data to be incorporated into MarketSim. Items 3 through 10 below will direct the user to the specific worksheets where the baseline supply and demand projections may be updated using data from EIA's NEMS model. Where necessary, special instructions are included with each of these items to address potential imbalances between supply and demand in the NEMS forecast. The bottom of each column in each worksheet includes detailed information on the AEO tables and rown numbers where baseline data are avaialble. However, because EIA changes these tables periodically, model users may need re-examine the structure of the EIA data and identify the correct tables/rows where the required baseline data are located.
B6: Energy Price Projections Item 11 below directs users to where they can update the baseline energy price projections. Extrapolation Beyond AEO Data Item 12 below is where model users must prompt MarketSim to extrapolate beyond the baseline NEMS data. Default Elasticity Values and Adjustment Rates Item 13 below provides directions on how to update elasticity values and adjustment rates in the model. Inflation Indices Item 14 below includes directions on how to update the inflation indices in the model.
A7: 1. | B7: CLEAR EXISTING BASELINE DATA IN MODEL
B8: It is recommended that users clear the existing baseline data using the button at right rather than copying over existing baseline data.
A9: 2. | B9: UPDATE FIRST AND LAST YEARS REPRESENTED IN BASELINE SUPPLY AND DEMAND DATA
B10: Enter the first year represented by the baseline data in MarketSim: | D10: 2019
B11: Enter the last year covered by the AEO baseline projection: | D11: 2050 | F11: Projections last updated on 11/2/2023 10:19:47 AM
A13: 3. | B13: UPDATE OIL SUPPLY PROJECTION
B14: Oil Supply | C14: Columns C through G, I, K, and O require updating. All other columns update automatically. Based on past experience, supply and demand in the NEMS oil market data may be imbalanced. To generate a balanced forecast, this worksheet is set up to calculate the difference between total supply and total demand and adjust "Other" domestic supply to force supply and demand to balance.
A16: 4. | B16: UPDATE GAS SUPPLY PROJECTION
B17: Gas Supply | C17: Columns C through J require updating.
A19: 5. | B19: UPDATE ELECTRICITY SUPPLY PROJECTION
B20: Electricity Supply | C20: Columns C through L require updating.
A22: 6. | B22: UPDATE COAL SUPPLY PROJECTION
B23: Coal Supply | C23: Columns C and D require updating.
A25: 7. | B25: UPDATE OIL DEMAND PROJECTION
B26: Oil Demand | C26: Columns C though J require updating. All other columns update automatically.
A28: 8. | B28: UPDATE GAS DEMAND PROJECTION
B29: Gas Demand | C29: Columns C through H require updating.
A31: 9. | B31: UPDATE ELECTRICITY DEMAND PROJECTION
B32: Electricity Demand | C32: Columns L through P require updating. If the note at the top of the worksheet indicates that supply and demand are not in equilibrium, click on the "Equilibrate Electricity" button.
A34: 10. | B34: UPDATE COAL DEMAND PROJECTION
B35: Coal Demand | C35: Columns C through F require updating.
A37: 11. | B37: UPDATE ENERGY PRICE PROJECTIONS
B38: Prices | C38: The baseline price projection in columns C through F require updating.
A40: 12. | B40: EXTRAPOLATE BEYOND AEO DATA
B41: Press the button at right to prompt MarketSim to extrapolate to years after the AEO forecast horizon.
H43: Projections last updated on 2020/08/13 4:53 PM
A45: 13. | B45: UPDATE DEFAULTS (IF UPDATING ELASTICITIES OR ADJUSTMENT RATES)
B46: Defaults | C46: The default values for supply and demand elasticities and adjustment rates are included in this worksheet. As new estimates for these values become available, model users can change the values on this worksheet to make these updated values the model defaults. After entering these new values, users are also encouraged to enter the corresponding source information. Once the new default values and the corresponding source information have been entered, go to any of the following worksheets and press "Restore THIS TAB's default elasticities" OR "Restore ALL default elasticities": Oil demand elasticities, Gas demand elasticities, Electricity demand elasticities, Coal demand elasticities, Oil supply elasticities, Gas supply elasticities, Electricity supply elasticities, Coal supply elasticities.
A50: 14. | B50: UPDATE INFLATION
B51: Inflation | C51: Columns C through E require updating.
C94: =Inflation!$C$7 -> GDP Chain-type Price Index | D94: =Inflation!$D$7 -> CPI All-urban | E94: =Inflation!$E$7 -> CPI Energy Commodities and Services | F94: =Inflation!$F$7 -> User defined

Sheet Model Run Interface
B1: Return to Table of Contents
B3: MODEL RUN INTERFACE
J4: SUMMARY RESULTS
A5: 1. | B5: INPUT E&D SCENARIO
B6: Jump to E&D scenario sheets to input OCS production schedules manually or import OECM scenario automatically. | J6: CHANGE IN PRODUCTION AND CONSUMPTION
K7: Baseline | L7: Simulation | M7: Change In Sector | N7: % Change In Sector
B9: E&D SCENARIO INPUT: OIL | J9: OIL (million barrels)
B10: E&D SCENARIO INPUT: GAS | J10: U.S. Consumption | K10: {=SUM(OFFSET(aeo_dem_oil_tot,begin_year-'OCS Oil SIM'!$B$10,0,length_year)-OFFSET(aeo_dem_oil_row,begin_year-'OCS Oil SIM'!$B$10,0,length_year))*365} -> 135117.83 | L10: {=SUM(OFFSET(sim_dem_oil_tot,begin_year-'OCS Oil SIM'!$B$11,0,length_year)-OFFSET(sim_dem_oil_row,begin_year-'OCS Oil SIM'!$B$11,0,length_year))*365} -> 135124.15 | M10: =L10-K10 -> 6.3206354 | N10: =IFERROR(M10/K10,0) -> 4.6778694e-05
J11: U.S. Production | K11: {=SUM(OFFSET(aeo_sup_oil_tot,begin_year-'OCS Oil SIM'!$B$10,0,length_year)-OFFSET(aeo_sup_oil_row,begin_year-'OCS Oil SIM'!$B$10,0,length_year))*365} -> 150552.41 | L11: {=SUM(OFFSET(sim_sup_oil_tot,begin_year-'OCS Oil SIM'!$B$11,0,length_year)+OFFSET(sim_sup_oil_ocs,begin_year-'OCS Oil SIM'!$B$10,0,length_year)-OFFSET(sim_sup_oil_row,begin_year-'OCS Oil SIM'!$B$11,0,length_year))*365} -> 150621.45 | M11: =L11-K11 -> 69.03709 | N11: =IFERROR(M11/K11,0) -> 0.00045855851
A12: 2. | B12: DEFINE SCENARIO PARAMETERS | J12: Lower 48 onshore, biofuels, other | K12: =K11-K13-K14-K15 -> 136029.54 | L12: =L11-L13-L14-L15 -> 136004.63 | M12: =L12-K12 -> -24.914874 | N12: =IFERROR(M12/K12,0) -> -0.00018315782
B13: Edit the scenario name and calculation parameters. | J13: Lower 48 offshore | K13: {=SUM(OFFSET(aeo_sup_oil_off,begin_year-'OCS Oil SIM'!$B$10,0,length_year))*365} -> 10296.63 | L13: {=SUM(OFFSET(sim_sup_oil_off,begin_year-'OCS Oil SIM'!$B$11,0,length_year)+OFFSET(sim_sup_oil_ocs_atn,begin_year-'OCS Oil SIM'!$B$10,0,length_year)+OFFSET(sim_sup_oil_ocs_atm,begin_year-'OCS Oil SIM'!$B$10,0,length_year)+OFFSET(sim_sup_oil_ocs_ats,begin_year-'OCS Oil SIM'!$B$10,0,length_year)+OFFSET(sim_sup_oil_ocs_atf,begin_year-'OCS Oil SIM'!$B$10,0,length_year)+OFFSET(sim_sup_oil_ocs_gme,begin_year-'OCS Oil SIM'!$B$10,0,length_year)+OFFSET(sim_sup_oil_ocs_gmc,begin_year-'OCS Oil SIM'!$B$10,0,length_year)+OFFSET(sim_sup_oil_ocs_gmw,begin_year-'OCS Oil SIM'!$B$10,0,length_year)+OFFSET(sim_sup_oil_ocs_pas,begin_year-'OCS Oil SIM'!$B$10,0,length_year)+OFFSET(sim_sup_oil_ocs_pac,begin_year-'OCS Oil SIM'!$B$10,0,length_year)+OFFSET(sim_sup_oil_ocs_pan,begin_year-'OCS Oil SIM'!$B$10,0,length_year)+OFFSET(sim_sup_oil_ocs_paw,begin_year-'OCS Oil SIM'!$B$10,0,length_year))*365} -> 10335.237 | M13: =L13-K13 -> 38.60712 | N13: =IFERROR(M13/K13,0) -> 0.0037494907
J14: Alaska onshore | K14: {=SUM(OFFSET(aeo_sup_oil_ala_on,begin_year-'OCS Oil SIM'!$B$10,0,length_year))*365} -> 3416.6201 | L14: {=SUM(OFFSET(sim_sup_oil_ala_on,begin_year-'OCS Oil SIM'!$B$11,0,length_year))*365} -> 3416.1559 | M14: =L14-K14 -> -0.46417095 | N14: =IFERROR(M14/K14,0) -> -0.00013585676
B15: Scenario name: | F15: GenericE&DtemplateCIandGOA | J15: Alaska offshore | K15: {=SUM(OFFSET(aeo_sup_oil_ala_off,begin_year-'OCS Oil SIM'!$B$10,0,length_year))*365} -> 809.61964 | L15: {=365*(SUM(OFFSET(sim_sup_oil_ala_off,begin_year-'OCS Oil SIM'!$B$11,0,length_year)+OFFSET(sim_sup_oil_ocs,begin_year-'OCS Oil SIM'!$B$10,0,length_year))-SUM(OFFSET(sim_sup_oil_ocs_atn,begin_year-'OCS Oil SIM'!$B$10,0,length_year)+OFFSET(sim_sup_oil_ocs_atm,begin_year-'OCS Oil SIM'!$B$10,0,length_year)+OFFSET(sim_sup_oil_ocs_ats,begin_year-'OCS Oil SIM'!$B$10,0,length_year)+OFFSET(sim_sup_oil_ocs_atf,begin_year-'OCS Oil SIM'!$B$10,0,length_year)+OFFSET(sim_sup_oil_ocs_gme,begin_year-'OCS Oil SIM'!$B$10,0,length_year)+OFFSET(sim_sup_oil_ocs_gmc,begin_year-'OCS Oil SIM'!$B$10,0,length_year)+OFFSET(sim_sup_oil_ocs_gmw,begin_year-'OCS Oil SIM'!$B$10,0,length_year)+OFFSET(sim_sup_oil_ocs_pas,begin_year-'OCS Oil SIM'!$B$10,0,length_year)+OFFSET(sim_sup_oil_ocs_pac,begin_year-'OCS Oil SIM'!$B$10,0,length_year)+OFFSET(sim_sup_oil_ocs_pan,begin_year-'OCS Oil SIM'!$B$10,0,length_year)+OFFSET(sim_sup_oil_ocs_paw,begin_year-'OCS Oil SIM'!$B$10,0,length_year)))} -> 865.42866 | M15: =L15-K15 -> 55.809016 | N15: =IFERROR(M15/K15,0) -> 0.068932388
B16: Scenario begin year: | F16: 2026 | J16: Net Imports | K16: =K10-K11 -> -15434.585 | L16: =L10-L11 -> -15497.301 | M16: =L16-K16 -> -62.716455 | N16: =IFERROR(M16/K16,0) -> 0.0040633716
B17: Scenario end year: | F17: {=OFFSET(year_oil,MATCH(2,INDEX(1/(sim_sup_oil_ocs+sim_sup_gas_ocs>0),0))-1,0)} -> 2044 | J17: GAS (trillion cubic feet)
B18: Scenario length (years): | F18: =end_year-begin_year+1 -> 19 | J18: U.S. Consumption | K18: {=SUM(OFFSET(aeo_dem_gas_tot,begin_year-'OCS Oil SIM'!$B$10,0,length_year)-OFFSET(aeo_dem_gas_exp,begin_year-'OCS Oil SIM'!$B$10,0,length_year))} -> 537.92636 | L18: {=SUM(OFFSET(sim_dem_gas_tot,begin_year-'OCS Oil SIM'!$B$11,0,length_year)-OFFSET(sim_dem_gas_exp,begin_year-'OCS Oil SIM'!$B$11,0,length_year))} -> 537.92836 | M18: =L18-K18 -> 0.0019971848 | N18: =IFERROR(M18/K18,0) -> 3.7127475e-06
B19: NPV base year: | F19: 2025 | J19: U.S. Production | K19: {=SUM(OFFSET(aeo_sup_gas_tot,begin_year-'OCS Oil SIM'!$B$10,0,length_year)-OFFSET(aeo_sup_gas_pip,begin_year-'OCS Oil SIM'!$B$10,0,length_year)-OFFSET(aeo_sup_gas_lng,begin_year-'OCS Oil SIM'!$B$10,0,length_year))} -> 735.68529 | L19: {=SUM(OFFSET(sim_sup_gas_tot,begin_year-'OCS Oil SIM'!$B$11,0,length_year)+OFFSET(sim_sup_gas_ocs,begin_year-'OCS Oil SIM'!$B$10,0,length_year)-OFFSET(sim_sup_gas_lng,begin_year-'OCS Oil SIM'!$B$11,0,length_year)-OFFSET(sim_sup_gas_pip,begin_year-'OCS Oil SIM'!$B$11,0,length_year))} -> 735.70769 | M19: =L19-K19 -> 0.022401529 | N19: =IFERROR(M19/K19,0) -> 3.0449881e-05
B20: Discount rate: | F20: 0.03 | J20: Lower 48 onshore and other | K20: =K19-K21-K22-K23 -> 715.51627 | L20: =L19-L21-L22-L23 -> 715.79924 | M20: =L20-K20 -> 0.2829649 | N20: =IFERROR(M20/K20,0) -> 0.00039546955 | P20: =10^12/(F24*10^6) -> 177.93594
B21: Baseline prices in constant dollars of year: | F21: 2019 | J21: Lower 48 offshore | K21: {=SUM(OFFSET(aeo_sup_gas_off,begin_year-'OCS Oil SIM'!$B$10,0,length_year))} -> 13.265218 | L21: {=SUM(OFFSET(sim_sup_gas_off,begin_year-'OCS Oil SIM'!$B$11,0,length_year)+OFFSET(sim_sup_gas_ocs_atn,begin_year-'OCS Oil SIM'!$B$10,0,length_year)+OFFSET(sim_sup_gas_ocs_atm,begin_year-'OCS Oil SIM'!$B$10,0,length_year)+OFFSET(sim_sup_gas_ocs_ats,begin_year-'OCS Oil SIM'!$B$10,0,length_year)+OFFSET(sim_sup_gas_ocs_atf,begin_year-'OCS Oil SIM'!$B$10,0,length_year)+OFFSET(sim_sup_gas_ocs_gme,begin_year-'OCS Oil SIM'!$B$10,0,length_year)+OFFSET(sim_sup_gas_ocs_gmc,begin_year-'OCS Oil SIM'!$B$10,0,length_year)+OFFSET(sim_sup_gas_ocs_gmw,begin_year-'OCS Oil SIM'!$B$10,0,length_year)+OFFSET(sim_sup_gas_ocs_pas,begin_year-'OCS Oil SIM'!$B$10,0,length_year)+OFFSET(sim_sup_gas_ocs_pac,begin_year-'OCS Oil SIM'!$B$10,0,length_year)+OFFSET(sim_sup_gas_ocs_pan,begin_year-'OCS Oil SIM'!$B$10,0,length_year)+OFFSET(sim_sup_gas_ocs_paw,begin_year-'OCS Oil SIM'!$B$10,0,length_year))} -> 13.291027 | M21: =L21-K21 -> 0.025808658 | N21: =IFERROR(M21/K21,0) -> 0.0019455887
B22: Inflation index: | F22: GDP Chain-type Price Index | J22: Alaska onshore | K22: {=SUM(OFFSET(aeo_sup_gas_ala_on,begin_year-'OCS Oil SIM'!$B$10,0,length_year))} -> 6.903796 | L22: {=SUM(OFFSET(sim_sup_gas_ala_on,begin_year-'OCS Oil SIM'!$B$10,0,length_year))} -> 6.561424 | M22: =L22-K22 -> -0.34237203 | N22: =IFERROR(M22/K22,0) -> -0.049591852
B23: Display dollars in constant dollars of year: | F23: 2026 | J23: Alaska offshore | K23: {=SUM(OFFSET(aeo_sup_gas_ala_off,begin_year-'OCS Oil SIM'!$B$10,0,length_year))} -> 0 | L23: {=SUM(OFFSET(sim_sup_gas_ala_off,begin_year-'OCS Oil SIM'!$B$10,0,length_year)+OFFSET(sim_sup_gas_ocs,begin_year-'OCS Oil SIM'!$B$10,0,length_year))-SUM(OFFSET(sim_sup_gas_ocs_atn,begin_year-'OCS Oil SIM'!$B$10,0,length_year)+OFFSET(sim_sup_gas_ocs_atm,begin_year-'OCS Oil SIM'!$B$10,0,length_year)+OFFSET(sim_sup_gas_ocs_ats,begin_year-'OCS Oil SIM'!$B$10,0,length_year)+OFFSET(sim_sup_gas_ocs_atf,begin_year-'OCS Oil SIM'!$B$10,0,length_year)+OFFSET(sim_sup_gas_ocs_gme,begin_year-'OCS Oil SIM'!$B$10,0,length_year)+OFFSET(sim_sup_gas_ocs_gmc,begin_year-'OCS Oil SIM'!$B$10,0,length_year)+OFFSET(sim_sup_gas_ocs_gmw,begin_year-'OCS Oil SIM'!$B$10,0,length_year)+OFFSET(sim_sup_gas_ocs_pas,begin_year-'OCS Oil SIM'!$B$10,0,length_year)+OFFSET(sim_sup_gas_ocs_pac,begin_year-'OCS Oil SIM'!$B$10,0,length_year)+OFFSET(sim_sup_gas_ocs_pan,begin_year-'OCS Oil SIM'!$B$10,0,length_year)+OFFSET(sim_sup_gas_ocs_paw,begin_year-'OCS Oil SIM'!$B$10,0,length_year))} -> 0.056 | M23: =L23-K23 -> 0.056 | N23: =IFERROR(M23/K23,0) -> 0
B24: Natural gas barrel of oil equiv. in cubic ft.: | F24: 5620 | J24: Net Imports | K24: =K18-K19 -> -197.75892 | L24: =L18-L19 -> -197.77933 | M24: =L24-K24 -> -0.020404345 | N24: =IFERROR(M24/K24,0) -> 0.00010317787
J25: COAL (million short tons)
A26: 3. | B26: EQUILIBRATE ELECTRICITY MARKET | J26: U.S. Consumption | K26: {=SUM(OFFSET(aeo_dem_coa_tot,begin_year-'OCS Oil SIM'!$B$10,0,length_year)-OFFSET(aeo_dem_coa_exp,begin_year-'OCS Oil SIM'!$B$10,0,length_year))} -> 4249.6128 | L26: {=SUM(OFFSET(sim_dem_coa_tot,begin_year-'OCS Oil SIM'!$B$11,0,length_year)-OFFSET(sim_dem_coa_exp,begin_year-'OCS Oil SIM'!$B$11,0,length_year))} -> 4249.5704 | M26: =L26-K26 -> -0.042361755 | N26: =M26/K26 -> -9.96838e-06
B27: Confirm that the AEO baseline electricity markets are in equilibrium. Jump to electricity demand tab to solve imbalance. | J27: U.S. Production | K27: {=SUM(OFFSET(aeo_sup_coa_dom,begin_year-'OCS Oil SIM'!$B$10,0,length_year))} -> 6383.5948 | L27: {=SUM(OFFSET(sim_sup_coa_dom,begin_year-'OCS Oil SIM'!$B$11,0,length_year))} -> 6383.5544 | M27: =L27-K27 -> -0.040417348 | N27: =M27/K27 -> -6.3314401e-06
J28: Net Exports | K28: =K27-K26 -> 2133.982 | L28: =L27-L26 -> 2133.984 | M28: =L28-K28 -> 0.0019444065 | N28: =M28/K28 -> 9.1116345e-07
J29: ELECTRICITY (billion kilowatt hours)
B30: Baseline electricity markets are: | F30: =ele_equil -> In equilibrium | J30: U.S. Consumption | K30: {=SUM(OFFSET(aeo_dem_ele_tot,begin_year-'OCS Oil SIM'!$B$10,0,length_year))} -> 80966.071 | L30: {=SUM(OFFSET(sim_dem_ele_tot,begin_year-'OCS Oil SIM'!$B$11,0,length_year))} -> 80964.449 | M30: =L30-K30 -> -1.6213822 | N30: =M30/K30 -> -2.0025452e-05
J31: U.S. Production | K31: {=SUM(OFFSET(aeo_sup_ele_tot,begin_year-'OCS Oil SIM'!$B$10,0,length_year)-OFFSET(aeo_sup_ele_imp,begin_year-'OCS Oil SIM'!$B$10,0,length_year))} -> 80138.681 | L31: {=SUM(OFFSET(sim_sup_ele_tot,begin_year-'OCS Oil SIM'!$B$11,0,length_year)-OFFSET(sim_sup_ele_imp,begin_year-'OCS Oil SIM'!$B$11,0,length_year))} -> 80137.066 | M31: =L31-K31 -> -1.6154003 | N31: =M31/K31 -> -2.015756e-05
B32: AEO BASELINE ELECTRICITY DEMAND | J32: Net Imports | K32: =K30-K31 -> 827.38954 | L32: =L30-L31 -> 827.38356 | M32: =L32-K32 -> -0.0059818741 | N32: =M32/K32 -> -7.229816e-06
J33: * AEO projections do not differentiate offshore and onshore gas production for Alaska.
A34: 4. | B34: RUN MARKET SIMULATION
B35: Once all parameters and scenarios are entered, run market simulation to find fuel prices that clear all markets. | J35: =IF('Detailed Results'!$H$46=2,"PRESENT VALUE CHANGE IN CONSUMER SURPLUS","NOMINAL CHANGE IN CONSUMER SURPLUS") -> PRESENT VALUE CHANGE IN CONSUMER SURPLUS
J36: Fuel | K36: ΔCS ($ million) | L36: OCS Oil & Gas Prod. (MMBOE) | M36: ΔCS per BOE
J38: OIL | K38: {=TRANSPOSE('Detailed Results'!$D$39:$H$39)} -> 216.13041 | L38: {=SUM(OFFSET(sim_sup_oil_ocs,begin_year-'OCS Oil SIM'!$B$10,0,length_year))*365+SUM(OFFSET(sim_sup_gas_ocs,begin_year-'OCS Oil SIM'!$B$10,0,length_year))*gas_boe} -> 109.59075 | M38: =K38/$L$38 -> 1.9721593
J39: GAS | K39: 13.103934 | M39: =K39/$L$38 -> 0.11957154
J40: ELECTRICITY | K40: 5.5325192 | M40: =K40/$L$38 -> 0.050483452
J41: COAL | K41: 0.00068938048 | M41: =K41/$L$38 -> 6.290499e-06
B42: Scenario markets are: | F42: =IF(IF(ISERROR(SUM(OFFSET(scenario_equilibrium,begin_year-'OCS Oil SIM'!$B$10,0,length_year-1))),1,SUM(OFFSET(scenario_equilibrium,begin_year-'OCS Oil SIM'!$B$10,0,length_year-1)))>0.00001,"IMBALANCED!","In equilibrium") -> In equilibrium | J42: TOTAL | K42: 234.76756 | L42: {=SUM(OFFSET(sim_sup_oil_ocs,begin_year-'OCS Oil SIM'!$B$10,0,length_year))*365+SUM(OFFSET(sim_sup_gas_ocs,begin_year-'OCS Oil SIM'!$B$10,0,length_year))*gas_boe} -> 109.59075 | M42: =K42/L42 -> 2.1422206
B46: DETAILED SIMULATION RESULTS
C80: =Inflation!$C$7 -> GDP Chain-type Price Index | D80: =Inflation!$D$7 -> CPI All-urban | E80: =Inflation!$E$7 -> CPI Energy Commodities and Services | F80: =Inflation!$F$7 -> User defined

Sheet Detailed Results
B1: Return to Table of Contents | E1: Jump to Alaska Offshore Correction and Conversions →
B3: DETAILED SIMULATION RESULTS
B4: =scenario_name -> GenericE&DtemplateCIandGOA
B5: =IF($H$46=1,IF($H$47=1,"Nominal Consumer Surplus Change from OCS Production by Planning Area and Fuel","Nominal Consumer Surplus Change Net of Domestic Producer Transfer from OCS Production by Planning Area and Fuel"),IF($H$47=1,"Net Present Value of Consumer Surplus Change from OCS Production by Planning Area and Fuel ("&TEXT(npv_base_year,0)&" Base Year, "&TEXT(inflator_year,0)&" Constant Dollars)","Net Present Value of Consumer Surplus Change Net of Domestic Producer Transfer from OCS Production by Planning Area and Fuel ("&TEXT(npv_base_year,0)&" Base Year, "&TEXT(inflator_year,0)&" Constant Dollars)")) -> Net Present Value of Consumer Surplus Change Net of Domestic Producer Transfer from OCS Production by Planning Area and Fuel (2025 Base Year, 2026 Constant Dollars)
K7: Production Effects | Q7: Substitution Effects | U7: Petroleum Export Details
B8: OCS Region | D8: Oil | E8: Gas | F8: Electricity | G8: Coal | H8: TOTAL | L8: Baseline | M8: Simulation | N8: Change In Sector | O8: % Change In Sector | R8: Foregone offshore oil production (mmbbl) | S8: =SUM(OFFSET(sim_sup_oil_ocs,begin_year-'OCS Oil SIM'!$B$10,0,length_year))*365 -> 95 | U8: Export Category | V8: Exports (millions of barrels)
R9: Foregone offshore gas (mmBOE) | S9: =SUM(OFFSET(sim_sup_gas_ocs,begin_year-'OCS Oil SIM'!$B$10,0,length_year))*gas_boe -> 14.590747
K10: OIL (millions of barrels) | R10: Total foregone production (mmBOE) | S10: =D41 -> 109.59075 | U10: Change in Crude Oil Exports | V10: =N68 -> 0.67855402 | AA10: Conversion Factors
C11: Planning Area | D11: $ million | E11: $ million | F11: $ million | G11: $ million | H11: $ million | K11: U.S. Production | L11: =SUM(L12,L16,L19:L20) -> 150552.41 | M11: =SUM(M12,M16,M19:M20) -> 150621.45 | N11: =M11-L11 -> 69.03709 | O11: =IFERROR(N11/L11,0) -> 0.00045855851 | U11: OCS Oil (low and high estimates, respectively) | V11: =IF(ocs_crude_export_low*365>V10,V10,ocs_crude_export_low*365) -> 0.67855402 | W11: =IF(ocs_crude_export_high*365>V10,V10,ocs_crude_export_high*365) -> 0.67855402 | AA11: Coal
B12: ATL | C12: North Atlantic | D12: {=SUM(OFFSET(sim_sup_per_ocs_atn,begin_year-'OCS Oil SIM'!$B$10,0)*IF(ISERROR(D$61:D$135),0,D$61:D$135))+sim_sup_tot_ocs_atn*D$38} -> 0 | E12: {=SUM(OFFSET(sim_sup_per_ocs_atn,begin_year-'OCS Oil SIM'!$B$10,0)*IF(ISERROR(E$61:E$135),0,E$61:E$135))+sim_sup_tot_ocs_atn*E$38} -> 0 | F12: {=SUM(OFFSET(sim_sup_per_ocs_atn,begin_year-'OCS Oil SIM'!$B$10,0)*IF(ISERROR(F$61:F$135),0,F$61:F$135))+sim_sup_tot_ocs_atn*F$38} -> 0 | G12: {=SUM(OFFSET(sim_sup_per_ocs_atn,begin_year-'OCS Oil SIM'!$B$10,0)*IF(ISERROR(G$61:G$135),0,G$61:G$135))+sim_sup_tot_ocs_atn*G$38} -> 0 | H12: =SUM(D12:G12) -> 0 | K12: U.S. Onshore | L12: =SUM(L13:L15) -> 77530.688 | M12: =SUM(M13:M15) -> 77515.151 | N12: =M12-L12 -> -15.537561 | O12: =IFERROR(N12/L12,0) -> -0.0002004053 | R12: Change in Sector (mmBOE) | S12: Change as % of Foregone | U12: Non-OCS Oil (high and low estimates, respectively) | V12: =V10-V11 -> 0 | W12: =V10-W11 -> 0 | AA12: Calculation | AC12: Conversion Factor | AD12: Source
C13: Mid-Atlantic | D13: {=SUM(OFFSET(sim_sup_per_ocs_atm,begin_year-'OCS Oil SIM'!$B$10,0)*IF(ISERROR(D$61:D$135),0,D$61:D$135))+sim_sup_tot_ocs_atm*D$38} -> 0 | E13: {=SUM(OFFSET(sim_sup_per_ocs_atm,begin_year-'OCS Oil SIM'!$B$10,0)*IF(ISERROR(E$61:E$135),0,E$61:E$135))+sim_sup_tot_ocs_atm*E$38} -> 0 | F13: {=SUM(OFFSET(sim_sup_per_ocs_atm,begin_year-'OCS Oil SIM'!$B$10,0)*IF(ISERROR(F$61:F$135),0,F$61:F$135))+sim_sup_tot_ocs_atm*F$38} -> 0 | G13: {=SUM(OFFSET(sim_sup_per_ocs_atm,begin_year-'OCS Oil SIM'!$B$10,0)*IF(ISERROR(G$61:G$135),0,G$61:G$135))+sim_sup_tot_ocs_atm*G$38} -> 0 | H13: =SUM(D13:G13) -> 0 | K13: Lower 48 Onshore (Tight) | L13: =SUM(OFFSET(aeo_sup_oil_l48_t,begin_year-'OCS Oil SIM'!$B$10,0,length_year))*365 -> 63599.445 | M13: =SUM(OFFSET(sim_sup_oil_l48_t,begin_year-'OCS Oil SIM'!$B$11,0,length_year))*365 -> 63587.08 | N13: =M13-L13 -> -12.365298 | O13: =IFERROR(N13/L13,0) -> -0.00019442462 | AA13: Convert Million Tons to Tons | AB13: * | AC13: 1000000 | AD13: http://www.eia.gov/forecasts/aeo/er/early_production.cfm
C14: South Atlantic | D14: {=SUM(OFFSET(sim_sup_per_ocs_ats,begin_year-'OCS Oil SIM'!$B$10,0)*IF(ISERROR(D$61:D$135),0,D$61:D$135))+sim_sup_tot_ocs_ats*D$38} -> 0 | E14: {=SUM(OFFSET(sim_sup_per_ocs_ats,begin_year-'OCS Oil SIM'!$B$10,0)*IF(ISERROR(E$61:E$135),0,E$61:E$135))+sim_sup_tot_ocs_ats*E$38} -> 0 | F14: {=SUM(OFFSET(sim_sup_per_ocs_ats,begin_year-'OCS Oil SIM'!$B$10,0)*IF(ISERROR(F$61:F$135),0,F$61:F$135))+sim_sup_tot_ocs_ats*F$38} -> 0 | G14: {=SUM(OFFSET(sim_sup_per_ocs_ats,begin_year-'OCS Oil SIM'!$B$10,0)*IF(ISERROR(G$61:G$135),0,G$61:G$135))+sim_sup_tot_ocs_ats*G$38} -> 0 | H14: =SUM(D14:G14) -> 0 | K14: Lower 48 Onshore (Conventional) | L14: =SUM(OFFSET(aeo_sup_oil_l48,begin_year-'OCS Oil SIM'!$B$10,0,length_year))*365 -> 10514.623 | M14: =SUM(OFFSET(sim_sup_oil_l48,begin_year-'OCS Oil SIM'!$B$11,0,length_year))*365 -> 10511.915 | N14: =M14-L14 -> -2.7080921 | O14: =IFERROR(N14/L14,0) -> -0.00025755485
C15: Straits of Florida | D15: {=SUM(OFFSET(sim_sup_per_ocs_atf,begin_year-'OCS Oil SIM'!$B$10,0)*IF(ISERROR(D$61:D$135),0,D$61:D$135))+sim_sup_tot_ocs_atf*D$38} -> 0 | E15: {=SUM(OFFSET(sim_sup_per_ocs_atf,begin_year-'OCS Oil SIM'!$B$10,0)*IF(ISERROR(E$61:E$135),0,E$61:E$135))+sim_sup_tot_ocs_atf*E$38} -> 0 | F15: {=SUM(OFFSET(sim_sup_per_ocs_atf,begin_year-'OCS Oil SIM'!$B$10,0)*IF(ISERROR(F$61:F$135),0,F$61:F$135))+sim_sup_tot_ocs_atf*F$38} -> 0 | G15: {=SUM(OFFSET(sim_sup_per_ocs_atf,begin_year-'OCS Oil SIM'!$B$10,0)*IF(ISERROR(G$61:G$135),0,G$61:G$135))+sim_sup_tot_ocs_atf*G$38} -> 0 | H15: =SUM(D15:G15) -> 0 | K15: Alaska Onshore | L15: {=SUM(OFFSET(aeo_sup_oil_ala_on,begin_year-'OCS Oil SIM'!$B$10,0,length_year))*365} -> 3416.6201 | M15: {=SUM(OFFSET(sim_sup_oil_ala_on,begin_year-'OCS Oil SIM'!$B$11,0,length_year))*365} -> 3416.1559 | N15: =M15-L15 -> -0.46417095 | O15: =IFERROR(N15/L15,0) -> -0.00013585676 | Q15: ONSHORE PRODUCTION | R15: =SUM(R16:R17) -> 26.09813 | S15: =T15/$T$44 -> 0.23852108 | T15: =R15/$S$10 -> 0.23814173 | U15: Change in Refined Product Exports | V15: =N69 -> 1.8576055 | AA15: Convert Short Tons to BTU | AB15: * | AC15: 20387454 | AD15: Whitney, G. , C.E. Behrens, and C. Glover, “U.S. Fossil Fuel Resources: Terminology, Reporting, and Summary,” CRS Report for Congress, R40872, Table 5 (Washington, DC: Congressional Research Service, Library of Congress, 30 October 2009), 17.
B16: GoM | C16: Eastern Gulf | D16: {=SUM(OFFSET(sim_sup_per_ocs_gme,begin_year-'OCS Oil SIM'!$B$10,0)*IF(ISERROR(D$61:D$135),0,D$61:D$135))+sim_sup_tot_ocs_gme*D$38} -> 0 | E16: {=SUM(OFFSET(sim_sup_per_ocs_gme,begin_year-'OCS Oil SIM'!$B$10,0)*IF(ISERROR(E$61:E$135),0,E$61:E$135))+sim_sup_tot_ocs_gme*E$38} -> 0 | F16: {=SUM(OFFSET(sim_sup_per_ocs_gme,begin_year-'OCS Oil SIM'!$B$10,0)*IF(ISERROR(F$61:F$135),0,F$61:F$135))+sim_sup_tot_ocs_gme*F$38} -> 0 | G16: {=SUM(OFFSET(sim_sup_per_ocs_gme,begin_year-'OCS Oil SIM'!$B$10,0)*IF(ISERROR(G$61:G$135),0,G$61:G$135))+sim_sup_tot_ocs_gme*G$38} -> 0 | H16: =SUM(D16:G16) -> 0 | K16: U.S. Offshore | L16: =SUM(L17:L18) -> 11106.25 | M16: =SUM(M17:M18) -> 11200.666 | N16: =M16-L16 -> 94.416135 | O16: =IFERROR(N16/L16,0) -> 0.0085011715 | Q16: Oil | R16: =-N12 -> 15.537561 | S16: =T16/$T$44 -> 0.14200388 | T16: =R16/$S$10 -> 0.14177804 | U16: Derived from OCS Oil | V16: =V15*ocs_feedstock_percent -> 0.28416882 | AA16: Convert BTU to BOE | AB16: / | AC16: 5800000
C17: Central Gulf | D17: {=SUM(OFFSET(sim_sup_per_ocs_gmc,begin_year-'OCS Oil SIM'!$B$10,0)*IF(ISERROR(D$61:D$135),0,D$61:D$135))+sim_sup_tot_ocs_gmc*D$38} -> 77.021782 | E17: {=SUM(OFFSET(sim_sup_per_ocs_gmc,begin_year-'OCS Oil SIM'!$B$10,0)*IF(ISERROR(E$61:E$135),0,E$61:E$135))+sim_sup_tot_ocs_gmc*E$38} -> 4.877229 | F17: {=SUM(OFFSET(sim_sup_per_ocs_gmc,begin_year-'OCS Oil SIM'!$B$10,0)*IF(ISERROR(F$61:F$135),0,F$61:F$135))+sim_sup_tot_ocs_gmc*F$38} -> 1.9656055 | G17: {=SUM(OFFSET(sim_sup_per_ocs_gmc,begin_year-'OCS Oil SIM'!$B$10,0)*IF(ISERROR(G$61:G$135),0,G$61:G$135))+sim_sup_tot_ocs_gmc*G$38} -> 0.0002917405 | H17: =SUM(D17:G17) -> 83.864908 | K17: Lower 48 Offshore | L17: {=SUM(OFFSET(aeo_sup_oil_off,begin_year-'OCS Oil SIM'!$B$10,0,length_year))*365} -> 10296.63 | M17: {=SUM(OFFSET(sim_sup_oil_off,begin_year-'OCS Oil SIM'!$B$11,0,length_year)+OFFSET(sim_sup_oil_ocs_atn,begin_year-'OCS Oil SIM'!$B$10,0,length_year)+OFFSET(sim_sup_oil_ocs_atm,begin_year-'OCS Oil SIM'!$B$10,0,length_year)+OFFSET(sim_sup_oil_ocs_ats,begin_year-'OCS Oil SIM'!$B$10,0,length_year)+OFFSET(sim_sup_oil_ocs_atf,begin_year-'OCS Oil SIM'!$B$10,0,length_year)+OFFSET(sim_sup_oil_ocs_gme,begin_year-'OCS Oil SIM'!$B$10,0,length_year)+OFFSET(sim_sup_oil_ocs_gmc,begin_year-'OCS Oil SIM'!$B$10,0,length_year)+OFFSET(sim_sup_oil_ocs_gmw,begin_year-'OCS Oil SIM'!$B$10,0,length_year)+OFFSET(sim_sup_oil_ocs_pas,begin_year-'OCS Oil SIM'!$B$10,0,length_year)+OFFSET(sim_sup_oil_ocs_pac,begin_year-'OCS Oil SIM'!$B$10,0,length_year)+OFFSET(sim_sup_oil_ocs_pan,begin_year-'OCS Oil SIM'!$B$10,0,length_year)+OFFSET(sim_sup_oil_ocs_paw,begin_year-'OCS Oil SIM'!$B$10,0,length_year))*365} -> 10335.237 | N17: =M17-L17 -> 38.60712 | O17: =IFERROR(N17/L17,0) -> 0.0037494907 | Q17: Natural Gas | R17: =-N26*gas_boe -> 10.560569 | S17: =T17/$T$44 -> 0.096517196 | T17: =R17/$S$10 -> 0.096363695 | U17: Derived from Non-OCS Oil | V17: =V15-V16 -> 1.5734367 | AA17: Convert BOE to million BOE | AB17: / | AC17: 1000000
C18: Western Gulf | D18: {=SUM(OFFSET(sim_sup_per_ocs_gmw,begin_year-'OCS Oil SIM'!$B$10,0)*IF(ISERROR(D$61:D$135),0,D$61:D$135))+sim_sup_tot_ocs_gmw*D$38} -> 0 | E18: {=SUM(OFFSET(sim_sup_per_ocs_gmw,begin_year-'OCS Oil SIM'!$B$10,0)*IF(ISERROR(E$61:E$135),0,E$61:E$135))+sim_sup_tot_ocs_gmw*E$38} -> 0 | F18: {=SUM(OFFSET(sim_sup_per_ocs_gmw,begin_year-'OCS Oil SIM'!$B$10,0)*IF(ISERROR(F$61:F$135),0,F$61:F$135))+sim_sup_tot_ocs_gmw*F$38} -> 0 | G18: {=SUM(OFFSET(sim_sup_per_ocs_gmw,begin_year-'OCS Oil SIM'!$B$10,0)*IF(ISERROR(G$61:G$135),0,G$61:G$135))+sim_sup_tot_ocs_gmw*G$38} -> 0 | H18: =SUM(D18:G18) -> 0 | K18: Alaska Offshore | L18: {=SUM(OFFSET(aeo_sup_oil_ala_off,begin_year-'OCS Oil SIM'!$B$10,0,length_year))*365} -> 809.61964 | M18: {=365*(SUM(OFFSET(sim_sup_oil_ala_off,begin_year-'OCS Oil SIM'!$B$11,0,length_year)))+365*SUM(OFFSET(sim_sup_oil_ocs,begin_year-'OCS Oil SIM'!$B$10,0,length_year))-365*SUM(OFFSET(sim_sup_oil_ocs_atn,begin_year-'OCS Oil SIM'!$B$10,0,length_year),OFFSET(sim_sup_oil_ocs_atm,begin_year-'OCS Oil SIM'!$B$10,0,length_year),OFFSET(sim_sup_oil_ocs_ats,begin_year-'OCS Oil SIM'!$B$10,0,length_year),OFFSET(sim_sup_oil_ocs_atf,begin_year-'OCS Oil SIM'!$B$10,0,length_year),OFFSET(sim_sup_oil_ocs_gme,begin_year-'OCS Oil SIM'!$B$10,0,length_year),OFFSET(sim_sup_oil_ocs_gmc,begin_year-'OCS Oil SIM'!$B$10,0,length_year),OFFSET(sim_sup_oil_ocs_gmw,begin_year-'OCS Oil SIM'!$B$10,0,length_year),OFFSET(sim_sup_oil_ocs_pas,begin_year-'OCS Oil SIM'!$B$10,0,length_year),OFFSET(sim_sup_oil_ocs_pac,begin_year-'OCS Oil SIM'!$B$10,0,length_year),OFFSET(sim_sup_oil_ocs_pan,begin_year-'OCS Oil SIM'!$B$10,0,length_year),OFFSET(sim_sup_oil_ocs_paw,begin_year-'OCS Oil SIM'!$B$10,0,length_year))} -> 865.42866 | N18: =M18-L18 -> 55.809016 | O18: =IFERROR(N18/L18,0) -> 0.068932388 | Q18: EXISTING OFFSHORE PRODUCTION | R18: =SUM(R19:R20) -> 0.61791141 | S18: =T18/$T$44 -> 0.0056473354 | T18: =R18/$S$10 -> 0.0056383538 | AA18: Coal Conversion Factor | AC18: =AC13*AC15/AC16/AC17 -> 3.5150783 | AD18: Million BOE / Million Metric Tons
B19: PAC | C19: Southern California | D19: {=SUM(OFFSET(sim_sup_per_ocs_pas,begin_year-'OCS Oil SIM'!$B$10,0)*IF(ISERROR(D$61:D$135),0,D$61:D$135))+sim_sup_tot_ocs_pas*D$38} -> 0 | E19: {=SUM(OFFSET(sim_sup_per_ocs_pas,begin_year-'OCS Oil SIM'!$B$10,0)*IF(ISERROR(E$61:E$135),0,E$61:E$135))+sim_sup_tot_ocs_pas*E$38} -> 0 | F19: {=SUM(OFFSET(sim_sup_per_ocs_pas,begin_year-'OCS Oil SIM'!$B$10,0)*IF(ISERROR(F$61:F$135),0,F$61:F$135))+sim_sup_tot_ocs_pas*F$38} -> 0 | G19: {=SUM(OFFSET(sim_sup_per_ocs_pas,begin_year-'OCS Oil SIM'!$B$10,0)*IF(ISERROR(G$61:G$135),0,G$61:G$135))+sim_sup_tot_ocs_pas*G$38} -> 0 | H19: =SUM(D19:G19) -> 0 | K19: Biofuels | L19: {=SUM(OFFSET(aeo_sup_oil_bio,begin_year-'OCS Oil SIM'!$B$10,0,length_year))*365} -> 7623.3568 | M19: {=SUM(OFFSET(sim_sup_oil_bio,begin_year-'OCS Oil SIM'!$B$11,0,length_year))*365} -> 7622.8796 | N19: =M19-L19 -> -0.47715398 | O19: =IFERROR(N19/L19,0) -> -6.259106e-05 | Q19: Oil | R19: =S8-N16 -> 0.58386474 | S19: =T19/$T$44 -> 0.0053361695 | T19: =R19/$S$10 -> 0.0053276828
C20: Central California | D20: {=SUM(OFFSET(sim_sup_per_ocs_pac,begin_year-'OCS Oil SIM'!$B$10,0)*IF(ISERROR(D$61:D$135),0,D$61:D$135))+sim_sup_tot_ocs_pac*D$38} -> 0 | E20: {=SUM(OFFSET(sim_sup_per_ocs_pac,begin_year-'OCS Oil SIM'!$B$10,0)*IF(ISERROR(E$61:E$135),0,E$61:E$135))+sim_sup_tot_ocs_pac*E$38} -> 0 | F20: {=SUM(OFFSET(sim_sup_per_ocs_pac,begin_year-'OCS Oil SIM'!$B$10,0)*IF(ISERROR(F$61:F$135),0,F$61:F$135))+sim_sup_tot_ocs_pac*F$38} -> 0 | G20: {=SUM(OFFSET(sim_sup_per_ocs_pac,begin_year-'OCS Oil SIM'!$B$10,0)*IF(ISERROR(G$61:G$135),0,G$61:G$135))+sim_sup_tot_ocs_pac*G$38} -> 0 | H20: =SUM(D20:G20) -> 0 | K20: Other | L20: {=SUM(OFFSET(aeo_sup_oil_oth,begin_year-'OCS Oil SIM'!$B$10,0,length_year))*365} -> 54292.117 | M20: {=SUM(OFFSET(sim_sup_oil_oth,begin_year-'OCS Oil SIM'!$B$11,0,length_year))*365} -> 54282.753 | N20: =M20-L20 -> -9.3643302 | O20: =IFERROR(N20/L20,0) -> -0.00017248048 | Q20: Natural Gas | R20: =S9-N31*gas_boe -> 0.034046668 | S20: =T20/$T$44 -> 0.00031116589 | T20: =R20/$S$10 -> 0.00031067101 | AA20: Electricity
C21: Northern California | D21: {=SUM(OFFSET(sim_sup_per_ocs_pan,begin_year-'OCS Oil SIM'!$B$10,0)*IF(ISERROR(D$61:D$135),0,D$61:D$135))+sim_sup_tot_ocs_pan*D$38} -> 0 | E21: {=SUM(OFFSET(sim_sup_per_ocs_pan,begin_year-'OCS Oil SIM'!$B$10,0)*IF(ISERROR(E$61:E$135),0,E$61:E$135))+sim_sup_tot_ocs_pan*E$38} -> 0 | F21: {=SUM(OFFSET(sim_sup_per_ocs_pan,begin_year-'OCS Oil SIM'!$B$10,0)*IF(ISERROR(F$61:F$135),0,F$61:F$135))+sim_sup_tot_ocs_pan*F$38} -> 0 | G21: {=SUM(OFFSET(sim_sup_per_ocs_pan,begin_year-'OCS Oil SIM'!$B$10,0)*IF(ISERROR(G$61:G$135),0,G$61:G$135))+sim_sup_tot_ocs_pan*G$38} -> 0 | H21: =SUM(D21:G21) -> 0 | K21: Rest of World | L21: {=SUM(OFFSET(aeo_sup_oil_row,begin_year-'OCS Oil SIM'!$B$10,0,length_year))*365} -> 593183.28 | M21: {=SUM(OFFSET(sim_sup_oil_row,begin_year-'OCS Oil SIM'!$B$11,0,length_year))*365} -> 593139.25 | N21: =M21-L21 -> -44.036919 | O21: =IFERROR(N21/L21,0) -> -7.4238301e-05 | Q21: IMPORTS | R21: =SUM(R22:R23) -> 63.514606 | S21: =T21/$T$44 -> 0.58048496 | T21: =R21/$S$10 -> 0.57956176 | AA21: Calculation | AC21: Conversion Factor | AD21: Source
C22: Washington/Oregon | D22: {=SUM(OFFSET(sim_sup_per_ocs_paw,begin_year-'OCS Oil SIM'!$B$10,0)*IF(ISERROR(D$61:D$135),0,D$61:D$135))+sim_sup_tot_ocs_paw*D$38} -> 0 | E22: {=SUM(OFFSET(sim_sup_per_ocs_paw,begin_year-'OCS Oil SIM'!$B$10,0)*IF(ISERROR(E$61:E$135),0,E$61:E$135))+sim_sup_tot_ocs_paw*E$38} -> 0 | F22: {=SUM(OFFSET(sim_sup_per_ocs_paw,begin_year-'OCS Oil SIM'!$B$10,0)*IF(ISERROR(F$61:F$135),0,F$61:F$135))+sim_sup_tot_ocs_paw*F$38} -> 0 | G22: {=SUM(OFFSET(sim_sup_per_ocs_paw,begin_year-'OCS Oil SIM'!$B$10,0)*IF(ISERROR(G$61:G$135),0,G$61:G$135))+sim_sup_tot_ocs_paw*G$38} -> 0 | H22: =SUM(D22:G22) -> 0 | K22: Net Imports | L22: {=SUM(OFFSET(aeo_dem_oil_tot,begin_year-'OCS Oil SIM'!$B$10,0,length_year)-OFFSET(aeo_dem_oil_row,begin_year-'OCS Oil SIM'!$B$10,0,length_year))*365-L11} -> -15434.585 | M22: {=SUM(OFFSET(sim_dem_oil_tot,begin_year-'OCS Oil SIM'!$B$11,0,length_year)-OFFSET(sim_dem_oil_row,begin_year-'OCS Oil SIM'!$B$11,0,length_year))*365-M11} -> -15497.301 | N22: =M22-L22 -> -62.716455 | O22: =IFERROR(N22/L22,0) -> 0.0040633716 | Q22: Oil | R22: =-N22 -> 62.716455 | S22: =T22/$T$44 -> 0.57319034 | T22: =R22/$S$10 -> 0.57227874 | AA22: Convert billion kWh to single units | AB22: * | AC22: 1000000000 | AD22: www.extension.iastate.edu/agdm/wholefarm/pdf/c6-86.pdf
B23: A L A S K A | C23: Gulf of Alaska | D23: {=SUM(OFFSET(sim_sup_per_ocs_goa,begin_year-'OCS Oil SIM'!$B$10,0)*IF(ISERROR(D$61:D$135),0,D$61:D$135))+sim_sup_tot_ocs_goa*D$38} -> 85.038198 | E23: {=SUM(OFFSET(sim_sup_per_ocs_goa,begin_year-'OCS Oil SIM'!$B$10,0)*IF(ISERROR(E$61:E$135),0,E$61:E$135))+sim_sup_tot_ocs_goa*E$38} -> 4.8028181 | F23: {=SUM(OFFSET(sim_sup_per_ocs_goa,begin_year-'OCS Oil SIM'!$B$10,0)*IF(ISERROR(F$61:F$135),0,F$61:F$135))+sim_sup_tot_ocs_goa*F$38} -> 2.1870294 | G23: {=SUM(OFFSET(sim_sup_per_ocs_goa,begin_year-'OCS Oil SIM'!$B$10,0)*IF(ISERROR(G$61:G$135),0,G$61:G$135))+sim_sup_tot_ocs_goa*G$38} -> 0.00019283382 | H23: =SUM(D23:G23) -> 92.028238 | K23: Alaska Total (reflected in categories above) | L23: =L15+L18 -> 4226.2397 | M23: =M15+M18 -> 4281.5846 | N23: =M23-L23 -> 55.344845 | O23: =IFERROR(N23/L23,0) -> 0.013095529 | Q23: Natural Gas | R23: =-N35*gas_boe -> 0.79815181 | S23: =T23/$T$44 -> 0.0072946233 | T23: =R23/$S$10 -> 0.0072830219 | AA23: Convert kilowatt hour to BTU | AB23: * | AC23: 3412 | AD23: Whitney, G. , C.E. Behrens, and C. Glover, “U.S. Fossil Fuel Resources: Terminology, Reporting, and Summary,” CRS Report for Congress, R40872, Table 5 (Washington, DC: Congressional Research Service, Library of Congress, 30 October 2009), 17.
C24: Cook Inlet | D24: {=SUM(OFFSET(sim_sup_per_ocs_coo,begin_year-'OCS Oil SIM'!$B$10,0)*IF(ISERROR(D$61:D$135),0,D$61:D$135))+sim_sup_tot_ocs_coo*D$38} -> 54.070435 | E24: {=SUM(OFFSET(sim_sup_per_ocs_coo,begin_year-'OCS Oil SIM'!$B$10,0)*IF(ISERROR(E$61:E$135),0,E$61:E$135))+sim_sup_tot_ocs_coo*E$38} -> 3.4238872 | F24: {=SUM(OFFSET(sim_sup_per_ocs_coo,begin_year-'OCS Oil SIM'!$B$10,0)*IF(ISERROR(F$61:F$135),0,F$61:F$135))+sim_sup_tot_ocs_coo*F$38} -> 1.3798843 | G24: {=SUM(OFFSET(sim_sup_per_ocs_coo,begin_year-'OCS Oil SIM'!$B$10,0)*IF(ISERROR(G$61:G$135),0,G$61:G$135))+sim_sup_tot_ocs_coo*G$38} -> 0.00020480616 | H24: =SUM(D24:G24) -> 58.874411 | K24: GAS (trillion cubic feet) | Q24: OTHER | R24: =SUM(R25:R27) -> 9.8515783 | S24: =T24/$T$44 -> 0.090037448 | T24: =R24/$S$10 -> 0.089894252 | AA24: Convert BTU to BOE | AB24: / | AC24: 5800000
C25: Kodiak | D25: {=SUM(OFFSET(sim_sup_per_ocs_kod,begin_year-'OCS Oil SIM'!$B$10,0)*IF(ISERROR(D$61:D$135),0,D$61:D$135))+sim_sup_tot_ocs_kod*D$38} -> 0 | E25: {=SUM(OFFSET(sim_sup_per_ocs_kod,begin_year-'OCS Oil SIM'!$B$10,0)*IF(ISERROR(E$61:E$135),0,E$61:E$135))+sim_sup_tot_ocs_kod*E$38} -> 0 | F25: {=SUM(OFFSET(sim_sup_per_ocs_kod,begin_year-'OCS Oil SIM'!$B$10,0)*IF(ISERROR(F$61:F$135),0,F$61:F$135))+sim_sup_tot_ocs_kod*F$38} -> 0 | G25: {=SUM(OFFSET(sim_sup_per_ocs_kod,begin_year-'OCS Oil SIM'!$B$10,0)*IF(ISERROR(G$61:G$135),0,G$61:G$135))+sim_sup_tot_ocs_kod*G$38} -> 0 | H25: =SUM(D25:G25) -> 0 | K25: U.S. Production | L25: =SUM(L26,L31,L34) -> 735.68529 | M25: =SUM(M26,M31,M34) -> 735.70769 | N25: =M25-L25 -> 0.022401529 | O25: =IFERROR(N25/L25,0) -> 3.0449881e-05 | Q25: Biofuels | R25: =-N19 -> 0.47715398 | S25: =T25/$T$44 -> 0.0043608979 | T25: =R25/$S$10 -> 0.0043539623 | AA25: Convert BOE to million BOE | AB25: / | AC25: 1000000
C26: Shumagin | D26: {=SUM(OFFSET(sim_sup_per_ocs_shu,begin_year-'OCS Oil SIM'!$B$10,0)*IF(ISERROR(D$61:D$135),0,D$61:D$135))+sim_sup_tot_ocs_shu*D$38} -> 0 | E26: {=SUM(OFFSET(sim_sup_per_ocs_shu,begin_year-'OCS Oil SIM'!$B$10,0)*IF(ISERROR(E$61:E$135),0,E$61:E$135))+sim_sup_tot_ocs_shu*E$38} -> 0 | F26: {=SUM(OFFSET(sim_sup_per_ocs_shu,begin_year-'OCS Oil SIM'!$B$10,0)*IF(ISERROR(F$61:F$135),0,F$61:F$135))+sim_sup_tot_ocs_shu*F$38} -> 0 | G26: {=SUM(OFFSET(sim_sup_per_ocs_shu,begin_year-'OCS Oil SIM'!$B$10,0)*IF(ISERROR(G$61:G$135),0,G$61:G$135))+sim_sup_tot_ocs_shu*G$38} -> 0 | H26: =SUM(D26:G26) -> 0 | K26: U.S. Onshore | L26: =SUM(L27,L30) -> 721.22188 | M26: =SUM(M27,M30) -> 721.16253 | N26: =M26-L26 -> -0.0593504 | O26: =IFERROR(N26/L26,0) -> -8.2291457e-05 | Q26: Other Oil | R26: =-N20 -> 9.3643302 | S26: =T26/$T$44 -> 0.085584296 | T26: =R26/$S$10 -> 0.085448183 | AA26: Electricity Conversion Factor | AC26: =AC22*AC23/AC24/AC25 -> 0.58827586 | AD26: Million BOE / Billion kWh
C27: North Aleutian Basin | D27: {=SUM(OFFSET(sim_sup_per_ocs_nab,begin_year-'OCS Oil SIM'!$B$10,0)*IF(ISERROR(D$61:D$135),0,D$61:D$135))+sim_sup_tot_ocs_nab*D$38} -> 0 | E27: {=SUM(OFFSET(sim_sup_per_ocs_nab,begin_year-'OCS Oil SIM'!$B$10,0)*IF(ISERROR(E$61:E$135),0,E$61:E$135))+sim_sup_tot_ocs_nab*E$38} -> 0 | F27: {=SUM(OFFSET(sim_sup_per_ocs_nab,begin_year-'OCS Oil SIM'!$B$10,0)*IF(ISERROR(F$61:F$135),0,F$61:F$135))+sim_sup_tot_ocs_nab*F$38} -> 0 | G27: {=SUM(OFFSET(sim_sup_per_ocs_nab,begin_year-'OCS Oil SIM'!$B$10,0)*IF(ISERROR(G$61:G$135),0,G$61:G$135))+sim_sup_tot_ocs_nab*G$38} -> 0 | H27: =SUM(D27:G27) -> 0 | K27: Lower 48 Onshore | L27: =SUM(L28:L29) -> 714.31808 | M27: =SUM(M28:M29) -> 714.26004 | N27: =M27-L27 -> -0.05804937 | O27: =IFERROR(N27/L27,0) -> -8.1265436e-05 | Q27: Other Natural Gas | R27: =-N34*gas_boe -> 0.010094077 | S27: =T27/$T$44 -> 9.225374e-05 | T27: =R27/$S$10 -> 9.2107019e-05
C28: Aleutian Arc | D28: {=SUM(OFFSET(sim_sup_per_ocs_ala,begin_year-'OCS Oil SIM'!$B$10,0)*IF(ISERROR(D$61:D$135),0,D$61:D$135))+sim_sup_tot_ocs_ala*D$38} -> 0 | E28: {=SUM(OFFSET(sim_sup_per_ocs_ala,begin_year-'OCS Oil SIM'!$B$10,0)*IF(ISERROR(E$61:E$135),0,E$61:E$135))+sim_sup_tot_ocs_ala*E$38} -> 0 | F28: {=SUM(OFFSET(sim_sup_per_ocs_ala,begin_year-'OCS Oil SIM'!$B$10,0)*IF(ISERROR(F$61:F$135),0,F$61:F$135))+sim_sup_tot_ocs_ala*F$38} -> 0 | G28: {=SUM(OFFSET(sim_sup_per_ocs_ala,begin_year-'OCS Oil SIM'!$B$10,0)*IF(ISERROR(G$61:G$135),0,G$61:G$135))+sim_sup_tot_ocs_ala*G$38} -> 0 | H28: =SUM(D28:G28) -> 0 | K28: Conventional | L28: {=SUM(OFFSET(aeo_sup_gas_con,begin_year-'OCS Oil SIM'!$B$10,0,length_year))} -> 29.170369 | M28: {=SUM(OFFSET(sim_sup_gas_con,begin_year-'OCS Oil SIM'!$B$11,0,length_year))} -> 29.168648 | N28: =M28-L28 -> -0.0017209422 | O28: =IFERROR(N28/L28,0) -> -5.8996243e-05 | Q28: COAL | R28: =SUM(R29:R30) -> 0.14221814 | S28: =T28/$T$44 -> 0.0012997875 | T28: =R28/$S$10 -> 0.0012977203
C29: St. George Basin | D29: {=SUM(OFFSET(sim_sup_per_ocs_sgb,begin_year-'OCS Oil SIM'!$B$10,0)*IF(ISERROR(D$61:D$135),0,D$61:D$135))+sim_sup_tot_ocs_sgb*D$38} -> 0 | E29: {=SUM(OFFSET(sim_sup_per_ocs_sgb,begin_year-'OCS Oil SIM'!$B$10,0)*IF(ISERROR(E$61:E$135),0,E$61:E$135))+sim_sup_tot_ocs_sgb*E$38} -> 0 | F29: {=SUM(OFFSET(sim_sup_per_ocs_sgb,begin_year-'OCS Oil SIM'!$B$10,0)*IF(ISERROR(F$61:F$135),0,F$61:F$135))+sim_sup_tot_ocs_sgb*F$38} -> 0 | G29: {=SUM(OFFSET(sim_sup_per_ocs_sgb,begin_year-'OCS Oil SIM'!$B$10,0)*IF(ISERROR(G$61:G$135),0,G$61:G$135))+sim_sup_tot_ocs_sgb*G$38} -> 0 | H29: =SUM(D29:G29) -> 0 | K29: Unconventional | L29: {=SUM(OFFSET(aeo_sup_gas_unc,begin_year-'OCS Oil SIM'!$B$10,0,length_year))} -> 685.14772 | M29: {=SUM(OFFSET(sim_sup_gas_unc,begin_year-'OCS Oil SIM'!$B$11,0,length_year))} -> 685.09139 | N29: =M29-L29 -> -0.056328428 | O29: =IFERROR(N29/L29,0) -> -8.2213553e-05 | Q29: Domestic | R29: =-N40*$AC$18 -> 0.14207014 | S29: =T29/$T$44 -> 0.0012984349 | T29: =R29/$S$10 -> 0.0012963699 | AA29: Sources
C30: St. Matthew Hall | D30: {=SUM(OFFSET(sim_sup_per_ocs_smh,begin_year-'OCS Oil SIM'!$B$10,0)*IF(ISERROR(D$61:D$135),0,D$61:D$135))+sim_sup_tot_ocs_smh*D$38} -> 0 | E30: {=SUM(OFFSET(sim_sup_per_ocs_smh,begin_year-'OCS Oil SIM'!$B$10,0)*IF(ISERROR(E$61:E$135),0,E$61:E$135))+sim_sup_tot_ocs_smh*E$38} -> 0 | F30: {=SUM(OFFSET(sim_sup_per_ocs_smh,begin_year-'OCS Oil SIM'!$B$10,0)*IF(ISERROR(F$61:F$135),0,F$61:F$135))+sim_sup_tot_ocs_smh*F$38} -> 0 | G30: {=SUM(OFFSET(sim_sup_per_ocs_smh,begin_year-'OCS Oil SIM'!$B$10,0)*IF(ISERROR(G$61:G$135),0,G$61:G$135))+sim_sup_tot_ocs_smh*G$38} -> 0 | H30: =SUM(D30:G30) -> 0 | K30: Alaska Onshore | L30: {=SUM(OFFSET(aeo_sup_gas_ala_on,begin_year-'OCS Oil SIM'!$B$10,0,length_year))} -> 6.903796 | M30: {=SUM(OFFSET(sim_sup_gas_ala_on,begin_year-'OCS Oil SIM'!$B$11,0,length_year))} -> 6.902495 | N30: =M30-L30 -> -0.0013010292 | O30: =IFERROR(N30/L30,0) -> -0.00018845129 | Q30: Imported | R30: =-N41*$AC$18 -> 0.00014799415 | S30: =T30/$T$44 -> 1.3525767e-06 | T30: =R30/$S$10 -> 1.3504256e-06 | AA30: EIA. January 2012. AEO 2012 Early Release Overview. Accessed online March 2012 at <http://www.eia.gov/forecasts/aeo/er/early_production.cfm>.
C31: Bowers Basin | D31: {=SUM(OFFSET(sim_sup_per_ocs_bow,begin_year-'OCS Oil SIM'!$B$10,0)*IF(ISERROR(D$61:D$135),0,D$61:D$135))+sim_sup_tot_ocs_bow*D$38} -> 0 | E31: {=SUM(OFFSET(sim_sup_per_ocs_bow,begin_year-'OCS Oil SIM'!$B$10,0)*IF(ISERROR(E$61:E$135),0,E$61:E$135))+sim_sup_tot_ocs_bow*E$38} -> 0 | F31: {=SUM(OFFSET(sim_sup_per_ocs_bow,begin_year-'OCS Oil SIM'!$B$10,0)*IF(ISERROR(F$61:F$135),0,F$61:F$135))+sim_sup_tot_ocs_bow*F$38} -> 0 | G31: {=SUM(OFFSET(sim_sup_per_ocs_bow,begin_year-'OCS Oil SIM'!$B$10,0)*IF(ISERROR(G$61:G$135),0,G$61:G$135))+sim_sup_tot_ocs_bow*G$38} -> 0 | H31: =SUM(D31:G31) -> 0 | K31: U.S. Offshore | L31: =SUM(L32:L33) -> 13.265218 | M31: =SUM(M32:M33) -> 13.347027 | N31: =M31-L31 -> 0.081808658 | O31: =IFERROR(N31/L31,0) -> 0.0061671552 | Q31: ELECTRICITY | R31: =SUM(R32:R38) -> 1.0547047 | S31: =T31/$T$44 -> 0.009639361 | T31: =R31/$S$10 -> 0.0096240305 | AA31: Whitney, G. , C.E. Behrens, and C. Glover, “U.S. Fossil Fuel Resources: Terminology, Reporting, and Summary,” CRS Report for Congress, R40872, Table 5 (Washington, DC: Congressional Research Service, Library of Congress, 30 October 2009), 17.
C32: Aleutian Basin | D32: {=SUM(OFFSET(sim_sup_per_ocs_alb,begin_year-'OCS Oil SIM'!$B$10,0)*IF(ISERROR(D$61:D$135),0,D$61:D$135))+sim_sup_tot_ocs_alb*D$38} -> 0 | E32: {=SUM(OFFSET(sim_sup_per_ocs_alb,begin_year-'OCS Oil SIM'!$B$10,0)*IF(ISERROR(E$61:E$135),0,E$61:E$135))+sim_sup_tot_ocs_alb*E$38} -> 0 | F32: {=SUM(OFFSET(sim_sup_per_ocs_alb,begin_year-'OCS Oil SIM'!$B$10,0)*IF(ISERROR(F$61:F$135),0,F$61:F$135))+sim_sup_tot_ocs_alb*F$38} -> 0 | G32: {=SUM(OFFSET(sim_sup_per_ocs_alb,begin_year-'OCS Oil SIM'!$B$10,0)*IF(ISERROR(G$61:G$135),0,G$61:G$135))+sim_sup_tot_ocs_alb*G$38} -> 0 | H32: =SUM(D32:G32) -> 0 | K32: Lower 48 Offshore | L32: {=SUM(OFFSET(aeo_sup_gas_off,begin_year-'OCS Oil SIM'!$B$10,0,length_year))} -> 13.265218 | M32: {=SUM(OFFSET(sim_sup_gas_off,begin_year-'OCS Oil SIM'!$B$11,0,length_year)+OFFSET(sim_sup_gas_ocs_atn,begin_year-'OCS Oil SIM'!$B$10,0,length_year)+OFFSET(sim_sup_gas_ocs_atm,begin_year-'OCS Oil SIM'!$B$10,0,length_year)+OFFSET(sim_sup_gas_ocs_ats,begin_year-'OCS Oil SIM'!$B$10,0,length_year)+OFFSET(sim_sup_gas_ocs_atf,begin_year-'OCS Oil SIM'!$B$10,0,length_year)+OFFSET(sim_sup_gas_ocs_gme,begin_year-'OCS Oil SIM'!$B$10,0,length_year)+OFFSET(sim_sup_gas_ocs_gmc,begin_year-'OCS Oil SIM'!$B$10,0,length_year)+OFFSET(sim_sup_gas_ocs_gmw,begin_year-'OCS Oil SIM'!$B$10,0,length_year)+OFFSET(sim_sup_gas_ocs_pas,begin_year-'OCS Oil SIM'!$B$10,0,length_year)+OFFSET(sim_sup_gas_ocs_pac,begin_year-'OCS Oil SIM'!$B$10,0,length_year)+OFFSET(sim_sup_gas_ocs_pan,begin_year-'OCS Oil SIM'!$B$10,0,length_year)+OFFSET(sim_sup_gas_ocs_paw,begin_year-'OCS Oil SIM'!$B$10,0,length_year))} -> 13.291027 | N32: =M32-L32 -> 0.025808658 | O32: =IFERROR(N32/L32,0) -> 0.0019455887 | Q32: Nuclear | R32: =(L47-M47)*$AC$26 -> 0.026230273 | S32: =T32/$T$44 -> 0.00023972878 | T32: =R32/$S$10 -> 0.00023934751 | AA32: Hofstrand, D. October 2008. Energy Measurements and Conversions. Iowa State University - University Extension. Accessed online March 2012 at <www.extension.iastate.edu/agdm/wholefarm/pdf/c6-86.pdf>.
C33: Navarin Basin | D33: {=SUM(OFFSET(sim_sup_per_ocs_nav,begin_year-'OCS Oil SIM'!$B$10,0)*IF(ISERROR(D$61:D$135),0,D$61:D$135))+sim_sup_tot_ocs_nav*D$38} -> 0 | E33: {=SUM(OFFSET(sim_sup_per_ocs_nav,begin_year-'OCS Oil SIM'!$B$10,0)*IF(ISERROR(E$61:E$135),0,E$61:E$135))+sim_sup_tot_ocs_nav*E$38} -> 0 | F33: {=SUM(OFFSET(sim_sup_per_ocs_nav,begin_year-'OCS Oil SIM'!$B$10,0)*IF(ISERROR(F$61:F$135),0,F$61:F$135))+sim_sup_tot_ocs_nav*F$38} -> 0 | G33: {=SUM(OFFSET(sim_sup_per_ocs_nav,begin_year-'OCS Oil SIM'!$B$10,0)*IF(ISERROR(G$61:G$135),0,G$61:G$135))+sim_sup_tot_ocs_nav*G$38} -> 0 | H33: =SUM(D33:G33) -> 0 | K33: Alaska Offshore | L33: {=SUM(OFFSET(aeo_sup_gas_ala_off,begin_year-'OCS Oil SIM'!$B$10,0,length_year))} -> 0 | M33: {=SUM(OFFSET(sim_sup_gas_ala_off,begin_year-'OCS Oil SIM'!$B$11,0,length_year))+SUM(OFFSET(sim_sup_gas_ocs,begin_year-'OCS Oil SIM'!$B$10,0,length_year))-SUM(OFFSET(sim_sup_gas_ocs_atn,begin_year-'OCS Oil SIM'!$B$10,0,length_year)+OFFSET(sim_sup_gas_ocs_atm,begin_year-'OCS Oil SIM'!$B$10,0,length_year)+OFFSET(sim_sup_gas_ocs_ats,begin_year-'OCS Oil SIM'!$B$10,0,length_year)+OFFSET(sim_sup_gas_ocs_atf,begin_year-'OCS Oil SIM'!$B$10,0,length_year)+OFFSET(sim_sup_gas_ocs_gme,begin_year-'OCS Oil SIM'!$B$10,0,length_year)+OFFSET(sim_sup_gas_ocs_gmc,begin_year-'OCS Oil SIM'!$B$10,0,length_year)+OFFSET(sim_sup_gas_ocs_gmw,begin_year-'OCS Oil SIM'!$B$10,0,length_year)+OFFSET(sim_sup_gas_ocs_pas,begin_year-'OCS Oil SIM'!$B$10,0,length_year)+OFFSET(sim_sup_gas_ocs_pac,begin_year-'OCS Oil SIM'!$B$10,0,length_year)+OFFSET(sim_sup_gas_ocs_pan,begin_year-'OCS Oil SIM'!$B$10,0,length_year)+OFFSET(sim_sup_gas_ocs_paw,begin_year-'OCS Oil SIM'!$B$10,0,length_year))} -> 0.056 | N33: =M33-L33 -> 0.056 | O33: =IFERROR(N33/L33,0) -> 0 | Q33: Hydro | R33: =(L48-M48)*$AC$26 -> 0.00085076167 | S33: =T33/$T$44 -> 7.7754455e-06 | T33: =R33/$S$10 -> 7.7630794e-06
C34: Norton Basin | D34: {=SUM(OFFSET(sim_sup_per_ocs_nor,begin_year-'OCS Oil SIM'!$B$10,0)*IF(ISERROR(D$61:D$135),0,D$61:D$135))+sim_sup_tot_ocs_nor*D$38} -> 0 | E34: {=SUM(OFFSET(sim_sup_per_ocs_nor,begin_year-'OCS Oil SIM'!$B$10,0)*IF(ISERROR(E$61:E$135),0,E$61:E$135))+sim_sup_tot_ocs_nor*E$38} -> 0 | F34: {=SUM(OFFSET(sim_sup_per_ocs_nor,begin_year-'OCS Oil SIM'!$B$10,0)*IF(ISERROR(F$61:F$135),0,F$61:F$135))+sim_sup_tot_ocs_nor*F$38} -> 0 | G34: {=SUM(OFFSET(sim_sup_per_ocs_nor,begin_year-'OCS Oil SIM'!$B$10,0)*IF(ISERROR(G$61:G$135),0,G$61:G$135))+sim_sup_tot_ocs_nor*G$38} -> 0 | H34: =SUM(D34:G34) -> 0 | K34: Other | L34: {=SUM(OFFSET(aeo_sup_gas_oth,begin_year-'OCS Oil SIM'!$B$10,0,length_year))} -> 1.19819 | M34: {=SUM(OFFSET(sim_sup_gas_oth,begin_year-'OCS Oil SIM'!$B$11,0,length_year))} -> 1.1981333 | N34: =M34-L34 -> -5.6728713e-05 | O34: =IFERROR(N34/L34,0) -> -4.734534e-05 | Q34: Solar | R34: =(L49-M49)*$AC$26 -> 0.77072367 | S34: =T34/$T$44 -> 0.0070439467 | T34: =R34/$S$10 -> 0.007032744
C35: Hope Basin | D35: {=SUM(OFFSET(sim_sup_per_ocs_hop,begin_year-'OCS Oil SIM'!$B$10,0)*IF(ISERROR(D$61:D$135),0,D$61:D$135))+sim_sup_tot_ocs_hop*D$38} -> 0 | E35: {=SUM(OFFSET(sim_sup_per_ocs_hop,begin_year-'OCS Oil SIM'!$B$10,0)*IF(ISERROR(E$61:E$135),0,E$61:E$135))+sim_sup_tot_ocs_hop*E$38} -> 0 | F35: {=SUM(OFFSET(sim_sup_per_ocs_hop,begin_year-'OCS Oil SIM'!$B$10,0)*IF(ISERROR(F$61:F$135),0,F$61:F$135))+sim_sup_tot_ocs_hop*F$38} -> 0 | G35: {=SUM(OFFSET(sim_sup_per_ocs_hop,begin_year-'OCS Oil SIM'!$B$10,0)*IF(ISERROR(G$61:G$135),0,G$61:G$135))+sim_sup_tot_ocs_hop*G$38} -> 0 | H35: =SUM(D35:G35) -> 0 | K35: Total Imports | L35: =SUM(L36:L37) -> 40.39316 | M35: =SUM(M36:M37) -> 40.388674 | N35: =M35-L35 -> -0.0044856132 | O35: =IFERROR(N35/L35,0) -> -0.00011104883 | Q35: Wind Onshore | R35: =(L50-M50)*$AC$26 -> 0.2563123 | S35: =T35/$T$44 -> 0.0023425389 | T35: =R35/$S$10 -> 0.0023388133
C36: Chukchi Sea | D36: {=SUM(OFFSET(sim_sup_per_ocs_chu,begin_year-'OCS Oil SIM'!$B$10,0)*IF(ISERROR(D$61:D$135),0,D$61:D$135))+sim_sup_tot_ocs_chu*D$38} -> 0 | E36: {=SUM(OFFSET(sim_sup_per_ocs_chu,begin_year-'OCS Oil SIM'!$B$10,0)*IF(ISERROR(E$61:E$135),0,E$61:E$135))+sim_sup_tot_ocs_chu*E$38} -> 0 | F36: {=SUM(OFFSET(sim_sup_per_ocs_chu,begin_year-'OCS Oil SIM'!$B$10,0)*IF(ISERROR(F$61:F$135),0,F$61:F$135))+sim_sup_tot_ocs_chu*F$38} -> 0 | G36: {=SUM(OFFSET(sim_sup_per_ocs_chu,begin_year-'OCS Oil SIM'!$B$10,0)*IF(ISERROR(G$61:G$135),0,G$61:G$135))+sim_sup_tot_ocs_chu*G$38} -> 0 | H36: =SUM(D36:G36) -> 0 | K36: Imports Pipeline | L36: {=SUM(OFFSET(aeo_sup_gas_pip,begin_year-'OCS Oil SIM'!$B$10,0,length_year))} -> 39.364191 | M36: {=SUM(OFFSET(sim_sup_gas_pip,begin_year-'OCS Oil SIM'!$B$11,0,length_year))} -> 39.359803 | N36: =M36-L36 -> -0.0043879428 | O36: =IFERROR(N36/L36,0) -> -0.00011147042 | Q36: Wind Offshore | R36: =(L51-M51)*$AC$26 -> 0.00044955737 | S36: =T36/$T$44 -> 4.1086816e-06 | T36: =R36/$S$10 -> 4.1021471e-06
C37: Beaufort Sea | D37: {=SUM(OFFSET(sim_sup_per_ocs_bea,begin_year-'OCS Oil SIM'!$B$10,0)*IF(ISERROR(D$61:D$135),0,D$61:D$135))+sim_sup_tot_ocs_bea*D$38} -> 0 | E37: {=SUM(OFFSET(sim_sup_per_ocs_bea,begin_year-'OCS Oil SIM'!$B$10,0)*IF(ISERROR(E$61:E$135),0,E$61:E$135))+sim_sup_tot_ocs_bea*E$38} -> 0 | F37: {=SUM(OFFSET(sim_sup_per_ocs_bea,begin_year-'OCS Oil SIM'!$B$10,0)*IF(ISERROR(F$61:F$135),0,F$61:F$135))+sim_sup_tot_ocs_bea*F$38} -> 0 | G37: {=SUM(OFFSET(sim_sup_per_ocs_bea,begin_year-'OCS Oil SIM'!$B$10,0)*IF(ISERROR(G$61:G$135),0,G$61:G$135))+sim_sup_tot_ocs_bea*G$38} -> 0 | H37: =SUM(D37:G37) -> 0 | K37: Imports LNG | L37: {=SUM(OFFSET(aeo_sup_gas_lng,begin_year-'OCS Oil SIM'!$B$10,0,length_year))} -> 1.028969 | M37: {=SUM(OFFSET(sim_sup_gas_lng,begin_year-'OCS Oil SIM'!$B$11,0,length_year))} -> 1.0288713 | N37: =M37-L37 -> -9.7670403e-05 | O37: =IFERROR(N37/L37,0) -> -9.4920646e-05 | Q37: Other Electric | R37: =(L52-M52)*$AC$26 -> -0.004064456 | S37: =T37/$T$44 -> -3.7146662e-05 | T37: =R37/$S$10 -> -3.7087583e-05
B38: TOTAL BENEFITS ($ million) | D38: {=SUM(IFERROR(IF((OFFSET(sim_sup_oil_ocs,begin_year-'OCS Oil SIM'!$B$10,0)+OFFSET(sim_sup_gas_ocs,begin_year-'OCS Oil SIM'!$B$10,0))>0,0,1),0)*IF(ISERROR(D$61:D$135),0,D$61:D$135))} -> 0 | E38: {=SUM(IFERROR(IF((OFFSET(sim_sup_oil_ocs,begin_year-'OCS Oil SIM'!$B$10,0)+OFFSET(sim_sup_gas_ocs,begin_year-'OCS Oil SIM'!$B$10,0))>0,0,1),0)*IF(ISERROR(E$61:E$135),0,E$61:E$135))} -> 0 | F38: {=SUM(IFERROR(IF((OFFSET(sim_sup_oil_ocs,begin_year-'OCS Oil SIM'!$B$10,0)+OFFSET(sim_sup_gas_ocs,begin_year-'OCS Oil SIM'!$B$10,0))>0,0,1),0)*IF(ISERROR(F$61:F$135),0,F$61:F$135))} -> 0 | G38: {=SUM(IFERROR(IF((OFFSET(sim_sup_oil_ocs,begin_year-'OCS Oil SIM'!$B$10,0)+OFFSET(sim_sup_gas_ocs,begin_year-'OCS Oil SIM'!$B$10,0))>0,0,1),0)*IF(ISERROR(G$61:G$135),0,G$61:G$135))} -> 0 | K38: Alaska Total (reflected in categories above) | L38: =L30+L33 -> 6.903796 | M38: =M30+M33 -> 6.958495 | N38: =M38-L38 -> 0.054698971 | O38: =IFERROR(N38/L38,0) -> 0.0079230283 | Q38: Imports | R38: =(L53-M53)*$AC$26 -> 0.0042025902 | S38: =T38/$T$44 -> 3.8409125e-05 | T38: =R38/$S$10 -> 3.8348039e-05
D39: {=SUM(IF(ISERROR(D$61:D$135),0,D$61:D$135))} -> 216.13041 | E39: {=SUM(IF(ISERROR(E$61:E$135),0,E$61:E$135))} -> 13.103934 | F39: {=SUM(IF(ISERROR(F$61:F$135),0,F$61:F$135))} -> 5.5325192 | G39: {=SUM(IF(ISERROR(G$61:G$135),0,G$61:G$135))} -> 0.00068938048 | H39: =SUM(D39:G39) -> 234.76756 | K39: COAL (million short tons) | Q39: REDUCED DEMAND | R39: =SUM(R40:R43) -> 8.1373047 | S39: =T39/$T$44 -> 0.074370027 | T39: =R39/$S$10 -> 0.074251749
K40: U.S. Production | L40: {=SUM(OFFSET(aeo_sup_coa_dom,begin_year-'OCS Oil SIM'!$B$10,0,length_year))} -> 6383.5948 | M40: {=SUM(OFFSET(sim_sup_coa_dom,begin_year-'OCS Oil SIM'!$B$11,0,length_year))} -> 6383.5544 | N40: =M40-L40 -> -0.040417348 | O40: =N40/L40 -> -6.3314401e-06 | Q40: Oil | R40: =SUM(M61:M64)-SUM(L61:L64) -> 6.3189755 | S40: =T40/$T$44 -> 0.057751602 | T40: =R40/$S$10 -> 0.057659754
B41: OCS scenario total million barrels of oil equivalent | D41: {=SUM(OFFSET(sim_sup_oil_ocs,begin_year-'OCS Oil SIM'!$B$10,0,length_year))*365+SUM(OFFSET(sim_sup_gas_ocs,begin_year-'OCS Oil SIM'!$B$10,0,length_year))*gas_boe} -> 109.59075 | H41: {=SUM(OFFSET(sim_sup_oil_ocs,begin_year-'OCS Oil SIM'!$B$10,0,length_year))*365+SUM(OFFSET(sim_sup_gas_ocs,begin_year-'OCS Oil SIM'!$B$10,0,length_year))*gas_boe} -> 109.59075 | K41: Total Imports | L41: {=SUM(OFFSET(aeo_sup_coa_imp,begin_year-'OCS Oil SIM'!$B$10,0,length_year))} -> 30.874451 | M41: {=SUM(OFFSET(sim_sup_coa_imp,begin_year-'OCS Oil SIM'!$B$11,0,length_year))} -> 30.874409 | N41: =M41-L41 -> -4.210266e-05 | O41: =N41/L41 -> -1.3636732e-06 | Q41: Natural Gas | R41: =(SUM(M72:M75,M78)-SUM(L72:L75,L78))*gas_boe -> 2.8930987 | S41: =T41/$T$44 -> 0.026441167 | T41: =R41/$S$10 -> 0.026399115
K42: ELECTRICITY (billion kilowatt hours) | Q42: Coal | R42: =(SUM(M80,M82,M84)-SUM(L80,L82,L84))*$AC$18 -> -0.12094959 | S42: =T42/$T$44 -> -0.0011054059 | T42: =R42/$S$10 -> -0.0011036478
B43: Consumer Surplus Benefits per barrel of oil equivalent | K43: U.S. Production | L43: {=SUM(OFFSET(aeo_sup_ele_tot,begin_year-'OCS Oil SIM'!$B$10,0,length_year)-OFFSET(aeo_sup_ele_imp,begin_year-'OCS Oil SIM'!$B$10,0,length_year))} -> 80138.681 | M43: {=SUM(OFFSET(sim_sup_ele_tot,begin_year-'OCS Oil SIM'!$B$11,0,length_year)-OFFSET(sim_sup_ele_imp,begin_year-'OCS Oil SIM'!$B$11,0,length_year))} -> 80137.066 | N43: =M43-L43 -> -1.6154003 | O43: =IFERROR(N43/L43,0) -> -2.015756e-05 | Q43: Electricity | R43: =(M91-L91)*$AC$26 -> -0.95381998 | S43: =T43/$T$44 -> -0.0087173359 | T43: =R43/$S$10 -> -0.0087034719
D44: =D39/$D$41 -> 1.9721593 | E44: =E39/$D$41 -> 0.11957154 | F44: =F39/$D$41 -> 0.050483452 | G44: =G39/$D$41 -> 6.290499e-06 | H44: =H39/$D$41 -> 2.1422206 | K44: Oil | L44: {=SUM(OFFSET(aeo_sup_ele_oil,begin_year-'OCS Oil SIM'!$B$10,0,length_year))} -> 113.56377 | M44: {=SUM(OFFSET(sim_sup_ele_oil,begin_year-'OCS Oil SIM'!$B$11,0,length_year))} -> 113.56466 | N44: =M44-L44 -> 0.00088717394 | O44: =IFERROR(N44/L44,0) -> 7.8121212e-06 | Q44: Total Substitution | R44: =SUM(R39,R31,R28,R24,R21,R18,R15) -> 109.41645 | S44: =SUM(S39,S31,S28,S24,S21,S18,S15) -> 1 | T44: =R44/$S$10 -> 0.9984096
K45: Natural Gas | L45: {=SUM(OFFSET(aeo_sup_ele_gas,begin_year-'OCS Oil SIM'!$B$10,0,length_year))} -> 16286.179 | M45: {=SUM(OFFSET(sim_sup_ele_gas,begin_year-'OCS Oil SIM'!$B$11,0,length_year))} -> 16286.36 | N45: =M45-L45 -> 0.18077102 | O45: =IFERROR(N45/L45,0) -> 1.1099658e-05 | Q45: Note: Coal, gas, and oil-fired electricity generation are not included as sub-categories under electricity because electricity produced from these fuels is reflected in the results reported for these fuels themselves.
G46: Discounted | H46: 2 | K46: Coal | L46: {=SUM(OFFSET(aeo_sup_ele_coa,begin_year-'OCS Oil SIM'!$B$10,0,length_year))} -> 6762.1386 | M46: {=SUM(OFFSET(sim_sup_ele_coa,begin_year-'OCS Oil SIM'!$B$11,0,length_year))} -> 6762.1272 | N46: =M46-L46 -> -0.01132804 | O46: =IFERROR(N46/L46,0) -> -1.6752155e-06
G47: Net PS | H47: 2 | K47: Nuclear | L47: {=SUM(OFFSET(aeo_sup_ele_nuc,begin_year-'OCS Oil SIM'!$B$10,0,length_year))} -> 13534.912 | M47: {=SUM(OFFSET(sim_sup_ele_nuc,begin_year-'OCS Oil SIM'!$B$11,0,length_year))} -> 13534.868 | N47: =M47-L47 -> -0.044588389 | O47: =IFERROR(N47/L47,0) -> -3.2943241e-06
K48: Hydro | L48: {=SUM(OFFSET(aeo_sup_ele_hyd,begin_year-'OCS Oil SIM'!$B$10,0,length_year))} -> 5528.4596 | M48: {=SUM(OFFSET(sim_sup_ele_hyd,begin_year-'OCS Oil SIM'!$B$11,0,length_year))} -> 5528.4581 | N48: =M48-L48 -> -0.0014461951 | O48: =IFERROR(N48/L48,0) -> -2.6159097e-07
K49: Solar | L49: {=SUM(OFFSET(aeo_sup_ele_sol,begin_year-'OCS Oil SIM'!$B$10,0,length_year))} -> 17739.291 | M49: {=SUM(OFFSET(sim_sup_ele_sol,begin_year-'OCS Oil SIM'!$B$11,0,length_year))} -> 17737.981 | N49: =M49-L49 -> -1.3101399 | O49: =IFERROR(N49/L49,0) -> -7.3855255e-05
K50: Wind Onshore | L50: {=SUM(OFFSET(aeo_sup_ele_won,begin_year-'OCS Oil SIM'!$B$10,0,length_year))} -> 19075.106 | M50: {=SUM(OFFSET(sim_sup_ele_won,begin_year-'OCS Oil SIM'!$B$11,0,length_year))} -> 19074.67 | N50: =M50-L50 -> -0.43570086 | O50: =IFERROR(N50/L50,0) -> -2.2841334e-05
K51: Wind Offshore | L51: {=SUM(OFFSET(aeo_sup_ele_wof,begin_year-'OCS Oil SIM'!$B$10,0,length_year))} -> 1091.4888 | M51: {=SUM(OFFSET(sim_sup_ele_wof,begin_year-'OCS Oil SIM'!$B$11,0,length_year))} -> 1091.488 | N51: =M51-L51 -> -0.00076419482 | O51: =IFERROR(N51/L51,0) -> -7.0013988e-07
K52: Other Electric | L52: {=SUM(OFFSET(aeo_sup_ele_oth,begin_year-'OCS Oil SIM'!$B$10,0,length_year))} -> 7.542223 | M52: {=SUM(OFFSET(sim_sup_ele_oth,begin_year-'OCS Oil SIM'!$B$11,0,length_year))} -> 7.5491321 | N52: =M52-L52 -> 0.0069090987 | O52: =IFERROR(N52/L52,0) -> 0.00091605601
D53: =H46 -> 2 | K53: Net Imports | L53: {=SUM(OFFSET(aeo_sup_ele_imp,begin_year-'OCS Oil SIM'!$B$10,0,length_year))} -> 827.38954 | M53: {=SUM(OFFSET(sim_sup_ele_imp,begin_year-'OCS Oil SIM'!$B$11,0,length_year))} -> 827.3824 | N53: =M53-L53 -> -0.0071439107 | O53: =IFERROR(N53/L53,0) -> -8.6342772e-06
D54: =H47 -> 2
L56: =L68/365 -> 62.373267 | M56: =M68/365 -> 62.375126
B57: Consumer Surplus Change from OCS Production by Year and Fuel | K57: Consumption Effects
D58: Oil | E58: Gas | F58: Electricity | G58: Coal | H58: TOTAL | L58: Baseline | M58: Simulation | N58: Change In Sector | O58: % Change In Sector
C59: Year
D60: $ million | E60: $ million | F60: $ million | G60: $ million | H60: $ million | K60: OIL (million barrels)
C61: {=OFFSET(year_oil,begin_year-'OCS Oil SIM'!$B$10,0,length_year)} -> 2026 | D61: {=IF($H$46=1,IF($H$47=1,inflation_multiplier*OFFSET(dcs_oil,begin_year-'OCS Oil SIM'!$B$10,0,length_year)*10^-6,inflation_multiplier*OFFSET(nps_oil,begin_year-'OCS Oil SIM'!$B$10,0,length_year)*10^-6),IF($H$47=1,inflation_multiplier*(OFFSET(dcs_oil,begin_year-'OCS Oil SIM'!$B$10,0,length_year)*10^-6)/(1+discount_rate)^(OFFSET(year_gas,begin_year-'OCS Oil SIM'!$B$10,0,length_year)-npv_base_year),inflation_multiplier*(OFFSET(nps_oil,begin_year-'OCS Oil SIM'!$B$10,0,length_year)*10^-6)/(1+discount_rate)^(OFFSET(year_gas,begin_year-'OCS Oil SIM'!$B$10,0,length_year)-npv_base_year)))} -> 0 | E61: {=IF($H$46=1,IF($H$47=1,inflation_multiplier*OFFSET(dcs_gas,begin_year-'OCS Oil SIM'!$B$10,0,length_year)*10^-6,inflation_multiplier*OFFSET(nps_gas,begin_year-'OCS Oil SIM'!$B$10,0,length_year)*10^-6),IF($H$47=1,inflation_multiplier*(OFFSET(dcs_gas,begin_year-'OCS Oil SIM'!$B$10,0,length_year)*10^-6)/(1+discount_rate)^(OFFSET(year_gas,begin_year-'OCS Oil SIM'!$B$10,0,length_year)-npv_base_year),inflation_multiplier*(OFFSET(nps_gas,begin_year-'OCS Oil SIM'!$B$10,0,length_year)*10^-6)/(1+discount_rate)^(OFFSET(year_gas,begin_year-'OCS Oil SIM'!$B$10,0,length_year)-npv_base_year)))} -> 0 | F61: {=IF($H$46=1,IF($H$47=1,inflation_multiplier*OFFSET(dcs_ele,begin_year-'OCS Oil SIM'!$B$10,0,length_year)*10^-6,inflation_multiplier*OFFSET(nps_ele,begin_year-'OCS Oil SIM'!$B$10,0,length_year)*10^-6),IF($H$47=1,inflation_multiplier*(OFFSET(dcs_ele,begin_year-'OCS Oil SIM'!$B$10,0,length_year)*10^-6)/(1+discount_rate)^(OFFSET(year_gas,begin_year-'OCS Oil SIM'!$B$10,0,length_year)-npv_base_year),inflation_multiplier*(OFFSET(nps_ele,begin_year-'OCS Oil SIM'!$B$10,0,length_year)*10^-6)/(1+discount_rate)^(OFFSET(year_gas,begin_year-'OCS Oil SIM'!$B$10,0,length_year)-npv_base_year)))} -> 0 | G61: {=IF($H$46=1,IF($H$47=1,inflation_multiplier*OFFSET(dcs_coa,begin_year-'OCS Oil SIM'!$B$10,0,length_year)*10^-6,inflation_multiplier*OFFSET(nps_coa,begin_year-'OCS Oil SIM'!$B$10,0,length_year)*10^-6),IF($H$47=1,inflation_multiplier*(OFFSET(dcs_coa,begin_year-'OCS Oil SIM'!$B$10,0,length_year)*10^-6)/(1+discount_rate)^(OFFSET(year_gas,begin_year-'OCS Oil SIM'!$B$10,0,length_year)-npv_base_year),inflation_multiplier*(OFFSET(nps_coa,begin_year-'OCS Oil SIM'!$B$10,0,length_year)*10^-6)/(1+discount_rate)^(OFFSET(year_gas,begin_year-'OCS Oil SIM'!$B$10,0,length_year)-npv_base_year)))} -> 0 | H61: =SUM(D61:G61) -> 0 | K61: Residential | L61: {=SUM(OFFSET(aeo_dem_oil_res,begin_year-'OCS Oil SIM'!$B$10,0,length_year))*365} -> 2968.2592 | M61: {=SUM(OFFSET(sim_dem_oil_res,begin_year-'OCS Oil SIM'!$B$11,0,length_year))*365} -> 2968.5379 | N61: =M61-L61 -> 0.27870362 | O61: =N61/L61 -> 9.3894635e-05
C62: 2027 | D62: 0 | E62: 0 | F62: 0 | G62: 0 | H62: =SUM(D62:G62) -> 0 | K62: Commercial | L62: {=SUM(OFFSET(aeo_dem_oil_com,begin_year-'OCS Oil SIM'!$B$10,0,length_year))*365} -> 3574.6059 | M62: {=SUM(OFFSET(sim_dem_oil_com,begin_year-'OCS Oil SIM'!$B$11,0,length_year))*365} -> 3574.8867 | N62: =M62-L62 -> 0.2807147 | O62: =N62/L62 -> 7.8530251e-05
C63: 2028 | D63: 0 | E63: 0 | F63: 0 | G63: 0 | H63: =SUM(D63:G63) -> 0 | K63: Industrial | L63: {=SUM(OFFSET(aeo_dem_oil_ind,begin_year-'OCS Oil SIM'!$B$10,0,length_year))*365} -> 42863.648 | M63: {=SUM(OFFSET(sim_dem_oil_ind,begin_year-'OCS Oil SIM'!$B$11,0,length_year))*365} -> 42864.656 | N63: =M63-L63 -> 1.0079988 | O63: =N63/L63 -> 2.3516403e-05
C64: 2029 | D64: 0 | E64: 0 | F64: 0 | G64: 0 | H64: =SUM(D64:G64) -> 0 | K64: Transport | L64: {=SUM(OFFSET(aeo_dem_oil_tra,begin_year-'OCS Oil SIM'!$B$10,0,length_year))*365} -> 85499.505 | M64: {=SUM(OFFSET(sim_dem_oil_tra,begin_year-'OCS Oil SIM'!$B$11,0,length_year))*365} -> 85504.256 | N64: =M64-L64 -> 4.7515584 | O64: =N64/L64 -> 5.5574105e-05
C65: 2030 | D65: 27.162197 | E65: 1.1046072 | F65: 0.71195265 | G65: 1.510501e-06 | H65: =SUM(D65:G65) -> 28.978758 | K65: Electric | L65: {=SUM(OFFSET(aeo_dem_oil_ele,begin_year-'OCS Oil SIM'!$B$10,0,length_year))*365} -> 211.80986 | M65: {=SUM(OFFSET(sim_dem_oil_ele,begin_year-'OCS Oil SIM'!$B$11,0,length_year))*365} -> 211.81152 | N65: =M65-L65 -> 0.0016598876 | O65: =N65/L65 -> 7.836687e-06
C66: 2031 | D66: 3.8055662 | E66: 0.27432373 | F66: 0.095192476 | G66: -1.3482846e-05 | H66: =SUM(D66:G66) -> 4.1750689 | K66: Total U.S. Demand | L66: =SUM(L61:L65) -> 135117.83 | M66: =SUM(M61:M65) -> 135124.15 | N66: =M66-L66 -> 6.3206354 | O66: =N66/L66 -> 4.6778694e-05
C67: 2032 | D67: 68.112275 | E67: 2.5615922 | F67: 1.8555159 | G67: 0.00021866487 | H67: =SUM(D67:G67) -> 72.529602 | K67: Rest of World Demand | L67: =SUM(L68:L70) -> 608617.87 | M67: =SUM(M68:M70) -> 608636.6 | N67: =M67-L67 -> 18.733384 | O67: =N67/L67 -> 3.0780206e-05
C68: 2033 | D68: 11.331216 | E68: 0.89200421 | F68: 0.21955348 | G68: 4.1101241e-05 | H68: =SUM(D68:G68) -> 12.442815 | K68: U.S. Crude Oil | L68: =SUM(OFFSET(aeo_dem_oil_row_crude,begin_year-'OCS Oil SIM'!$B$10,0,length_year))*365 -> 22766.242 | M68: =SUM(OFFSET(sim_dem_oil_row_crude,begin_year-'OCS Oil SIM'!$B$11,0,length_year))*365 -> 22766.921 | N68: =M68-L68 -> 0.67855402 | O68: =N68/L68 -> 2.9805271e-05
C69: 2034 | D69: 10.172929 | E69: 0.88494757 | F69: 0.2425165 | G69: 4.4144197e-05 | H69: =SUM(D69:G69) -> 11.300437 | K69: U.S. Refined Petroleum Products | L69: =SUM(OFFSET(aeo_dem_oil_row_ref,begin_year-'OCS Oil SIM'!$B$10,0,length_year))*365 -> 56702.303 | M69: =SUM(OFFSET(sim_dem_oil_row_ref,begin_year-'OCS Oil SIM'!$B$11,0,length_year))*365 -> 56704.16 | N69: =M69-L69 -> 1.8576055 | O69: =N69/L69 -> 3.2760671e-05
C70: 2035 | D70: 9.9108906 | E70: 0.84856124 | F70: 0.27091131 | G70: 3.0418564e-05 | H70: =SUM(D70:G70) -> 11.030394 | K70: Non-U.S. sources | L70: =SUM(OFFSET(aeo_dem_oil_row_non_us,begin_year-'OCS Oil SIM'!$B$10,0,length_year))*365 -> 529149.32 | M70: =SUM(OFFSET(sim_dem_oil_row_non_us,begin_year-'OCS Oil SIM'!$B$11,0,length_year))*365 -> 529165.52 | N70: =M70-L70 -> 16.197224 | O70: =N70/L70 -> 3.0609931e-05
C71: 2036 | D71: 9.0788847 | E71: 0.79058681 | F71: 0.28246262 | G71: 2.4827215e-05 | H71: =SUM(D71:G71) -> 10.151959 | K71: GAS (trillion cubic feet)
C72: 2037 | D72: 8.6733749 | E72: 0.75065664 | F72: 0.25359059 | G72: 6.1464235e-05 | H72: =SUM(D72:G72) -> 9.6776836 | K72: Residential | L72: {=SUM(OFFSET(aeo_dem_gas_res,begin_year-'OCS Gas SIM'!$B$10,0,length_year))} -> 90.611159 | M72: {=SUM(OFFSET(sim_dem_gas_res,begin_year-'OCS Gas SIM'!$B$11,0,length_year))} -> 90.610551 | N72: =M72-L72 -> -0.0006075141 | O72: =N72/L72 -> -6.7046278e-06
C73: 2038 | D73: 9.1808647 | E73: 0.76061849 | F73: 0.27020466 | G73: 1.5480733e-05 | H73: =SUM(D73:G73) -> 10.211703 | K73: Commercial | L73: {=SUM(OFFSET(aeo_dem_gas_com,begin_year-'OCS Gas SIM'!$B$10,0,length_year))} -> 66.570249 | M73: {=SUM(OFFSET(sim_dem_gas_com,begin_year-'OCS Gas SIM'!$B$11,0,length_year))} -> 66.569915 | N73: =M73-L73 -> -0.00033405362 | O73: =N73/L73 -> -5.0180618e-06
C74: 2039 | D74: 8.6957315 | E74: 0.71264033 | F74: 0.23754566 | G74: 6.0413186e-05 | H74: =SUM(D74:G74) -> 9.6459779 | K74: Industrial | L74: {=SUM(OFFSET(aeo_dem_gas_ind,begin_year-'OCS Gas SIM'!$B$10,0,length_year))} -> 209.4698 | M74: {=SUM(OFFSET(sim_dem_gas_ind,begin_year-'OCS Gas SIM'!$B$11,0,length_year))} -> 209.4687 | N74: =M74-L74 -> -0.001104855 | O74: =N74/L74 -> -5.274531e-06
C75: 2040 | D75: 9.4548861 | E75: 0.72404449 | F75: 0.24881206 | G75: 4.2218375e-05 | H75: =SUM(D75:G75) -> 10.427785 | K75: Transport | L75: {=SUM(OFFSET(aeo_dem_gas_tra,begin_year-'OCS Gas SIM'!$B$10,0,length_year))} -> 27.865111 | M75: {=SUM(OFFSET(sim_dem_gas_tra,begin_year-'OCS Gas SIM'!$B$11,0,length_year))} -> 27.867548 | N75: =M75-L75 -> 0.0024374124 | O75: =N75/L75 -> 8.7471834e-05
C76: 2041 | D76: 9.2493318 | E76: 0.73667717 | F76: 0.22069245 | G76: 4.8213665e-05 | H76: =SUM(D76:G76) -> 10.20675 | K76: Electric | L76: {=SUM(OFFSET(aeo_dem_gas_ele,begin_year-'OCS Gas SIM'!$B$10,0,length_year))} -> 143.41004 | M76: {=SUM(OFFSET(sim_dem_gas_ele,begin_year-'OCS Gas SIM'!$B$11,0,length_year))} -> 143.41165 | N76: =M76-L76 -> 0.0016061951 | O76: =N76/L76 -> 1.1200018e-05
C77: 2042 | D77: 10.219443 | E77: 0.70512205 | F77: 0.21744939 | G77: 3.7904145e-05 | H77: =SUM(D77:G77) -> 11.142052 | K77: Total U.S. Demand | L77: =SUM(L72:L76) -> 537.92636 | M77: =SUM(M72:M76) -> 537.92836 | N77: =M77-L77 -> 0.0019971848 | O77: =N77/L77 -> 3.7127475e-06
C78: 2043 | D78: 10.409588 | E78: 0.68148975 | F78: 0.21336678 | G78: 4.2673392e-05 | H78: =SUM(D78:G78) -> 11.304488 | K78: Exports | L78: {=SUM(OFFSET(aeo_dem_gas_exp,begin_year-'OCS Gas SIM'!$B$10,0,length_year))} -> 238.15215 | M78: {=SUM(OFFSET(sim_dem_gas_exp,begin_year-'OCS Gas SIM'!$B$11,0,length_year))} -> 238.16802 | N78: =M78-L78 -> 0.015868225 | O78: =N78/L78 -> 6.6630619e-05
C79: 2044 | D79: 10.673235 | E79: 0.6760625 | F79: 0.1927527 | G79: 3.3829012e-05 | H79: =SUM(D79:G79) -> 11.542084 | K79: COAL (million short tons)
C80: #N/A | D80: #N/A | E80: #N/A | F80: #N/A | G80: #N/A | H80: =SUM(D80:G80) -> #N/A | K80: Industrial | L80: {=SUM(OFFSET(aeo_dem_coa_ind,begin_year-'OCS Oil SIM'!$B$10,0,length_year))} -> 658.72662 | M80: {=SUM(OFFSET(sim_dem_coa_ind,begin_year-'OCS Oil SIM'!$B$11,0,length_year))} -> 658.69066 | N80: =M80-L80 -> -0.035959976 | O80: =N80/L80 -> -5.4590136e-05
C81: #N/A | D81: #N/A | E81: #N/A | F81: #N/A | G81: #N/A | H81: =SUM(D81:G81) -> #N/A | K81: Electric | L81: {=SUM(OFFSET(aeo_dem_coa_ele,begin_year-'OCS Oil SIM'!$B$10,0,length_year))} -> 3644.2663 | M81: {=SUM(OFFSET(sim_dem_coa_ele,begin_year-'OCS Oil SIM'!$B$11,0,length_year))} -> 3644.2602 | N81: =M81-L81 -> -0.0061205204 | O81: =N81/L81 -> -1.6794932e-06
C82: #N/A | D82: #N/A | E82: #N/A | F82: #N/A | G82: #N/A | H82: =SUM(D82:G82) -> #N/A | K82: Other | L82: {=SUM(OFFSET(aeo_dem_coa_oth,begin_year-'OCS Oil SIM'!$B$10,0,length_year))} -> -53.380129 | M82: {=SUM(OFFSET(sim_dem_coa_oth,begin_year-'OCS Oil SIM'!$B$11,0,length_year))} -> -53.38041 | N82: =M82-L82 -> -0.00028125887 | O82: =N82/L82 -> 5.2689806e-06
C83: #N/A | D83: #N/A | E83: #N/A | F83: #N/A | G83: #N/A | H83: =SUM(D83:G83) -> #N/A | K83: Total U.S. Demand | L83: =SUM(L80:L82) -> 4249.6128 | M83: =SUM(M80:M82) -> 4249.5704 | N83: =M83-L83 -> -0.042361755 | O83: =N83/L83 -> -9.96838e-06
C84: #N/A | D84: #N/A | E84: #N/A | F84: #N/A | G84: #N/A | H84: =SUM(D84:G84) -> #N/A | K84: Exports | L84: {=SUM(OFFSET(aeo_dem_coa_exp,begin_year-'OCS Oil SIM'!$B$10,0,length_year))} -> 2164.8565 | M84: {=SUM(OFFSET(sim_dem_coa_exp,begin_year-'OCS Oil SIM'!$B$11,0,length_year))} -> 2164.8583 | N84: =M84-L84 -> 0.001832444 | O84: =N84/L84 -> 8.4645055e-07
C85: #N/A | D85: #N/A | E85: #N/A | F85: #N/A | G85: #N/A | H85: =SUM(D85:G85) -> #N/A | K85: ELECTRICITY (billion kilowatt hours)
C86: #N/A | D86: #N/A | E86: #N/A | F86: #N/A | G86: #N/A | H86: =SUM(D86:G86) -> #N/A | K86: Residential | L86: {=SUM(OFFSET(aeo_dem_ele_res,begin_year-'OCS Gas SIM'!$B$10,0,length_year))} -> 28936.493 | M86: {=SUM(OFFSET(sim_dem_ele_res,begin_year-'OCS Gas SIM'!$B$11,0,length_year))} -> 28935.304 | N86: =M86-L86 -> -1.1885554 | O86: =N86/L86 -> -4.1074619e-05
C87: #N/A | D87: #N/A | E87: #N/A | F87: #N/A | G87: #N/A | H87: =SUM(D87:G87) -> #N/A | K87: Commercial | L87: {=SUM(OFFSET(aeo_dem_ele_com,begin_year-'OCS Gas SIM'!$B$10,0,length_year))} -> 24846.117 | M87: {=SUM(OFFSET(sim_dem_ele_com,begin_year-'OCS Gas SIM'!$B$11,0,length_year))} -> 24845.669 | N87: =M87-L87 -> -0.44749777 | O87: =N87/L87 -> -1.8010773e-05
C88: #N/A | D88: #N/A | E88: #N/A | F88: #N/A | G88: #N/A | H88: =SUM(D88:G88) -> #N/A | K88: Industrial | L88: {=SUM(OFFSET(aeo_dem_ele_ind,begin_year-'OCS Gas SIM'!$B$10,0,length_year))} -> 19439.962 | M88: {=SUM(OFFSET(sim_dem_ele_ind,begin_year-'OCS Gas SIM'!$B$11,0,length_year))} -> 19439.795 | N88: =M88-L88 -> -0.16738376 | O88: =N88/L88 -> -8.6102924e-06
C89: #N/A | D89: #N/A | E89: #N/A | F89: #N/A | G89: #N/A | H89: =SUM(D89:G89) -> #N/A | K89: Transport | L89: {=SUM(OFFSET(aeo_dem_ele_tra,begin_year-'OCS Gas SIM'!$B$10,0,length_year))} -> 2088.7288 | M89: {=SUM(OFFSET(sim_dem_ele_tra,begin_year-'OCS Gas SIM'!$B$11,0,length_year))} -> 2088.863 | N89: =M89-L89 -> 0.13418144 | O89: =N89/L89 -> 6.424072e-05
C90: #N/A | D90: #N/A | E90: #N/A | F90: #N/A | G90: #N/A | H90: =SUM(D90:G90) -> #N/A | K90: Other | L90: {=SUM(OFFSET(aeo_dem_ele_oth,begin_year-'OCS Oil SIM'!$B$10,0,length_year))} -> 5654.7701 | M90: {=SUM(OFFSET(sim_dem_ele_oth,begin_year-'OCS Oil SIM'!$B$11,0,length_year))} -> 5654.818 | N90: =M90-L90 -> 0.047873353 | O90: =N90/L90 -> 8.4660123e-06
C91: #N/A | D91: #N/A | E91: #N/A | F91: #N/A | G91: #N/A | H91: =SUM(D91:G91) -> #N/A | K91: Total U.S. Demand | L91: =SUM(L86:L90) -> 80966.071 | M91: =SUM(M86:M90) -> 80964.449 | N91: =M91-L91 -> -1.6213822 | O91: =N91/L91 -> -2.0025452e-05
C92: #N/A | D92: #N/A | E92: #N/A | F92: #N/A | G92: #N/A | H92: =SUM(D92:G92) -> #N/A
C93: #N/A | D93: #N/A | E93: #N/A | F93: #N/A | G93: #N/A | H93: =SUM(D93:G93) -> #N/A
C94: #N/A | D94: #N/A | E94: #N/A | F94: #N/A | G94: #N/A | H94: =SUM(D94:G94) -> #N/A
C95: #N/A | D95: #N/A | E95: #N/A | F95: #N/A | G95: #N/A | H95: =SUM(D95:G95) -> #N/A
C96: #N/A | D96: #N/A | E96: #N/A | F96: #N/A | G96: #N/A | H96: =SUM(D96:G96) -> #N/A
C97: #N/A | D97: #N/A | E97: #N/A | F97: #N/A | G97: #N/A | H97: =SUM(D97:G97) -> #N/A
C98: #N/A | D98: #N/A | E98: #N/A | F98: #N/A | G98: #N/A | H98: =SUM(D98:G98) -> #N/A
C99: #N/A | D99: #N/A | E99: #N/A | F99: #N/A | G99: #N/A | H99: =SUM(D99:G99) -> #N/A
C100: #N/A | D100: #N/A | E100: #N/A | F100: #N/A | G100: #N/A | H100: =SUM(D100:G100) -> #N/A
C101: #N/A | D101: #N/A | E101: #N/A | F101: #N/A | G101: #N/A | H101: =SUM(D101:G101) -> #N/A
C102: #N/A | D102: #N/A | E102: #N/A | F102: #N/A | G102: #N/A | H102: =SUM(D102:G102) -> #N/A
C103: #N/A | D103: #N/A | E103: #N/A | F103: #N/A | G103: #N/A | H103: =SUM(D103:G103) -> #N/A
...

Sheet Inflation
B1: Return to Table of Contents
B6: INFLATION INDICES
B7: Series | C7: GDP Chain-type Price Index | D7: CPI All-urban | E7: CPI Energy Commodities and Services | F7: User defined
B8: 2000 | C8: 0.780685 | D8: 2.180762 | E8: 2.116822
B9: 2001 | C9: 0.798215 | D9: 2.24923 | E9: 2.437438
B10: 2002 | C10: 0.810387 | D10: 2.295861 | E10: 2.459985
B11: 2003 | C11: 0.82567 | D11: 2.329518 | E11: 2.443281
B12: 2004 | C12: 0.847782 | D12: 2.36715 | E12: 2.433069
B13: 2005 | C13: 0.87407 | D13: 2.370018 | E13: 2.026325
B14: 2006 | C14: 0.90074 | D14: 2.400054 | E14: 1.895002
B15: 2007 | C15: 0.924977 | D15: 2.45121 | E15: 2.046964
B16: 2008 | C16: 0.942635 | D16: 2.510989 | E16: 2.198792 | H16: =INDEX(indices,MATCH(inflator_year,Inflation!$B$8:$B$48,0),MATCH(inflation_index,Inflation!$C$7:$F$7,0))/INDEX(indices,MATCH(dollars_year,Inflation!$B$8:$B$48,0),MATCH(inflation_index,Inflation!$C$7:$F$7,0)) -> 1.2583816
B17: 2009 | C17: 0.94999 | D17: 2.556465 | E17: 2.152251
B18: 2010 | C18: 0.96164 | D18: 2.588382 | E18: 1.972384
B19: 2011 | C19: 0.98157 | D19: 2.709654 | E19: 2.382787
B20: 2012 | C20: 1 | D20: 2.928036 | E20: 3.001973
B21: 2013 | C21: 1.017685 | D21: 3.055286 | E21: 3.011671
B22: 2014 | C22: 1.036622 | D22: 3.138497 | E22: 3.029936
B23: 2015 | C23: 1.046612 | D23: 3.201509 | E23: 2.939096
B24: 2016 | C24: 1.05703 | D24: 3.265631 | E24: 2.936678
B25: 2017 | C25: 1.077417 | D25: 3.331863 | E25: 2.951837
B26: 2018 | C26: 1.103262 | D26: 3.399124 | E26: 2.980038
B27: 2019 | C27: 1.122785 | D27: 3.467353 | E27: 3.017051
B28: 2020 | C28: 1.1374 | D28: 3.539269 | E28: 3.0807
... B48: 2040 | C48: 1.924443 | D48: 5.515447 | E48: 5.0995
B49: = 1.000 | C49: 1.967735 | D49: 1982-84 | E49: 1982-84
B50: Scenario | C50: 2.012073 | D50: AEO 2020-Special NEMS run | E50: AEO 2020-Special NEMS run
B51: Datekey | C51: 2.057696 | D51: BOEM_REF.0714b | E51: BOEM_REF.0714b
B52: Release | C52: 2.104642 | D52: June 2020 | E52: June 2020
B53: Table | C53: 2.152927 | D53: Summary Table 18 - 18. Macroeconomic Indicators | E53: Summary Table 18 - 18. Macroeconomic Indicators
B54: Line | C54: 2.202949 | D54: 2546 | E54: 2547
B55: Row Info. | C55: 2.255066 | D55: Consumer Price Index - All-urban | E55: Consumer Price Index - Energy Commodities and Services
C56: 2.30909
C57: 2.364755
C58: 2.422203

Sheet Oil supply projection
A1: Return to Table of Contents
B6: AEO BASELINE OIL SUPPLY PROJECTION
C8: Lower 48 Onshore (tight) | D8: Lower 48 Onshore (conventional) | E8: Lower 48 Offshore | F8: Alaska Onshore | G8: Alaska Offshore | H8: Biofuels | I8: Other | J8: Rest of World | K8: Total Supply | L8: Pipeline Share of Imports | N8: Alaska Total | P8: Other (No adjustment) | Q8: Total Supply (No adjustment) | R8: Adjustment | T8: Forecast Supply
B9: Year | C9: 106 barrels per day | D9: 106 barrels per day | E9: 106 barrels per day | F9: 106 barrels per day | G9: 106 barrels per day | H9: 106 barrels per day | I9: 106 barrels per day | J9: 106 barrels per day | K9: 106 barrels per day | L9: 106 barrels per day | N9: 106 barrels per day | P9: 106 barrels per day | Q9: 106 barrels per day | R9: 106 barrels per day | T9: %
B10: =baseline_start_year -> 2019 | C10: 7.936 | D10: 1.889 | E10: 1.954 | F10: 0.379793 | G10: 0.085207 | H10: 1.116819 | I10: =P10+ R10 -> 5.584398 | J10: 82.039636 | K10: {=aeo_sup_oil_l48_t+aeo_sup_oil_l48+aeo_sup_oil_off+aeo_sup_oil_ala_on+aeo_sup_oil_ala_off+aeo_sup_oil_bio+aeo_sup_oil_oth+aeo_sup_oil_row} -> 100.98485 | L10: 2.8804875 | N10: =SUM(F10,G10) -> 0.465 | P10: 6.557122 | Q10: =aeo_sup_oil_l48_t+aeo_sup_oil_l48+aeo_sup_oil_off+aeo_sup_oil_ala_on+aeo_sup_oil_ala_off+aeo_sup_oil_bio+aeo_sup_oil_row+P10 -> 101.95758 | R10: =IF(B10<=baseline_aeo_end_year,'Oil demand projection'!K10-Q10,"") -> -0.972724 | T10: 0.0071552974
B11: =B10+1 -> 2020 | C11: 7.469 | D11: 1.632 | E11: 1.695 | F11: 0.361657 | G11: 0.086343 | H11: 1.003683 | I11: =P11+ R11 -> 6.013676 | J11: 81.75325 | K11: 100.01461 | L11: 2.7524577 | N11: =SUM(F11,G11) -> 0.448 | P11: 6.973526 | Q11: =aeo_sup_oil_l48_t+aeo_sup_oil_l48+aeo_sup_oil_off+aeo_sup_oil_ala_on+aeo_sup_oil_ala_off+aeo_sup_oil_bio+aeo_sup_oil_row+P11 -> 100.97446 | R11: =IF(B11<=baseline_aeo_end_year,'Oil demand projection'!K11-Q11,"") -> -0.95985 | T11: =(INDEX(aeo_sup_oil_tot,MATCH(baseline_aeo_end_year,B10:B84,0),1)/INDEX(aeo_sup_oil_tot,MATCH(baseline_aeo_end_year-10,B10:B84,0),1))^(1/10)-1 -> 0.00014957369
B12: =B11+1 -> 2021 | C12: 7.308 | D12: 1.65 | E12: 1.753 | F12: 0.353779 | G12: 0.083221 | H12: 1.067889 | I12: =P12+ R12 -> 8.397823 | J12: 82.460802 | K12: 103.07451 | L12: 3.1700675 | N12: =SUM(F12,G12) -> 0.437 | P12: 6.953009 | Q12: =aeo_sup_oil_l48_t+aeo_sup_oil_l48+aeo_sup_oil_off+aeo_sup_oil_ala_on+aeo_sup_oil_ala_off+aeo_sup_oil_bio+aeo_sup_oil_row+P12 -> 101.6297 | R12: =IF(B12<=baseline_aeo_end_year,'Oil demand projection'!K12-Q12,"") -> 1.444814
B13: =B12+1 -> 2022 | C13: 8.005 | D13: 1.583554 | E13: 1.803407 | F13: 0.362024 | G13: 0.074428 | H13: 1.089317 | I13: =P13+ R13 -> 7.513996 | J13: 79.64 | K13: 100.07173 | L13: 3.4017636 | N13: =SUM(F13,G13) -> 0.436452 | P13: 7.513996 | Q13: =aeo_sup_oil_l48_t+aeo_sup_oil_l48+aeo_sup_oil_off+aeo_sup_oil_ala_on+aeo_sup_oil_ala_off+aeo_sup_oil_bio+aeo_sup_oil_row+P13 -> 100.07173 | R13: =IF(B13<=baseline_aeo_end_year,'Oil demand projection'!K13-Q13,"") -> -1.4210855e-14
B14: =B13+1 -> 2023 | C14: 8.669035 | D14: 1.390027 | E14: 1.855688 | F14: 0.336099 | G14: 0.06969 | H14: 1.058557 | I14: =P14+ R14 -> 7.578831 | J14: 80.11 | K14: 101.06793 | L14: 3.6603931 | N14: =SUM(F14,G14) -> 0.405789 | P14: 7.578831 | Q14: =aeo_sup_oil_l48_t+aeo_sup_oil_l48+aeo_sup_oil_off+aeo_sup_oil_ala_on+aeo_sup_oil_ala_off+aeo_sup_oil_bio+aeo_sup_oil_row+P14 -> 101.06793 | R14: =IF(B14<=baseline_aeo_end_year,'Oil demand projection'!K14-Q14,"") -> 0
B15: =B14+1 -> 2024 | C15: 9.057658 | D15: 1.298054 | E15: 1.927653 | F15: 0.311161 | G15: 0.07084 | H15: 1.134723 | I15: =P15+ R15 -> 7.635142 | J15: 81.06 | K15: 102.49523 | L15: 3.828191 | N15: =SUM(F15,G15) -> 0.382001 | P15: 7.635142 | Q15: =aeo_sup_oil_l48_t+aeo_sup_oil_l48+aeo_sup_oil_off+aeo_sup_oil_ala_on+aeo_sup_oil_ala_off+aeo_sup_oil_bio+aeo_sup_oil_row+P15 -> 102.49523 | R15: =IF(B15<=baseline_aeo_end_year,'Oil demand projection'!K15-Q15,"") -> 0
B16: =B15+1 -> 2025 | C16: 9.084526 | D16: 1.31292 | E16: 1.972143 | F16: 0.377749 | G16: 0.076492 | H16: 1.122123 | I16: =P16+ R16 -> 7.700105 | J16: 81.841848 | K16: 103.48791 | L16: 3.7744069 | N16: =SUM(F16,G16) -> 0.454241 | P16: 7.700105 | Q16: =aeo_sup_oil_l48_t+aeo_sup_oil_l48+aeo_sup_oil_off+aeo_sup_oil_ala_on+aeo_sup_oil_ala_off+aeo_sup_oil_bio+aeo_sup_oil_row+P16 -> 103.48791 | R16: =IF(B16<=baseline_aeo_end_year,'Oil demand projection'!K16-Q16,"") -> 0
B17: =B16+1 -> 2026 | C17: 9.141235 | D17: 1.335239 | E17: 1.996534 | F17: 0.396468 | G17: 0.080133 | H17: 1.117145 | I17: =P17+ R17 -> 7.732854 | J17: 82.623696 | K17: 104.4233 | L17: 3.7343871 | N17: =SUM(F17,G17) -> 0.476601 | P17: 7.732854 | Q17: =aeo_sup_oil_l48_t+aeo_sup_oil_l48+aeo_sup_oil_off+aeo_sup_oil_ala_on+aeo_sup_oil_ala_off+aeo_sup_oil_bio+aeo_sup_oil_row+P17 -> 104.4233 | R17: =IF(B17<=baseline_aeo_end_year,'Oil demand projection'!K17-Q17,"") -> -1.4210855e-14
B18: =B17+1 -> 2027 | C18: 9.115246 | D18: 1.354258 | E18: 1.972699 | F18: 0.428724 | G18: 0.076696 | H18: 1.117601 | I18: =P18+ R18 -> 7.828615 | J18: 83.405544 | K18: 105.29938 | L18: 3.8535112 | N18: =SUM(F18,G18) -> 0.50542 | P18: 7.828615 | Q18: =aeo_sup_oil_l48_t+aeo_sup_oil_l48+aeo_sup_oil_off+aeo_sup_oil_ala_on+aeo_sup_oil_ala_off+aeo_sup_oil_bio+aeo_sup_oil_row+P18 -> 105.29938 | R18: =IF(B18<=baseline_aeo_end_year,'Oil demand projection'!K18-Q18,"") -> 1.4210855e-14
B19: =B18+1 -> 2028 | C19: 9.113306 | D19: 1.375898 | E19: 1.936125 | F19: 0.478108 | G19: 0.073567 | H19: 1.095393 | I19: =P19+ R19 -> 7.884715 | J19: 84.187393 | K19: 106.1445 | L19: 3.9214651 | N19: =SUM(F19,G19) -> 0.551675 | P19: 7.884715 | Q19: =aeo_sup_oil_l48_t+aeo_sup_oil_l48+aeo_sup_oil_off+aeo_sup_oil_ala_on+aeo_sup_oil_ala_off+aeo_sup_oil_bio+aeo_sup_oil_row+P19 -> 106.1445 | R19: =IF(B19<=baseline_aeo_end_year,'Oil demand projection'!K19-Q19,"") -> 1.4210855e-14
B20: =B19+1 -> 2029 | C20: 9.053332 | D20: 1.400924 | E20: 1.929052 | F20: 0.491656 | G20: 0.070713 | H20: 1.095818 | I20: =P20+ R20 -> 7.931115 | J20: 84.969241 | K20: 106.94185 | L20: 4.0011599 | N20: =SUM(F20,G20) -> 0.562369 | P20: 7.931115 | Q20: =aeo_sup_oil_l48_t+aeo_sup_oil_l48+aeo_sup_oil_off+aeo_sup_oil_ala_on+aeo_sup_oil_ala_off+aeo_sup_oil_bio+aeo_sup_oil_row+P20 -> 106.94185 | R20: =IF(B20<=baseline_aeo_end_year,'Oil demand projection'!K20-Q20,"") -> 0
B21: =B20+1 -> 2030 | C21: 9.068573 | D21: 1.43167 | E21: 1.853453 | F21: 0.499385 | G21: 0.100983 | H21: 1.094847 | I21: =P21+ R21 -> 7.870033 | J21: 85.751089 | K21: 107.67003 | L21: 4.0043225 | N21: =SUM(F21,G21) -> 0.600368 | P21: 7.870033 | Q21: =aeo_sup_oil_l48_t+aeo_sup_oil_l48+aeo_sup_oil_off+aeo_sup_oil_ala_on+aeo_sup_oil_ala_off+aeo_sup_oil_bio+aeo_sup_oil_row+P21 -> 107.67003 | R21: =IF(B21<=baseline_aeo_end_year,'Oil demand projection'!K21-Q21,"") -> 0
B22: =B21+1 -> 2031 | C22: 9.063829 | D22: 1.44935 | E22: 1.799278 | F22: 0.492452 | G22: 0.107721 | H22: 1.093637 | I22: =P22+ R22 -> 7.862193 | J22: 85.786398 | K22: 107.65486 | L22: 4.0484565 | N22: =SUM(F22,G22) -> 0.600173 | P22: 7.862193 | Q22: =aeo_sup_oil_l48_t+aeo_sup_oil_l48+aeo_sup_oil_off+aeo_sup_oil_ala_on+aeo_sup_oil_ala_off+aeo_sup_oil_bio+aeo_sup_oil_row+P22 -> 107.65486 | R22: =IF(B22<=baseline_aeo_end_year,'Oil demand projection'!K22-Q22,"") -> -1.4210855e-14
B23: =B22+1 -> 2032 | C23: 9.132184 | D23: 1.459578 | E23: 1.727129 | F23: 0.522988 | G23: 0.107015 | H23: 1.090641 | I23: =P23+ R23 -> 7.823495 | J23: 85.821708 | K23: 107.68474 | L23: 4.0444117 | N23: =SUM(F23,G23) -> 0.630003 | P23: 7.823495 | Q23: =aeo_sup_oil_l48_t+aeo_sup_oil_l48+aeo_sup_oil_off+aeo_sup_oil_ala_on+aeo_sup_oil_ala_off+aeo_sup_oil_bio+aeo_sup_oil_row+P23 -> 107.68474 | R23: =IF(B23<=baseline_aeo_end_year,'Oil demand projection'!K23-Q23,"") -> 1.4210855e-14
... B41: =B40+1 -> 2050 | C41: 9.641992 | D41: 1.556447 | E41: 0.561889 | F41: 0.524969 | G41: 0.195953 | H41: 1.176264 | I41: =P41+ R41 -> 7.62355 | J41: 86.457274 | K41: 107.73834 | L41: 3.9982651 | N41: =SUM(F41,G41) -> 0.720922 | P41: 7.62355 | Q41: =aeo_sup_oil_l48_t+aeo_sup_oil_l48+aeo_sup_oil_off+aeo_sup_oil_ala_on+aeo_sup_oil_ala_off+aeo_sup_oil_bio+aeo_sup_oil_row+P41 -> 107.73834 | R41: =IF(B41<=baseline_aeo_end_year,'Oil demand projection'!K41-Q41,"") -> 0
B42: =B41+1 -> 2051 | C42: =C41*(1+oil_forecast) -> 9.7109833 | D42: =D41*(1+oil_forecast) -> 1.5675838 | E42: =E41*(1+oil_forecast) -> 0.56590948 | F42: =F41*(1+oil_forecast) -> 0.52872531 | G42: =G41*(1+oil_forecast) -> 0.1973551 | H42: =H41*(1+oil_forecast) -> 1.1846805 | I42: =I41*(1+oil_forecast) -> 7.6780988 | J42: =J41*(1+oil_forecast) -> 87.075902 | K42: 108.50924 | L42: =L41*(1+oil_forecast) -> 4.0268738 | N42: =SUM(F42,G42) -> 0.72608041 | P42: =P41*(1+oil_forecast) -> 7.6780988 | Q42: =aeo_sup_oil_l48_t+aeo_sup_oil_l48+aeo_sup_oil_off+aeo_sup_oil_ala_on+aeo_sup_oil_ala_off+aeo_sup_oil_bio+aeo_sup_oil_row+P42 -> 108.50924 | R42: =IF(B42<=baseline_aeo_end_year,'Oil demand projection'!K42-Q42,"")
B43: =B42+1 -> 2052 | C43: =C42*(1+oil_forecast) -> 9.7804683 | D43: =D42*(1+oil_forecast) -> 1.5788004 | E43: =E42*(1+oil_forecast) -> 0.56995873 | F43: =F42*(1+oil_forecast) -> 0.5325085 | G43: =G42*(1+oil_forecast) -> 0.19876724 | H43: =H42*(1+oil_forecast) -> 1.1931573 | I43: =I42*(1+oil_forecast) -> 7.7330378 | J43: =J42*(1+oil_forecast) -> 87.698956 | K43: 109.28565 | L43: =L42*(1+oil_forecast) -> 4.0556873 | N43: =SUM(F43,G43) -> 0.73127573 | P43: =P42*(1+oil_forecast) -> 7.7330378 | Q43: =aeo_sup_oil_l48_t+aeo_sup_oil_l48+aeo_sup_oil_off+aeo_sup_oil_ala_on+aeo_sup_oil_ala_off+aeo_sup_oil_bio+aeo_sup_oil_row+P43 -> 109.28565 | R43: =IF(B43<=baseline_aeo_end_year,'Oil demand projection'!K43-Q43,"")
B44: =B43+1 -> 2053 | C44: =C43*(1+oil_forecast) -> 9.8504505 | D44: =D43*(1+oil_forecast) -> 1.5900972 | E44: =E43*(1+oil_forecast) -> 0.57403696 | F44: =F43*(1+oil_forecast) -> 0.53631875 | G44: =G43*(1+oil_forecast) -> 0.20018948 | H44: =H43*(1+oil_forecast) -> 1.2016947 | I44: =I43*(1+oil_forecast) -> 7.78837 | J44: =J43*(1+oil_forecast) -> 88.326468 | K44: 110.06763 | L44: =L43*(1+oil_forecast) -> 4.084707 | N44: =SUM(F44,G44) -> 0.73650823 | P44: =P43*(1+oil_forecast) -> 7.78837 | Q44: =aeo_sup_oil_l48_t+aeo_sup_oil_l48+aeo_sup_oil_off+aeo_sup_oil_ala_on+aeo_sup_oil_ala_off+aeo_sup_oil_bio+aeo_sup_oil_row+P44 -> 110.06763 | R44: =IF(B44<=baseline_aeo_end_year,'Oil demand projection'!K44-Q44,"")
B45: =B44+1 -> 2054 | C45: =C44*(1+oil_forecast) -> 9.9209334 | D45: =D44*(1+oil_forecast) -> 1.6014748 | E45: =E44*(1+oil_forecast) -> 0.57814436 | F45: =F44*(1+oil_forecast) -> 0.54015627 | G45: =G44*(1+oil_forecast) -> 0.20162189 | H45: =H44*(1+oil_forecast) -> 1.2102931 | I45: =I44*(1+oil_forecast) -> 7.8440981 | J45: =J44*(1+oil_forecast) -> 88.95847 | K45: 110.85519 | L45: =L44*(1+oil_forecast) -> 4.1139343 | N45: =SUM(F45,G45) -> 0.74177816 | P45: =P44*(1+oil_forecast) -> 7.8440981 | Q45: =aeo_sup_oil_l48_t+aeo_sup_oil_l48+aeo_sup_oil_off+aeo_sup_oil_ala_on+aeo_sup_oil_ala_off+aeo_sup_oil_bio+aeo_sup_oil_row+P45 -> 110.85519 | R45: =IF(B45<=baseline_aeo_end_year,'Oil demand projection'!K45-Q45,"")
B46: =B45+1 -> 2055 | C46: =C45*(1+oil_forecast) -> 9.9919206 | D46: =D45*(1+oil_forecast) -> 1.6129338 | E46: =E45*(1+oil_forecast) -> 0.58228116 | F46: =F45*(1+oil_forecast) -> 0.54402125 | G46: =G45*(1+oil_forecast) -> 0.20306455 | H46: =H45*(1+oil_forecast) -> 1.2189531 | I46: =I45*(1+oil_forecast) -> 7.900225 | J46: =J45*(1+oil_forecast) -> 89.594994 | K46: 111.64839 | L46: =L45*(1+oil_forecast) -> 4.1433707 | N46: =SUM(F46,G46) -> 0.74708581 | P46: =P45*(1+oil_forecast) -> 7.900225 | Q46: =aeo_sup_oil_l48_t+aeo_sup_oil_l48+aeo_sup_oil_off+aeo_sup_oil_ala_on+aeo_sup_oil_ala_off+aeo_sup_oil_bio+aeo_sup_oil_row+P46 -> 111.64839 | R46: =IF(B46<=baseline_aeo_end_year,'Oil demand projection'!K46-Q46,"")
B47: =B46+1 -> 2056 | C47: =C46*(1+oil_forecast) -> 10.063416 | D47: =D46*(1+oil_forecast) -> 1.6244748 | E47: =E46*(1+oil_forecast) -> 0.58644755 | F47: =F46*(1+oil_forecast) -> 0.54791389 | G47: =G46*(1+oil_forecast) -> 0.20451754 | H47: =H46*(1+oil_forecast) -> 1.2276751 | I47: =I46*(1+oil_forecast) -> 7.9567535 | J47: =J46*(1+oil_forecast) -> 90.236073 | K47: 112.44727 | L47: =L46*(1+oil_forecast) -> 4.1730177 | N47: =SUM(F47,G47) -> 0.75243143 | P47: =P46*(1+oil_forecast) -> 7.9567535 | Q47: =aeo_sup_oil_l48_t+aeo_sup_oil_l48+aeo_sup_oil_off+aeo_sup_oil_ala_on+aeo_sup_oil_ala_off+aeo_sup_oil_bio+aeo_sup_oil_row+P47 -> 112.44727 | R47: =IF(B47<=baseline_aeo_end_year,'Oil demand projection'!K47-Q47,"")
B48: =B47+1 -> 2057 | C48: =C47*(1+oil_forecast) -> 10.135422 | D48: =D47*(1+oil_forecast) -> 1.6360984 | E48: =E47*(1+oil_forecast) -> 0.59064376 | F48: =F47*(1+oil_forecast) -> 0.55183437 | G48: =G47*(1+oil_forecast) -> 0.20598093 | H48: =H47*(1+oil_forecast) -> 1.2364595 | I48: =I47*(1+oil_forecast) -> 8.0136864 | J48: =J47*(1+oil_forecast) -> 90.881739 | K48: 113.25187 | L48: =L47*(1+oil_forecast) -> 4.2028769 | N48: =SUM(F48,G48) -> 0.7578153 | P48: =P47*(1+oil_forecast) -> 8.0136864 | Q48: =aeo_sup_oil_l48_t+aeo_sup_oil_l48+aeo_sup_oil_off+aeo_sup_oil_ala_on+aeo_sup_oil_ala_off+aeo_sup_oil_bio+aeo_sup_oil_row+P48 -> 113.25187 | R48: =IF(B48<=baseline_aeo_end_year,'Oil demand projection'!K48-Q48,"")
B49: =B48+1 -> 2058 | C49: =C48*(1+oil_forecast) -> 10.207944 | D49: =D48*(1+oil_forecast) -> 1.6478052 | E49: =E48*(1+oil_forecast) -> 0.59486999 | F49: =F48*(1+oil_forecast) -> 0.55578291 | G49: =G48*(1+oil_forecast) -> 0.20745478 | H49: =H48*(1+oil_forecast) -> 1.2453067 | I49: =I48*(1+oil_forecast) -> 8.0710267 | J49: =J48*(1+oil_forecast) -> 91.532025 | K49: 114.06222 | L49: =L48*(1+oil_forecast) -> 4.2329498 | N49: =SUM(F49,G49) -> 0.76323769 | P49: =P48*(1+oil_forecast) -> 8.0710267 | Q49: =aeo_sup_oil_l48_t+aeo_sup_oil_l48+aeo_sup_oil_off+aeo_sup_oil_ala_on+aeo_sup_oil_ala_off+aeo_sup_oil_bio+aeo_sup_oil_row+P49 -> 114.06222 | R49: =IF(B49<=baseline_aeo_end_year,'Oil demand projection'!K49-Q49,"")
B50: =B49+1 -> 2059 | C50: =C49*(1+oil_forecast) -> 10.280985 | D50: =D49*(1+oil_forecast) -> 1.6595957 | E50: =E49*(1+oil_forecast) -> 0.59912646 | F50: =F49*(1+oil_forecast) -> 0.5597597 | G50: =G49*(1+oil_forecast) -> 0.20893918 | H50: =H49*(1+oil_forecast) -> 1.2542173 | I50: =I49*(1+oil_forecast) -> 8.1287773 | J50: =J49*(1+oil_forecast) -> 92.186964 | K50: 114.87836 | L50: =L49*(1+oil_forecast) -> 4.2632378 | N50: =SUM(F50,G50) -> 0.76869888 | P50: =P49*(1+oil_forecast) -> 8.1287773 | Q50: =aeo_sup_oil_l48_t+aeo_sup_oil_l48+aeo_sup_oil_off+aeo_sup_oil_ala_on+aeo_sup_oil_ala_off+aeo_sup_oil_bio+aeo_sup_oil_row+P50 -> 114.87836 | R50: =IF(B50<=baseline_aeo_end_year,'Oil demand projection'!K50-Q50,"")
B51: =B50+1 -> 2060 | C51: =C50*(1+oil_forecast) -> 10.354549 | D51: =D50*(1+oil_forecast) -> 1.6714706 | E51: =E50*(1+oil_forecast) -> 0.60341339 | F51: =F50*(1+oil_forecast) -> 0.56376495 | G51: =G50*(1+oil_forecast) -> 0.2104342 | H51: =H50*(1+oil_forecast) -> 1.2631916 | I51: =I50*(1+oil_forecast) -> 8.1869411 | J51: =J50*(1+oil_forecast) -> 92.846589 | K51: 115.70035 | L51: =L50*(1+oil_forecast) -> 4.2937425 | N51: =SUM(F51,G51) -> 0.77419915 | P51: =P50*(1+oil_forecast) -> 8.1869411 | Q51: =aeo_sup_oil_l48_t+aeo_sup_oil_l48+aeo_sup_oil_off+aeo_sup_oil_ala_on+aeo_sup_oil_ala_off+aeo_sup_oil_bio+aeo_sup_oil_row+P51 -> 115.70035 | R51: =IF(B51<=baseline_aeo_end_year,'Oil demand projection'!K51-Q51,"")
B52: =B51+1 -> 2061 | C52: =C51*(1+oil_forecast) -> 10.428639 | D52: =D51*(1+oil_forecast) -> 1.6834305 | E52: =E51*(1+oil_forecast) -> 0.60773099 | F52: =F51*(1+oil_forecast) -> 0.56779886 | G52: =G51*(1+oil_forecast) -> 0.21193992 | H52: =H51*(1+oil_forecast) -> 1.2722301 | I52: =I51*(1+oil_forecast) -> 8.2455211 | J52: =J51*(1+oil_forecast) -> 93.510934 | K52: 116.52822 | L52: =L51*(1+oil_forecast) -> 4.3244655 | N52: =SUM(F52,G52) -> 0.77973878 | P52: =P51*(1+oil_forecast) -> 8.2455211 | Q52: =aeo_sup_oil_l48_t+aeo_sup_oil_l48+aeo_sup_oil_off+aeo_sup_oil_ala_on+aeo_sup_oil_ala_off+aeo_sup_oil_bio+aeo_sup_oil_row+P52 -> 116.52822 | R52: =IF(B52<=baseline_aeo_end_year,'Oil demand projection'!K52-Q52,"")
B53: =B52+1 -> 2062 | C53: =C52*(1+oil_forecast) -> 10.503259 | D53: =D52*(1+oil_forecast) -> 1.6954759 | E53: =E52*(1+oil_forecast) -> 0.61207949 | F53: =F52*(1+oil_forecast) -> 0.57186163 | G53: =G52*(1+oil_forecast) -> 0.21345642 | H53: =H52*(1+oil_forecast) -> 1.2813333 | I53: =I52*(1+oil_forecast) -> 8.3045203 | J53: =J52*(1+oil_forecast) -> 94.180033 | K53: 117.36202 | L53: =L52*(1+oil_forecast) -> 4.3554083 | N53: =SUM(F53,G53) -> 0.78531804 | P53: =P52*(1+oil_forecast) -> 8.3045203 | Q53: =aeo_sup_oil_l48_t+aeo_sup_oil_l48+aeo_sup_oil_off+aeo_sup_oil_ala_on+aeo_sup_oil_ala_off+aeo_sup_oil_bio+aeo_sup_oil_row+P53 -> 117.36202 | R53: =IF(B53<=baseline_aeo_end_year,'Oil demand projection'!K53-Q53,"")
... B84: =B83+1 -> 2093 | C84: =C83*(1+oil_forecast) -> 13.10128 | D84: =D83*(1+oil_forecast) -> 2.1148585 | E84: =E83*(1+oil_forecast) -> 0.76347972 | F84: =F83*(1+oil_forecast) -> 0.71331382 | G84: =G83*(1+oil_forecast) -> 0.26625569 | H84: =H83*(1+oil_forecast) -> 1.598276 | I84: =I83*(1+oil_forecast) -> 10.358676 | J84: =J83*(1+oil_forecast) -> 117.47583 | K84: 146.39197 | L84: =L83*(1+oil_forecast) -> 5.4327355 | N84: =SUM(F84,G84) -> 0.97956951 | P84: =P83*(1+oil_forecast) -> 10.358676 | Q84: =aeo_sup_oil_l48_t+aeo_sup_oil_l48+aeo_sup_oil_off+aeo_sup_oil_ala_on+aeo_sup_oil_ala_off+aeo_sup_oil_bio+aeo_sup_oil_row+P84 -> 146.39197 | R84: =IF(B84<=baseline_aeo_end_year,'Oil demand projection'!K84-Q84,"")
B85: Scenario | C85: AEO 2023-Special NEMS run | D85: AEO 2023-Special NEMS run | E85: AEO 2023-Special NEMS run | F85: AEO 2023-Special NEMS run | G85: AEO 2023-Special NEMS run | H85: AEO 2023-Special NEMS run | J85: AEO 2023-Special NEMS run | K85: Row Sum | L85: Based on AEO 2023 Special NEMS Run and ratio derived from historical pipeline share of imports | N85: AEO 2023-Special NEMS run | P85: AEO 2023-Special NEMS run
B86: Datekey | C86: BOEM_REF2023.d032923b | D86: BOEM_REF2023.d032923b | E86: BOEM_REF2023.d032923b | F86: BOEM_REF2023.d032923b | G86: BOEM_REF2023.d032923b | H86: BOEM_REF2023.d032923b | J86: BOEM_REF2023.d032923b | L86: Reference Case | N86: BOEM_REF2023.d032923b | P86: BOEM_REF2023.d032923b
B87: Release | C87: April 2023 | D87: April 2023 | E87: April 2023 | F87: April 2023 | G87: April 2023 | H87: April 2023 | I87: April 2023 | J87: April 2023 | L87: May 2023 | N87: April 2023 | P87: April 2023
B88: Table | C88: Summary Table 14 - Oil and Gas Supply | D88: Summary Table 14 - Oil and Gas Supply | E88: Summary Table 14 - Oil and Gas Supply | F88: Summary Table 14 - Oil and Gas Supply | G88: Summary Table 14 - Oil and Gas Supply | H88: Summary Table 11 - Petroleum and Other Liquids Supply and Disposition | I88: Updated Col P Instead | J88: Summary Table 19 - 19. International Petroleum and Other Liquids Supply, Disposition, and Prices | L88: Table 11 and Special worksheet. See notes below. | N88: table = sum, no update | P88: Summary Table 11 - Petroleum and Other Liquids Supply and Disposition
B89: Line | C89: 2113 | D89: 2114+2115 | E89: 2116 | F89: 2120 | G89: 2121+2122 | H89: 1650+1652+1654+1656+1658+1660 | I89: As per update directions | J89: 2665 - 2647 | L89: 1635 and other worksheets | N89: Annual sum of cells in Columns E and F | P89: 1637+1645+1646+1647+1662+1663
B90: Row Info. | C90: Lower 48 Onshore: Tight Oil | D90: Lower 48 Onshore (Non-tight): Lower 48 Onshore Total - Lower 48 Onshore: Tight Oil | E90: Lower 48 Offshore | F90: Alaska: Onshore | G90: Alaska: State Offshore + Federal Offshore | H90: Domestic Production (Ethanol) + Domestic Production (Biodiesel) + Domestic Production (Other Biomass-derived liquids) + Stock Withdrawal | J90: Total Petroleum Production - United States (50 states) | L90: Gross Imports * Ratio | N90: Alaska Onshore + Alaska Offshore | P90: Other Crude Supply + Refinery Processing Gain + Product Stock Withdrawal + Natural Gas Plant Liquids + Liquids from Coal + Other
L92: Notes: See file "2020 Pipeline Share of Imports Calculations" for data sources and methodology. File located at: J:\offhqshare\Econ Modeling\Env.Social Costs&MktSim\2020 MarketSim Update_Internal\Pipeline Share of Imports files

Sheet Gas supply projection
A1: Return to Table of Contents
B6: AEO BASELINE NATURAL GAS SUPPLY PROJECTION
C8: Lower 48 Conventional | D8: Lower 48 Unconventional | E8: Lower 48 Offshore | F8: Alaska Onshore | G8: Alaska Offshore | H8: Other | I8: Imports Pipeline | J8: Imports LNG | K8: Total Supply | M8: Forecast Supply
B9: Year | C9: 1012 cubic feet | D9: 1012 cubic feet | E9: 1012 cubic feet | F9: 1012 cubic feet | G9: 1012 cubic feet | H9: 1012 cubic feet | I9: 1012 cubic feet | J9: 1012 cubic feet | K9: 1012 cubic feet | M9: %
B10: ='Oil supply projection'!$B10 -> 2019 | C10: 2.65278 | D10: 29.915885 | E10: 1.019864 | F10: 0.304851 | H10: 0.060765 | I10: 2.687779 | J10: 0.052678 | K10: {=aeo_sup_gas_con+aeo_sup_gas_unc+aeo_sup_gas_ala_on+aeo_sup_gas_ala_off+aeo_sup_gas_off+aeo_sup_gas_oth+aeo_sup_gas_pip+aeo_sup_gas_lng} -> 36.694602 | M10: 0.002969585
B11: ='Oil supply projection'!$B11 -> 2020 | C11: 2.565241 | D11: 29.809835 | E11: 0.792516 | F11: 0.303039 | H11: 0.063145 | I11: 2.501835 | J11: 0.049169 | K11: 36.08478 | M11: =(INDEX(aeo_sup_gas_tot,MATCH(baseline_aeo_end_year,B10:B84,0),1)/INDEX(aeo_sup_gas_tot,MATCH(baseline_aeo_end_year-10,B10:B84,0),1))^(1/10)-1 -> 0.002969585
B12: ='Oil supply projection'!$B12 -> 2021 | C12: 2.648991 | D12: 30.985999 | E12: 0.809318 | F12: 0.302724 | H12: 0.065689 | I12: 2.7656 | J12: 0.021424 | K12: 37.599745
B13: ='Oil supply projection'!$B13 -> 2022 | C13: 2.62482 | D13: 32.421447 | E13: 1.070654 | F13: 0.347862 | H13: 0.066783 | I13: 2.883263 | J13: 0.025682 | K13: 39.440511
B14: ='Oil supply projection'!$B14 -> 2023 | C14: 2.471103 | D14: 32.866078 | E14: 0.823955 | F14: 0.325372 | H14: 0.068295 | I14: 2.718317 | J14: 0.02132 | K14: 39.29444
B15: ='Oil supply projection'!$B15 -> 2024 | C15: 2.194472 | D15: 32.244557 | E15: 0.795425 | F15: 0.330591 | H15: 0.067215 | I15: 2.373989 | J15: 0.028101 | K15: 38.03435
B16: ='Oil supply projection'!$B16 -> 2025 | C16: 2.14478 | D16: 32.359822 | E16: 0.846275 | F16: 0.340373 | H16: 0.066134 | I16: 2.261526 | J16: 0.034883 | K16: 38.053793
B17: ='Oil supply projection'!$B17 -> 2026 | C17: 2.071491 | D17: 32.832016 | E17: 0.868767 | F17: 0.341071 | H17: 0.065053 | I17: 2.160842 | J17: 0.041664 | K17: 38.380904
B18: ='Oil supply projection'!$B18 -> 2027 | C18: 1.928922 | D18: 32.87506 | E18: 0.869912 | F18: 0.34651 | H18: 0.063973 | I18: 2.095736 | J18: 0.048446 | K18: 38.228559
B19: ='Oil supply projection'!$B19 -> 2028 | C19: 1.830736 | D19: 33.135717 | E19: 0.860716 | F19: 0.352726 | H19: 0.062892 | I19: 1.992164 | J19: 0.055227 | K19: 38.290178
B20: ='Oil supply projection'!$B20 -> 2029 | C20: 1.744173 | D20: 33.248218 | E20: 0.866908 | F20: 0.352955 | H20: 0.062892 | I20: 1.936276 | J20: 0.055227 | K20: 38.266649
B21: ='Oil supply projection'!$B21 -> 2030 | C21: 1.694079 | D21: 33.634056 | E21: 0.848348 | F21: 0.35975 | H21: 0.062892 | I21: 1.97868 | J21: 0.055227 | K21: 38.633032
B22: ='Oil supply projection'!$B22 -> 2031 | C22: 1.641855 | D22: 34.215996 | E22: 0.83727 | F22: 0.357872 | H22: 0.062892 | I22: 1.980683 | J22: 0.055227 | K22: 39.151795
B23: ='Oil supply projection'!$B23 -> 2032 | C23: 1.600781 | D23: 34.936125 | E23: 0.813321 | F23: 0.364334 | H23: 0.062892 | I23: 2.040562 | J23: 0.055227 | K23: 39.873242
... B41: ='Oil supply projection'!$B41 -> 2050 | C41: 1.173674 | D41: 39.297329 | E41: 0.37913 | F41: 0.386719 | H41: 0.062892 | I41: 2.537287 | J41: 0.055227 | K41: 43.892258
B42: ='Oil supply projection'!$B42 -> 2051 | C42: =C41*(1+gas_forecast) -> 1.1771593 | D42: =D41*(1+gas_forecast) -> 39.414026 | E42: =E41*(1+gas_forecast) -> 0.38025586 | F42: =F41*(1+gas_forecast) -> 0.38786739 | G42: =G41*(1+gas_forecast) -> 0 | H42: =H41*(1+gas_forecast) -> 0.063078763 | I42: =I41*(1+gas_forecast) -> 2.5448217 | J42: =J41*(1+gas_forecast) -> 0.055391001 | K42: 44.0226
B43: ='Oil supply projection'!$B43 -> 2052 | C43: =C42*(1+gas_forecast) -> 1.180655 | D43: =D42*(1+gas_forecast) -> 39.531069 | E43: =E42*(1+gas_forecast) -> 0.38138506 | F43: =F42*(1+gas_forecast) -> 0.3890192 | G43: =G42*(1+gas_forecast) -> 0 | H43: =H42*(1+gas_forecast) -> 0.063266081 | I43: =I42*(1+gas_forecast) -> 2.5523788 | J43: =J42*(1+gas_forecast) -> 0.05555549 | K43: 44.153329
B44: ='Oil supply projection'!$B44 -> 2053 | C44: =C43*(1+gas_forecast) -> 1.1841611 | D44: =D43*(1+gas_forecast) -> 39.64846 | E44: =E43*(1+gas_forecast) -> 0.38251762 | F44: =F43*(1+gas_forecast) -> 0.39017443 | G44: =G43*(1+gas_forecast) -> 0 | H44: =H43*(1+gas_forecast) -> 0.063453955 | I44: =I43*(1+gas_forecast) -> 2.5599583 | J44: =J43*(1+gas_forecast) -> 0.055720466 | K44: 44.284446
B45: ='Oil supply projection'!$B45 -> 2054 | C45: =C44*(1+gas_forecast) -> 1.1876775 | D45: =D44*(1+gas_forecast) -> 39.766199 | E45: =E44*(1+gas_forecast) -> 0.38365353 | F45: =F44*(1+gas_forecast) -> 0.39133308 | G45: =G44*(1+gas_forecast) -> 0 | H45: =H44*(1+gas_forecast) -> 0.063642387 | I45: =I44*(1+gas_forecast) -> 2.5675603 | J45: =J44*(1+gas_forecast) -> 0.055885933 | K45: 44.415952
B46: ='Oil supply projection'!$B46 -> 2055 | C46: =C45*(1+gas_forecast) -> 1.1912044 | D46: =D45*(1+gas_forecast) -> 39.884289 | E46: =E45*(1+gas_forecast) -> 0.38479283 | F46: =F45*(1+gas_forecast) -> 0.39249518 | G46: =G45*(1+gas_forecast) -> 0 | H46: =H45*(1+gas_forecast) -> 0.063831378 | I46: =I45*(1+gas_forecast) -> 2.5751849 | J46: =J45*(1+gas_forecast) -> 0.056051891 | K46: 44.547849
B47: ='Oil supply projection'!$B47 -> 2056 | C47: =C46*(1+gas_forecast) -> 1.1947418 | D47: =D46*(1+gas_forecast) -> 40.002728 | E47: =E46*(1+gas_forecast) -> 0.3859355 | F47: =F46*(1+gas_forecast) -> 0.39366073 | G47: =G46*(1+gas_forecast) -> 0 | H47: =H46*(1+gas_forecast) -> 0.064020931 | I47: =I46*(1+gas_forecast) -> 2.5828321 | J47: =J46*(1+gas_forecast) -> 0.056218342 | K47: 44.680138
B48: ='Oil supply projection'!$B48 -> 2057 | C48: =C47*(1+gas_forecast) -> 1.1982897 | D48: =D47*(1+gas_forecast) -> 40.12152 | E48: =E47*(1+gas_forecast) -> 0.38708157 | F48: =F47*(1+gas_forecast) -> 0.39482974 | G48: =G47*(1+gas_forecast) -> 0 | H48: =H47*(1+gas_forecast) -> 0.064211047 | I48: =I47*(1+gas_forecast) -> 2.590502 | J48: =J47*(1+gas_forecast) -> 0.056385287 | K48: 44.812819
B49: ='Oil supply projection'!$B49 -> 2058 | C49: =C48*(1+gas_forecast) -> 1.2018481 | D49: =D48*(1+gas_forecast) -> 40.240664 | E49: =E48*(1+gas_forecast) -> 0.38823104 | F49: =F48*(1+gas_forecast) -> 0.39600222 | G49: =G48*(1+gas_forecast) -> 0 | H49: =H48*(1+gas_forecast) -> 0.064401727 | I49: =I48*(1+gas_forecast) -> 2.5981947 | J49: =J48*(1+gas_forecast) -> 0.056552728 | K49: 44.945895
B50: ='Oil supply projection'!$B50 -> 2059 | C50: =C49*(1+gas_forecast) -> 1.2054171 | D50: =D49*(1+gas_forecast) -> 40.360162 | E50: =E49*(1+gas_forecast) -> 0.38938393 | F50: =F49*(1+gas_forecast) -> 0.39717818 | G50: =G49*(1+gas_forecast) -> 0 | H50: =H49*(1+gas_forecast) -> 0.064592973 | I50: =I49*(1+gas_forecast) -> 2.6059103 | J50: =J49*(1+gas_forecast) -> 0.056720666 | K50: 45.079365
B51: ='Oil supply projection'!$B51 -> 2060 | C51: =C50*(1+gas_forecast) -> 1.2089967 | D51: =D50*(1+gas_forecast) -> 40.480015 | E51: =E50*(1+gas_forecast) -> 0.39054024 | F51: =F50*(1+gas_forecast) -> 0.39835763 | G51: =G50*(1+gas_forecast) -> 0 | H51: =H50*(1+gas_forecast) -> 0.064784787 | I51: =I50*(1+gas_forecast) -> 2.6136488 | J51: =J50*(1+gas_forecast) -> 0.056889103 | K51: 45.213232
B52: ='Oil supply projection'!$B52 -> 2061 | C52: =C51*(1+gas_forecast) -> 1.2125869 | D52: =D51*(1+gas_forecast) -> 40.600224 | E52: =E51*(1+gas_forecast) -> 0.39169998 | F52: =F51*(1+gas_forecast) -> 0.39954059 | G52: =G51*(1+gas_forecast) -> 0 | H52: =H51*(1+gas_forecast) -> 0.064977171 | I52: =I51*(1+gas_forecast) -> 2.6214102 | J52: =J51*(1+gas_forecast) -> 0.05705804 | K52: 45.347497
B53: ='Oil supply projection'!$B53 -> 2062 | C53: =C52*(1+gas_forecast) -> 1.2161878 | D53: =D52*(1+gas_forecast) -> 40.72079 | E53: =E52*(1+gas_forecast) -> 0.39286316 | F53: =F52*(1+gas_forecast) -> 0.40072706 | G53: =G52*(1+gas_forecast) -> 0 | H53: =H52*(1+gas_forecast) -> 0.065170127 | I53: =I52*(1+gas_forecast) -> 2.6291947 | J53: =J52*(1+gas_forecast) -> 0.057227479 | K53: 45.48216
... B84: ='Oil supply projection'!$B84 -> 2093 | C84: =C83*(1+gas_forecast) -> 1.3332798 | D84: =D83*(1+gas_forecast) -> 44.641302 | E84: =E83*(1+gas_forecast) -> 0.43068721 | F84: =F83*(1+gas_forecast) -> 0.43930822 | G84: =G83*(1+gas_forecast) -> 0 | H84: =H83*(1+gas_forecast) -> 0.07144457 | I84: =I83*(1+gas_forecast) -> 2.8823281 | J84: =J83*(1+gas_forecast) -> 0.06273722 | K84: 49.861087
B85: Scenario | C85: AEO 2023-Special NEMS run | D85: AEO 2023-Special NEMS run | E85: AEO 2023-Special NEMS run | F85: AEO 2023-Special NEMS run | G85: No update (not in table) | H85: AEO 2023-Special NEMS run | I85: AEO 2023-Special NEMS run | J85: AEO 2023-Special NEMS run | K85: Row Sum
B86: Datekey | C86: BOEM_REF2023.d032923b | D86: BOEM_REF2023.d032923b | E86: BOEM_REF2023.d032923b | F86: BOEM_REF2023.d032923b | H86: BOEM_REF2023.d032923b | I86: BOEM_REF2023.d032923b | J86: BOEM_REF2023.d032923b
B87: Release | C87: April 2023 | D87: April 2023 | E87: April 2023 | F87: April 2023 | H87: April 2023 | I87: April 2023 | J87: April 2023
B88: Table | C88: Summary Table 14 - Oil and Gas Supply | D88: Summary Table 14 - Oil and Gas Supply | E88: Summary Table 14 - Oil and Gas Supply | F88: Summary Table 14 - Oil and Gas Supply | H88: Summary Table 14 | I88: Summary Table 76 - 76. Natural Gas Imports and Exports | J88: Summary Table 76 - 76. Natural Gas Imports and Exports
B89: Line | C89: 2142 | D89: 2139+2140+2141 | E89: 2143 | F89: 2146 | H89: 2148 | I89: 3982+3983 | J89: 3992+3988
B90: Row Info. | C90: Lower 48 Onshore // Other | D90: Lower 48 Onshore: Tight Gas + Shale Gas and Tight Oil Plays + Coalbed Methane | E90: Lower 48 Offshore | F90: Alaska | H90: Supplemental Gas Supplies (tcf) | I90: Pipeline Imports from Canada + Pipeline Imports from Mexico | J90: Liquefied Natural Gas Imports
F91: No longer broken out into offshore and onshore. There is a single row for Alaska (row 2146). Current methodology is to assume 100% onshore - placing 100% of EIA's reported Natural Gas supply for Alaska in the onshore column. | G91: No longer broken out into offshore and onshore. There is a single row for Alaska (row 2146). Current methodology is to assume 100% onshore - placing 100% of EIA's reported Natural Gas supply for Alaska in the onshore column.

Sheet Electricity supply projection
A1: Return to Table of Contents
E4: AEO baseline electricity supply and demand are: | F4: =ele_equil -> In equilibrium
B6: AEO BASELINE ELECTRICITY SUPPLY PROJECTION
C8: Oil | D8: Natural Gas | E8: Coal | F8: Nuclear | G8: Hydro | H8: Solar | I8: Wind Onshore | J8: Wind Offshore | K8: Other Electric | L8: Net imports | M8: Total Supply | O8: Forecast Supply
B9: Year | C9: 109 kW h | D9: 109 kW h | E9: 109 kW h | F9: 109 kW h | G9: 109 kW h | H9: 109 kW h | I9: 109 kW h | J9: 109 kW h | K9: 109 kW h | L9: 109 kW h | M9: 109 kW h | O9: %
B10: ='Oil supply projection'!$B10 -> 2019 | C10: 15.373374 | D10: 1360.8629 | E10: 947.89062 | F10: 809.40924 | G10: 286.4071 | H10: 68.046822 | I10: 295.60403 | J10: 0 | K10: 19.57921 | L10: 39.04443 | M10: {=aeo_sup_ele_oil+aeo_sup_ele_gas+aeo_sup_ele_coa+aeo_sup_ele_nuc+aeo_sup_ele_hyd+aeo_sup_ele_sol+aeo_sup_ele_won+aeo_sup_ele_wof+aeo_sup_ele_oth+aeo_sup_ele_imp} -> 3842.2178 | O10: 0.0084083082
B11: ='Oil supply projection'!$B11 -> 2020 | C11: 13.665286 | D11: 1405.178 | E11: 757.76324 | F11: 789.87884 | G11: 284.05933 | H11: 85.3787 | I11: 337.15289 | J11: 0 | K11: 18.539803 | L11: 48.077648 | M11: 3739.6937 | O11: {=(INDEX(aeo_sup_ele_tot,MATCH(baseline_aeo_end_year,B10:B84,0),1)/INDEX(aeo_sup_ele_tot,MATCH(baseline_aeo_end_year-10,B10:B84,0),1))^(1/10)-1} -> 0.0084083082
B12: ='Oil supply projection'!$B12 -> 2021 | C12: 15.614943 | D12: 1363.6437 | E12: 882.30536 | F12: 778.18799 | G12: 250.39098 | H12: 111.60156 | I12: 377.91733 | J12: 0 | K12: 17.28599 | L12: 37.968922 | M12: 3834.9167
B13: ='Oil supply projection'!$B13 -> 2022 | C13: 10.011641 | D13: 1451.5491 | E13: 832.22632 | F13: 771.98438 | G13: 275.04477 | H13: 131.15712 | I13: 437.39526 | J13: 1.44935 | K13: 13.175932 | L13: 42.686222 | M13: 3966.6801
B14: ='Oil supply projection'!$B14 -> 2023 | C14: 9.507455 | D14: 1354.0076 | E14: 783.51874 | F14: 783.71594 | G14: 281.19339 | H14: 172.77576 | I14: 462.89889 | J14: 3.102872 | K14: 12.663155 | L14: 50.749699 | M14: 3914.1335
B15: ='Oil supply projection'!$B15 -> 2024 | C15: 9.580185 | D15: 1260.2686 | E15: 822.87207 | F15: 789.40369 | G15: 290.52017 | H15: 247.21266 | I15: 466.08728 | J15: 5.569778 | K15: 13.129585 | L15: 43.72879 | M15: 3948.3728
B16: ='Oil supply projection'!$B16 -> 2025 | C16: 9.264454 | D16: 1193.9293 | E16: 754.82117 | F16: 782.25647 | G16: 298.56491 | H16: 365.23227 | I16: 505.68097 | J16: 6.071972 | K16: 12.511452 | L16: 38.605705 | M16: 3966.9387
B17: ='Oil supply projection'!$B17 -> 2026 | C17: 8.566787 | D17: 1133.4957 | E17: 650.24542 | F17: 774.68359 | G17: 299.28418 | H17: 500.20071 | I17: 574.66333 | J17: 6.883739 | K17: 12.187555 | L17: 39.76387 | M17: 3999.9749
B18: ='Oil supply projection'!$B18 -> 2027 | C18: 7.882752 | D18: 1045.3157 | E18: 554.14319 | F18: 774.66992 | G18: 299.32053 | H18: 621.4231 | I18: 662.60303 | J18: 6.881344 | K18: 11.81308 | L18: 43.742729 | M18: 4027.7953
B19: ='Oil supply projection'!$B19 -> 2028 | C19: 7.173945 | D19: 995.14343 | E19: 455.10489 | F19: 765.54077 | G19: 297.98276 | H19: 703.25769 | I19: 769.13452 | J19: 10.333075 | K19: 10.422989 | L19: 46.183384 | M19: 4060.2775
B20: ='Oil supply projection'!$B20 -> 2029 | C20: 6.783045 | D20: 927.6416 | E20: 389.3721 | F20: 765.54077 | G20: 295.70837 | H20: 750.57294 | I20: 890.1748 | J20: 11.199924 | K20: 9.446502 | L20: 43.442635 | M20: 4089.8827
B21: ='Oil supply projection'!$B21 -> 2030 | C21: 6.451933 | D21: 880.17126 | E21: 340.84738 | F21: 765.54175 | G21: 292.43408 | H21: 772.65405 | I21: 971.27753 | J21: 31.590298 | K21: 9.134968 | L21: 46.496151 | M21: 4116.5994
B22: ='Oil supply projection'!$B22 -> 2031 | C22: 6.171555 | D22: 848.72186 | E22: 333.401 | F22: 760.27576 | G22: 292.51761 | H22: 806.37116 | I22: 1008.949 | J22: 36.69278 | K22: 7.686771 | L22: 43.695644 | M22: 4144.4832
B23: ='Oil supply projection'!$B23 -> 2032 | C23: 6.171712 | D23: 835.0412 | E23: 342.18567 | F23: 760.2832 | G23: 291.10406 | H23: 839.74268 | I23: 1017.777 | J23: 36.695629 | K23: 6.91813 | L23: 44.675964 | M23: 4180.5952
... B41: ='Oil supply projection'!$B41 -> 2050 | C41: 3.643483 | D41: 868.44592 | E41: 239.0378 | F41: 636.42035 | G41: 284.26334 | H41: 1494.1025 | I41: 1155.7758 | J41: 84.79187 | K41: -27.376453 | L41: 40.348297 | M41: 4779.4529
B42: ='Oil supply projection'!$B42 -> 2051 | C42: =C41*(1+elect_forecast) -> 3.6741185 | D42: =D41*(1+elect_forecast) -> 875.74808 | E42: =E41*(1+elect_forecast) -> 241.0477 | F42: =F41*(1+elect_forecast) -> 641.77157 | G42: =G41*(1+elect_forecast) -> 286.65351 | H42: =H41*(1+elect_forecast) -> 1506.6654 | I42: =I41*(1+elect_forecast) -> 1165.4939 | J42: =J41*(1+elect_forecast) -> 85.504826 | ... L42: =L41*(1+elect_forecast) -> 40.687558 | M42: 4819.64
B43: ='Oil supply projection'!$B43 -> 2052 | C43: =C42*(1+elect_forecast) -> 3.7050116 | D43: =D42*(1+elect_forecast) -> 883.11164 | E43: =E42*(1+elect_forecast) -> 243.0745 | F43: =F42*(1+elect_forecast) -> 647.16778 | G43: =G42*(1+elect_forecast) -> 289.06378 | H43: =H42*(1+elect_forecast) -> 1519.3339 | I43: =I42*(1+elect_forecast) -> 1175.2937 | J43: =J42*(1+elect_forecast) -> 86.223777 | ... L43: =L42*(1+elect_forecast) -> 41.029671 | M43: 4860.165
B44: ='Oil supply projection'!$B44 -> 2053 | C44: =C43*(1+elect_forecast) -> 3.7361645 | D44: =D43*(1+elect_forecast) -> 890.53712 | E44: =E43*(1+elect_forecast) -> 245.11835 | F44: =F43*(1+elect_forecast) -> 652.60937 | G44: =G43*(1+elect_forecast) -> 291.49432 | H44: =H43*(1+elect_forecast) -> 1532.1089 | I44: =I43*(1+elect_forecast) -> 1185.1759 | J44: =J43*(1+elect_forecast) -> 86.948773 | ... L44: =L43*(1+elect_forecast) -> 41.374662 | M44: 4901.0308
B45: ='Oil supply projection'!$B45 -> 2054 | C45: =C44*(1+elect_forecast) -> 3.7675794 | D45: =D44*(1+elect_forecast) -> 898.02503 | E45: =E44*(1+elect_forecast) -> 247.17938 | F45: =F44*(1+elect_forecast) -> 658.09671 | G45: =G44*(1+elect_forecast) -> 293.94529 | H45: =H44*(1+elect_forecast) -> 1544.9914 | I45: =I44*(1+elect_forecast) -> 1195.1413 | J45: =J44*(1+elect_forecast) -> 87.679865 | ... L45: =L44*(1+elect_forecast) -> 41.722552 | M45: 4942.2402
B46: ='Oil supply projection'!$B46 -> 2055 | C46: =C45*(1+elect_forecast) -> 3.7992583 | D46: =D45*(1+elect_forecast) -> 905.5759 | E46: =E45*(1+elect_forecast) -> 249.25774 | F46: =F45*(1+elect_forecast) -> 663.63019 | G46: =G45*(1+elect_forecast) -> 296.41687 | H46: =H45*(1+elect_forecast) -> 1557.9822 | I46: =I45*(1+elect_forecast) -> 1205.1904 | J46: =J45*(1+elect_forecast) -> 88.417105 | ... L46: =L45*(1+elect_forecast) -> 42.073369 | M46: 4983.796
B47: ='Oil supply projection'!$B47 -> 2056 | C47: =C46*(1+elect_forecast) -> 3.8312037 | D47: =D46*(1+elect_forecast) -> 913.19026 | E47: =E46*(1+elect_forecast) -> 251.35358 | F47: =F46*(1+elect_forecast) -> 669.21019 | G47: =G46*(1+elect_forecast) -> 298.90924 | H47: =H46*(1+elect_forecast) -> 1571.0822 | I47: =I46*(1+elect_forecast) -> 1215.324 | J47: =J46*(1+elect_forecast) -> 89.160543 | ... L47: =L46*(1+elect_forecast) -> 42.427134 | M47: 5025.7013
B48: ='Oil supply projection'!$B48 -> 2057 | C48: =C47*(1+elect_forecast) -> 3.8634176 | D48: =D47*(1+elect_forecast) -> 920.86865 | E48: =E47*(1+elect_forecast) -> 253.46703 | F48: =F47*(1+elect_forecast) -> 674.83712 | G48: =G47*(1+elect_forecast) -> 301.42256 | H48: =H47*(1+elect_forecast) -> 1584.2923 | I48: =I47*(1+elect_forecast) -> 1225.5428 | J48: =J47*(1+elect_forecast) -> 89.910232 | ... L48: =L47*(1+elect_forecast) -> 42.783875 | M48: 5067.959
B49: ='Oil supply projection'!$B49 -> 2058 | C49: =C48*(1+elect_forecast) -> 3.8959024 | D49: =D48*(1+elect_forecast) -> 928.61159 | E49: =E48*(1+elect_forecast) -> 255.59826 | F49: =F48*(1+elect_forecast) -> 680.51136 | G49: =G48*(1+elect_forecast) -> 303.95701 | H49: =H48*(1+elect_forecast) -> 1597.6135 | I49: =I48*(1+elect_forecast) -> 1235.8476 | J49: =J48*(1+elect_forecast) -> 90.666225 | ... L49: =L48*(1+elect_forecast) -> 43.143615 | M49: 5110.5719
B50: ='Oil supply projection'!$B50 -> 2059 | C50: =C49*(1+elect_forecast) -> 3.9286603 | D50: =D49*(1+elect_forecast) -> 936.41965 | E50: =E49*(1+elect_forecast) -> 257.74741 | F50: =F49*(1+elect_forecast) -> 686.23331 | G50: =G49*(1+elect_forecast) -> 306.51278 | H50: =H49*(1+elect_forecast) -> 1611.0467 | I50: =I49*(1+elect_forecast) -> 1246.2389 | J50: =J49*(1+elect_forecast) -> 91.428575 | ... L50: =L49*(1+elect_forecast) -> 43.50638 | M50: 5153.5432
B51: ='Oil supply projection'!$B51 -> 2060 | C51: =C50*(1+elect_forecast) -> 3.9616937 | D51: =D50*(1+elect_forecast) -> 944.29335 | E51: =E50*(1+elect_forecast) -> 259.91463 | F51: =F50*(1+elect_forecast) -> 692.00337 | G51: =G50*(1+elect_forecast) -> 309.09003 | H51: =H50*(1+elect_forecast) -> 1624.5929 | I51: =I50*(1+elect_forecast) -> 1256.7177 | J51: =J50*(1+elect_forecast) -> 92.197334 | ... L51: =L50*(1+elect_forecast) -> 43.872195 | M51: 5196.8758
B52: ='Oil supply projection'!$B52 -> 2061 | C52: =C51*(1+elect_forecast) -> 3.9950049 | D52: =D51*(1+elect_forecast) -> 952.23326 | E52: =E51*(1+elect_forecast) -> 262.10007 | F52: =F51*(1+elect_forecast) -> 697.82195 | G52: =G51*(1+elect_forecast) -> 311.68896 | H52: =H51*(1+elect_forecast) -> 1638.253 | I52: =I51*(1+elect_forecast) -> 1267.2846 | J52: =J51*(1+elect_forecast) -> 92.972558 | ... L52: =L51*(1+elect_forecast) -> 44.241086 | M52: 5240.5727
B53: ='Oil supply projection'!$B53 -> 2062 | C53: =C52*(1+elect_forecast) -> 4.0285961 | D53: =D52*(1+elect_forecast) -> 960.23993 | E53: =E52*(1+elect_forecast) -> 264.30389 | F53: =F52*(1+elect_forecast) -> 703.68945 | G53: =G52*(1+elect_forecast) -> 314.30973 | H53: =H52*(1+elect_forecast) -> 1652.0279 | I53: =I52*(1+elect_forecast) -> 1277.9403 | J53: =J52*(1+elect_forecast) -> 93.7543 | ... L53: =L52*(1+elect_forecast) -> 44.613078 | M53: 5284.6371
... B84: ='Oil supply projection'!$B84 -> 2093 | C84: =C83*(1+elect_forecast) -> 5.2225499 | D84: =D83*(1+elect_forecast) -> 1244.8259 | E84: =E83*(1+elect_forecast) -> 342.63555 | F84: =F83*(1+elect_forecast) -> 912.24167 | G84: =G83*(1+elect_forecast) -> 407.46161 | H84: =H83*(1+elect_forecast) -> 2141.6389 | I84: =I83*(1+elect_forecast) -> 1656.6831 | J84: =J83*(1+elect_forecast) -> 121.54023 | ... L84: =L83*(1+elect_forecast) -> 57.835043 | M84: 6850.8433
B85: Scenario | C85: AEO 2023-Special NEMS run | D85: AEO 2023-Special NEMS run | E85: AEO 2023-Special NEMS run | F85: AEO 2023-Special NEMS run | G85: AEO 2023-Special NEMS run | H85: AEO 2023-Special NEMS run | I85: AEO 2023-Special NEMS run | J85: AEO 2023-Special NEMS run | K85: AEO 2023-Special NEMS run | L85: AEO 2023-Special NEMS run | M85: Row Sum
B86: Datekey | C86: BOEM_REF2023.d032923b | D86: BOEM_REF2023.d032923b | E86: BOEM_REF2023.d032923b | F86: BOEM_REF2023.d032923b | G86: BOEM_REF2023.d032923b | H86: BOEM_REF2023.d032923b | I86: BOEM_REF2023.d032923b | J86: BOEM_REF2023.d032923b | K86: BOEM_REF2023.d032923b | L86: BOEM_REF2023.d032923b
B87: Release | C87: April 2023 | D87: April 2023 | E87: April 2023 | F87: April 2023 | G87: April 2023 | H87: April 2023 | I87: April 2023 | J87: April 2023 | K87: April 2023 | L87: April 2023
B88: Table | C88: Summary Table 8 - 8. Electricity Supply, Disposition, Prices, and Emissions | D88: Summary Table 8 - 8. Electricity Supply, Disposition, Prices, and Emissions | E88: Summary Table 8 - 8. Electricity Supply, Disposition, Prices, and Emissions | F88: Summary Table 8 - 8. Electricity Supply, Disposition, Prices, and Emissions | G88: Summary Table 16 - 16. Renewable Energy Generating Capacity and Generation | H88: Summary Table 16 - 16. Renewable Energy Generating Capacity and Generation | I88: Summary Table 16 - 16. Renewable Energy Generating Capacity and Generation | J88: Summary Table 16 - 16. Renewable Energy Generating Capacity and Generation | K88: Summary Table 8 - Summary Table 16 | L88: Summary Table 8 - 8. Electricity Supply, Disposition, Prices, and Emissions
B89: Line | C89: 1310+1319 | D89: 1311+1320 | E89: 1309+1318 | F89: 1312 | G89: 2368 | H89: 2374+2375 | I89: 2376 | J89: 2377 | K89: (1313+1314+1315+1321)-(2368+2374+2375+2376+2377) | L89: 1350
B90: Row Info. | C90: Electric Power Sector: Power Only (Petroleum) + Combined Heat and Power (Petroleum) | D90: Electric Power Sector: Power Only (Natural Gas) + Combined Heat and Power (Natural Gas) | E90: Electric Power Sector: Power Only (Coal) + Combined Heat and Power (Coal) | F90: Electric Power Sector: Power Only (Nuclear) | G90: Electric Power Sector / Generation / Conventional Hydroelectric Power | H90: Electric Power Sector / Generation / Solar Thermal + Electric Power Sector / Generation / Solar Photovoltaic | I90: Electric Power Sector / Generation / Wind | J90: Electric Power Sector / Generation / Offshore Wind | K90: Sum of table 8 leftovers (Pumped Storage/Renewable/Distrbuted Generation/Renewable Sources) less sum of table 16 | L90: Net Imports

Sheet Coal supply projection
A1: Return to Table of Contents
B6: AEO BASELINE COAL SUPPLY PROJECTION
C8: Domestic | D8: Imports | E8: Total Supply | G8: Forecast Supply
B9: Year | C9: 106 short tons | D9: 106 short tons | E9: 106 short tons | G9: %
B10: ='Oil supply projection'!$B10 -> 2019 | C10: 694.22805 | D10: 6.697 | E10: {=aeo_sup_coa_dom+aeo_sup_coa_imp} -> 700.92505 | G10: -0.0088829578
B11: ='Oil supply projection'!$B11 -> 2020 | C11: 544.07 | D11: 4.79 | E11: 548.86 | G11: =(INDEX(aeo_sup_coa_tot,MATCH(baseline_aeo_end_year,B10:B84,0),1)/INDEX(aeo_sup_coa_tot,MATCH(baseline_aeo_end_year-10,B10:B84,0),1))^(1/10)-1 -> -0.0088829578
B12: ='Oil supply projection'!$B12 -> 2021 | C12: 585.34999 | D12: 5.39 | E12: 590.73999
B13: ='Oil supply projection'!$B13 -> 2022 | C13: 590.77046 | D13: 7.27356 | E13: 598.04402
B14: ='Oil supply projection'!$B14 -> 2023 | C14: 568.82525 | D14: 9.040501 | E14: 577.86575
B15: ='Oil supply projection'!$B15 -> 2024 | C15: 588.20207 | D15: 1.03713 | E15: 589.2392
B16: ='Oil supply projection'!$B16 -> 2025 | C16: 549.86666 | D16: 1.119332 | E16: 550.98599
B17: ='Oil supply projection'!$B17 -> 2026 | C17: 497.98121 | D17: 1.35665 | E17: 499.33786
B18: ='Oil supply projection'!$B18 -> 2027 | C18: 438.6353 | D18: 1.360078 | E18: 439.99538
B19: ='Oil supply projection'!$B19 -> 2028 | C19: 389.90549 | D19: 1.899219 | E19: 391.80471
B20: ='Oil supply projection'!$B20 -> 2029 | C20: 356.36828 | D20: 1.866627 | E20: 358.23491
B21: ='Oil supply projection'!$B21 -> 2030 | C21: 333.57429 | D21: 1.844103 | E21: 335.41839
B22: ='Oil supply projection'!$B22 -> 2031 | C22: 331.99835 | D22: 1.812055 | E22: 333.81041
B23: ='Oil supply projection'!$B23 -> 2032 | C23: 337.29013 | D23: 1.791025 | E23: 339.08116
... B41: ='Oil supply projection'!$B41 -> 2050 | C41: 268.37308 | D41: 1.642514 | E41: 270.01559
B42: ='Oil supply projection'!$B42 -> 2051 | C42: =C41*(1+coal_forecast) -> 265.98913 | D42: =D41*(1+coal_forecast) -> 1.6279236 | E42: 267.61705
B43: ='Oil supply projection'!$B43 -> 2052 | C43: =C42*(1+coal_forecast) -> 263.62636 | D43: =D42*(1+coal_forecast) -> 1.6134628 | E43: 265.23982
B44: ='Oil supply projection'!$B44 -> 2053 | C44: =C43*(1+coal_forecast) -> 261.28458 | D44: =D43*(1+coal_forecast) -> 1.5991305 | E44: 262.88371
B45: ='Oil supply projection'!$B45 -> 2054 | C45: =C44*(1+coal_forecast) -> 258.9636 | D45: =D44*(1+coal_forecast) -> 1.5849255 | E45: 260.54852
B46: ='Oil supply projection'!$B46 -> 2055 | C46: =C45*(1+coal_forecast) -> 256.66324 | D46: =D45*(1+coal_forecast) -> 1.5708467 | E46: 258.23408
B47: ='Oil supply projection'!$B47 -> 2056 | C47: =C46*(1+coal_forecast) -> 254.38331 | D47: =D46*(1+coal_forecast) -> 1.5568929 | E47: 255.9402
B48: ='Oil supply projection'!$B48 -> 2057 | C48: =C47*(1+coal_forecast) -> 252.12363 | D48: =D47*(1+coal_forecast) -> 1.5430631 | E48: 253.66669
B49: ='Oil supply projection'!$B49 -> 2058 | C49: =C48*(1+coal_forecast) -> 249.88403 | D49: =D48*(1+coal_forecast) -> 1.5293561 | E49: 251.41338
B50: ='Oil supply projection'!$B50 -> 2059 | C50: =C49*(1+coal_forecast) -> 247.66432 | D50: =D49*(1+coal_forecast) -> 1.5157709 | E50: 249.18009
B51: ='Oil supply projection'!$B51 -> 2060 | C51: =C50*(1+coal_forecast) -> 245.46433 | D51: =D50*(1+coal_forecast) -> 1.5023064 | E51: 246.96663
B52: ='Oil supply projection'!$B52 -> 2061 | C52: =C51*(1+coal_forecast) -> 243.28388 | D52: =D51*(1+coal_forecast) -> 1.4889615 | E52: 244.77284
B53: ='Oil supply projection'!$B53 -> 2062 | C53: =C52*(1+coal_forecast) -> 241.1228 | D53: =D52*(1+coal_forecast) -> 1.4757351 | E53: 242.59853
... B84: ='Oil supply projection'!$B84 -> 2093 | C84: =C83*(1+coal_forecast) -> 182.85698 | D84: =D83*(1+coal_forecast) -> 1.1191329 | E84: 183.97611
B85: Scenario | C85: AEO 2023-Special NEMS run | D85: AEO 2023-Special NEMS run | E85: Row Sum
B86: Datekey | C86: BOEM_REF2023.d032923b | D86: BOEM_REF2023.d032923b
B87: Release | C87: April 2023 | D87: April 2023
B88: Table | C88: Summary Table 15 | D88: Summary Table 15
B89: Line | C89: 2262+2264 | D89: 2267
B90: Row Info. | C90: Production 1/ Total + Waste Coal Supplied 2/ | D90: Imports 3/

Sheet Oil demand projection
A1: Return to Table of Contents
B6: AEO BASELINE OIL DEMAND PROJECTION
C8: Residential | D8: Commercial | E8: Industrial | F8: Transport | G8: Electric | H8: Rest of World (U.S. Crude Oil) | I8: Rest of World (U.S. Refined Products) | J8: Rest of World (non-U.S. Sources) | K8: Total Demand | M8: Rest of World (Total)
B9: Year | C9: 106 barrels per day | D9: 106 barrels per day | E9: 106 barrels per day | F9: 106 barrels per day | G9: 106 barrels per day | H9: 106 barrels per day | I9: 106 barrels per day | J9: 106 barrels per day | K9: 106 barrels per day | M9: 106 barrels per day
B10: ='Oil supply projection'!$B10 -> 2019 | C10: 0.60512949 | D10: 0.51135651 | E10: 5.151413 | F10: 14.108962 | G10: 0.086406 | H10: 2.982 | I10: 5.489 | J10: 72.050586 | K10: {=aeo_dem_oil_res+aeo_dem_oil_com+aeo_dem_oil_ind+aeo_dem_oil_tra+aeo_dem_oil_ele+aeo_dem_oil_row_crude+aeo_dem_oil_row_ref+aeo_dem_oil_row_non_us} -> 100.98485 | M10: {=aeo_dem_oil_row_crude+aeo_dem_oil_row_ref+aeo_dem_oil_row_non_us} -> 80.521586
B11: ='Oil supply projection'!$B11 -> 2020 | C11: 0.53212463 | D11: 0.49656737 | E11: 5.084597 | F11: 12.012855 | G11: 0.083318 | H11: 3.206 | I11: 5.306 | J11: 73.293147 | K11: 100.01461 | M11: 81.805147
B12: ='Oil supply projection'!$B12 -> 2021 | C12: 0.5348248 | D12: 0.5222822 | E12: 5.288411 | F12: 13.296215 | G12: 0.093314 | H12: 2.963 | I12: 5.586 | J12: 74.790467 | K12: 103.07451 | M12: 83.339467
B13: ='Oil supply projection'!$B13 -> 2022 | C13: 0.53441004 | D13: 0.50989996 | E13: 5.541788 | F13: 13.689624 | G13: 0.05182 | H13: 3.459625 | I13: 6.156 | J13: 70.128559 | K13: 100.07173 | M13: 79.744184
B14: ='Oil supply projection'!$B14 -> 2023 | C14: 0.52450464 | D14: 0.50729836 | E14: 5.608357 | F14: 13.674638 | G14: 0.048966 | H14: 3.318643 | I14: 6.502 | J14: 70.88352 | K14: 101.06793 | M14: 80.704163
B15: ='Oil supply projection'!$B15 -> 2024 | C15: 0.47464442 | D15: 0.50063058 | E15: 5.481437 | F15: 13.502675 | G15: 0.049362 | H15: 3.226185 | I15: 7.349445 | J15: 71.910852 | K15: 102.49523 | M15: 82.486482
B16: ='Oil supply projection'!$B16 -> 2025 | C16: 0.46978633 | D16: 0.50345467 | E16: 5.584795 | F16: 13.346295 | G16: 0.047667 | H16: 3.227644 | I16: 7.480367 | J16: 72.827897 | K16: 103.48791 | M16: 83.535908
B17: ='Oil supply projection'!$B17 -> 2026 | C17: 0.46568204 | D17: 0.50495596 | E17: 5.697606 | F17: 13.225303 | G17: 0.043813 | H17: 3.216783 | I17: 7.711962 | J17: 73.557199 | K17: 104.4233 | M17: 84.485944
B18: ='Oil supply projection'!$B18 -> 2027 | C18: 0.46172607 | D18: 0.50593093 | E18: 5.781187 | F18: 13.113745 | G18: 0.04015 | H18: 3.281538 | I18: 7.740853 | J18: 74.374253 | K18: 105.29938 | M18: 85.396644
B19: ='Oil supply projection'!$B19 -> 2028 | C19: 0.45738449 | D19: 0.50921051 | E19: 5.839291 | F19: 12.976136 | G19: 0.036338 | H19: 3.315877 | I19: 7.699915 | J19: 75.310353 | K19: 106.1445 | M19: 86.326145
B20: ='Oil supply projection'!$B20 -> 2029 | C20: 0.45292977 | D20: 0.51142523 | E20: 5.89426 | F20: 12.827898 | G20: 0.034269 | H20: 3.346755 | I20: 7.737927 | J20: 76.136387 | K20: 106.94185 | M20: 87.221069
B21: ='Oil supply projection'!$B21 -> 2030 | C21: 0.44849466 | D21: 0.51291634 | E21: 5.943753 | F21: 12.672229 | G21: 0.03261 | H21: 3.404837 | I21: 7.826201 | J21: 76.828992 | K21: 107.67003 | M21: 88.06003
B22: ='Oil supply projection'!$B22 -> 2031 | C22: 0.44379239 | D22: 0.51415161 | E22: 5.994033 | F22: 12.542238 | G22: 0.031107 | H22: 3.392623 | I22: 7.866532 | J22: 76.870381 | K22: 107.65486 | M22: 88.129536
... B41: ='Oil supply projection'!$B41 -> 2050 | C41: 0.38243762 | D41: 0.52155838 | E41: 6.823233 | F41: 12.298192 | G41: 0.02047 | H41: 2.940725 | I41: 8.144195 | J41: 76.607527 | K41: 107.73834 | M41: 87.692447
B42: ='Oil supply projection'!$B42 -> 2051 | C42: =C41*(1+oil_forecast) -> 0.38517407 | D42: =D41*(1+oil_forecast) -> 0.52529029 | E42: =E41*(1+oil_forecast) -> 6.8720553 | F42: =F41*(1+oil_forecast) -> 12.386189 | G42: =G41*(1+oil_forecast) -> 0.020616469 | H42: =H41*(1+oil_forecast) -> 2.9617668 | I42: =I41*(1+oil_forecast) -> 8.2024691 | J42: =J41*(1+oil_forecast) -> 77.155677 | K42: 108.50924 | M42: 88.319913
B43: ='Oil supply projection'!$B43 -> 2052 | C43: =C42*(1+oil_forecast) -> 0.38793011 | D43: =D42*(1+oil_forecast) -> 0.5290489 | E43: =E42*(1+oil_forecast) -> 6.9212269 | F43: =F42*(1+oil_forecast) -> 12.474816 | G43: =G42*(1+oil_forecast) -> 0.020763986 | H43: =H42*(1+oil_forecast) -> 2.9829591 | I43: =I42*(1+oil_forecast) -> 8.2611602 | J43: =J42*(1+oil_forecast) -> 77.707749 | K43: 109.28565 | M43: 88.951868
B44: ='Oil supply projection'!$B44 -> 2053 | C44: =C43*(1+oil_forecast) -> 0.39070586 | D44: =D43*(1+oil_forecast) -> 0.5328344 | E44: =E43*(1+oil_forecast) -> 6.9707503 | F44: =F43*(1+oil_forecast) -> 12.564077 | G44: =G43*(1+oil_forecast) -> 0.020912558 | H44: =H43*(1+oil_forecast) -> 3.004303 | I44: =I43*(1+oil_forecast) -> 8.3202713 | J44: =J43*(1+oil_forecast) -> 78.263771 | K44: 110.06763 | M44: 89.588345
B45: ='Oil supply projection'!$B45 -> 2054 | C45: =C44*(1+oil_forecast) -> 0.39350148 | D45: =D44*(1+oil_forecast) -> 0.53664699 | E45: =E44*(1+oil_forecast) -> 7.0206281 | F45: =F44*(1+oil_forecast) -> 12.653977 | G45: =G44*(1+oil_forecast) -> 0.021062194 | H45: =H44*(1+oil_forecast) -> 3.0257997 | I45: =I44*(1+oil_forecast) -> 8.3798053 | J45: =J44*(1+oil_forecast) -> 78.823771 | K45: 110.85519 | M45: 90.229377
B46: ='Oil supply projection'!$B46 -> 2055 | C46: =C45*(1+oil_forecast) -> 0.3963171 | D46: =D45*(1+oil_forecast) -> 0.54048685 | E46: =E45*(1+oil_forecast) -> 7.0708628 | F46: =F45*(1+oil_forecast) -> 12.74452 | G46: =G45*(1+oil_forecast) -> 0.0212129 | H46: =H45*(1+oil_forecast) -> 3.0474502 | I46: =I45*(1+oil_forecast) -> 8.4397653 | J46: =J45*(1+oil_forecast) -> 79.387779 | K46: 111.64839 | M46: 90.874995
B47: ='Oil supply projection'!$B47 -> 2056 | C47: =C46*(1+oil_forecast) -> 0.39915287 | D47: =D46*(1+oil_forecast) -> 0.5443542 | E47: =E46*(1+oil_forecast) -> 7.1214569 | F47: =F46*(1+oil_forecast) -> 12.835711 | G47: =G46*(1+oil_forecast) -> 0.021364685 | H47: =H46*(1+oil_forecast) -> 3.0692556 | I47: =I46*(1+oil_forecast) -> 8.5001543 | J47: =J46*(1+oil_forecast) -> 79.955822 | K47: 112.44727 | M47: 91.525232
B48: ='Oil supply projection'!$B48 -> 2057 | C48: =C47*(1+oil_forecast) -> 0.40200892 | D48: =D47*(1+oil_forecast) -> 0.54824922 | E48: =E47*(1+oil_forecast) -> 7.172413 | F48: =F47*(1+oil_forecast) -> 12.927554 | G48: =G47*(1+oil_forecast) -> 0.021517556 | H48: =H47*(1+oil_forecast) -> 3.0912171 | I48: =I47*(1+oil_forecast) -> 8.5609755 | J48: =J47*(1+oil_forecast) -> 80.52793 | K48: 113.25187 | M48: 92.180122
B49: ='Oil supply projection'!$B49 -> 2058 | C49: =C48*(1+oil_forecast) -> 0.40488542 | D49: =D48*(1+oil_forecast) -> 0.5521721 | E49: =E48*(1+oil_forecast) -> 7.2237338 | F49: =F48*(1+oil_forecast) -> 13.020054 | G49: =G48*(1+oil_forecast) -> 0.02167152 | H49: =H48*(1+oil_forecast) -> 3.1133356 | I49: =I48*(1+oil_forecast) -> 8.6222318 | J49: =J48*(1+oil_forecast) -> 81.104131 | K49: 114.06222 | M49: 92.839699
B50: ='Oil supply projection'!$B50 -> 2059 | C50: =C49*(1+oil_forecast) -> 0.40778249 | D50: =D49*(1+oil_forecast) -> 0.55612306 | E50: =E49*(1+oil_forecast) -> 7.2754217 | F50: =F49*(1+oil_forecast) -> 13.113217 | G50: =G49*(1+oil_forecast) -> 0.021826586 | H50: =H49*(1+oil_forecast) -> 3.1356125 | I50: =I49*(1+oil_forecast) -> 8.6839264 | J50: =J49*(1+oil_forecast) -> 81.684455 | K50: 114.87836 | M50: 93.503994
B51: ='Oil supply projection'!$B51 -> 2060 | C51: =C50*(1+oil_forecast) -> 0.4107003 | D51: =D50*(1+oil_forecast) -> 0.56010228 | E51: =E50*(1+oil_forecast) -> 7.3274796 | F51: =F50*(1+oil_forecast) -> 13.207046 | G51: =G50*(1+oil_forecast) -> 0.021982762 | H51: =H50*(1+oil_forecast) -> 3.1580487 | I51: =I50*(1+oil_forecast) -> 8.7460625 | J51: =J50*(1+oil_forecast) -> 82.268932 | K51: 115.70035 | M51: 94.173043
B52: ='Oil supply projection'!$B52 -> 2061 | C52: =C51*(1+oil_forecast) -> 0.41363898 | D52: =D51*(1+oil_forecast) -> 0.56410998 | E52: =E51*(1+oil_forecast) -> 7.3799098 | F52: =F51*(1+oil_forecast) -> 13.301546 | G52: =G51*(1+oil_forecast) -> 0.022140055 | H52: =H51*(1+oil_forecast) -> 3.1806455 | I52: =I51*(1+oil_forecast) -> 8.8086432 | J52: =J51*(1+oil_forecast) -> 82.857591 | K52: 116.52822 | M52: 94.846879
B53: ='Oil supply projection'!$B53 -> 2062 | C53: =C52*(1+oil_forecast) -> 0.41659869 | D53: =D52*(1+oil_forecast) -> 0.56814636 | E53: =E52*(1+oil_forecast) -> 7.4327153 | F53: =F52*(1+oil_forecast) -> 13.396723 | G53: =G52*(1+oil_forecast) -> 0.022298474 | H53: =H52*(1+oil_forecast) -> 3.203404 | I53: =I52*(1+oil_forecast) -> 8.8716717 | J53: =J52*(1+oil_forecast) -> 83.450461 | K53: 117.36202 | M53: 95.525537
... B84: ='Oil supply projection'!$B84 -> 2093 | C84: =C83*(1+oil_forecast) -> 0.51964599 | D84: =D83*(1+oil_forecast) -> 0.70867956 | E84: =E83*(1+oil_forecast) -> 9.2712263 | F84: =F83*(1+oil_forecast) -> 16.710454 | G84: =G83*(1+oil_forecast) -> 0.027814088 | H84: =H83*(1+oil_forecast) -> 3.9957784 | I84: =I83*(1+oil_forecast) -> 11.066114 | J84: =J83*(1+oil_forecast) -> 104.09226 | K84: 146.39197 | M84: 119.15415
B85: Scenario | C85: AEO 2023-Special NEMS run | D85: AEO 2023-Special NEMS run | E85: AEO 2023-Special NEMS run | F85: AEO 2023-Special NEMS run | G85: AEO 2023-Special NEMS run | H85: AEO 2023-Special NEMS run | I85: AEO 2023-Special NEMS run | J85: AEO 2023-Special NEMS run | K85: Row Sum | M85: Sum of ROW components
B86: Datekey | C86: BOEM_REF2023.d032923b | D86: BOEM_REF2023.d032923b | E86: BOEM_REF2023.d032923b | F86: BOEM_REF2023.d032923b | G86: BOEM_REF2023.d032923b | H86: BOEM_REF2023.d032923b | I86: BOEM_REF2023.d032923b | J86: BOEM_REF2023.d032923b
B87: Release | C87: April 2023 | D87: April 2023 | E87: April 2023 | F87: April 2023 | G87: April 2023 | H87: April 2023 | I87: April 2023 | J87: April 2023
B88: Table | C88: Summary Table 11 (Summary Table 2) | D88: Summary Table 11 (Summary Table 2) | E88: Summary Table 11 | F88: Summary Table 11 | G88: Summary Table 11 | H88: Summary Table 11 | I88: Summary Table 11 | J88: Summary Tables 11 and 19
B89: Line | C89: 1679 Multiplied by Ratio of 183 (Residential) :: 197 (Commercial), aka 1679 * (183/(183+197)) | D89: 1679 Multiplied by Ratio of 183 (Residential) :: 197 (Commercial), aka 1679 * (197/(183+197)) | E89: 1680 | F89: 1681 | G89: 1682 | H89: 1636 | I89: 1644 | J89: (2636-2615-2616)-1636-1644
B90: Row Info. | C90: Residential and Commercial (Petroleum and Other Liquids Subtotal) | D90: Residential and Commercial (Petroleum and Other Liquids Subtotal) | E90: Industrial 14/ | F90: Transportation | G90: Electric Power 15/ | H90: Crude Oil // Exports | I90: Net Product Imports // Exports | J90: "Total Liquids Consumption" - "United States (50 states)" - "United States Territories" - ROW US Crude in column H - ROW US refined products in column I

Sheet Gas demand projection
A1: Return to Table of Contents
B6: AEO BASELINE NATURAL GAS DEMAND PROJECTION
C8: Residential | D8: Commercial | E8: Industrial | F8: Transport | G8: Electric | H8: Exports | I8: Total Demand
B9: Year | C9: 1012 cubic feet | D9: 1012 cubic feet | E9: 1012 cubic feet | F9: 1012 cubic feet | G9: 1012 cubic feet | H9: 1012 cubic feet | I9: 1012 cubic feet
B10: ='Oil supply projection'!$B10 -> 2019 | C10: 5.036032 | D10: 3.523504 | E10: 10.223234 | F10: 1.102648 | G10: 12.153634 | H10: 4.655544 | I10: {=aeo_dem_gas_res+aeo_dem_gas_com+aeo_dem_gas_ind+aeo_dem_gas_tra+aeo_dem_gas_ele+aeo_dem_gas_exp} -> 36.694596
B11: ='Oil supply projection'!$B11 -> 2020 | C11: 4.692554 | D11: 3.179619 | E11: 9.933685 | F11: 1.087062 | G11: 11.910897 | H11: 5.280966 | I11: 36.084783
B12: ='Oil supply projection'!$B12 -> 2021 | C12: 4.716203 | D12: 3.298216 | E12: 10.196525 | F12: 1.226581 | G12: 11.510985 | H12: 6.651236 | I12: 37.599746
B13: ='Oil supply projection'!$B13 -> 2022 | C13: 4.956103 | D13: 3.467453 | E13: 10.48014 | F13: 1.298118 | G13: 12.145529 | H13: 7.093177 | I13: 39.44052
B14: ='Oil supply projection'!$B14 -> 2023 | C14: 4.991772 | D14: 3.474632 | E14: 10.226868 | F14: 1.267272 | G14: 11.458883 | H14: 7.875016 | I14: 39.294443
B15: ='Oil supply projection'!$B15 -> 2024 | C15: 4.758908 | D15: 3.371266 | E15: 10.13094 | F15: 1.2243 | G15: 10.676357 | H15: 7.872577 | I15: 38.034348
B16: ='Oil supply projection'!$B16 -> 2025 | C16: 4.78721 | D16: 3.408103 | E16: 10.257669 | F16: 1.211378 | G16: 10.129159 | H16: 8.260273 | I16: 38.053792
B17: ='Oil supply projection'!$B17 -> 2026 | C17: 4.812058 | D17: 3.44426 | E17: 10.484219 | F17: 1.228666 | G17: 9.650112 | H17: 8.761587 | I17: 38.380902
B18: ='Oil supply projection'!$B18 -> 2027 | C18: 4.827391 | D18: 3.462832 | E18: 10.595479 | F18: 1.21859 | G18: 8.945479 | H18: 9.178788 | I18: 38.228559
B19: ='Oil supply projection'!$B19 -> 2028 | C19: 4.834881 | D19: 3.49003 | E19: 10.667993 | F19: 1.209457 | G19: 8.509435 | H19: 9.578387 | I19: 38.290183
B20: ='Oil supply projection'!$B20 -> 2029 | C20: 4.831081 | D20: 3.506521 | E20: 10.710865 | F20: 1.233437 | G20: 8.049894 | H20: 9.934856 | I20: 38.266654
B21: ='Oil supply projection'!$B21 -> 2030 | C21: 4.820789 | D21: 3.517758 | E21: 10.737951 | F21: 1.28203 | G21: 7.697816 | H21: 10.576688 | I21: 38.633032
B22: ='Oil supply projection'!$B22 -> 2031 | C22: 4.805618 | D22: 3.527292 | E22: 10.766996 | F22: 1.33372 | G22: 7.446169 | H22: 11.272001 | I22: 39.151796
... B41: ='Oil supply projection'!$B41 -> 2050 | C41: 4.703437 | D41: 3.443761 | E41: 11.90325 | F41: 1.77057 | G41: 7.902023 | H41: 14.169222 | I41: 43.892263
B42: ='Oil supply projection'!$B42 -> 2051 | C42: =C41*(1+gas_forecast) -> 4.7174043 | D42: =D41*(1+gas_forecast) -> 3.4539875 | E42: =E41*(1+gas_forecast) -> 11.938598 | F42: =F41*(1+gas_forecast) -> 1.7758279 | G42: =G41*(1+gas_forecast) -> 7.9254887 | H42: =H41*(1+gas_forecast) -> 14.211299 | I42: 44.022605
B43: ='Oil supply projection'!$B43 -> 2052 | C43: =C42*(1+gas_forecast) -> 4.731413 | D43: =D42*(1+gas_forecast) -> 3.4642445 | E43: =E42*(1+gas_forecast) -> 11.97405 | F43: =F42*(1+gas_forecast) -> 1.7811013 | G43: =G42*(1+gas_forecast) -> 7.9490241 | H43: =H42*(1+gas_forecast) -> 14.2535 | I43: 44.153334
B44: ='Oil supply projection'!$B44 -> 2053 | C44: =C43*(1+gas_forecast) -> 4.7454633 | D44: =D43*(1+gas_forecast) -> 3.4745318 | E44: =E43*(1+gas_forecast) -> 12.009608 | F44: =F43*(1+gas_forecast) -> 1.7863905 | G44: =G43*(1+gas_forecast) -> 7.9726294 | H44: =H43*(1+gas_forecast) -> 14.295827 | I44: 44.284451
B45: ='Oil supply projection'!$B45 -> 2054 | C45: =C44*(1+gas_forecast) -> 4.7595554 | D45: =D44*(1+gas_forecast) -> 3.4848497 | E45: =E44*(1+gas_forecast) -> 12.045272 | F45: =F44*(1+gas_forecast) -> 1.7916953 | G45: =G44*(1+gas_forecast) -> 7.9963048 | H45: =H44*(1+gas_forecast) -> 14.33828 | I45: 44.415957
B46: ='Oil supply projection'!$B46 -> 2055 | C46: =C45*(1+gas_forecast) -> 4.7736893 | D46: =D45*(1+gas_forecast) -> 3.4951983 | E46: =E45*(1+gas_forecast) -> 12.081041 | F46: =F45*(1+gas_forecast) -> 1.7970159 | G46: =G45*(1+gas_forecast) -> 8.0200506 | H46: =H45*(1+gas_forecast) -> 14.380859 | I46: 44.547854
B47: ='Oil supply projection'!$B47 -> 2056 | C47: =C46*(1+gas_forecast) -> 4.7878652 | D47: =D46*(1+gas_forecast) -> 3.5055776 | E47: =E46*(1+gas_forecast) -> 12.116917 | F47: =F46*(1+gas_forecast) -> 1.8023523 | G47: =G46*(1+gas_forecast) -> 8.0438668 | H47: =H46*(1+gas_forecast) -> 14.423564 | I47: 44.680143
B48: ='Oil supply projection'!$B48 -> 2057 | C48: =C47*(1+gas_forecast) -> 4.8020831 | D48: =D47*(1+gas_forecast) -> 3.5159877 | E48: =E47*(1+gas_forecast) -> 12.152899 | F48: =F47*(1+gas_forecast) -> 1.8077045 | G48: =G47*(1+gas_forecast) -> 8.0677537 | H48: =H47*(1+gas_forecast) -> 14.466396 | I48: 44.812824
B49: ='Oil supply projection'!$B49 -> 2058 | C49: =C48*(1+gas_forecast) -> 4.8163433 | D49: =D48*(1+gas_forecast) -> 3.5264287 | E49: =E48*(1+gas_forecast) -> 12.188988 | F49: =F48*(1+gas_forecast) -> 1.8130727 | G49: =G48*(1+gas_forecast) -> 8.0917116 | H49: =H48*(1+gas_forecast) -> 14.509355 | I49: 44.9459
B50: ='Oil supply projection'!$B50 -> 2059 | C50: =C49*(1+gas_forecast) -> 4.8306459 | D50: =D49*(1+gas_forecast) -> 3.5369007 | E50: =E49*(1+gas_forecast) -> 12.225185 | F50: =F49*(1+gas_forecast) -> 1.8184567 | G50: =G49*(1+gas_forecast) -> 8.1157406 | H50: =H49*(1+gas_forecast) -> 14.552442 | I50: 45.07937
B51: ='Oil supply projection'!$B51 -> 2060 | C51: =C50*(1+gas_forecast) -> 4.8449909 | D51: =D50*(1+gas_forecast) -> 3.5474039 | E51: =E50*(1+gas_forecast) -> 12.261488 | F51: =F50*(1+gas_forecast) -> 1.8238568 | G51: =G50*(1+gas_forecast) -> 8.139841 | H51: =H50*(1+gas_forecast) -> 14.595657 | I51: 45.213237
B52: ='Oil supply projection'!$B52 -> 2061 | C52: =C51*(1+gas_forecast) -> 4.8593785 | D52: =D51*(1+gas_forecast) -> 3.5579382 | E52: =E51*(1+gas_forecast) -> 12.2979 | F52: =F51*(1+gas_forecast) -> 1.8292729 | G52: =G51*(1+gas_forecast) -> 8.164013 | H52: =H51*(1+gas_forecast) -> 14.639 | I52: 45.347502
B53: ='Oil supply projection'!$B53 -> 2062 | C53: =C52*(1+gas_forecast) -> 4.8738088 | D53: =D52*(1+gas_forecast) -> 3.5685038 | E53: =E52*(1+gas_forecast) -> 12.334419 | F53: =F52*(1+gas_forecast) -> 1.8347051 | G53: =G52*(1+gas_forecast) -> 8.1882567 | H53: =H52*(1+gas_forecast) -> 14.682471 | I53: 45.482165
... B84: ='Oil supply projection'!$B84 -> 2093 | C84: =C83*(1+gas_forecast) -> 5.3430489 | D84: =D83*(1+gas_forecast) -> 3.9120719 | E84: =E83*(1+gas_forecast) -> 13.521952 | F84: =F83*(1+gas_forecast) -> 2.0113466 | G84: =G83*(1+gas_forecast) -> 8.9766049 | H84: =H83*(1+gas_forecast) -> 16.096069 | I84: 49.861093
B85: Scenario | C85: AEO 2023-Special NEMS run | D85: AEO 2023-Special NEMS run | E85: AEO 2023-Special NEMS run | F85: AEO 2023-Special NEMS run | G85: AEO 2023-Special NEMS run | H85: AEO 2023-Special NEMS run | I85: Row Sum
B86: Datekey | C86: BOEM_REF2023.d032923b | D86: BOEM_REF2023.d032923b | E86: BOEM_REF2023.d032923b | F86: BOEM_REF2023.d032923b | G86: BOEM_REF2023.d032923b | H86: BOEM_REF2023.d032923b
B87: Release | C87: April 2023 | D87: April 2023 | E87: April 2023 | F87: April 2023 | G87: April 2023 | H87: April 2023
B88: Table | C88: Summary Table 13 | D88: Summary Table 13 | E88: Summary Table 13 | F88: Summary Table 13 | G88: Summary Table 13 | H88: Summary Table 13 Summary Table 76 (Natural Gas Imports and Exports)
B89: Line | C89: 1991 | D89: 1992 | E89: 1994+1995 | F89: 1999 | G89: 2002+2004 | H89: 1996+3985
B90: Row Info. | C90: Residential | D90: Commercial | E90: Industrial 4/ minus Fuel Used to Liquefry Gas for Export 6/ | F90: Transportation 8/ | G90: Electric Power 9/ + Discrepancy 10/ | H90: Fuel Used to Liquefry Gas for Export 6/ + Exports

Sheet Electricity demand projection
A1: Return to Table of Contents
E4: AEO baseline electricity supply and demand are: | F4: {=IF(SUM(IF(ISERROR(ABS(aeo_sup_ele_tot-aeo_dem_ele_tot)/((aeo_sup_ele_tot+aeo_dem_ele_tot)/2)),0,ABS(aeo_sup_ele_tot-aeo_dem_ele_tot)/((aeo_sup_ele_tot+aeo_dem_ele_tot)/2)))>10^-10,"IMBALANCED!","In equilibrium")} -> In equilibrium | AC4: Equilibration notes
B6: AEO BASELINE ELECTRICITY DEMAND PROJECTION
C7: Display as: | J7: =CHOOSE(K7,"nem","equ") -> equ | K7: 2
C8: Residential | D8: Commercial | E8: Industrial | F8: Transport | G8: Other | H8: Total Demand | L8: Residential | M8: Commercial | N8: Industrial | O8: Transport | P8: Other | Q8: Total Demand
B9: Year | C9: 109 kW h | D9: 109 kW h | E9: 109 kW h | F9: 109 kW h | G9: 109 kW h | H9: 109 kW h | L9: Paste values here. Table at left is calculated automatically.
B10: ='Oil supply projection'!$B10 -> 2019 | C10: {=INDIRECT($J$7&"_dem_ele_res")} -> 1388.176 | D10: {=INDIRECT($J$7&"_dem_ele_com")} -> 1311.6547 | E10: {=INDIRECT($J$7&"_dem_ele_ind")} -> 966.09983 | F10: {=INDIRECT($J$7&"_dem_ele_tra")} -> 10.914184 | G10: {=INDIRECT($J$7&"_dem_ele_oth")} -> 165.37298 | H10: {=aeo_dem_ele_res+aeo_dem_ele_com+aeo_dem_ele_ind+aeo_dem_ele_tra+aeo_dem_ele_oth} -> 3842.2178 | L10: 1440.2677 | M10: 1360.8749 | N10: 1002.353 | O10: 11.323741 | P10: 171.57864 | Q10: =SUM(L10:P10) -> 3986.3979 | R10: {=nem_dem_ele_res/nem_dem_ele_tot} -> 0.36129552 | S10: {=nem_dem_ele_com/nem_dem_ele_tot} -> 0.34137959 | T10: {=nem_dem_ele_ind/nem_dem_ele_tot} -> 0.25144328 | U10: {=nem_dem_ele_tra/nem_dem_ele_tot} -> 0.0028405947 | V10: {=nem_dem_ele_oth/nem_dem_ele_tot} -> 0.043041023 | W10: {=aeo_sup_ele_tot-nem_dem_ele_tot} -> -144.18017 | X10: {=per_dem_ele_res*dis_dem_ele_tot+nem_dem_ele_res} -> 1388.176 | Y10: {=per_dem_ele_com*dis_dem_ele_tot+nem_dem_ele_com} -> 1311.6547 | Z10: {=per_dem_ele_ind*dis_dem_ele_tot+nem_dem_ele_ind} -> 966.09983 | AA10: {=per_dem_ele_tra*dis_dem_ele_tot+nem_dem_ele_tra} -> 10.914184 | AB10: {=per_dem_ele_oth*dis_dem_ele_tot+nem_dem_ele_oth} -> 165.37298
B11: ='Oil supply projection'!$B11 -> 2020 | C11: 1406.5372 | D11: 1236.4155 | E11: 921.07156 | F11: 10.603891 | G11: 165.06558 | H11: 3739.6937 | L11: 1464.5818 | M11: 1287.4396 | N11: 959.08209 | O11: 11.04149 | P11: 171.87746 | Q11: =SUM(L11:P11) -> 3894.0224 | R11: 0.37611026 | S11: 0.33061946 | T11: 0.24629599 | U11: 0.0028354973 | V11: 0.044138795 | W11: -154.32868 | X11: 1406.5372 | Y11: 1236.4155 | Z11: 921.07156 | AA11: 10.603891 | AB11: 165.06558
B12: ='Oil supply projection'!$B12 -> 2021 | C12: 1421.8543 | D12: 1275.7165 | E12: 950.25007 | F12: 12.72075 | G12: 174.37508 | H12: 3834.9167 | L12: 1476.54 | M12: 1324.7816 | N12: 986.79749 | O12: 13.210001 | P12: 181.0817 | Q12: =SUM(L12:P12) -> 3982.4108 | R12: 0.37076537 | S12: 0.3326582 | T12: 0.24778897 | U12: 0.0033170864 | V12: 0.04547037 | W12: -147.4941 | X12: 1421.8543 | Y12: 1275.7165 | Z12: 950.25007 | AA12: 12.72075 | AB12: 174.37508
B13: ='Oil supply projection'!$B13 -> 2022 | C13: 1466.1502 | D13: 1308.6448 | E13: 985.26721 | F13: 16.46646 | G13: 190.15135 | H13: 3966.6801 | L13: 1508.6479 | M13: 1346.5771 | N13: 1013.8261 | O13: 16.943756 | P13: 195.66307 | Q13: =SUM(L13:P13) -> 4081.658 | R13: 0.36961645 | S13: 0.32990935 | T13: 0.24838585 | U13: 0.0041511944 | V13: 0.047937154 | W13: -114.97797 | X13: 1466.1502 | Y13: 1308.6448 | Z13: 985.26721 | AA13: 16.46646 | AB13: 190.15135
B14: ='Oil supply projection'!$B14 -> 2023 | C14: 1430.9564 | D14: 1281.344 | E14: 983.9589 | F14: 19.854473 | G14: 198.01966 | H14: 3914.1335 | L14: 1479.0585 | M14: 1324.4167 | N14: 1017.035 | O14: 20.521887 | P14: 204.67615 | Q14: =SUM(L14:P14) -> 4045.7082 | R14: 0.36558703 | S14: 0.32736339 | T14: 0.25138614 | U14: 0.0050725079 | V14: 0.050590931 | W14: -131.57476 | X14: 1430.9564 | Y14: 1281.344 | Z14: 983.9589 | AA14: 19.854473 | AB14: 198.01966
B15: ='Oil supply projection'!$B15 -> 2024 | C15: 1446.5407 | D15: 1285.841 | E15: 975.22145 | F15: 23.99192 | G15: 216.77777 | H15: 3948.3728 | L15: 1498.6884 | M15: 1332.1954 | N15: 1010.3781 | O15: 24.856827 | P15: 224.59259 | Q15: =SUM(L15:P15) -> 4090.7113 | R15: 0.36636375 | S15: 0.32566352 | T15: 0.24699326 | U15: 0.006076407 | V15: 0.054903065 | W15: -142.33855 | X15: 1446.5407 | Y15: 1285.841 | Z15: 975.22145 | AA15: 23.99192 | AB15: 216.77777
B16: ='Oil supply projection'!$B16 -> 2025 | C16: 1455.2737 | D16: 1280.0051 | E16: 978.85576 | F16: 28.670985 | G16: 224.13314 | H16: 3966.9387 | L16: 1511.4412 | M16: 1329.408 | N16: 1016.6355 | O16: 29.777565 | P16: 232.78374 | Q16: =SUM(L16:P16) -> 4120.0459 | R16: 0.36685056 | S16: 0.32266824 | T16: 0.24675344 | U16: 0.0072274838 | V16: 0.056500277 | W16: -153.10723 | X16: 1455.2737 | Y16: 1280.0051 | Z16: 978.85576 | AA16: 28.670985 | AB16: 224.13314
B17: ='Oil supply projection'!$B17 -> 2026 | C17: 1465.4181 | D17: 1279.9634 | E17: 989.09719 | F17: 34.33468 | G17: 231.16149 | H17: 3999.9749 | L17: 1523.4509 | M17: 1330.652 | N17: 1028.267 | O17: 35.694386 | P17: 240.31584 | Q17: =SUM(L17:P17) -> 4158.3801 | R17: 0.36635682 | S17: 0.31999287 | T17: 0.24727585 | U17: 0.0085837237 | V17: 0.057790735 | W17: -158.40518 | X17: 1465.4181 | Y17: 1279.9634 | Z17: 989.09719 | AA17: 34.33468 | AB17: 231.16149
B18: ='Oil supply projection'!$B18 -> 2027 | C18: 1475.7824 | D18: 1277.9043 | E18: 995.41651 | F18: 41.012454 | G18: 237.67969 | H18: 4027.7953 | L18: 1536.5179 | M18: 1330.4962 | N18: 1036.3827 | O18: 42.700314 | P18: 247.46135 | Q18: =SUM(L18:P18) -> 4193.5585 | R18: 0.36639955 | S18: 0.31727141 | T18: 0.24713681 | U18: 0.010182358 | V18: 0.059009872 | W18: -165.76318 | X18: 1475.7824 | Y18: 1277.9043 | Z18: 995.41651 | AA18: 41.012454 | AB18: 237.67969
B19: ='Oil supply projection'!$B19 -> 2028 | C19: 1484.5421 | D19: 1283.6422 | E19: 998.91467 | F19: 48.652401 | G19: 244.52612 | H19: 4060.2775 | L19: 1546.4294 | M19: 1337.1544 | N19: 1040.5573 | O19: 50.680614 | P19: 254.71988 | Q19: =SUM(L19:P19) -> 4229.5416 | R19: 0.36562578 | S19: 0.31614642 | T19: 0.24602128 | U19: 0.011982531 | V19: 0.060223992 | W19: -169.26415 | X19: 1484.5421 | Y19: 1283.6422 | Z19: 998.91467 | AA19: 48.652401 | AB19: 244.52612
B20: ='Oil supply projection'!$B20 -> 2029 | C20: 1490.2482 | D20: 1288.6909 | E20: 1001.8303 | F20: 57.288704 | G20: 251.82447 | H20: 4089.8827 | L20: 1554.7205 | M20: 1344.4432 | N20: 1045.1722 | O20: 59.76717 | P20: 262.71909 | Q20: =SUM(L20:P20) -> 4266.8222 | R20: 0.36437433 | S20: 0.3150924 | T20: 0.24495332 | U20: 0.01400742 | V20: 0.061572541 | W20: -176.9395 | X20: 1490.2482 | Y20: 1288.6909 | Z20: 1001.8303 | AA20: 57.288704 | AB20: 251.82447
B21: ='Oil supply projection'!$B21 -> 2030 | C21: 1494.1885 | D21: 1292.7786 | E21: 1003.6945 | F21: 66.859308 | G21: 259.0786 | H21: 4116.5994 | L21: 1560.6414 | M21: 1350.2739 | N21: 1048.333 | O21: 69.832825 | P21: 270.60092 | Q21: =SUM(L21:P21) -> 4299.682 | R21: 0.36296669 | S21: 0.31404041 | T21: 0.2438164 | U21: 0.016241393 | V21: 0.062935101 | W21: -183.08263 | X21: 1494.1885 | Y21: 1292.7786 | Z21: 1003.6945 | AA21: 66.859308 | AB21: 259.0786
B22: ='Oil supply projection'!$B22 -> 2031 | C22: 1497.5805 | D22: 1298.2363 | E22: 1006.7873 | F22: 75.690928 | G22: 266.18807 | H22: 4144.4832 | L22: 1566.0306 | M22: 1357.575 | N22: 1052.8047 | O22: 79.150543 | P22: 278.35477 | Q22: =SUM(L22:P22) -> 4333.9156 | R22: 0.36134313 | S22: 0.31324444 | T22: 0.24292229 | U22: 0.018263056 | V22: 0.064227085 | W22: -189.43242 | X22: 1497.5805 | Y22: 1298.2363 | Z22: 1006.7873 | AA22: 75.690928 | AB22: 266.18807
... B41: ='Oil supply projection'!$B41 -> 2050 | C41: 1679.6704 | D41: 1383.3619 | E41: 1086.907 | F41: 206.50798 | G41: 423.00552 | H41: 4779.4529 | L41: 1808.8438 | M41: 1489.7479 | N41: 1170.4945 | O41: 222.38927 | P41: 455.53632 | Q41: =SUM(L41:P41) -> 5147.0118 | R41: 0.35143571 | S41: 0.28943939 | T41: 0.22741244 | U41: 0.043207453 | V41: 0.088505008 | W41: -367.55887 | X41: 1679.6704 | Y41: 1383.3619 | Z41: 1086.907 | AA41: 206.50798 | AB41: 423.00552
B42: ='Oil supply projection'!$B42 -> 2051 | C42: 1693.7936 | D42: 1394.9936 | E42: 1096.0461 | F42: 208.24437 | G42: 426.56228 | H42: 4819.64 | J42: =J41*(1+elect_forecast) -> 0 | K42: =K41*(1+elect_forecast) -> 0 | L42: =L41*(1+elect_forecast) -> 1824.0531 | M42: =M41*(1+elect_forecast) -> 1502.2742 | N42: =N41*(1+elect_forecast) -> 1180.3364 | O42: =O41*(1+elect_forecast) -> 224.25918 | P42: =P41*(1+elect_forecast) -> 459.36661 | Q42: =SUM(L42:P42) -> 5190.2894 | R42: 0.35143571 | S42: 0.28943939 | T42: 0.22741244 | U42: 0.043207453 | V42: 0.088505008 | W42: -370.64942 | X42: 1693.7936 | Y42: 1394.9936 | Z42: 1096.0461 | AA42: 208.24437 | AB42: 426.56228
B43: ='Oil supply projection'!$B43 -> 2052 | C43: 1708.0356 | D43: 1406.7232 | E43: 1105.262 | F43: 209.99535 | G43: 430.14894 | H43: 4860.165 | J43: =J42*(1+elect_forecast) -> 0 | K43: =K42*(1+elect_forecast) -> 0 | L43: =L42*(1+elect_forecast) -> 1839.3903 | M43: =M42*(1+elect_forecast) -> 1514.9058 | N43: =N42*(1+elect_forecast) -> 1190.261 | O43: =O42*(1+elect_forecast) -> 226.14482 | P43: =P42*(1+elect_forecast) -> 463.2291 | Q43: =SUM(L43:P43) -> 5233.931 | R43: 0.35143571 | S43: 0.28943939 | T43: 0.22741244 | U43: 0.043207453 | V43: 0.088505008 | W43: -373.76595 | X43: 1708.0356 | Y43: 1406.7232 | Z43: 1105.262 | AA43: 209.99535 | AB43: 430.14894
B44: ='Oil supply projection'!$B44 -> 2053 | C44: 1722.3973 | D44: 1418.5513 | E44: 1114.5554 | F44: 211.76106 | G44: 433.76577 | H44: 4901.0308 | J44: =J43*(1+elect_forecast) -> 0 | K44: =K43*(1+elect_forecast) -> 0 | L44: =L43*(1+elect_forecast) -> 1854.8564 | M44: =M43*(1+elect_forecast) -> 1527.6436 | N44: =N43*(1+elect_forecast) -> 1200.2691 | O44: =O43*(1+elect_forecast) -> 228.04632 | P44: =P43*(1+elect_forecast) -> 467.12407 | Q44: =Q43*(1+elect_forecast) -> 5277.9395 | R44: 0.35143571 | S44: 0.28943939 | T44: 0.22741244 | U44: 0.043207453 | V44: 0.088505008 | W44: -376.90869 | X44: 1722.3973 | Y44: 1418.5513 | Z44: 1114.5554 | AA44: 211.76106 | AB44: 433.76577
B45: ='Oil supply projection'!$B45 -> 2054 | C45: 1736.8797 | D45: 1430.479 | E45: 1123.9269 | F45: 213.54161 | G45: 437.413 | H45: 4942.2402 | J45: =J44*(1+elect_forecast) -> 0 | K45: =K44*(1+elect_forecast) -> 0 | L45: =L44*(1+elect_forecast) -> 1870.4526 | M45: =M44*(1+elect_forecast) -> 1540.4885 | N45: =N44*(1+elect_forecast) -> 1210.3613 | O45: =O44*(1+elect_forecast) -> 229.9638 | P45: =P44*(1+elect_forecast) -> 471.0518 | Q45: =Q44*(1+elect_forecast) -> 5322.318 | R45: 0.35143571 | S45: 0.28943939 | T45: 0.22741244 | U45: 0.043207453 | V45: 0.088505008 | W45: -380.07785 | X45: 1736.8797 | Y45: 1430.479 | Z45: 1123.9269 | AA45: 213.54161 | AB45: 437.413
B46: ='Oil supply projection'!$B46 -> 2055 | C46: 1751.4839 | D46: 1442.5069 | E46: 1133.3772 | F46: 215.33713 | G46: 441.09091 | H46: 4983.796 | J46: =J45*(1+elect_forecast) -> 0 | K46: =K45*(1+elect_forecast) -> 0 | L46: =L45*(1+elect_forecast) -> 1886.18 | M46: =M45*(1+elect_forecast) -> 1553.4414 | N46: =N45*(1+elect_forecast) -> 1220.5384 | O46: =O45*(1+elect_forecast) -> 231.89741 | P46: =P45*(1+elect_forecast) -> 475.01255 | Q46: =Q45*(1+elect_forecast) -> 5367.0697 | R46: 0.35143571 | S46: 0.28943939 | T46: 0.22741244 | U46: 0.043207453 | V46: 0.088505008 | W46: -383.27367 | X46: 1751.4839 | Y46: 1442.5069 | Z46: 1133.3772 | AA46: 215.33713 | AB46: 441.09091
B47: ='Oil supply projection'!$B47 -> 2056 | C47: 1766.2109 | D47: 1454.6359 | E47: 1142.907 | F47: 217.14775 | G47: 444.79974 | H47: 5025.7013 | J47: =J46*(1+elect_forecast) -> 0 | K47: =K46*(1+elect_forecast) -> 0 | L47: =L46*(1+elect_forecast) -> 1902.0396 | M47: =M46*(1+elect_forecast) -> 1566.5032 | N47: =N46*(1+elect_forecast) -> 1230.8011 | O47: =O46*(1+elect_forecast) -> 233.84728 | P47: =P46*(1+elect_forecast) -> 479.0066 | Q47: =Q46*(1+elect_forecast) -> 5412.1977 | R47: 0.35143571 | S47: 0.28943939 | T47: 0.22741244 | U47: 0.043207453 | V47: 0.088505008 | W47: -386.49635 | X47: 1766.2109 | Y47: 1454.6359 | Z47: 1142.907 | AA47: 217.14775 | AB47: 444.79974
B48: ='Oil supply projection'!$B48 -> 2057 | C48: 1781.0618 | D48: 1466.8669 | E48: 1152.5169 | F48: 218.9736 | G48: 448.53975 | H48: 5067.959 | J48: =J47*(1+elect_forecast) -> 0 | K48: =K47*(1+elect_forecast) -> 0 | L48: =L47*(1+elect_forecast) -> 1918.0325 | M48: =M47*(1+elect_forecast) -> 1579.6748 | N48: =N47*(1+elect_forecast) -> 1241.15 | O48: =O47*(1+elect_forecast) -> 235.81354 | P48: =P47*(1+elect_forecast) -> 483.03423 | Q48: =Q47*(1+elect_forecast) -> 5457.7051 | R48: 0.35143571 | S48: 0.28943939 | T48: 0.22741244 | U48: 0.043207453 | V48: 0.088505008 | W48: -389.74613 | X48: 1781.0618 | Y48: 1466.8669 | Z48: 1152.5169 | AA48: 218.9736 | AB48: 448.53975
B49: ='Oil supply projection'!$B49 -> 2058 | C49: 1796.0375 | D49: 1479.2008 | E49: 1162.2076 | F49: 220.8148 | G49: 452.31121 | H49: 5110.5719 | J49: =J48*(1+elect_forecast) -> 0 | K49: =K48*(1+elect_forecast) -> 0 | L49: =L48*(1+elect_forecast) -> 1934.1599 | M49: =M48*(1+elect_forecast) -> 1592.9572 | N49: =N48*(1+elect_forecast) -> 1251.586 | O49: =O48*(1+elect_forecast) -> 237.79633 | P49: =P48*(1+elect_forecast) -> 487.09573 | Q49: =Q48*(1+elect_forecast) -> 5503.5952 | R49: 0.35143571 | S49: 0.28943939 | T49: 0.22741244 | U49: 0.043207453 | V49: 0.088505008 | W49: -393.02324 | X49: 1796.0375 | Y49: 1479.2008 | Z49: 1162.2076 | AA49: 220.8148 | AB49: 452.31121
B50: ='Oil supply projection'!$B50 -> 2059 | C50: 1811.1391 | D50: 1491.6384 | E50: 1171.9798 | F50: 222.67147 | G50: 456.11438 | H50: 5153.5432 | J50: =J49*(1+elect_forecast) -> 0 | K50: =K49*(1+elect_forecast) -> 0 | L50: =L49*(1+elect_forecast) -> 1950.4229 | M50: =M49*(1+elect_forecast) -> 1606.3513 | N50: =N49*(1+elect_forecast) -> 1262.1097 | O50: =O49*(1+elect_forecast) -> 239.79579 | P50: =P49*(1+elect_forecast) -> 491.19139 | Q50: =Q49*(1+elect_forecast) -> 5549.8711 | R50: 0.35143571 | S50: 0.28943939 | T50: 0.22741244 | U50: 0.043207453 | V50: 0.088505008 | W50: -396.3279 | X50: 1811.1391 | Y50: 1491.6384 | Z50: 1171.9798 | AA50: 222.67147 | AB50: 456.11438
B51: ='Oil supply projection'!$B51 -> 2060 | C51: 1826.3678 | D51: 1504.1805 | E51: 1181.8342 | F51: 224.54376 | G51: 459.94953 | H51: 5196.8758 | J51: =J50*(1+elect_forecast) -> 0 | K51: =K50*(1+elect_forecast) -> 0 | L51: =L50*(1+elect_forecast) -> 1966.8227 | M51: =M50*(1+elect_forecast) -> 1619.858 | N51: =N50*(1+elect_forecast) -> 1272.7219 | O51: =O50*(1+elect_forecast) -> 241.81207 | P51: =P50*(1+elect_forecast) -> 495.32147 | Q51: =Q50*(1+elect_forecast) -> 5596.5361 | R51: 0.35143571 | S51: 0.28943939 | T51: 0.22741244 | U51: 0.043207453 | V51: 0.088505008 | W51: -399.66034 | X51: 1826.3678 | Y51: 1504.1805 | Z51: 1181.8342 | AA51: 224.54376 | AB51: 459.94953
B52: ='Oil supply projection'!$B52 -> 2061 | C52: 1841.7244 | D52: 1516.8282 | E52: 1191.7714 | F52: 226.4318 | G52: 463.81693 | H52: 5240.5727 | J52: =J51*(1+elect_forecast) -> 0 | K52: =K51*(1+elect_forecast) -> 0 | L52: =L51*(1+elect_forecast) -> 1983.3603 | M52: =M51*(1+elect_forecast) -> 1633.4782 | N52: =N51*(1+elect_forecast) -> 1283.4234 | O52: =O51*(1+elect_forecast) -> 243.8453 | P52: =P51*(1+elect_forecast) -> 499.48629 | Q52: =Q51*(1+elect_forecast) -> 5643.5935 | R52: 0.35143571 | S52: 0.28943939 | T52: 0.22741244 | U52: 0.043207453 | V52: 0.088505008 | W52: -403.02081 | X52: 1841.7244 | Y52: 1516.8282 | Z52: 1191.7714 | AA52: 226.4318 | AB52: 463.81693
B53: ='Oil supply projection'!$B53 -> 2062 | C53: 1857.2102 | D53: 1529.5821 | E53: 1201.7922 | F53: 228.33571 | G53: 467.71685 | H53: 5284.6371 | J53: =J52*(1+elect_forecast) -> 0 | K53: =K52*(1+elect_forecast) -> 0 | L53: =L52*(1+elect_forecast) -> 2000.037 | M53: =M52*(1+elect_forecast) -> 1647.213 | N53: =N52*(1+elect_forecast) -> 1294.2148 | O53: =O52*(1+elect_forecast) -> 245.89563 | P53: =P52*(1+elect_forecast) -> 503.68612 | Q53: =Q52*(1+elect_forecast) -> 5691.0466 | R53: 0.35143571 | S53: 0.28943939 | T53: 0.22741244 | U53: 0.043207453 | V53: 0.088505008 | W53: -406.40953 | X53: 1857.2102 | Y53: 1529.5821 | Z53: 1201.7922 | AA53: 228.33571 | AB53: 467.71685
B54: ='Oil supply projection'!$B54 -> 2063 | C54: 1872.8262 | D54: 1542.4433 | E54: 1211.8973 | F54: 230.25562 | G54: 471.64955 | H54: 5329.0719 | J54: =J53*(1+elect_forecast) -> 0 | K54: =K53*(1+elect_forecast) -> 0 | L54: =L53*(1+elect_forecast) -> 2016.854 | M54: =M53*(1+elect_forecast) -> 1661.0633 | N54: =N53*(1+elect_forecast) -> 1305.097 | O54: =O53*(1+elect_forecast) -> 247.96319 | P54: =P53*(1+elect_forecast) -> 507.92127 | Q54: =Q53*(1+elect_forecast) -> 5738.8987 | R54: 0.35143571 | S54: 0.28943939 | T54: 0.22741244 | U54: 0.043207453 | V54: 0.088505008 | W54: -409.82675 | X54: 1872.8262 | Y54: 1542.4433 | Z54: 1211.8973 | AA54: 230.25562 | AB54: 471.64955
B55: ='Oil supply projection'!$B55 -> 2064 | C55: 1888.5735 | D55: 1555.4126 | E55: 1222.0873 | F55: 232.19168 | G55: 475.61533 | H55: 5373.8804 | J55: =J54*(1+elect_forecast) -> 0 | K55: =K54*(1+elect_forecast) -> 0 | L55: =L54*(1+elect_forecast) -> 2033.8123 | M55: =M54*(1+elect_forecast) -> 1675.03 | N55: =N54*(1+elect_forecast) -> 1316.0706 | O55: =O54*(1+elect_forecast) -> 250.04814 | P55: =P54*(1+elect_forecast) -> 512.19203 | Q55: =Q54*(1+elect_forecast) -> 5787.1531 | R55: 0.35143571 | S55: 0.28943939 | T55: 0.22741244 | U55: 0.043207453 | V55: 0.088505008 | W55: -413.2727 | X55: 1888.5735 | Y55: 1555.4126 | Z55: 1222.0873 | AA55: 232.19168 | AB55: 475.61533
... B84: ='Oil supply projection'!$B84 -> 2093 | C84: 2407.631 | D84: 1982.9039 | E84: 1557.967 | F84: 296.00749 | G84: 606.33394 | H84: 6850.8433 | J84: =J83*(1+elect_forecast) -> 0 | K84: =K83*(1+elect_forecast) -> 0 | L84: =L83*(1+elect_forecast) -> 2592.7874 | M84: =M83*(1+elect_forecast) -> 2135.3971 | N84: =N83*(1+elect_forecast) -> 1677.7808 | O84: =O83*(1+elect_forecast) -> 318.77164 | P84: =P83*(1+elect_forecast) -> 652.96343 | Q84: =Q83*(1+elect_forecast) -> 7377.7003 | R84: 0.35143571 | S84: 0.28943939 | T84: 0.22741244 | U84: 0.043207453 | V84: 0.088505008 | W84: -526.857 | X84: 2407.631 | Y84: 1982.9039 | Z84: 1557.967 | AA84: 296.00749 | AB84: 606.33394
B85: Scenario* | C85: AEO 2023-Special NEMS run | D85: AEO 2023-Special NEMS run | E85: AEO 2023-Special NEMS run | F85: AEO 2023-Special NEMS run | G85: AEO 2023-Special NEMS run | H85: Row Sum | L85: AEO 2023-Special NEMS run | M85: AEO 2023-Special NEMS run | N85: AEO 2023-Special NEMS run | O85: AEO 2023-Special NEMS run | P85: AEO 2023-Special NEMS run
B86: Datekey* | C86: BOEM_REF2023.d032923b | D86: BOEM_REF2023.d032923b | E86: BOEM_REF2023.d032923b | F86: BOEM_REF2023.d032923b | G86: BOEM_REF2023.d032923b | L86: BOEM_REF2023.d032923b | M86: BOEM_REF2023.d032923b | N86: BOEM_REF2023.d032923b | O86: BOEM_REF2023.d032923b | P86: BOEM_REF2023.d032923b
B87: Release* | C87: April 2023 | D87: April 2023 | E87: April 2023 | F87: April 2023 | G87: April 2023 | L87: April 2023 | M87: April 2023 | N87: April 2023 | O87: April 2023 | P87: April 2023
B88: Table* | C88: Summary Table 8 | D88: Summary Table 8 | E88: Summary Table 8 | F88: Summary Table 8 | G88: Summary Table 8 | L88: Summary Table 8 | M88: Summary Table 8 | N88: Summary Table 8 | O88: Summary Table 8 | P88: Summary Table 8
B89: Line* | C89: 1353 | D89: 1354 | E89: 1355 | F89: 1356 | G89: 1358 | L89: 1353 | M89: 1354 | N89: 1355 | O89: 1356 | P89: 1358
B90: Row Info.* | C90: Residential | D90: Commercial | E90: Industrial | F90: Transportation | G90: Direct Use | L90: Residential | M90: Commercial | N90: Industrial | O90: Transportation | P90: Direct Use
C91: * Equilibrium Calculated Data are not NEMS output values. Above sources are only valid for AEO Baseline Data (at right in Columns L through P).
C92: Equilibrium Calculated Data are electricity demand quantities from NEMS output that have been adjusted by proportionately
C93: allocating the disparity between electricity supply and demand quantities over the various submarkets of electricity demand.

Sheet Coal demand projection
A1: Return to Table of Contents
B6: AEO BASELINE COAL DEMAND PROJECTION
C8: Industrial | D8: Electricity | E8: Other | F8: Exports | G8: Total Demand
B9: Year | C9: 106 short tons | D9: 106 short tons | E9: 106 short tons | F9: 106 short tons | G9: 106 short tons
B10: ='Oil supply projection'!$B10 -> 2019 | C10: 48.36 | D10: 552.61505 | E10: 7.098022 | F10: 92.851997 | G10: {=aeo_dem_coa_ind+aeo_dem_coa_ele+aeo_dem_coa_oth+aeo_dem_coa_exp} -> 700.92507
B11: ='Oil supply projection'!$B11 -> 2020 | C11: 39.939004 | D11: 436.60287 | E11: 3.248141 | F11: 69.07 | G11: 548.86002
B12: ='Oil supply projection'!$B12 -> 2021 | C12: 43.271608 | D12: 501.24997 | E12: -44.651609 | F12: 90.869995 | G12: 590.73996
B13: ='Oil supply projection'!$B13 -> 2022 | C13: 40.484536 | D13: 458.04172 | E13: 14.473817 | F13: 85.043938 | G13: 598.04401
B14: ='Oil supply projection'!$B14 -> 2023 | C14: 38.20497 | D14: 429.44376 | E14: 24.831985 | F14: 85.38504 | G14: 577.86575
B15: ='Oil supply projection'!$B15 -> 2024 | C15: 38.801312 | D15: 449.53473 | E15: -8.371066 | F15: 109.27424 | G15: 589.23921
B16: ='Oil supply projection'!$B16 -> 2025 | C16: 38.492277 | D16: 408.03464 | E16: -3.05878 | F16: 107.51787 | G16: 550.986
B17: ='Oil supply projection'!$B17 -> 2026 | C17: 38.554706 | D17: 343.55801 | E17: -0.544928 | F17: 117.77007 | G17: 499.33786
B18: ='Oil supply projection'!$B18 -> 2027 | C18: 38.400813 | D18: 287.96149 | E18: -2.783747 | F18: 116.41683 | G18: 439.99538
B19: ='Oil supply projection'!$B19 -> 2028 | C19: 38.099317 | D19: 237.22894 | E19: -0.137387 | F19: 116.61382 | G19: 391.8047
B20: ='Oil supply projection'!$B20 -> 2029 | C20: 37.697584 | D20: 211.31615 | E20: -6.766893 | F20: 115.98806 | G20: 358.2349
B21: ='Oil supply projection'!$B21 -> 2030 | C21: 37.207003 | D21: 187.86005 | E21: -4.149663 | F21: 114.50099 | G21: 335.41838
B22: ='Oil supply projection'!$B22 -> 2031 | C22: 36.773034 | D22: 183.87074 | E22: -3.1092 | F22: 116.27583 | G22: 333.81041
... B41: ='Oil supply projection'!$B41 -> 2050 | C41: 29.521989 | D41: 128.36481 | E41: 0.625621 | F41: 111.50318 | G41: 270.0156
B42: ='Oil supply projection'!$B42 -> 2051 | C42: =C41*(1+coal_forecast) -> 29.259746 | D42: =D41*(1+coal_forecast) -> 127.22455 | E42: =E41*(1+coal_forecast) -> 0.62006364 | F42: =F41*(1+coal_forecast) -> 110.5127 | G42: 267.61706
B43: ='Oil supply projection'!$B43 -> 2052 | C43: =C42*(1+coal_forecast) -> 28.999833 | D43: =D42*(1+coal_forecast) -> 126.09442 | E43: =E42*(1+coal_forecast) -> 0.61455564 | F43: =F42*(1+coal_forecast) -> 109.53102 | G43: 265.23983
B44: ='Oil supply projection'!$B44 -> 2053 | C44: =C43*(1+coal_forecast) -> 28.742229 | D44: =D43*(1+coal_forecast) -> 124.97433 | E44: =E43*(1+coal_forecast) -> 0.60909656 | F44: =F43*(1+coal_forecast) -> 108.55806 | G44: 262.88372
B45: ='Oil supply projection'!$B45 -> 2054 | C45: =C44*(1+coal_forecast) -> 28.486913 | D45: =D44*(1+coal_forecast) -> 123.86418 | E45: =E44*(1+coal_forecast) -> 0.60368599 | F45: =F44*(1+coal_forecast) -> 107.59375 | G45: 260.54853
B46: ='Oil supply projection'!$B46 -> 2055 | C46: =C45*(1+coal_forecast) -> 28.233865 | D46: =D45*(1+coal_forecast) -> 122.7639 | E46: =E45*(1+coal_forecast) -> 0.59832347 | F46: =F45*(1+coal_forecast) -> 106.638 | G46: 258.23409
B47: ='Oil supply projection'!$B47 -> 2056 | C47: =C46*(1+coal_forecast) -> 27.983065 | D47: =D46*(1+coal_forecast) -> 121.6734 | E47: =E46*(1+coal_forecast) -> 0.59300859 | F47: =F46*(1+coal_forecast) -> 105.69074 | G47: 255.94021
B48: ='Oil supply projection'!$B48 -> 2057 | C48: =C47*(1+coal_forecast) -> 27.734492 | D48: =D47*(1+coal_forecast) -> 120.59258 | E48: =E47*(1+coal_forecast) -> 0.58774092 | F48: =F47*(1+coal_forecast) -> 104.75189 | G48: 253.6667
B49: ='Oil supply projection'!$B49 -> 2058 | C49: =C48*(1+coal_forecast) -> 27.488128 | D49: =D48*(1+coal_forecast) -> 119.52136 | E49: =E48*(1+coal_forecast) -> 0.58252004 | F49: =F48*(1+coal_forecast) -> 103.82138 | G49: 251.41339
B50: ='Oil supply projection'!$B50 -> 2059 | C50: =C49*(1+coal_forecast) -> 27.243952 | D50: =D49*(1+coal_forecast) -> 118.45966 | E50: =E49*(1+coal_forecast) -> 0.57734554 | F50: =F49*(1+coal_forecast) -> 102.89914 | G50: 249.1801
B51: ='Oil supply projection'!$B51 -> 2060 | C51: =C50*(1+coal_forecast) -> 27.001945 | D51: =D50*(1+coal_forecast) -> 117.40738 | E51: =E50*(1+coal_forecast) -> 0.572217 | F51: =F50*(1+coal_forecast) -> 101.98509 | G51: 246.96664
B52: ='Oil supply projection'!$B52 -> 2061 | C52: =C51*(1+coal_forecast) -> 26.762088 | D52: =D51*(1+coal_forecast) -> 116.36446 | E52: =E51*(1+coal_forecast) -> 0.56713402 | F52: =F51*(1+coal_forecast) -> 101.07916 | G52: 244.77284
B53: ='Oil supply projection'!$B53 -> 2062 | C53: =C52*(1+coal_forecast) -> 26.524362 | D53: =D52*(1+coal_forecast) -> 115.3308 | E53: =E52*(1+coal_forecast) -> 0.56209619 | F53: =F52*(1+coal_forecast) -> 100.18128 | G53: 242.59854
... B84: ='Oil supply projection'!$B84 -> 2093 | C84: =C83*(1+coal_forecast) -> 20.114915 | D84: =D83*(1+coal_forecast) -> 87.46183 | E84: =E83*(1+coal_forecast) -> 0.42626915 | F84: =F83*(1+coal_forecast) -> 75.973099 | G84: 183.97611
B85: Scenario* | C85: AEO 2023-Special NEMS run | D85: AEO 2023-Special NEMS run | E85: AEO 2023-Special NEMS run | F85: AEO 2023-Special NEMS run | G85: Row Sum
B86: Datekey* | C86: BOEM_REF2023.d032923b | D86: BOEM_REF2023.d032923b | E86: BOEM_REF2023.d032923b | F86: BOEM_REF2023.d032923b
B87: Release* | C87: April 2023 | D87: April 2023 | E87: April 2023 | F87: April 2023
B88: Table* | C88: Summary Table 15 | D88: Summary Table 15 | E88: Summary Table 15 | F88: Summary Table 15
B89: Line* | C89: 2275+2276 | D89: 2279 | E89: 2274+2277+2278+2282 | F89: 2268
B90: Row Info.* | C90: Coke Plants + Other Industrial 5/ | D90: Electric Power 6/ | E90: Commercial and Institutional + Coal-to-Liquids Heat and Power + Coal to Liquids Production + Discrepancy and Stock Change | F90: Exports

Sheet Oil supply SIM
A1: Return to Table of Contents
B6: OIL SUPPLY SIMULATION
C8: Lower 48 Onshore (Tight) | D8: Lower 48 Onshore (Conventional) | E8: Lower 48 Offshore | F8: Alaska Onshore | G8: Alaska Offshore | H8: Biofuels | I8: Other | J8: Rest of World | K8: Total Supply | L8: Pipeline Share of Imports*
B9: Year | C9: 106 barrels per day | D9: 106 barrels per day | E9: 106 barrels per day | F9: 106 barrels per day | G9: 106 barrels per day | H9: 106 barrels per day | I9: 106 barrels per day | J9: 106 barrels per day | K9: 106 barrels per day | L9: 106 barrels per day
B10: ='Oil supply projection'!$B10 -> 2019 | C10: {=aeo_sup_oil_2010} -> 7.936 | D10: 1.889 | E10: 1.954 | F10: 0.379793 | G10: 0.085207 | H10: 1.116819 | I10: 5.584398 | J10: 82.039636 | K10: 100.98485 | L10: 2.8804875
B11: ='Oil supply projection'!$B11 -> 2020 | C11: {=(b_oil_l48_t*sim_price_oil^e_sup_oil_l48_t+(1-g_sup_oil_l48_t)*OFFSET(sim_sup_oil_l48_t,-1,0))*display} -> 7.469 | D11: {=(b_oil_l48*sim_price_oil^e_sup_oil_l48+(1-g_sup_oil_l48)*OFFSET(sim_sup_oil_l48,-1,0))*display} -> 1.632 | E11: {=(b_oil_off*sim_price_oil^e_sup_oil_off+(1-g_sup_oil_off)*OFFSET(sim_sup_oil_off,-1,0))*display} -> 1.695 | F11: {=(b_oil_ala_on*sim_price_oil^e_sup_oil_ala_on+(1-g_sup_oil_ala_on)*OFFSET(sim_sup_oil_ala_on,-1,0))*display} -> 0.361657 | G11: {=(b_oil_ala_off*sim_price_oil^e_sup_oil_ala_off+(1-g_sup_oil_ala_off)*OFFSET(sim_sup_oil_ala_off,-1,0))*display} -> 0.086343 | H11: {=(b_oil_bio*sim_price_oil^e_sup_oil_bio+(1-g_sup_oil_bio)*OFFSET(sim_sup_oil_bio,-1,0))*display} -> 1.003683 | I11: {=(b_oil_oth*sim_price_oil^e_sup_oil_oth+(1-g_sup_oil_oth)*OFFSET(sim_sup_oil_oth,-1,0))*display} -> 6.013676 | J11: {=(b_oil_row*sim_price_oil^e_sup_oil_row+(1-g_sup_oil_row)*OFFSET(sim_sup_oil_row,-1,0))*display} -> 81.75325 | K11: {=(sim_sup_oil_l48_t+sim_sup_oil_l48+sim_sup_oil_off+sim_sup_oil_ala_on+sim_sup_oil_ala_off+sim_sup_oil_bio+sim_sup_oil_oth+sim_sup_oil_row)*display} -> 100.01461 | L11: {=(b_oil_can*sim_price_oil^e_sup_oil_can+(1-g_sup_oil_can)*OFFSET(sim_sup_oil_can,-1,0))*display} -> 2.7524577
B12: ='Oil supply projection'!$B12 -> 2021 | C12: 7.308 | D12: 1.65 | E12: 1.753 | F12: 0.353779 | G12: 0.083221 | H12: 1.067889 | I12: 8.397823 | J12: 82.460802 | K12: 103.07451 | L12: 3.1700675
B13: ='Oil supply projection'!$B13 -> 2022 | C13: 8.005 | D13: 1.583554 | E13: 1.803407 | F13: 0.362024 | G13: 0.074428 | H13: 1.089317 | I13: 7.513996 | J13: 79.64 | K13: 100.07173 | L13: 3.4017636
B14: ='Oil supply projection'!$B14 -> 2023 | C14: 8.669035 | D14: 1.390027 | E14: 1.855688 | F14: 0.336099 | G14: 0.06969 | H14: 1.058557 | I14: 7.578831 | J14: 80.11 | K14: 101.06793 | L14: 3.6603931
B15: ='Oil supply projection'!$B15 -> 2024 | C15: 9.057658 | D15: 1.298054 | E15: 1.927653 | F15: 0.311161 | G15: 0.07084 | H15: 1.134723 | I15: 7.635142 | J15: 81.06 | K15: 102.49523 | L15: 3.828191
B16: ='Oil supply projection'!$B16 -> 2025 | C16: 9.084526 | D16: 1.31292 | E16: 1.972143 | F16: 0.377749 | G16: 0.076492 | H16: 1.122123 | I16: 7.700105 | J16: 81.841848 | K16: 103.48791 | L16: 3.7744069
B17: ='Oil supply projection'!$B17 -> 2026 | C17: 9.141235 | D17: 1.335239 | E17: 1.996534 | F17: 0.396468 | G17: 0.080133 | H17: 1.117145 | I17: 7.732854 | J17: 82.623696 | K17: 104.4233 | L17: 3.7343871
B18: ='Oil supply projection'!$B18 -> 2027 | C18: 9.115246 | D18: 1.354258 | E18: 1.972699 | F18: 0.428724 | G18: 0.076696 | H18: 1.117601 | I18: 7.828615 | J18: 83.405544 | K18: 105.29938 | L18: 3.8535112
B19: ='Oil supply projection'!$B19 -> 2028 | C19: 9.113306 | D19: 1.375898 | E19: 1.936125 | F19: 0.478108 | G19: 0.073567 | H19: 1.095393 | I19: 7.884715 | J19: 84.187393 | K19: 106.1445 | L19: 3.9214651
B20: ='Oil supply projection'!$B20 -> 2029 | C20: 9.053332 | D20: 1.400924 | E20: 1.929052 | F20: 0.491656 | G20: 0.070713 | H20: 1.095818 | I20: 7.931115 | J20: 84.969241 | K20: 106.94185 | L20: 4.0011599
B21: ='Oil supply projection'!$B21 -> 2030 | C21: 9.067851 | D21: 1.4315087 | E21: 1.8534237 | F21: 0.49935859 | G21: 0.10096239 | H21: 1.0948186 | I21: 7.8694884 | J21: 85.748361 | K21: 107.66577 | L21: 4.0041574
B22: ='Oil supply projection'!$B22 -> 2031 | C22: 9.0631136 | D22: 1.4491907 | E22: 1.7992488 | F22: 0.49242641 | G22: 0.10770191 | H22: 1.0936089 | I22: 7.8616494 | J22: 85.783708 | K22: 107.65065 | L22: 4.048291
B23: ='Oil supply projection'!$B23 -> 2032 | C23: 9.1295321 | D23: 1.4590276 | E23: 1.7270304 | F23: 0.5228741 | G23: 0.10697756 | H23: 1.0905409 | I23: 7.8215344 | J23: 85.812334 | K23: 107.66985 | L23: 4.0438214
... B84: ='Oil supply projection'!$B84 -> 2093 | C84: 0 | D84: 0 | E84: 0 | F84: 0 | G84: 0 | H84: 0 | I84: 0 | J84: 0 | K84: 0 | L84: 0
D85: * All pipeline imports are assumed to be of Canadian origin.

Sheet Gas supply SIM
A1: Return to Table of Contents
B6: NATURAL GAS SUPPLY SIMULATION
C8: Lower 48 Conventional | D8: Lower 48 Unconventional | E8: Lower 48 Offshore | F8: Alaska Onshore | G8: Alaska Offshore | H8: Other | I8: Imports Pipeline | J8: Imports LNG | K8: Total Supply
B9: Year | C9: 1012 cubic feet | D9: 1012 cubic feet | E9: 1012 cubic feet | F9: 1012 cubic feet | G9: 1012 cubic feet | H9: 1012 cubic feet | I9: 1012 cubic feet | J9: 1012 cubic feet | K9: 1012 cubic feet
B10: ='Oil supply projection'!$B10 -> 2019 | C10: {=aeo_sup_gas_2010} -> 2.65278 | D10: 29.915885 | E10: 1.019864 | F10: 0.304851 | G10: 0 | H10: 0.060765 | I10: 2.687779 | J10: 0.052678 | K10: 36.694602
B11: ='Oil supply projection'!$B11 -> 2020 | C11: {=(b_gas_con*sim_price_gas^e_sup_gas_con+(1-g_sup_gas_con)*OFFSET(sim_sup_gas_con,-1,0))*display} -> 2.565241 | D11: {=(b_gas_unc*sim_price_gas^e_sup_gas_unc+(1-g_sup_gas_unc)*OFFSET(sim_sup_gas_unc,-1,0))*display} -> 29.809835 | E11: {=(b_gas_off*sim_price_gas^e_sup_gas_off+(1-g_sup_gas_off)*OFFSET(sim_sup_gas_off,-1,0))*display} -> 0.792516 | F11: {=(b_gas_ala_on*sim_price_gas^e_sup_gas_ala_on+(1-g_sup_gas_ala_on)*OFFSET(sim_sup_gas_ala_on,-1,0))*display} -> 0.303039 | G11: {=(b_gas_ala_off*sim_price_gas^e_sup_gas_ala_off+(1-g_sup_gas_ala_off)*OFFSET(sim_sup_gas_ala_off,-1,0))*display} -> 0 | H11: {=(b_gas_oth*sim_price_gas^e_sup_gas_oth+(1-g_sup_gas_oth)*OFFSET(sim_sup_gas_oth,-1,0))*display} -> 0.063145 | I11: {=(b_gas_pip*sim_price_gas^e_sup_gas_pip+(1-g_sup_gas_pip)*OFFSET(sim_sup_gas_pip,-1,0))*display} -> 2.501835 | J11: {=(b_gas_lng*sim_price_gas^e_sup_gas_lng+(1-g_sup_gas_lng)*OFFSET(sim_sup_gas_lng,-1,0))*display} -> 0.049169 | K11: {=(sim_sup_gas_con+sim_sup_gas_unc+sim_sup_gas_ala_on+sim_sup_gas_ala_off+sim_sup_gas_off+sim_sup_gas_oth+sim_sup_gas_pip+sim_sup_gas_lng)*display} -> 36.08478
B12: ='Oil supply projection'!$B12 -> 2021 | C12: 2.648991 | D12: 30.985999 | E12: 0.809318 | F12: 0.302724 | G12: {=(b_gas_ala_off*sim_price_gas^e_sup_gas_ala_off+(1-g_sup_gas_ala_off)*OFFSET(sim_sup_gas_ala_off,-1,0))*display} -> 0 | H12: 0.065689 | I12: 2.7656 | J12: 0.021424 | K12: 37.599745
B13: ='Oil supply projection'!$B13 -> 2022 | C13: 2.62482 | D13: 32.421447 | E13: 1.070654 | F13: 0.347862 | G13: {=(b_gas_ala_off*sim_price_gas^e_sup_gas_ala_off+(1-g_sup_gas_ala_off)*OFFSET(sim_sup_gas_ala_off,-1,0))*display} -> 0 | H13: 0.066783 | I13: 2.883263 | J13: 0.025682 | K13: 39.440511
B14: ='Oil supply projection'!$B14 -> 2023 | C14: 2.471103 | D14: 32.866078 | E14: 0.823955 | F14: 0.325372 | G14: {=(b_gas_ala_off*sim_price_gas^e_sup_gas_ala_off+(1-g_sup_gas_ala_off)*OFFSET(sim_sup_gas_ala_off,-1,0))*display} -> 0 | H14: 0.068295 | I14: 2.718317 | J14: 0.02132 | K14: 39.29444
B15: ='Oil supply projection'!$B15 -> 2024 | C15: 2.194472 | D15: 32.244557 | E15: 0.795425 | F15: 0.330591 | G15: {=(b_gas_ala_off*sim_price_gas^e_sup_gas_ala_off+(1-g_sup_gas_ala_off)*OFFSET(sim_sup_gas_ala_off,-1,0))*display} -> 0 | H15: 0.067215 | I15: 2.373989 | J15: 0.028101 | K15: 38.03435
B16: ='Oil supply projection'!$B16 -> 2025 | C16: 2.14478 | D16: 32.359822 | E16: 0.846275 | F16: 0.340373 | G16: {=(b_gas_ala_off*sim_price_gas^e_sup_gas_ala_off+(1-g_sup_gas_ala_off)*OFFSET(sim_sup_gas_ala_off,-1,0))*display} -> 0 | H16: 0.066134 | I16: 2.261526 | J16: 0.034883 | K16: 38.053793
B17: ='Oil supply projection'!$B17 -> 2026 | C17: 2.071491 | D17: 32.832016 | E17: 0.868767 | F17: 0.341071 | G17: {=(b_gas_ala_off*sim_price_gas^e_sup_gas_ala_off+(1-g_sup_gas_ala_off)*OFFSET(sim_sup_gas_ala_off,-1,0))*display} -> 0 | H17: 0.065053 | I17: 2.160842 | J17: 0.041664 | K17: 38.380904
B18: ='Oil supply projection'!$B18 -> 2027 | C18: 1.928922 | D18: 32.87506 | E18: 0.869912 | F18: 0.34651 | G18: {=(b_gas_ala_off*sim_price_gas^e_sup_gas_ala_off+(1-g_sup_gas_ala_off)*OFFSET(sim_sup_gas_ala_off,-1,0))*display} -> 0 | H18: 0.063973 | I18: 2.095736 | J18: 0.048446 | K18: 38.228559
B19: ='Oil supply projection'!$B19 -> 2028 | C19: 1.830736 | D19: 33.135717 | E19: 0.860716 | F19: 0.352726 | G19: {=(b_gas_ala_off*sim_price_gas^e_sup_gas_ala_off+(1-g_sup_gas_ala_off)*OFFSET(sim_sup_gas_ala_off,-1,0))*display} -> 0 | H19: 0.062892 | I19: 1.992164 | J19: 0.055227 | K19: 38.290178
B20: ='Oil supply projection'!$B20 -> 2029 | C20: 1.744173 | D20: 33.248218 | E20: 0.866908 | F20: 0.352955 | G20: {=(b_gas_ala_off*sim_price_gas^e_sup_gas_ala_off+(1-g_sup_gas_ala_off)*OFFSET(sim_sup_gas_ala_off,-1,0))*display} -> 0 | H20: 0.062892 | I20: 1.936276 | J20: 0.055227 | K20: 38.266649
B21: ='Oil supply projection'!$B21 -> 2030 | C21: 1.6940417 | D21: 33.6324 | E21: 0.84834302 | F21: 0.3597229 | G21: {=(b_gas_ala_off*sim_price_gas^e_sup_gas_ala_off+(1-g_sup_gas_ala_off)*OFFSET(sim_sup_gas_ala_off,-1,0))*display} -> 0 | H21: 0.062890869 | I21: 1.9785916 | J21: 0.055225052 | K21: 38.631215
B22: ='Oil supply projection'!$B22 -> 2031 | C22: 1.6418147 | D22: 34.214425 | E22: 0.83726452 | F22: 0.35784326 | G22: {=(b_gas_ala_off*sim_price_gas^e_sup_gas_ala_off+(1-g_sup_gas_ala_off)*OFFSET(sim_sup_gas_ala_off,-1,0))*display} -> 0 | H22: 0.062890766 | I22: 1.9805887 | J22: 0.055224875 | K22: 39.150052
B23: ='Oil supply projection'!$B23 -> 2032 | C23: 1.6006706 | D23: 34.931327 | E23: 0.81330678 | F23: 0.36425213 | G23: {=(b_gas_ala_off*sim_price_gas^e_sup_gas_ala_off+(1-g_sup_gas_ala_off)*OFFSET(sim_sup_gas_ala_off,-1,0))*display} -> 0 | H23: 0.062888569 | I23: 2.0402822 | J23: 0.055221093 | K23: 39.867949
... B84: ='Oil supply projection'!$B84 -> 2093 | C84: 0 | D84: 0 | E84: 0 | F84: 0 | G84: {=(b_gas_ala_off*sim_price_gas^e_sup_gas_ala_off+(1-g_sup_gas_ala_off)*OFFSET(sim_sup_gas_ala_off,-1,0))*display} -> 0 | H84: 0 | I84: 0 | J84: 0 | K84: 0

Sheet Electricity supply SIM
A1: Return to Table of Contents
B6: ELECTRICITY SUPPLY SIMULATION
C8: Oil | D8: Natural Gas | E8: Coal | F8: Nuclear | G8: Hydro | H8: Solar | I8: Wind Onshore | J8: Wind Offshore | K8: Other Electric | L8: Net imports | M8: Total Supply
B9: Year | C9: 109 kW h | D9: 109 kW h | E9: 109 kW h | F9: 109 kW h | G9: 109 kW h | H9: 109 kW h | I9: 109 kW h | J9: 109 kW h | K9: 109 kW h | L9: 109 kW h | M9: 109 kW h
B10: ='Oil supply projection'!$B10 -> 2019 | C10: {=aeo_sup_ele_2010} -> 15.373374 | D10: 1360.8629 | E10: 947.89062 | F10: 809.40924 | G10: 286.4071 | H10: 68.046822 | I10: 295.60403 | J10: 0 | K10: 19.57921 | L10: 39.04443 | M10: 3842.2178
B11: ='Oil supply projection'!$B11 -> 2020 | C11: {=(c_ele_oil*(sim_price_ele/sim_price_oil)^e_sup_ele_oil+(1-g_sup_ele_oil)*OFFSET(sim_sup_ele_oil,-1,0))*display} -> 13.665286 | D11: {=(c_ele_gas*(sim_price_ele/sim_price_gas)^e_sup_ele_gas+(1-g_sup_ele_gas)*OFFSET(sim_sup_ele_gas,-1,0))*display} -> 1405.178 | E11: {=(c_ele_coa*(sim_price_ele/sim_price_coa)^e_sup_ele_coa+(1-g_sup_ele_coa)*OFFSET(sim_sup_ele_coa,-1,0))*display} -> 757.76324 | F11: {=(c_ele_nuc*sim_price_ele^e_sup_ele_nuc+(1-g_sup_ele_nuc)*OFFSET(sim_sup_ele_nuc,-1,0))*display} -> 789.87884 | G11: {=(c_ele_hyd*sim_price_ele^e_sup_ele_hyd+(1-g_sup_ele_hyd)*OFFSET(sim_sup_ele_hyd,-1,0))*display} -> 284.05933 | H11: {=(c_ele_sol*sim_price_ele^e_sup_ele_sol+(1-g_sup_ele_sol)*OFFSET(sim_sup_ele_sol,-1,0))*display} -> 85.3787 | I11: {=(c_ele_won*sim_price_ele^e_sup_ele_won+(1-g_sup_ele_won)*OFFSET(sim_sup_ele_won,-1,0))*display} -> 337.15289 | J11: {=(c_ele_wof*sim_price_ele^e_sup_ele_wof+(1-g_sup_ele_wof)*OFFSET(sim_sup_ele_wof,-1,0))*display} -> 0 | K11: {=(c_ele_oth*sim_price_ele^e_sup_ele_rnh+(1-g_sup_ele_oth)*OFFSET(sim_sup_ele_oth,-1,0))*display} -> 18.539803 | L11: {=(c_ele_imp*sim_price_ele^e_sup_ele_imp+(1-g_sup_ele_imp)*OFFSET(sim_sup_ele_imp,-1,0))*display} -> 48.077648 | M11: {=(sim_sup_ele_oil+sim_sup_ele_gas+sim_sup_ele_coa+sim_sup_ele_nuc+sim_sup_ele_hyd+sim_sup_ele_sol+sim_sup_ele_won+sim_sup_ele_wof+sim_sup_ele_oth+sim_sup_ele_imp)*display} -> 3739.6937
B12: ='Oil supply projection'!$B12 -> 2021 | C12: 15.614943 | D12: 1363.6437 | E12: 882.30536 | F12: 778.18799 | G12: 250.39098 | H12: 111.60156 | I12: 377.91733 | J12: 0 | K12: 17.28599 | L12: 37.968922 | M12: 3834.9167
B13: ='Oil supply projection'!$B13 -> 2022 | C13: 10.011641 | D13: 1451.5491 | E13: 832.22632 | F13: 771.98438 | G13: 275.04477 | H13: 131.15712 | I13: 437.39526 | J13: 1.44935 | K13: 13.175932 | L13: 42.686222 | M13: 3966.6801
B14: ='Oil supply projection'!$B14 -> 2023 | C14: 9.507455 | D14: 1354.0076 | E14: 783.51874 | F14: 783.71594 | G14: 281.19339 | H14: 172.77576 | I14: 462.89889 | J14: 3.102872 | K14: 12.663155 | L14: 50.749699 | M14: 3914.1335
B15: ='Oil supply projection'!$B15 -> 2024 | C15: 9.580185 | D15: 1260.2686 | E15: 822.87207 | F15: 789.40369 | G15: 290.52017 | H15: 247.21266 | I15: 466.08728 | J15: 5.569778 | K15: 13.129585 | L15: 43.72879 | M15: 3948.3728
B16: ='Oil supply projection'!$B16 -> 2025 | C16: 9.264454 | D16: 1193.9293 | E16: 754.82117 | F16: 782.25647 | G16: 298.56491 | H16: 365.23227 | I16: 505.68097 | J16: 6.071972 | K16: 12.511452 | L16: 38.605705 | M16: 3966.9387
B17: ='Oil supply projection'!$B17 -> 2026 | C17: 8.566787 | D17: 1133.4957 | E17: 650.24542 | F17: 774.68359 | G17: 299.28418 | H17: 500.20071 | I17: 574.66333 | J17: 6.883739 | K17: 12.187555 | L17: 39.76387 | M17: 3999.9749
B18: ='Oil supply projection'!$B18 -> 2027 | C18: 7.882752 | D18: 1045.3157 | E18: 554.14319 | F18: 774.66992 | G18: 299.32053 | H18: 621.4231 | I18: 662.60303 | J18: 6.881344 | K18: 11.81308 | L18: 43.742729 | M18: 4027.7953
B19: ='Oil supply projection'!$B19 -> 2028 | C19: 7.173945 | D19: 995.14343 | E19: 455.10489 | F19: 765.54077 | G19: 297.98276 | H19: 703.25769 | I19: 769.13452 | J19: 10.333075 | K19: 10.422989 | L19: 46.183384 | M19: 4060.2775
B20: ='Oil supply projection'!$B20 -> 2029 | C20: 6.783045 | D20: 927.6416 | E20: 389.3721 | F20: 765.54077 | G20: 295.70837 | H20: 750.57294 | I20: 890.1748 | J20: 11.199924 | K20: 9.446502 | L20: 43.442635 | M20: 4089.8827
B21: ='Oil supply projection'!$B21 -> 2030 | C21: 6.4519195 | D21: 880.16878 | E21: 340.84868 | F21: 765.54084 | G21: 292.43408 | H21: 772.63978 | I21: 971.26651 | J21: 31.59027 | K21: 9.1349693 | L21: 46.495948 | M21: 4116.5718
B22: ='Oil supply projection'!$B22 -> 2031 | C22: 6.1715407 | D22: 848.71934 | E22: 333.40223 | F22: 760.27478 | G22: 292.5176 | H22: 806.35487 | I22: 1008.9375 | J22: 36.692752 | K22: 7.6867879 | L22: 43.695457 | M22: 4144.4528
B23: ='Oil supply projection'!$B23 -> 2032 | C23: 6.1717696 | D23: 835.04114 | E23: 342.18486 | F23: 760.27965 | G23: 291.10401 | H23: 839.67554 | I23: 1017.7511 | J23: 36.695595 | K23: 6.9182849 | L23: 44.675488 | M23: 4180.4974
... B35: ='Oil supply projection'!$B35 -> 2044 | C35: 4.0199975 | D35: 840.50666 | E35: 279.06032 | F35: 658.10211 | G35: 286.49566 | H35: 1238.0771 | I35: 1115.9008 | J35: 86.801974 | K35: -15.435964 | L35: 43.311657 | M35: 4536.8403
B36: ='Oil supply projection'!$B36 -> 2045 | C36: #DIV/0! | D36: #DIV/0! | E36: #DIV/0! | F36: 0 | G36: 0 | H36: 0 | I36: 0 | J36: 0 | K36: 0 | L36: 0 | M36: #DIV/0!
B37: ='Oil supply projection'!$B37 -> 2046 | C37: #DIV/0! | D37: #DIV/0! | E37: #DIV/0! | F37: 0 | G37: 0 | H37: 0 | I37: 0 | J37: 0 | K37: 0 | L37: 0 | M37: #DIV/0!
B38: ='Oil supply projection'!$B38 -> 2047 | C38: #DIV/0! | D38: #DIV/0! | E38: #DIV/0! | F38: 0 | G38: 0 | H38: 0 | I38: 0 | J38: 0 | K38: 0 | L38: 0 | M38: #DIV/0!
B39: ='Oil supply projection'!$B39 -> 2048 | C39: #DIV/0! | D39: #DIV/0! | E39: #DIV/0! | F39: 0 | G39: 0 | H39: 0 | I39: 0 | J39: 0 | K39: 0 | L39: 0 | M39: #DIV/0!
B40: ='Oil supply projection'!$B40 -> 2049 | C40: #DIV/0! | D40: #DIV/0! | E40: #DIV/0! | F40: 0 | G40: 0 | H40: 0 | I40: 0 | J40: 0 | K40: 0 | L40: 0 | M40: #DIV/0!
B41: ='Oil supply projection'!$B41 -> 2050 | C41: #DIV/0! | D41: #DIV/0! | E41: #DIV/0! | F41: 0 | G41: 0 | H41: 0 | I41: 0 | J41: 0 | K41: 0 | L41: 0 | M41: #DIV/0!
B42: ='Oil supply projection'!$B42 -> 2051 | C42: #DIV/0! | D42: #DIV/0! | E42: #DIV/0! | F42: 0 | G42: 0 | H42: 0 | I42: 0 | J42: 0 | K42: 0 | L42: 0 | M42: #DIV/0!
B43: ='Oil supply projection'!$B43 -> 2052 | C43: #DIV/0! | D43: #DIV/0! | E43: #DIV/0! | F43: 0 | G43: 0 | H43: 0 | I43: 0 | J43: 0 | K43: 0 | L43: 0 | M43: #DIV/0!
B44: ='Oil supply projection'!$B44 -> 2053 | C44: #DIV/0! | D44: #DIV/0! | E44: #DIV/0! | F44: 0 | G44: 0 | H44: 0 | I44: 0 | J44: 0 | K44: 0 | L44: 0 | M44: #DIV/0!
B45: ='Oil supply projection'!$B45 -> 2054 | C45: #DIV/0! | D45: #DIV/0! | E45: #DIV/0! | F45: 0 | G45: 0 | H45: 0 | I45: 0 | J45: 0 | K45: 0 | L45: 0 | M45: #DIV/0!
B46: ='Oil supply projection'!$B46 -> 2055 | C46: #DIV/0! | D46: #DIV/0! | E46: #DIV/0! | F46: 0 | G46: 0 | H46: 0 | I46: 0 | J46: 0 | K46: 0 | L46: 0 | M46: #DIV/0!
B47: ='Oil supply projection'!$B47 -> 2056 | C47: #DIV/0! | D47: #DIV/0! | E47: #DIV/0! | F47: 0 | G47: 0 | H47: 0 | I47: 0 | J47: 0 | K47: 0 | L47: 0 | M47: #DIV/0!
... B84: ='Oil supply projection'!$B84 -> 2093 | C84: #DIV/0! | D84: #DIV/0! | E84: #DIV/0! | F84: 0 | G84: 0 | H84: 0 | I84: 0 | J84: 0 | K84: 0 | L84: 0 | M84: #DIV/0!

Sheet Coal supply SIM
A1: Return to Table of Contents
B6: COAL SUPPLY SIMULATION
C8: Domestic | D8: Imports | E8: Total Supply
B9: Year | C9: 106 short tons | D9: 106 short tons | E9: 106 short tons
B10: ='Oil supply projection'!$B10 -> 2019 | C10: {=aeo_sup_coa_2010} -> 694.22805 | D10: 6.697 | E10: 700.92505
B11: ='Oil supply projection'!$B11 -> 2020 | C11: {=(b_coa_dom*sim_price_coa^e_sup_coa_dom+(1-g_sup_coa_dom)*OFFSET(sim_sup_coa_dom,-1,0))*display} -> 544.07 | D11: {=(b_coa_imp*sim_price_coa^e_sup_coa_imp+(1-g_sup_coa_imp)*OFFSET(sim_sup_coa_imp,-1,0))*display} -> 4.79 | E11: {=(sim_sup_coa_dom+sim_sup_coa_imp)*display} -> 548.86
B12: ='Oil supply projection'!$B12 -> 2021 | C12: 585.34999 | D12: 5.39 | E12: 590.73999
B13: ='Oil supply projection'!$B13 -> 2022 | C13: 590.77046 | D13: 7.27356 | E13: 598.04402
B14: ='Oil supply projection'!$B14 -> 2023 | C14: 568.82525 | D14: 9.040501 | E14: 577.86575
B15: ='Oil supply projection'!$B15 -> 2024 | C15: 588.20207 | D15: 1.03713 | E15: 589.2392
B16: ='Oil supply projection'!$B16 -> 2025 | C16: 549.86666 | D16: 1.119332 | E16: 550.98599
B17: ='Oil supply projection'!$B17 -> 2026 | C17: 497.98121 | D17: 1.35665 | E17: 499.33786
B18: ='Oil supply projection'!$B18 -> 2027 | C18: 438.6353 | D18: 1.360078 | E18: 439.99538
B19: ='Oil supply projection'!$B19 -> 2028 | C19: 389.90549 | D19: 1.899219 | E19: 391.80471
B20: ='Oil supply projection'!$B20 -> 2029 | C20: 356.36828 | D20: 1.866627 | E20: 358.23491
B21: ='Oil supply projection'!$B21 -> 2030 | C21: 333.57428 | D21: 1.844103 | E21: 335.41839
B22: ='Oil supply projection'!$B22 -> 2031 | C22: 331.99847 | D22: 1.8120551 | E22: 333.81052
B23: ='Oil supply projection'!$B23 -> 2032 | C23: 337.28767 | D23: 1.7910227 | E23: 339.07869
... B84: ='Oil supply projection'!$B84 -> 2093 | C84: 0 | D84: 0 | E84: 0

Sheet OCS Refined Product Data
A1: Return to Table of Contents
B5: DATA TO SUPPORT ESTIMATION OF REFINED PRODUCT EXPORTS DERIVED FROM OCS OIL
B6: Data Element | C6: Value
B7: Offshore Crude Oil Production in the U.S. (millions of barrels) | C7: ='Detailed Results'!M16 -> 11200.666
B8: Onshore Crude Oil Production (millions of barrels) | C8: ='Detailed Results'!M12 -> 77515.151
B9: Net Imports of Crude Oil (millions of barrels) | C9: ='Detailed Results'!M22 -> -15497.301
B11: OCS Crude Oil's Share of U.S. Refinery Feedstock | C11: =C7/SUM(C7,C8,C9) -> 0.15297587

Sheet API Production and Imports
A1: Return to Table of Contents | M1: Yes
M2: No
B3: U.S. CRUDE OIL PRODUCTION AND IMPORTS BY API GRAVITY CATEGORY
B4: API Gravity Category | C4: Total Imports (thousands of Barrels) | D4: Production (thousands of barrels) | E4: Total (thousands of barrels) | F4: Imports as % of Total | G4: Export? (user entered) | H4: If Exported, Percent Exported: Low | I4: If Exported, Percent Exported: High
B5: Heavy | C5: 1530662 | D5: 261927 | E5: 1869103 | F5: =C5/E5 -> 0.81892865 | G5: No | H5: 0.25 | I5: 0.75
B6: Medium | C6: 676036 | D6: 960881 | E6: 1796941 | F6: =C6/E6 -> 0.37621491 | G6: No
B7: Light | C7: 261759 | D7: 2181004 | E7: 2425177 | F7: =C7/E7 -> 0.10793398 | G7: Yes
B8: Total | C8: 2468457 | D8: 3403812 | E8: 6091221 | F8: =C8/E8 -> 0.40524831 | G8: Not applicable | H8: Not applicable | I8: Not applicable
B9: Data Sources: Import data presented here are derived from EIA, Company Level Imports, https://www.eia.gov/petroleum/imports/browser/#/?gg=i&vs=PET_IMPORTS.WORLD-US-LSW.A. They are the 2019 data. Production data by API gravity category derived from EIA, U.S. Crude Oil Projections to 2025: Updated Projection of Crude Types, May 28, 2015.
B11: Note - Consistent with EIA data, API Gravity categories defined as follows: Heavy: API Gravity<27 Medium: API Gravity >=27 but <35 Light: API Gravity>=35

Sheet OCS Oil API
A1: Return to Table of Contents
B7: DISTRIBUTION OF OCS OIL ACROSS API GRAVITY CATEGORIES
C8: Atlantic Region | G8: Gulf Of Mexico Region | J8: Pacific Region | N8: Alaska Region
C10: North Atlantic | D10: Mid-Atlantic | E10: South Atlantic | F10: Straits of Florida | G10: Eastern Gulf | H10: Central Gulf | I10: Western Gulf | J10: Southern California | K10: Central California | L10: Northern California | M10: Washington Oregon | N10: Gulf of Alaska | O10: Cook Inlet | P10: Kodiak | Q10: Shumagin | R10: North Aleutian Basin | S10: Aleutian Arc | T10: St. George Basin | U10: St. Matthew Hall | V10: Bowers Basin | W10: Aleutian Basin | X10: Navarin Basin | Y10: Norton Basin | Z10: Hope Basin | AA10: Chukchi Sea | AB10: Beaufort Sea
B11: API Gravity | C11: % of Oil | D11: % of Oil | E11: % of Oil | F11: % of Oil | G11: % of Oil | H11: % of Oil | I11: % of Oil | J11: % of Oil | K11: % of Oil | L11: % of Oil | M11: % of Oil | N11: % of Oil | O11: % of Oil | P11: % of Oil | Q11: % of Oil | R11: % of Oil | S11: % of Oil | T11: % of Oil | U11: % of Oil | V11: % of Oil | W11: % of Oil | X11: % of Oil | Y11: % of Oil | Z11: % of Oil | AA11: % of Oil | AB11: % of Oil
B12: Heavy* | C12: 0.14 | D12: 0.25 | E12: 0.22 | F12: 0.19 | G12: 0.39 | H12: 0.3 | I12: 0.28 | J12: 0.15 | K12: 0.15 | L12: 0.15 | M12: 0.15 | N12: 0.15 | O12: 0.32 | P12: 0.25 | Q12: 0.25 | R12: 0.25 | S12: 0.25 | T12: 0.25 | U12: 0.25 | V12: 0.25 | W12: 0.25 | X12: 0.25 | Y12: 0.25 | Z12: 0.25 | AA12: 0.48 | AB12: 0.47
B13: Medium* | C13: 0.55 | D13: 0.6 | E13: 0.37 | F13: 0.76 | G13: 0.44 | H13: 0.65 | I13: 0.65 | J13: 0.65 | K13: 0.65 | L13: 0.65 | M13: 0.65 | N13: 0.5 | O13: 0.55 | P13: 0.45 | Q13: 0.45 | R13: 0.45 | S13: 0.45 | T13: 0.45 | U13: 0.45 | V13: 0.45 | W13: 0.45 | X13: 0.45 | Y13: 0.45 | Z13: 0.45 | AA13: 0.45 | AB13: 0.45
B14: Light* | C14: 0.31 | D14: 0.15 | E14: 0.41 | F14: 0.05 | G14: 0.17 | H14: 0.05 | I14: 0.07 | J14: 0.2 | K14: 0.2 | L14: 0.2 | M14: 0.2 | N14: 0.35 | O14: 0.13 | P14: 0.3 | Q14: 0.3 | R14: 0.3 | S14: 0.3 | T14: 0.3 | U14: 0.3 | V14: 0.3 | W14: 0.3 | X14: 0.3 | Y14: 0.3 | Z14: 0.3 | AA14: 0.07 | AB14: 0.08
B15: Total | C15: =SUM(C12:C14) -> 1 | D15: =SUM(D12:D14) -> 1 | E15: =SUM(E12:E14) -> 1 | F15: =SUM(F12:F14) -> 1 | G15: =SUM(G12:G14) -> 1 | H15: =SUM(H12:H14) -> 1 | I15: =SUM(I12:I14) -> 1 | J15: =SUM(J12:J14) -> 1 | ... AB15: =SUM(AB12:AB14) -> 1
C16: =IF(C15=1,0,1) -> 0 | D16: =IF(D15=1,0,1) -> 0 | E16: =IF(E15=1,0,1) -> 0 | F16: =IF(F15=1,0,1) -> 0 | G16: =IF(G15=1,0,1) -> 0 | H16: =IF(H15=1,0,1) -> 0 | I16: =IF(I15=1,0,1) -> 0 | J16: =IF(J15=1,0,1) -> 0 | ... AB16: =IF(AB15=1,0,1) -> 0
C17: =IF(SUM(C16:AB16)=0,"","Edit the above percentages so that the total for each planning area is 100%.")
B18: Note - Consistent with EIA data, API Gravity categories defined as follows: Heavy: API Gravity<27 Medium: API Gravity >=27 but <35 Light: API Gravity>=35

Sheet OCS Crude Exports
A1: Return to Table of Contents
B7: CALCULATION OF CRUDE OIL EXPORTS
C8: Atlantic Region | G8: Gulf Of Mexico Region | J8: Pacific Region | N8: Alaska Region
C10: North Atlantic | D10: Mid-Atlantic | E10: South Atlantic | F10: Straits of Florida | G10: Eastern Gulf | H10: Central Gulf | I10: Western Gulf | J10: Southern California | K10: Central California | L10: Northern California | M10: Washington Oregon | N10: Gulf of Alaska | O10: Cook Inlet | P10: Kodiak | Q10: Shumagin | R10: North Aleutian Basin | S10: Aleutian Arc | T10: St. George Basin | U10: St. Matthew Hall | V10: Bowers Basin | W10: Aleutian Basin | X10: Navarin Basin | Y10: Norton Basin | Z10: Hope Basin | AA10: Chukchi Sea | AB10: Beaufort Sea | AC10: Total
B11: API Gravity | C11: 106 barrels per day | D11: 106 barrels per day | E11: 106 barrels per day | F11: 106 barrels per day | G11: 106 barrels per day | H11: 106 barrels per day | I11: 106 barrels per day | J11: 106 barrels per day | K11: 106 barrels per day | L11: 106 barrels per day | M11: 106 barrels per day | N11: 106 barrels per day | O11: 106 barrels per day | P11: 106 barrels per day | Q11: 106 barrels per day | R11: 106 barrels per day | S11: 106 barrels per day | T11: 106 barrels per day | U11: 106 barrels per day | V11: 106 barrels per day | W11: 106 barrels per day | X11: 106 barrels per day | Y11: 106 barrels per day | Z11: 106 barrels per day | AA11: 106 barrels per day | AB11: 106 barrels per day | AC11: 106 barrels per day
A12: Low | B12: Heavy | C12: {=IF(ocs_oil_export_heavy="No",0,ocs_oil_percent_export_low*ocs_oil_percent_heavy*ocs_oil_sim_plan_area)} -> 0 | D12: {=IF(ocs_oil_export_heavy="No",0,ocs_oil_percent_export_low*ocs_oil_percent_heavy*ocs_oil_sim_plan_area)} -> 0 | E12: {=IF(ocs_oil_export_heavy="No",0,ocs_oil_percent_export_low*ocs_oil_percent_heavy*ocs_oil_sim_plan_area)} -> 0 | F12: {=IF(ocs_oil_export_heavy="No",0,ocs_oil_percent_export_low*ocs_oil_percent_heavy*ocs_oil_sim_plan_area)} -> 0 | G12: {=IF(ocs_oil_export_heavy="No",0,ocs_oil_percent_export_low*ocs_oil_percent_heavy*ocs_oil_sim_plan_area)} -> 0 | H12: {=IF(ocs_oil_export_heavy="No",0,ocs_oil_percent_export_low*ocs_oil_percent_heavy*ocs_oil_sim_plan_area)} -> 0 | I12: {=IF(ocs_oil_export_heavy="No",0,ocs_oil_percent_export_low*ocs_oil_percent_heavy*ocs_oil_sim_plan_area)} -> 0 | J12: {=IF(ocs_oil_export_heavy="No",0,ocs_oil_percent_export_low*ocs_oil_percent_heavy*ocs_oil_sim_plan_area)} -> 0 | ... AB12: {=IF(ocs_oil_export_heavy="No",0,ocs_oil_percent_export_low*ocs_oil_percent_heavy*ocs_oil_sim_plan_area)} -> 0 | AC12: =SUM(C12:AB12) -> 0
B13: Medium | C13: {=IF(ocs_oil_export_medium="No",0,ocs_oil_percent_export_low*ocs_oil_percent_medium*ocs_oil_sim_plan_area)} -> 0 | D13: 0 | E13: 0 | F13: 0 | G13: 0 | H13: 0 | I13: 0 | J13: 0 | K13: 0 | L13: 0 | M13: 0 | N13: 0 | O13: 0 | P13: 0 | Q13: 0 | R13: 0 | S13: 0 | T13: 0 | U13: 0 | V13: 0 | W13: 0 | X13: 0 | Y13: 0 | Z13: 0 | AA13: 0 | AB13: 0 | AC13: =SUM(C13:AB13) -> 0
